Workbook

Sheet 猫统计
A1: 姓名 | B1: 生日 | C1: 年龄 | D1: 类型 | E1: 预留 | F1: 房间 | G1: 窝数 | H1: No.1 | I1: 配猫日期 | J1: 生产日期 | K1: 天数 | L1: 死亡 | M1: 生存 | N1: No.2 | O1: 配猫日期 | P1: 生产日期 | Q1: 天数 | R1: 死亡 | S1: 生存 | T1: No.3 | U1: 配猫日期 | V1: 生产日期 | W1: 天数 | X1: 死亡 | Y1: 生存 | Z1: No.4 | AA1: 配猫日期 | AB1: 生产日期 | AC1: 天数 | AD1: 死亡 | AE1: 生存 | AF1: No.5 | AG1: 配猫日期 | AH1: 生产日期 | AI1: 天数 | AJ1: 死亡 | AK1: 生存 | AL1: No.6 | AM1: 配猫日期 | AN1: 生产日期 | AO1: 天数 | AP1: 死亡 | AQ1: 生存 | AR1: No.7 | AS1: 配猫日期 | AT1: 生产日期 | AU1: 天数 | AV1: 死亡 | AW1: 生存 | AX1: No.8 | AY1: 配猫日期 | AZ1: 生产日期 | BA1: 天数 | BB1: 死亡 | BC1: 生存 | BD1: No.9 | BE1: 配猫日期 | BF1: 生产日期 | BG1: 天数 | BH1: 死亡 | BI1: 生存 | BJ1: No.10 | BK1: 配猫日期 | BL1: 生产日期 | BM1: 天数 | BN1: 死亡 | BO1: 生存
A2: YUKI的孩子 | B2: 45344 | C2: =(TODAY()-B2)/30 -> 7.5666667 | D2: 种母 | E2: 种母 | F2: 猫舍1F小卧室
A3: YUKI的孩子 | B3: 45344 | C3: =(TODAY()-B3)/30 -> 7.5666667 | D3: 库存猫 | E3: 种母 | F3: 猫舍1F小卧室
A4: 刘亦菲 | B4: 45132 | C4: =(TODAY()-B4)/30 -> 14.633333 | D4: 种公 | E4: 种公 | F4: 猫舍1F大卧室
A5: 咖啡 | B5: 43739 | C5: =(TODAY()-B5)/30 -> 61.066667 | D5: 种母 | E5: 种母 | F5: 猫舍1F大卧室 | G5: =COUNTIFS(猫统计!I5,"<>")+COUNTIFS(猫统计!O5,"<>")+COUNTIFS(猫统计!U5,"<>")+COUNTIFS(猫统计!AA5,"<>")+COUNTIFS(猫统计!AG5,"<>")+COUNTIFS(猫统计!AM5,"<>")+COUNTIFS(猫统计!AS5,"<>")+COUNTIFS(猫统计!AY5,"<>")+COUNTIFS(猫统计!BE5,"<>")+COUNTIFS(猫统计!BK5,"<>") -> 4 | I5: 44442 | J5: 44506 | K5: =J5-I5 -> 64 | L5: 0 | M5: 3 | O5: 44657 | P5: 44722 | Q5: =P5-O5 -> 65 | R5: 0 | S5: 3 | U5: 44959 | V5: 45023 | W5: =V5-U5 -> 64 | X5: 0 | Y5: 4 | AA5: 45386 | AB5: 45452 | AC5: =AB5-AA5 -> 66 | AD5: 0 | AE5: 4
A6: 小鸡仔 | B6: 45347 | C6: =(TODAY()-B6)/30 -> 7.4666667 | D6: 种公 | E6: 种公 | F6: 猫舍1F小卧室
A7: 咖啡的金渐层 | B7: 45452 | C7: =(TODAY()-B7)/30 -> 3.9666667 | D7: 库存猫 | F7: 猫舍1F大卧室
A8: 咖啡的金渐层 | B8: 45452 | C8: =(TODAY()-B8)/30 -> 3.9666667 | D8: 种母 | E8: 种母 | F8: 猫舍1F大卧室
A9: 咖啡的金渐层 | B9: 45452 | C9: =(TODAY()-B9)/30 -> 3.9666667 | D9: 库存猫 | F9: 猫舍1F大卧室
A10: 土豆 | B10: 44394 | C10: =(TODAY()-B10)/30 -> 39.233333 | D10: 库存猫 | F10: 猫舍1F大卧室
A11: KIMI | B11: 43793 | C11: =(TODAY()-B11)/30 -> 59.266667 | D11: 预售 | F11: 猫舍1F大卧室
A12: 哈哈 | B12: 44435 | C12: =(TODAY()-B12)/30 -> 37.866667 | D12: 种母 | F12: 猫舍1F客厅 | G12: =COUNTIFS(猫统计!I12,"<>")+COUNTIFS(猫统计!O12,"<>")+COUNTIFS(猫统计!U12,"<>")+COUNTIFS(猫统计!AA12,"<>")+COUNTIFS(猫统计!AG12,"<>")+COUNTIFS(猫统计!AM12,"<>")+COUNTIFS(猫统计!AS12,"<>")+COUNTIFS(猫统计!AY12,"<>")+COUNTIFS(猫统计!BE12,"<>")+COUNTIFS(猫统计!BK12,"<>") -> 3 | I12: 45222 | J12: 45290 | K12: =J12-I12 -> 68 | L12: 2 | M12: 0 | O12: 45354 | P12: 45419 | Q12: =P12-O12 -> 65 | R12: 1 | S12: 1 | U12: 45477 | V12: 45548 | W12: =V12-U12 -> 71 | X12: 1 | Y12: 1
A13: 哈哈的蓝金加白矮脚 | B13: 45548 | C13: =(TODAY()-B13)/30 -> 0.76666667 | D13: 奶猫 | F13: 猫舍1F客厅
A14: 小鹿 | B14: 44980 | C14: =(TODAY()-B14)/30 -> 19.7 | D14: 预售 | F14: 猫舍1F客厅 | G14: 1 | I14: 45452 | J14: 45521 | K14: =J14-I14 -> 69 | L14: 0 | M14: 4
A15: 小鹿的尾尖樊色金白 | B15: 45521 | C15: =(TODAY()-B15)/30 -> 1.6666667 | D15: 奶猫 | F15: 猫舍1F客厅
A16: 小鹿的樊色金白 | B16: 45521 | C16: =(TODAY()-B16)/30 -> 1.6666667 | D16: 奶猫 | F16: 猫舍1F客厅
A17: 小鹿的双色金白 | B17: 45521 | C17: =(TODAY()-B17)/30 -> 1.6666667 | D17: 奶猫 | F17: 猫舍1F客厅
A18: 小鹿的翅膀金白 | B18: 45521 | C18: =(TODAY()-B18)/30 -> 1.6666667 | D18: 奶猫 | F18: 猫舍1F客厅
A19: 借配的金 | D19: 库存猫 | F19: 猫舍1F客厅 | G19: 1 | I19: 45363 | J19: 45428 | K19: =J19-I19 -> 65 | L19: 0 | M19: 2 | O19: 45504 | P19: 45571 | R19: 1 | S19: 3
A20: 借配金的金渐层 | B20: 45571 | C20: =(TODAY()-B20)/30 -> 0 | D20: 奶猫 | F20: 猫舍1F客厅
A21: 借配金的金白矮脚 | B21: 45571 | C21: =(TODAY()-B21)/30 -> 0 | D21: 奶猫 | F21: 猫舍1F客厅
A22: 借配金的金白矮脚 | B22: 45571 | C22: =(TODAY()-B22)/30 -> 0 | D22: 奶猫 | F22: 猫舍1F客厅
A23: 紫薯的金白 | B23: 45456 | C23: =(TODAY()-B23)/30 -> 3.8333333 | D23: 库存猫 | F23: 猫舍1F客厅
A24: 紫薯的蓝金白 | B24: 45456 | C24: =(TODAY()-B24)/30 -> 3.8333333 | D24: 种母 | E24: 种母 | F24: 猫舍1F客厅
A25: 借配的短鼻金白 | B25: 45428 | C25: =(TODAY()-B25)/30 -> 4.7666667 | D25: 种母 | E25: 种母 | F25: 猫舍1F客厅
A26: 冉冉 | B26: 45258 | C26: =(TODAY()-B26)/30 -> 10.433333 | D26: 种母 | E26: 种母 | F26: 猫舍1F客厅
A27: 香蕉的金白 | B27: 45304 | C27: =(TODAY()-B27)/30 -> 8.9 | D27: 预售 | F27: 猫舍1F客厅
A28: YUKI | B28: 43793 | C28: =(TODAY()-B28)/30 -> 59.266667 | D28: 种母 | F28: 猫舍1F小卧室 | G28: =COUNTIFS(猫统计!I28,"<>")+COUNTIFS(猫统计!O28,"<>")+COUNTIFS(猫统计!U28,"<>")+COUNTIFS(猫统计!AA28,"<>")+COUNTIFS(猫统计!AG28,"<>")+COUNTIFS(猫统计!AM28,"<>")+COUNTIFS(猫统计!AS28,"<>")+COUNTIFS(猫统计!AY28,"<>")+COUNTIFS(猫统计!BE28,"<>")+COUNTIFS(猫统计!BK28,"<>") -> 7 | I28: 44186 | J28: 44251 | K28: =J28-I28 -> 65 | L28: 0 | M28: 4 | O28: 44318 | P28: 44382 | Q28: =P28-O28 -> 64 | R28: 3 | S28: 1 | U28: 44605 | V28: 44671 | W28: =V28-U28 -> 66 | X28: 0 | Y28: 2 | AA28: 44936 | AB28: 45001 | AC28: =AB28-AA28 -> 65 | AD28: 0 | AE28: 3 | AG28: 45093 | AH28: 45159 | AI28: =AH28-AG28 -> 66 | AJ28: 0 | AK28: 5 | AM28: 45277 | AN28: 45344 | AO28: =AN28-AM28 -> 67 | AP28: 1 | AQ28: 2 | AS28: 45476 | AT28: 45542 | AU28: =AT28-AS28 -> 66 | AV28: 1 | AW28: 3
A29: YUKI的金白矮脚 | B29: 45538 | C29: =(TODAY()-B29)/30 -> 1.1 | D29: 奶猫 | F29: 猫舍1F小卧室
A30: YUKI的金渐层 | B30: 45538 | C30: =(TODAY()-B30)/30 -> 1.1 | D30: 奶猫 | F30: 猫舍1F小卧室
A31: YUKI的金渐层 | B31: 45538 | C31: =(TODAY()-B31)/30 -> 1.1 | D31: 奶猫 | F31: 猫舍1F小卧室
A32: 地瓜的孩子 | D32: 库存猫 | F32: 猫舍1F小卧室
A34: 妞妞 | B34: 43221 | G34: =COUNTIFS(猫统计!I34,"<>")+COUNTIFS(猫统计!O34,"<>")+COUNTIFS(猫统计!U34,"<>")+COUNTIFS(猫统计!AA34,"<>")+COUNTIFS(猫统计!AG34,"<>")+COUNTIFS(猫统计!AM34,"<>")+COUNTIFS(猫统计!AS34,"<>")+COUNTIFS(猫统计!AY34,"<>")+COUNTIFS(猫统计!BE34,"<>")+COUNTIFS(猫统计!BK34,"<>") -> 1 | I34: 43969 | J34: 44034 | K34: =J34-I34 -> 65 | L34: 3 | M34: 1
A35: 馒头 | B35: 44097 | G35: =COUNTIFS(猫统计!I35,"<>")+COUNTIFS(猫统计!O35,"<>")+COUNTIFS(猫统计!U35,"<>")+COUNTIFS(猫统计!AA35,"<>")+COUNTIFS(猫统计!AG35,"<>")+COUNTIFS(猫统计!AM35,"<>")+COUNTIFS(猫统计!AS35,"<>")+COUNTIFS(猫统计!AY35,"<>")+COUNTIFS(猫统计!BE35,"<>")+COUNTIFS(猫统计!BK35,"<>") -> 2 | I35: 44035 | J35: 44097 | K35: =J35-I35 -> 62 | L35: 0 | M35: 3 | O35: 44147 | P35: 44213 | Q35: =P35-O35 -> 66 | R35: 1 | S35: 2
A36: 菲菲 | B36: 43717 | G36: =COUNTIFS(猫统计!I36,"<>")+COUNTIFS(猫统计!O36,"<>")+COUNTIFS(猫统计!U36,"<>")+COUNTIFS(猫统计!AA36,"<>")+COUNTIFS(猫统计!AG36,"<>")+COUNTIFS(猫统计!AM36,"<>")+COUNTIFS(猫统计!AS36,"<>")+COUNTIFS(猫统计!AY36,"<>")+COUNTIFS(猫统计!BE36,"<>")+COUNTIFS(猫统计!BK36,"<>") -> 1 | I36: 44154 | J36: 44220 | K36: =J36-I36 -> 66 | L36: 1 | M36: 4
A37: 琉璃 | B37: 43843 | G37: =COUNTIFS(猫统计!I37,"<>")+COUNTIFS(猫统计!O37,"<>")+COUNTIFS(猫统计!U37,"<>")+COUNTIFS(猫统计!AA37,"<>")+COUNTIFS(猫统计!AG37,"<>")+COUNTIFS(猫统计!AM37,"<>")+COUNTIFS(猫统计!AS37,"<>")+COUNTIFS(猫统计!AY37,"<>")+COUNTIFS(猫统计!BE37,"<>")+COUNTIFS(猫统计!BK37,"<>") -> 1 | I37: 44154 | J37: 44220 | K37: =J37-I37 -> 66 | L37: 0 | M37: 3
A38: 憨憨 | B38: 43954 | G38: =COUNTIFS(猫统计!I38,"<>")+COUNTIFS(猫统计!O38,"<>")+COUNTIFS(猫统计!U38,"<>")+COUNTIFS(猫统计!AA38,"<>")+COUNTIFS(猫统计!AG38,"<>")+COUNTIFS(猫统计!AM38,"<>")+COUNTIFS(猫统计!AS38,"<>")+COUNTIFS(猫统计!AY38,"<>")+COUNTIFS(猫统计!BE38,"<>")+COUNTIFS(猫统计!BK38,"<>") -> 1 | I38: 44217 | J38: 44282 | K38: =J38-I38 -> 65 | L38: 2 | M38: 3
A39: 蜜芽 | G39: =COUNTIFS(猫统计!I39,"<>")+COUNTIFS(猫统计!O39,"<>")+COUNTIFS(猫统计!U39,"<>")+COUNTIFS(猫统计!AA39,"<>")+COUNTIFS(猫统计!AG39,"<>")+COUNTIFS(猫统计!AM39,"<>")+COUNTIFS(猫统计!AS39,"<>")+COUNTIFS(猫统计!AY39,"<>")+COUNTIFS(猫统计!BE39,"<>")+COUNTIFS(猫统计!BK39,"<>") -> 1 | I39: 44243 | J39: 44309 | K39: =J39-I39 -> 66 | L39: 1 | M39: 5
A40: 银点 | B40: 43941 | G40: =COUNTIFS(猫统计!I40,"<>")+COUNTIFS(猫统计!O40,"<>")+COUNTIFS(猫统计!U40,"<>")+COUNTIFS(猫统计!AA40,"<>")+COUNTIFS(猫统计!AG40,"<>")+COUNTIFS(猫统计!AM40,"<>")+COUNTIFS(猫统计!AS40,"<>")+COUNTIFS(猫统计!AY40,"<>")+COUNTIFS(猫统计!BE40,"<>")+COUNTIFS(猫统计!BK40,"<>") -> 1 | I40: 44274 | J40: 44342 | K40: =J40-I40 -> 68 | L40: 1 | M40: 0
A41: 糖糖 | B41: 43875 | G41: =COUNTIFS(猫统计!I41,"<>")+COUNTIFS(猫统计!O41,"<>")+COUNTIFS(猫统计!U41,"<>")+COUNTIFS(猫统计!AA41,"<>")+COUNTIFS(猫统计!AG41,"<>")+COUNTIFS(猫统计!AM41,"<>")+COUNTIFS(猫统计!AS41,"<>")+COUNTIFS(猫统计!AY41,"<>")+COUNTIFS(猫统计!BE41,"<>")+COUNTIFS(猫统计!BK41,"<>") -> 1 | I41: 44233 | J41: 44300 | K41: =J41-I41 -> 67 | L41: 1 | M41: 4
A42: 如意 | B42: 43763 | G42: =COUNTIFS(猫统计!I42,"<>")+COUNTIFS(猫统计!O42,"<>")+COUNTIFS(猫统计!U42,"<>")+COUNTIFS(猫统计!AA42,"<>")+COUNTIFS(猫统计!AG42,"<>")+COUNTIFS(猫统计!AM42,"<>")+COUNTIFS(猫统计!AS42,"<>")+COUNTIFS(猫统计!AY42,"<>")+COUNTIFS(猫统计!BE42,"<>")+COUNTIFS(猫统计!BK42,"<>") -> 1 | I42: 44274 | J42: 44328 | K42: =J42-I42 -> 54 | L42: 3 | M42: 4
A43: 小熊猫 | B43: 43525 | G43: =COUNTIFS(猫统计!I43,"<>")+COUNTIFS(猫统计!O43,"<>")+COUNTIFS(猫统计!U43,"<>")+COUNTIFS(猫统计!AA43,"<>")+COUNTIFS(猫统计!AG43,"<>")+COUNTIFS(猫统计!AM43,"<>")+COUNTIFS(猫统计!AS43,"<>")+COUNTIFS(猫统计!AY43,"<>")+COUNTIFS(猫统计!BE43,"<>")+COUNTIFS(猫统计!BK43,"<>") -> 1 | I43: 44205 | J43: 44272 | K43: =J43-I43 -> 67 | L43: 3 | M43: 1
A44: YOYO | B44: 43981 | G44: =COUNTIFS(猫统计!I44,"<>")+COUNTIFS(猫统计!O44,"<>")+COUNTIFS(猫统计!U44,"<>")+COUNTIFS(猫统计!AA44,"<>")+COUNTIFS(猫统计!AG44,"<>")+COUNTIFS(猫统计!AM44,"<>")+COUNTIFS(猫统计!AS44,"<>")+COUNTIFS(猫统计!AY44,"<>")+COUNTIFS(猫统计!BE44,"<>")+COUNTIFS(猫统计!BK44,"<>") -> 0
A45: 寿司 | B45: 44029 | G45: =COUNTIFS(猫统计!I45,"<>")+COUNTIFS(猫统计!O45,"<>")+COUNTIFS(猫统计!U45,"<>")+COUNTIFS(猫统计!AA45,"<>")+COUNTIFS(猫统计!AG45,"<>")+COUNTIFS(猫统计!AM45,"<>")+COUNTIFS(猫统计!AS45,"<>")+COUNTIFS(猫统计!AY45,"<>")+COUNTIFS(猫统计!BE45,"<>")+COUNTIFS(猫统计!BK45,"<>") -> 2 | I45: 44205 | J45: 44271 | K45: =J45-I45 -> 66 | L45: 0 | M45: 4 | O45: 44326 | P45: 44391 | Q45: =P45-O45 -> 65 | R45: 0 | S45: 5
A46: 奶酪 | B46: 76458 | G46: =COUNTIFS(猫统计!I46,"<>")+COUNTIFS(猫统计!O46,"<>")+COUNTIFS(猫统计!U46,"<>")+COUNTIFS(猫统计!AA46,"<>")+COUNTIFS(猫统计!AG46,"<>")+COUNTIFS(猫统计!AM46,"<>")+COUNTIFS(猫统计!AS46,"<>")+COUNTIFS(猫统计!AY46,"<>")+COUNTIFS(猫统计!BE46,"<>")+COUNTIFS(猫统计!BK46,"<>") -> 3 | I46: 43979 | J46: 44044 | K46: =J46-I46 -> 65 | L46: 0 | M46: 1 | O46: 44203 | P46: 44268 | Q46: =P46-O46 -> 65 | R46: 0 | S46: 3 | U46: 44322 | V46: 44388 | W46: =V46-U46 -> 66 | X46: 0 | Y46: 1
A47: 小花花 | B47: 43833 | G47: =COUNTIFS(猫统计!I47,"<>")+COUNTIFS(猫统计!O47,"<>")+COUNTIFS(猫统计!U47,"<>")+COUNTIFS(猫统计!AA47,"<>")+COUNTIFS(猫统计!AG47,"<>")+COUNTIFS(猫统计!AM47,"<>")+COUNTIFS(猫统计!AS47,"<>")+COUNTIFS(猫统计!AY47,"<>")+COUNTIFS(猫统计!BE47,"<>")+COUNTIFS(猫统计!BK47,"<>") -> 2 | I47: 44183 | J47: 44247 | K47: =J47-I47 -> 64 | L47: 0 | M47: 3 | O47: 44381 | P47: 44445 | Q47: =P47-O47 -> 64 | R47: 0 | S47: 3
A48: 玲珑 | B48: 43915 | G48: =COUNTIFS(猫统计!I48,"<>")+COUNTIFS(猫统计!O48,"<>")+COUNTIFS(猫统计!U48,"<>")+COUNTIFS(猫统计!AA48,"<>")+COUNTIFS(猫统计!AG48,"<>")+COUNTIFS(猫统计!AM48,"<>")+COUNTIFS(猫统计!AS48,"<>")+COUNTIFS(猫统计!AY48,"<>")+COUNTIFS(猫统计!BE48,"<>")+COUNTIFS(猫统计!BK48,"<>") -> 2 | I48: 44246 | J48: 44312 | K48: =J48-I48 -> 66 | L48: 2 | M48: 4 | O48: 44381 | P48: 44447 | Q48: =P48-O48 -> 66 | R48: 2 | S48: 2
A49: 咖啡豆 | B49: 43961 | G49: =COUNTIFS(猫统计!I49,"<>")+COUNTIFS(猫统计!O49,"<>")+COUNTIFS(猫统计!U49,"<>")+COUNTIFS(猫统计!AA49,"<>")+COUNTIFS(猫统计!AG49,"<>")+COUNTIFS(猫统计!AM49,"<>")+COUNTIFS(猫统计!AS49,"<>")+COUNTIFS(猫统计!AY49,"<>")+COUNTIFS(猫统计!BE49,"<>")+COUNTIFS(猫统计!BK49,"<>") -> 2 | I49: 44257 | J49: 44326 | K49: =J49-I49 -> 69 | L49: 0 | M49: 1 | O49: 44395 | P49: 44461 | Q49: =P49-O49 -> 66 | R49: 0 | S49: 3
A50: 阿比 | G50: =COUNTIFS(猫统计!I50,"<>")+COUNTIFS(猫统计!O50,"<>")+COUNTIFS(猫统计!U50,"<>")+COUNTIFS(猫统计!AA50,"<>")+COUNTIFS(猫统计!AG50,"<>")+COUNTIFS(猫统计!AM50,"<>")+COUNTIFS(猫统计!AS50,"<>")+COUNTIFS(猫统计!AY50,"<>")+COUNTIFS(猫统计!BE50,"<>")+COUNTIFS(猫统计!BK50,"<>") -> 1 | I50: 44342 | J50: 44406 | K50: =J50-I50 -> 64 | L50: 0 | M50: 7
A51: 德文串 | G51: =COUNTIFS(猫统计!I51,"<>")+COUNTIFS(猫统计!O51,"<>")+COUNTIFS(猫统计!U51,"<>")+COUNTIFS(猫统计!AA51,"<>")+COUNTIFS(猫统计!AG51,"<>")+COUNTIFS(猫统计!AM51,"<>")+COUNTIFS(猫统计!AS51,"<>")+COUNTIFS(猫统计!AY51,"<>")+COUNTIFS(猫统计!BE51,"<>")+COUNTIFS(猫统计!BK51,"<>") -> 1 | I51: 44347 | J51: 44412 | K51: =J51-I51 -> 65 | L51: 0 | M51: 7
A52: 南瓜 | B52: 43781 | G52: =COUNTIFS(猫统计!I52,"<>")+COUNTIFS(猫统计!O52,"<>")+COUNTIFS(猫统计!U52,"<>")+COUNTIFS(猫统计!AA52,"<>")+COUNTIFS(猫统计!AG52,"<>")+COUNTIFS(猫统计!AM52,"<>")+COUNTIFS(猫统计!AS52,"<>")+COUNTIFS(猫统计!AY52,"<>")+COUNTIFS(猫统计!BE52,"<>")+COUNTIFS(猫统计!BK52,"<>") -> 2 | I52: 44232 | J52: 44299 | K52: =J52-I52 -> 67 | L52: 1 | M52: 3 | O52: 44412 | P52: 44478 | Q52: =P52-O52 -> 66 | R52: 0 | S52: 4
A53: 小巧 | B53: 43915 | G53: =COUNTIFS(猫统计!I53,"<>")+COUNTIFS(猫统计!O53,"<>")+COUNTIFS(猫统计!U53,"<>")+COUNTIFS(猫统计!AA53,"<>")+COUNTIFS(猫统计!AG53,"<>")+COUNTIFS(猫统计!AM53,"<>")+COUNTIFS(猫统计!AS53,"<>")+COUNTIFS(猫统计!AY53,"<>")+COUNTIFS(猫统计!BE53,"<>")+COUNTIFS(猫统计!BK53,"<>") -> 2 | I53: 44215 | J53: 44280 | K53: =J53-I53 -> 65 | L53: 2 | M53: 2 | O53: 44505 | P53: 44570 | Q53: =P53-O53 -> 65 | R53: 3 | S53: 2
A54: 珊瑚 | G54: =COUNTIFS(猫统计!I54,"<>")+COUNTIFS(猫统计!O54,"<>")+COUNTIFS(猫统计!U54,"<>")+COUNTIFS(猫统计!AA54,"<>")+COUNTIFS(猫统计!AG54,"<>")+COUNTIFS(猫统计!AM54,"<>")+COUNTIFS(猫统计!AS54,"<>")+COUNTIFS(猫统计!AY54,"<>")+COUNTIFS(猫统计!BE54,"<>")+COUNTIFS(猫统计!BK54,"<>") -> 1 | I54: 44421 | J54: 44485 | K54: =J54-I54 -> 64 | L54: 2 | M54: 5
A55: 牛奶 | B55: 43709 | G55: =COUNTIFS(猫统计!I55,"<>")+COUNTIFS(猫统计!O55,"<>")+COUNTIFS(猫统计!U55,"<>")+COUNTIFS(猫统计!AA55,"<>")+COUNTIFS(猫统计!AG55,"<>")+COUNTIFS(猫统计!AM55,"<>")+COUNTIFS(猫统计!AS55,"<>")+COUNTIFS(猫统计!AY55,"<>")+COUNTIFS(猫统计!BE55,"<>")+COUNTIFS(猫统计!BK55,"<>") -> 3 | I55: 44064 | J55: 44132 | K55: =J55-I55 -> 68 | L55: 0 | M55: 3 | O55: 44209 | P55: 44275 | Q55: =P55-O55 -> 66 | R55: 0 | S55: 4 | U55: 44370 | V55: 44435 | W55: =V55-U55 -> 65 | X55: 0 | Y55: 3
A56: Pigi | B56: 44309 | G56: =COUNTIFS(猫统计!I56,"<>")+COUNTIFS(猫统计!O56,"<>")+COUNTIFS(猫统计!U56,"<>")+COUNTIFS(猫统计!AA56,"<>")+COUNTIFS(猫统计!AG56,"<>")+COUNTIFS(猫统计!AM56,"<>")+COUNTIFS(猫统计!AS56,"<>")+COUNTIFS(猫统计!AY56,"<>")+COUNTIFS(猫统计!BE56,"<>")+COUNTIFS(猫统计!BK56,"<>") -> 1 | I56: 44575 | J56: 44639 | K56: =J56-I56 -> 64 | L56: 0 | M56: 6
A57: 菠萝包 | B57: 44061 | G57: =COUNTIFS(猫统计!I57,"<>")+COUNTIFS(猫统计!O57,"<>")+COUNTIFS(猫统计!U57,"<>")+COUNTIFS(猫统计!AA57,"<>")+COUNTIFS(猫统计!AG57,"<>")+COUNTIFS(猫统计!AM57,"<>")+COUNTIFS(猫统计!AS57,"<>")+COUNTIFS(猫统计!AY57,"<>")+COUNTIFS(猫统计!BE57,"<>")+COUNTIFS(猫统计!BK57,"<>") -> 1 | I57: 44393 | J57: 44456 | K57: =J57-I57 -> 63 | L57: 0 | M57: 4
A58: 香菜 | B58: 44283 | G58: =COUNTIFS(猫统计!I58,"<>")+COUNTIFS(猫统计!O58,"<>")+COUNTIFS(猫统计!U58,"<>")+COUNTIFS(猫统计!AA58,"<>")+COUNTIFS(猫统计!AG58,"<>")+COUNTIFS(猫统计!AM58,"<>")+COUNTIFS(猫统计!AS58,"<>")+COUNTIFS(猫统计!AY58,"<>")+COUNTIFS(猫统计!BE58,"<>")+COUNTIFS(猫统计!BK58,"<>") -> 1 | I58: 44607 | J58: 44674 | K58: =J58-I58 -> 67 | L58: 2 | M58: 1
A59: 好好的白拿破仑 | G59: =COUNTIFS(猫统计!I59,"<>")+COUNTIFS(猫统计!O59,"<>")+COUNTIFS(猫统计!U59,"<>")+COUNTIFS(猫统计!AA59,"<>")+COUNTIFS(猫统计!AG59,"<>")+COUNTIFS(猫统计!AM59,"<>")+COUNTIFS(猫统计!AS59,"<>")+COUNTIFS(猫统计!AY59,"<>")+COUNTIFS(猫统计!BE59,"<>")+COUNTIFS(猫统计!BK59,"<>") -> 1 | I59: 44677 | J59: 44739 | K59: =J59-I59 -> 62 | L59: 2 | M59: 2
A60: 果果 | B60: 43875 | G60: =COUNTIFS(猫统计!I60,"<>")+COUNTIFS(猫统计!O60,"<>")+COUNTIFS(猫统计!U60,"<>")+COUNTIFS(猫统计!AA60,"<>")+COUNTIFS(猫统计!AG60,"<>")+COUNTIFS(猫统计!AM60,"<>")+COUNTIFS(猫统计!AS60,"<>")+COUNTIFS(猫统计!AY60,"<>")+COUNTIFS(猫统计!BE60,"<>")+COUNTIFS(猫统计!BK60,"<>") -> 2 | I60: 44433 | J60: 44498 | K60: =J60-I60 -> 65 | L60: 2 | M60: 4 | O60: 44641 | P60: 44707 | Q60: =P60-O60 -> 66 | R60: 0 | S60: 6
A61: 月芽 | B61: 44097 | G61: =COUNTIFS(猫统计!I61,"<>")+COUNTIFS(猫统计!O61,"<>")+COUNTIFS(猫统计!U61,"<>")+COUNTIFS(猫统计!AA61,"<>")+COUNTIFS(猫统计!AG61,"<>")+COUNTIFS(猫统计!AM61,"<>")+COUNTIFS(猫统计!AS61,"<>")+COUNTIFS(猫统计!AY61,"<>")+COUNTIFS(猫统计!BE61,"<>")+COUNTIFS(猫统计!BK61,"<>") -> 2 | I61: 44366 | J61: 44430 | K61: =J61-I61 -> 64 | L61: 0 | M61: 5 | O61: 44651 | P61: 44715 | Q61: =P61-O61 -> 64 | R61: 0 | S61: 5
A62: 三文鱼 | B62: 44271 | G62: =COUNTIFS(猫统计!I62,"<>")+COUNTIFS(猫统计!O62,"<>")+COUNTIFS(猫统计!U62,"<>")+COUNTIFS(猫统计!AA62,"<>")+COUNTIFS(猫统计!AG62,"<>")+COUNTIFS(猫统计!AM62,"<>")+COUNTIFS(猫统计!AS62,"<>")+COUNTIFS(猫统计!AY62,"<>")+COUNTIFS(猫统计!BE62,"<>")+COUNTIFS(猫统计!BK62,"<>") -> 1 | I62: 44600 | J62: 44662 | K62: =J62-I62 -> 62 | L62: 3 | M62: 1
A63: 粘豆包 | B63: 44118 | G63: =COUNTIFS(猫统计!I63,"<>")+COUNTIFS(猫统计!O63,"<>")+COUNTIFS(猫统计!U63,"<>")+COUNTIFS(猫统计!AA63,"<>")+COUNTIFS(猫统计!AG63,"<>")+COUNTIFS(猫统计!AM63,"<>")+COUNTIFS(猫统计!AS63,"<>")+COUNTIFS(猫统计!AY63,"<>")+COUNTIFS(猫统计!BE63,"<>")+COUNTIFS(猫统计!BK63,"<>") -> 3 | I63: 44489 | J63: 44552 | K63: =J63-I63 -> 63 | L63: 0 | M63: 5 | O63: 44529 | P63: 44595 | Q63: =P63-O63 -> 66 | R63: 0 | S63: 4 | U63: 44677 | V63: 44740 | W63: =V63-U63 -> 63 | X63: 1 | Y63: 3
A64: 傻蛋 | B64: 44312 | G64: =COUNTIFS(猫统计!I64,"<>")+COUNTIFS(猫统计!O64,"<>")+COUNTIFS(猫统计!U64,"<>")+COUNTIFS(猫统计!AA64,"<>")+COUNTIFS(猫统计!AG64,"<>")+COUNTIFS(猫统计!AM64,"<>")+COUNTIFS(猫统计!AS64,"<>")+COUNTIFS(猫统计!AY64,"<>")+COUNTIFS(猫统计!BE64,"<>")+COUNTIFS(猫统计!BK64,"<>") -> 2 | I64: 44593 | J64: 44657 | K64: =J64-I64 -> 64 | L64: 0 | M64: 5 | O64: 44721 | P64: 44786 | Q64: =P64-O64 -> 65 | R64: 0 | S64: 5
A65: 点点 | B65: 44447 | G65: =COUNTIFS(猫统计!I65,"<>")+COUNTIFS(猫统计!O65,"<>")+COUNTIFS(猫统计!U65,"<>")+COUNTIFS(猫统计!AA65,"<>")+COUNTIFS(猫统计!AG65,"<>")+COUNTIFS(猫统计!AM65,"<>")+COUNTIFS(猫统计!AS65,"<>")+COUNTIFS(猫统计!AY65,"<>")+COUNTIFS(猫统计!BE65,"<>")+COUNTIFS(猫统计!BK65,"<>") -> 1 | I65: 44711 | J65: 44778 | K65: =J65-I65 -> 67 | L65: 1 | M65: 3
A66: 小灰灰 | B66: 43969 | G66: =COUNTIFS(猫统计!I66,"<>")+COUNTIFS(猫统计!O66,"<>")+COUNTIFS(猫统计!U66,"<>")+COUNTIFS(猫统计!AA66,"<>")+COUNTIFS(猫统计!AG66,"<>")+COUNTIFS(猫统计!AM66,"<>")+COUNTIFS(猫统计!AS66,"<>")+COUNTIFS(猫统计!AY66,"<>")+COUNTIFS(猫统计!BE66,"<>")+COUNTIFS(猫统计!BK66,"<>") -> 2 | I66: 44519 | J66: 44585 | K66: =J66-I66 -> 66 | L66: 1 | M66: 4 | O66: 44751 | P66: 44814 | Q66: =P66-O66 -> 63 | R66: 0 | S66: 5
A67: 麦田家的长毛银点 | G67: =COUNTIFS(猫统计!I67,"<>")+COUNTIFS(猫统计!O67,"<>")+COUNTIFS(猫统计!U67,"<>")+COUNTIFS(猫统计!AA67,"<>")+COUNTIFS(猫统计!AG67,"<>")+COUNTIFS(猫统计!AM67,"<>")+COUNTIFS(猫统计!AS67,"<>")+COUNTIFS(猫统计!AY67,"<>")+COUNTIFS(猫统计!BE67,"<>")+COUNTIFS(猫统计!BK67,"<>") -> 1 | I67: 44696 | J67: 44760 | K67: =J67-I67 -> 64 | L67: 3 | M67: 3
A68: 橘子 | B68: 44382 | G68: =COUNTIFS(猫统计!I68,"<>")+COUNTIFS(猫统计!O68,"<>")+COUNTIFS(猫统计!U68,"<>")+COUNTIFS(猫统计!AA68,"<>")+COUNTIFS(猫统计!AG68,"<>")+COUNTIFS(猫统计!AM68,"<>")+COUNTIFS(猫统计!AS68,"<>")+COUNTIFS(猫统计!AY68,"<>")+COUNTIFS(猫统计!BE68,"<>")+COUNTIFS(猫统计!BK68,"<>") -> 2 | I68: 44707 | J68: 44772 | K68: =J68-I68 -> 65 | L68: 1 | M68: 1 | O68: 44876 | P68: 44941 | Q68: =P68-O68 -> 65 | R68: 0 | S68: 2
A69: 花花 | B69: 43653 | G69: =COUNTIFS(猫统计!I69,"<>")+COUNTIFS(猫统计!O69,"<>")+COUNTIFS(猫统计!U69,"<>")+COUNTIFS(猫统计!AA69,"<>")+COUNTIFS(猫统计!AG69,"<>")+COUNTIFS(猫统计!AM69,"<>")+COUNTIFS(猫统计!AS69,"<>")+COUNTIFS(猫统计!AY69,"<>")+COUNTIFS(猫统计!BE69,"<>")+COUNTIFS(猫统计!BK69,"<>") -> 4 | I69: 44041 | J69: 44108 | K69: =J69-I69 -> 67 | L69: 5 | M69: 0 | O69: 44200 | P69: 44266 | Q69: =P69-O69 -> 66 | R69: 1 | S69: 2 | U69: 44342 | V69: 44406 | W69: =V69-U69 -> 64 | X69: 2 | Y69: 3 | AA69: 44916 | AB69: 44981 | AC69: =AB69-AA69 -> 65 | AD69: 3 | AE69: 2
A70: 菠萝蜜 | B70: 43969 | G70: =COUNTIFS(猫统计!I70,"<>")+COUNTIFS(猫统计!O70,"<>")+COUNTIFS(猫统计!U70,"<>")+COUNTIFS(猫统计!AA70,"<>")+COUNTIFS(猫统计!AG70,"<>")+COUNTIFS(猫统计!AM70,"<>")+COUNTIFS(猫统计!AS70,"<>")+COUNTIFS(猫统计!AY70,"<>")+COUNTIFS(猫统计!BE70,"<>")+COUNTIFS(猫统计!BK70,"<>") -> 3 | I70: 44578 | J70: 44641 | K70: =J70-I70 -> 63 | L70: 1 | M70: 4 | O70: 44700 | P70: 44764 | Q70: =P70-O70 -> 64 | R70: 3 | S70: 5 | U70: 44977 | V70: 45041 | W70: =V70-U70 -> 64 | X70: 0 | Y70: 4
A71: 小豆豆 | B71: 44595 | G71: =COUNTIFS(猫统计!I71,"<>")+COUNTIFS(猫统计!O71,"<>")+COUNTIFS(猫统计!U71,"<>")+COUNTIFS(猫统计!AA71,"<>")+COUNTIFS(猫统计!AG71,"<>")+COUNTIFS(猫统计!AM71,"<>")+COUNTIFS(猫统计!AS71,"<>")+COUNTIFS(猫统计!AY71,"<>")+COUNTIFS(猫统计!BE71,"<>")+COUNTIFS(猫统计!BK71,"<>") -> 2 | I71: 44916 | J71: 44981 | K71: =J71-I71 -> 65 | L71: 2 | M71: 1 | O71: 45003 | P71: 45069 | Q71: =P71-O71 -> 66 | R71: 1 | S71: 1
A72: 奶糖 | B72: 44774 | G72: =COUNTIFS(猫统计!I72,"<>")+COUNTIFS(猫统计!O72,"<>")+COUNTIFS(猫统计!U72,"<>")+COUNTIFS(猫统计!AA72,"<>")+COUNTIFS(猫统计!AG72,"<>")+COUNTIFS(猫统计!AM72,"<>")+COUNTIFS(猫统计!AS72,"<>")+COUNTIFS(猫统计!AY72,"<>")+COUNTIFS(猫统计!BE72,"<>")+COUNTIFS(猫统计!BK72,"<>") -> 2 | I72: 44944 | J72: 45010 | K72: =J72-I72 -> 66 | L72: 0 | M72: 2 | O72: 45077 | P72: 45144 | Q72: =P72-O72 -> 67 | R72: 0 | S72: 5
A73: 巧克力 | B73: 44715 | G73: =COUNTIFS(猫统计!I73,"<>")+COUNTIFS(猫统计!O73,"<>")+COUNTIFS(猫统计!U73,"<>")+COUNTIFS(猫统计!AA73,"<>")+COUNTIFS(猫统计!AG73,"<>")+COUNTIFS(猫统计!AM73,"<>")+COUNTIFS(猫统计!AS73,"<>")+COUNTIFS(猫统计!AY73,"<>")+COUNTIFS(猫统计!BE73,"<>")+COUNTIFS(猫统计!BK73,"<>") -> 2 | I73: 44862 | J73: 44928 | K73: =J73-I73 -> 66 | L73: 0 | M73: 5 | O73: 44984 | P73: 45050 | Q73: =P73-O73 -> 66 | R73: 6 | S73: 6
A74: 地瓜 | B74: 44473 | G74: =COUNTIFS(猫统计!I74,"<>")+COUNTIFS(猫统计!O74,"<>")+COUNTIFS(猫统计!U74,"<>")+COUNTIFS(猫统计!AA74,"<>")+COUNTIFS(猫统计!AG74,"<>")+COUNTIFS(猫统计!AM74,"<>")+COUNTIFS(猫统计!AS74,"<>")+COUNTIFS(猫统计!AY74,"<>")+COUNTIFS(猫统计!BE74,"<>")+COUNTIFS(猫统计!BK74,"<>") -> 2 | I74: 44700 | J74: 44767 | K74: =J74-I74 -> 67 | L74: 0 | M74: 2 | O74: 44940 | P74: 45007 | Q74: =P74-O74 -> 67 | R74: 0 | S74: 5
A75: 胡萝卜 | B75: 44767 | G75: =COUNTIFS(猫统计!I75,"<>")+COUNTIFS(猫统计!O75,"<>")+COUNTIFS(猫统计!U75,"<>")+COUNTIFS(猫统计!AA75,"<>")+COUNTIFS(猫统计!AG75,"<>")+COUNTIFS(猫统计!AM75,"<>")+COUNTIFS(猫统计!AS75,"<>")+COUNTIFS(猫统计!AY75,"<>")+COUNTIFS(猫统计!BE75,"<>")+COUNTIFS(猫统计!BK75,"<>") -> 1 | I75: 45107 | J75: 45178 | K75: =J75-I75 -> 71 | L75: 0 | M75: 1
A76: 小豆包 | B76: 44118 | G76: =COUNTIFS(猫统计!I76,"<>")+COUNTIFS(猫统计!O76,"<>")+COUNTIFS(猫统计!U76,"<>")+COUNTIFS(猫统计!AA76,"<>")+COUNTIFS(猫统计!AG76,"<>")+COUNTIFS(猫统计!AM76,"<>")+COUNTIFS(猫统计!AS76,"<>")+COUNTIFS(猫统计!AY76,"<>")+COUNTIFS(猫统计!BE76,"<>")+COUNTIFS(猫统计!BK76,"<>") -> 5 | I76: 44329 | J76: 44394 | K76: =J76-I76 -> 65 | L76: 1 | M76: 3 | O76: 44641 | P76: 44706 | Q76: =P76-O76 -> 65 | R76: 1 | S76: 3 | U76: 44762 | V76: 44829 | W76: =V76-U76 -> 67 | X76: 0 | Y76: 4 | AA76: 44969 | AB76: 45033 | AC76: =AB76-AA76 -> 64 | AD76: 0 | AE76: 4 | AG76: 45125 | AH76: 45190 | AI76: =AH76-AG76 -> 65 | AJ76: 0 | AK76: 3
A77: 巧克力豆 | B77: 44714 | G77: =COUNTIFS(猫统计!I77,"<>")+COUNTIFS(猫统计!O77,"<>")+COUNTIFS(猫统计!U77,"<>")+COUNTIFS(猫统计!AA77,"<>")+COUNTIFS(猫统计!AG77,"<>")+COUNTIFS(猫统计!AM77,"<>")+COUNTIFS(猫统计!AS77,"<>")+COUNTIFS(猫统计!AY77,"<>")+COUNTIFS(猫统计!BE77,"<>")+COUNTIFS(猫统计!BK77,"<>") -> 3 | I77: 44922 | J77: 44986 | K77: =J77-I77 -> 64 | L77: 1 | M77: 5 | O77: 45067 | P77: 45131 | Q77: =P77-O77 -> 64 | R77: 0 | S77: 6 | U77: 45232 | V77: 45297 | W77: =V77-U77 -> 65 | X77: 0 | Y77: 5
A78: 香瓜 | B78: 44964 | G78: =COUNTIFS(猫统计!I78,"<>")+COUNTIFS(猫统计!O78,"<>")+COUNTIFS(猫统计!U78,"<>")+COUNTIFS(猫统计!AA78,"<>")+COUNTIFS(猫统计!AG78,"<>")+COUNTIFS(猫统计!AM78,"<>")+COUNTIFS(猫统计!AS78,"<>")+COUNTIFS(猫统计!AY78,"<>")+COUNTIFS(猫统计!BE78,"<>")+COUNTIFS(猫统计!BK78,"<>") -> 1 | I78: 45231 | J78: 45296 | K78: =J78-I78 -> 65 | L78: 0 | M78: 5
A79: 香蕉 | B79: 44251 | G79: =COUNTIFS(猫统计!I79,"<>")+COUNTIFS(猫统计!O79,"<>")+COUNTIFS(猫统计!U79,"<>")+COUNTIFS(猫统计!AA79,"<>")+COUNTIFS(猫统计!AG79,"<>")+COUNTIFS(猫统计!AM79,"<>")+COUNTIFS(猫统计!AS79,"<>")+COUNTIFS(猫统计!AY79,"<>")+COUNTIFS(猫统计!BE79,"<>")+COUNTIFS(猫统计!BK79,"<>") -> 4 | I79: 44608 | J79: 44673 | K79: =J79-I79 -> 65 | L79: 5 | M79: 0 | O79: 44696 | P79: 44762 | Q79: =P79-O79 -> 66 | R79: 4 | S79: 0 | U79: 44898 | V79: 44964 | W79: =V79-U79 -> 66 | X79: 0 | Y79: 2 | AA79: 45238 | AB79: 45304 | AC79: =AB79-AA79 -> 66 | AD79: 1 | AE79: 2
A80: 皮蛋 | B80: 44657 | G80: =COUNTIFS(猫统计!I80,"<>")+COUNTIFS(猫统计!O80,"<>")+COUNTIFS(猫统计!U80,"<>")+COUNTIFS(猫统计!AA80,"<>")+COUNTIFS(猫统计!AG80,"<>")+COUNTIFS(猫统计!AM80,"<>")+COUNTIFS(猫统计!AS80,"<>")+COUNTIFS(猫统计!AY80,"<>")+COUNTIFS(猫统计!BE80,"<>")+COUNTIFS(猫统计!BK80,"<>") -> 3 | I80: 44994 | J80: 45058 | K80: =J80-I80 -> 64 | L80: 1 | M80: 0 | O80: 45181 | P80: 45246 | Q80: =P80-O80 -> 65 | R80: 0 | S80: 2 | U80: 45345 | V80: 45410 | W80: =V80-U80 -> 65 | X80: 0 | Y80: 1
A81: 鸭蛋 | B81: 44641 | G81: =COUNTIFS(猫统计!I81,"<>")+COUNTIFS(猫统计!O81,"<>")+COUNTIFS(猫统计!U81,"<>")+COUNTIFS(猫统计!AA81,"<>")+COUNTIFS(猫统计!AG81,"<>")+COUNTIFS(猫统计!AM81,"<>")+COUNTIFS(猫统计!AS81,"<>")+COUNTIFS(猫统计!AY81,"<>")+COUNTIFS(猫统计!BE81,"<>")+COUNTIFS(猫统计!BK81,"<>") -> 3 | I81: 44941 | J81: 45008 | K81: =J81-I81 -> 67 | L81: 2 | M81: 2 | O81: 45125 | P81: 45187 | Q81: =P81-O81 -> 62 | R81: 3 | S81: 1 | U81: 45360 | V81: 45426 | W81: =V81-U81 -> 66 | X81: 1 | Y81: 1
A82: 四月 | B82: 44299 | G82: =COUNTIFS(猫统计!I82,"<>")+COUNTIFS(猫统计!O82,"<>")+COUNTIFS(猫统计!U82,"<>")+COUNTIFS(猫统计!AA82,"<>")+COUNTIFS(猫统计!AG82,"<>")+COUNTIFS(猫统计!AM82,"<>")+COUNTIFS(猫统计!AS82,"<>")+COUNTIFS(猫统计!AY82,"<>")+COUNTIFS(猫统计!BE82,"<>")+COUNTIFS(猫统计!BK82,"<>") -> 5 | I82: 44650 | J82: 44715 | K82: =J82-I82 -> 65 | L82: 7 | M82: 3 | O82: 44857 | P82: 44924 | Q82: =P82-O82 -> 67 | R82: 0 | S82: 3 | U82: 45016 | V82: 45080 | W82: =V82-U82 -> 64 | X82: 3 | Y82: 4 | AA82: 45192 | AB82: 45258 | AC82: =AB82-AA82 -> 66 | AD82: 0 | AE82: 6 | AG82: 45369 | AH82: 45435 | AI82: =AH82-AG82 -> 66 | AJ82: 4 | AK82: 0
A83: 冰冰 | G83: =COUNTIFS(猫统计!I83,"<>")+COUNTIFS(猫统计!O83,"<>")+COUNTIFS(猫统计!U83,"<>")+COUNTIFS(猫统计!AA83,"<>")+COUNTIFS(猫统计!AG83,"<>")+COUNTIFS(猫统计!AM83,"<>")+COUNTIFS(猫统计!AS83,"<>")+COUNTIFS(猫统计!AY83,"<>")+COUNTIFS(猫统计!BE83,"<>")+COUNTIFS(猫统计!BK83,"<>") -> 1 | I83: 45362 | J83: 45430 | K83: =J83-I83 -> 68 | L83: 1 | M83: 3
A84: 紫薯 | B84: 45190 | G84: 1 | I84: 45390 | J84: 45456 | K84: 65 | L84: 0 | M84: 3
A85: 腿腿 | B85: 42856 | G85: =COUNTIFS(猫统计!I85,"<>")+COUNTIFS(猫统计!O85,"<>")+COUNTIFS(猫统计!U85,"<>")+COUNTIFS(猫统计!AA85,"<>")+COUNTIFS(猫统计!AG85,"<>")+COUNTIFS(猫统计!AM85,"<>")+COUNTIFS(猫统计!AS85,"<>")+COUNTIFS(猫统计!AY85,"<>")+COUNTIFS(猫统计!BE85,"<>")+COUNTIFS(猫统计!BK85,"<>") -> 5 | I85: 43922 | J85: 43988 | K85: =J85-I85 -> 66 | L85: 0 | M85: 2 | O85: 44052 | P85: 44118 | Q85: =P85-O85 -> 66 | R85: 1 | S85: 4 | U85: 44217 | V85: 44283 | W85: =V85-U85 -> 66 | X85: 1 | Y85: 5 | AA85: 44403 | AB85: 44469 | AC85: =AB85-AA85 -> 66 | AD85: 2 | AE85: 4 | AG85: 45371 | AH85: 45437 | AI85: =AH85-AG85 -> 66 | AJ85: 2 | AK85: 1
A86: MINI | B86: 45159 | G86: 1 | I86: 45444 | J86: 45509 | K86: =J86-I86 -> 65 | L86: 3 | M86: 0

Sheet 数量统计
A1: 日期 | B1: 种公数量 | C1: 种母数量 | D1: 预备种公数量 | E1: 预备种母数量 | F1: 奶猫数(3个月以下) | G1: 库存猫数 | H1: 种公数 | I1: 种母数 | J1: 其它猫数 | K1: 猫总数 | M1: 种公数量 | N1: 种母数量 | O1: 预备种公数量 | P1: 预备种母数量 | Q1: 奶猫数量(3个月以下) | R1: 库存猫数量(3个月以上) | S1: 种公数 | T1: 种母数 | U1: 其它猫数 | V1: 猫总数
A2: 44470 | B2: 3 | C2: 15 | D2: 2 | E2: 9 | F2: 57 | G2: 24 | H2: 5 | I2: 24 | J2: 81 | K2: 110 | M2: =COUNTIF(猫统计!D:D,"种公") -> 2 | N2: =COUNTIF(猫统计!D:D,"种母") -> 8 | O2: =COUNTIF(猫统计!D:D,"预备种公") -> 0 | P2: =COUNTIF(猫统计!D:D,"预备种母") -> 0 | Q2: =COUNTIF(猫统计!D:D,"奶猫") -> 11 | R2: =COUNTIF(猫统计!D:D,"库存猫")+COUNTIF(猫统计!D:D,"预售") -> 10 | S2: =M2+O2 -> 2 | T2: =N2+P2 -> 8 | U2: =Q2+R2 -> 21 | V2: =S2+T2+U2 -> 31
A3: 44501 | B3: 2 | C3: 8 | D3: 3 | E3: 8 | F3: 34 | G3: 51 | H3: 5 | I3: 16 | J3: 85 | K3: 106
A4: 44531 | B4: 2 | C4: 8 | D4: 3 | E4: 11 | F4: 28 | G4: 33 | H4: 5 | I4: 19 | J4: 61 | K4: 85
A5: 44562 | B5: 2 | C5: 8 | D5: 3 | E5: 12 | F5: 12 | G5: 46 | H5: 5 | I5: 20 | J5: 58 | K5: 83
A6: 44593 | B6: 3 | C6: 18 | D6: 2 | E6: 4 | F6: 15 | G6: 25 | H6: 5 | I6: 22 | J6: 40 | K6: 67
A7: 44621 | B7: 2 | C7: 19 | D7: 2 | E7: 2 | F7: 19 | G7: 24 | H7: 4 | I7: 21 | J7: 43 | K7: 68
A8: 44652 | B8: 2 | C8: 19 | D8: 2 | E8: 2 | F8: 21 | G8: 27 | H8: 4 | I8: 21 | J8: 48 | K8: 73
A9: 44682 | B9: 2 | C9: 17 | D9: 3 | E9: 3 | F9: 18 | G9: 12 | H9: 5 | I9: 20 | J9: 30 | K9: 55
A10: 44713 | B10: 3 | C10: 18 | D10: 2 | E10: 7 | F10: 31 | G10: 17 | H10: 5 | I10: 25 | J10: 48 | K10: 78
A11: 44743 | B11: 3 | C11: 14 | D11: 2 | E11: 7 | F11: 37 | G11: 12 | H11: 5 | I11: 21 | J11: 49 | K11: 75
A12: 44774 | B12: 3 | C12: 16 | D12: 3 | E12: 6 | F12: 21 | G12: 9 | H12: 6 | I12: 22 | J12: 30 | K12: 58
A13: 44805 | B13: 3 | C13: 15 | D13: 3 | E13: 6 | F13: 28 | G13: 12 | H13: 6 | I13: 21 | J13: 40 | K13: 67
A14: 44835 | B14: 3 | C14: 10 | D14: 3 | E14: 6 | F14: 8 | G14: 20 | H14: 6 | I14: 16 | J14: 28 | K14: 50
... A38: 45566 | B38: 2 | C38: 8 | D38: 0 | E38: 0 | F38: 11 | G38: 10 | H38: 2 | I38: 8 | J38: 21 | K38: 31
A39: 45597
A40: 45627

Sheet 繁育统计
A1: 日期 | B1: 产妇数量 | C1: 出生数 | D1: 死亡数 | E1: 存活数 | F1: 季度存活率 | G1: 季度单窝存活数
A2: 44013 | B2: =COUNTIFS(猫统计!J:J,">="&EOMONTH(A2,-1)+1,猫统计!J:J,"<="&EOMONTH(A2,0))+COUNTIFS(猫统计!P:P,">="&EOMONTH(A2,-1)+1,猫统计!P:P,"<="&EOMONTH(A2,0))+COUNTIFS(猫统计!V:V,">="&EOMONTH(A2,-1)+1,猫统计!V:V,"<="&EOMONTH(A2,0))+COUNTIFS(猫统计!AB:AB,">="&EOMONTH(A2,-1)+1,猫统计!AB:AB,"<="&EOMONTH(A2,0))+COUNTIFS(猫统计!AH:AH,">="&EOMONTH(A2,-1)+1,猫统计!AH:AH,"<="&EOMONTH(A2,0))+COUNTIFS(猫统计!AN:AN,">="&EOMONTH(A2,-1)+1,猫统计!AN:AN,"<="&EOMONTH(A2,0))+COUNTIFS(猫统计!AT:AT,">="&EOMONTH(A2,-1)+1,猫统计!AT:AT,"<="&EOMONTH(A2,0))+COUNTIFS(猫统计!AZ:AZ,">="&EOMONTH(A2,-1)+1,猫统计!AZ:AZ,"<="&EOMONTH(A2,0))+COUNTIFS(猫统计!BF:BF,">="&EOMONTH(A2,-1)+1,猫统计!BF:BF,"<="&EOMONTH(A2,0))+COUNTIFS(猫统计!BL:BL,">="&EOMONTH(A2,-1)+1,猫统计!BL:BL,"<="&EOMONTH(A2,0)) -> 1 | C2: =D2+E2 -> 4 | D2: =SUMIFS(猫统计!L:L,猫统计!J:J,">="&EOMONTH(A2,-1)+1,猫统计!J:J,"<="&EOMONTH(A2,0))+SUMIFS(猫统计!R:R,猫统计!P:P,">="&EOMONTH(A2,-1)+1,猫统计!P:P,"<="&EOMONTH(A2,0))+SUMIFS(猫统计!X:X,猫统计!V:V,">="&EOMONTH(A2,-1)+1,猫统计!V:V,"<="&EOMONTH(A2,0))+SUMIFS(猫统计!AD:AD,猫统计!AB:AB,">="&EOMONTH(A2,-1)+1,猫统计!AB:AB,"<="&EOMONTH(A2,0))+SUMIFS(猫统计!AJ:AJ,猫统计!AH:AH,">="&EOMONTH(A2,-1)+1,猫统计!AH:AH,"<="&EOMONTH(A2,0))+SUMIFS(猫统计!AP:AP,猫统计!AN:AN,">="&EOMONTH(A2,-1)+1,猫统计!AN:AN,"<="&EOMONTH(A2,0))+SUMIFS(猫统计!AV:AV,猫统计!AT:AT,">="&EOMONTH(A2,-1)+1,猫统计!AT:AT,"<="&EOMONTH(A2,0))+SUMIFS(猫统计!BB:BB,猫统计!AZ:AZ,">="&EOMONTH(A2,-1)+1,猫统计!AZ:AZ,"<="&EOMONTH(A2,0))+SUMIFS(猫统计!BH:BH,猫统计!BF:BF,">="&EOMONTH(A2,-1)+1,猫统计!BF:BF,"<="&EOMONTH(A2,0))+SUMIFS(猫统计!BN:BN,猫统计!BL:BL,">="&EOMONTH(A2,-1)+1,猫统计!BL:BL,"<="&EOMONTH(A2,0)) -> 3 | E2: =SUMIFS(猫统计!M:M,猫统计!J:J,">="&EOMONTH(A2,-1)+1,猫统计!J:J,"<="&EOMONTH(A2,0))+SUMIFS(猫统计!S:S,猫统计!P:P,">="&EOMONTH(A2,-1)+1,猫统计!P:P,"<="&EOMONTH(A2,0))+SUMIFS(猫统计!Y:Y,猫统计!V:V,">="&EOMONTH(A2,-1)+1,猫统计!V:V,"<="&EOMONTH(A2,0))+SUMIFS(猫统计!AE:AE,猫统计!AB:AB,">="&EOMONTH(A2,-1)+1,猫统计!AB:AB,"<="&EOMONTH(A2,0))+SUMIFS(猫统计!AK:AK,猫统计!AH:AH,">="&EOMONTH(A2,-1)+1,猫统计!AH:AH,"<="&EOMONTH(A2,0))+SUMIFS(猫统计!AQ:AQ,猫统计!AN:AN,">="&EOMONTH(A2,-1)+1,猫统计!AN:AN,"<="&EOMONTH(A2,0))+SUMIFS(猫统计!AW:AW,猫统计!AT:AT,">="&EOMONTH(A2,-1)+1,猫统计!AT:AT,"<="&EOMONTH(A2,0))+SUMIFS(猫统计!BC:BC,猫统计!AZ:AZ,">="&EOMONTH(A2,-1)+1,猫统计!AZ:AZ,"<="&EOMONTH(A2,0))+SUMIFS(猫统计!BI:BI,猫统计!BF:BF,">="&EOMONTH(A2,-1)+1,猫统计!BF:BF,"<="&EOMONTH(A2,0))+SUMIFS(猫统计!BO:BO,猫统计!BL:BL,">="&EOMONTH(A2,-1)+1,猫统计!BL:BL,"<="&EOMONTH(A2,0)) -> 1
A3: 44044 | B3: =COUNTIFS(猫统计!J:J,">="&EOMONTH(A3,-1)+1,猫统计!J:J,"<="&EOMONTH(A3,0))+COUNTIFS(猫统计!P:P,">="&EOMONTH(A3,-1)+1,猫统计!P:P,"<="&EOMONTH(A3,0))+COUNTIFS(猫统计!V:V,">="&EOMONTH(A3,-1)+1,猫统计!V:V,"<="&EOMONTH(A3,0))+COUNTIFS(猫统计!AB:AB,">="&EOMONTH(A3,-1)+1,猫统计!AB:AB,"<="&EOMONTH(A3,0))+COUNTIFS(猫统计!AH:AH,">="&EOMONTH(A3,-1)+1,猫统计!AH:AH,"<="&EOMONTH(A3,0))+COUNTIFS(猫统计!AN:AN,">="&EOMONTH(A3,-1)+1,猫统计!AN:AN,"<="&EOMONTH(A3,0))+COUNTIFS(猫统计!AT:AT,">="&EOMONTH(A3,-1)+1,猫统计!AT:AT,"<="&EOMONTH(A3,0))+COUNTIFS(猫统计!AZ:AZ,">="&EOMONTH(A3,-1)+1,猫统计!AZ:AZ,"<="&EOMONTH(A3,0))+COUNTIFS(猫统计!BF:BF,">="&EOMONTH(A3,-1)+1,猫统计!BF:BF,"<="&EOMONTH(A3,0))+COUNTIFS(猫统计!BL:BL,">="&EOMONTH(A3,-1)+1,猫统计!BL:BL,"<="&EOMONTH(A3,0)) -> 1 | C3: =D3+E3 -> 1 | D3: =SUMIFS(猫统计!L:L,猫统计!J:J,">="&EOMONTH(A3,-1)+1,猫统计!J:J,"<="&EOMONTH(A3,0))+SUMIFS(猫统计!R:R,猫统计!P:P,">="&EOMONTH(A3,-1)+1,猫统计!P:P,"<="&EOMONTH(A3,0))+SUMIFS(猫统计!X:X,猫统计!V:V,">="&EOMONTH(A3,-1)+1,猫统计!V:V,"<="&EOMONTH(A3,0))+SUMIFS(猫统计!AD:AD,猫统计!AB:AB,">="&EOMONTH(A3,-1)+1,猫统计!AB:AB,"<="&EOMONTH(A3,0))+SUMIFS(猫统计!AJ:AJ,猫统计!AH:AH,">="&EOMONTH(A3,-1)+1,猫统计!AH:AH,"<="&EOMONTH(A3,0))+SUMIFS(猫统计!AP:AP,猫统计!AN:AN,">="&EOMONTH(A3,-1)+1,猫统计!AN:AN,"<="&EOMONTH(A3,0))+SUMIFS(猫统计!AV:AV,猫统计!AT:AT,">="&EOMONTH(A3,-1)+1,猫统计!AT:AT,"<="&EOMONTH(A3,0))+SUMIFS(猫统计!BB:BB,猫统计!AZ:AZ,">="&EOMONTH(A3,-1)+1,猫统计!AZ:AZ,"<="&EOMONTH(A3,0))+SUMIFS(猫统计!BH:BH,猫统计!BF:BF,">="&EOMONTH(A3,-1)+1,猫统计!BF:BF,"<="&EOMONTH(A3,0))+SUMIFS(猫统计!BN:BN,猫统计!BL:BL,">="&EOMONTH(A3,-1)+1,猫统计!BL:BL,"<="&EOMONTH(A3,0)) -> 0 | E3: =SUMIFS(猫统计!M:M,猫统计!J:J,">="&EOMONTH(A3,-1)+1,猫统计!J:J,"<="&EOMONTH(A3,0))+SUMIFS(猫统计!S:S,猫统计!P:P,">="&EOMONTH(A3,-1)+1,猫统计!P:P,"<="&EOMONTH(A3,0))+SUMIFS(猫统计!Y:Y,猫统计!V:V,">="&EOMONTH(A3,-1)+1,猫统计!V:V,"<="&EOMONTH(A3,0))+SUMIFS(猫统计!AE:AE,猫统计!AB:AB,">="&EOMONTH(A3,-1)+1,猫统计!AB:AB,"<="&EOMONTH(A3,0))+SUMIFS(猫统计!AK:AK,猫统计!AH:AH,">="&EOMONTH(A3,-1)+1,猫统计!AH:AH,"<="&EOMONTH(A3,0))+SUMIFS(猫统计!AQ:AQ,猫统计!AN:AN,">="&EOMONTH(A3,-1)+1,猫统计!AN:AN,"<="&EOMONTH(A3,0))+SUMIFS(猫统计!AW:AW,猫统计!AT:AT,">="&EOMONTH(A3,-1)+1,猫统计!AT:AT,"<="&EOMONTH(A3,0))+SUMIFS(猫统计!BC:BC,猫统计!AZ:AZ,">="&EOMONTH(A3,-1)+1,猫统计!AZ:AZ,"<="&EOMONTH(A3,0))+SUMIFS(猫统计!BI:BI,猫统计!BF:BF,">="&EOMONTH(A3,-1)+1,猫统计!BF:BF,"<="&EOMONTH(A3,0))+SUMIFS(猫统计!BO:BO,猫统计!BL:BL,">="&EOMONTH(A3,-1)+1,猫统计!BL:BL,"<="&EOMONTH(A3,0)) -> 1
A4: 44075 | B4: =COUNTIFS(猫统计!J:J,">="&EOMONTH(A4,-1)+1,猫统计!J:J,"<="&EOMONTH(A4,0))+COUNTIFS(猫统计!P:P,">="&EOMONTH(A4,-1)+1,猫统计!P:P,"<="&EOMONTH(A4,0))+COUNTIFS(猫统计!V:V,">="&EOMONTH(A4,-1)+1,猫统计!V:V,"<="&EOMONTH(A4,0))+COUNTIFS(猫统计!AB:AB,">="&EOMONTH(A4,-1)+1,猫统计!AB:AB,"<="&EOMONTH(A4,0))+COUNTIFS(猫统计!AH:AH,">="&EOMONTH(A4,-1)+1,猫统计!AH:AH,"<="&EOMONTH(A4,0))+COUNTIFS(猫统计!AN:AN,">="&EOMONTH(A4,-1)+1,猫统计!AN:AN,"<="&EOMONTH(A4,0))+COUNTIFS(猫统计!AT:AT,">="&EOMONTH(A4,-1)+1,猫统计!AT:AT,"<="&EOMONTH(A4,0))+COUNTIFS(猫统计!AZ:AZ,">="&EOMONTH(A4,-1)+1,猫统计!AZ:AZ,"<="&EOMONTH(A4,0))+COUNTIFS(猫统计!BF:BF,">="&EOMONTH(A4,-1)+1,猫统计!BF:BF,"<="&EOMONTH(A4,0))+COUNTIFS(猫统计!BL:BL,">="&EOMONTH(A4,-1)+1,猫统计!BL:BL,"<="&EOMONTH(A4,0)) -> 1 | C4: =D4+E4 -> 3 | D4: =SUMIFS(猫统计!L:L,猫统计!J:J,">="&EOMONTH(A4,-1)+1,猫统计!J:J,"<="&EOMONTH(A4,0))+SUMIFS(猫统计!R:R,猫统计!P:P,">="&EOMONTH(A4,-1)+1,猫统计!P:P,"<="&EOMONTH(A4,0))+SUMIFS(猫统计!X:X,猫统计!V:V,">="&EOMONTH(A4,-1)+1,猫统计!V:V,"<="&EOMONTH(A4,0))+SUMIFS(猫统计!AD:AD,猫统计!AB:AB,">="&EOMONTH(A4,-1)+1,猫统计!AB:AB,"<="&EOMONTH(A4,0))+SUMIFS(猫统计!AJ:AJ,猫统计!AH:AH,">="&EOMONTH(A4,-1)+1,猫统计!AH:AH,"<="&EOMONTH(A4,0))+SUMIFS(猫统计!AP:AP,猫统计!AN:AN,">="&EOMONTH(A4,-1)+1,猫统计!AN:AN,"<="&EOMONTH(A4,0))+SUMIFS(猫统计!AV:AV,猫统计!AT:AT,">="&EOMONTH(A4,-1)+1,猫统计!AT:AT,"<="&EOMONTH(A4,0))+SUMIFS(猫统计!BB:BB,猫统计!AZ:AZ,">="&EOMONTH(A4,-1)+1,猫统计!AZ:AZ,"<="&EOMONTH(A4,0))+SUMIFS(猫统计!BH:BH,猫统计!BF:BF,">="&EOMONTH(A4,-1)+1,猫统计!BF:BF,"<="&EOMONTH(A4,0))+SUMIFS(猫统计!BN:BN,猫统计!BL:BL,">="&EOMONTH(A4,-1)+1,猫统计!BL:BL,"<="&EOMONTH(A4,0)) -> 0 | E4: =SUMIFS(猫统计!M:M,猫统计!J:J,">="&EOMONTH(A4,-1)+1,猫统计!J:J,"<="&EOMONTH(A4,0))+SUMIFS(猫统计!S:S,猫统计!P:P,">="&EOMONTH(A4,-1)+1,猫统计!P:P,"<="&EOMONTH(A4,0))+SUMIFS(猫统计!Y:Y,猫统计!V:V,">="&EOMONTH(A4,-1)+1,猫统计!V:V,"<="&EOMONTH(A4,0))+SUMIFS(猫统计!AE:AE,猫统计!AB:AB,">="&EOMONTH(A4,-1)+1,猫统计!AB:AB,"<="&EOMONTH(A4,0))+SUMIFS(猫统计!AK:AK,猫统计!AH:AH,">="&EOMONTH(A4,-1)+1,猫统计!AH:AH,"<="&EOMONTH(A4,0))+SUMIFS(猫统计!AQ:AQ,猫统计!AN:AN,">="&EOMONTH(A4,-1)+1,猫统计!AN:AN,"<="&EOMONTH(A4,0))+SUMIFS(猫统计!AW:AW,猫统计!AT:AT,">="&EOMONTH(A4,-1)+1,猫统计!AT:AT,"<="&EOMONTH(A4,0))+SUMIFS(猫统计!BC:BC,猫统计!AZ:AZ,">="&EOMONTH(A4,-1)+1,猫统计!AZ:AZ,"<="&EOMONTH(A4,0))+SUMIFS(猫统计!BI:BI,猫统计!BF:BF,">="&EOMONTH(A4,-1)+1,猫统计!BF:BF,"<="&EOMONTH(A4,0))+SUMIFS(猫统计!BO:BO,猫统计!BL:BL,">="&EOMONTH(A4,-1)+1,猫统计!BL:BL,"<="&EOMONTH(A4,0)) -> 3 | F4: =(E2+E3+E4)/(C2+C3+C4) -> 0.625 | G4: =(E2+E3+E4)/(B2+B3+B4) -> 1.6666667
A5: 44105 | B5: =COUNTIFS(猫统计!J:J,">="&EOMONTH(A5,-1)+1,猫统计!J:J,"<="&EOMONTH(A5,0))+COUNTIFS(猫统计!P:P,">="&EOMONTH(A5,-1)+1,猫统计!P:P,"<="&EOMONTH(A5,0))+COUNTIFS(猫统计!V:V,">="&EOMONTH(A5,-1)+1,猫统计!V:V,"<="&EOMONTH(A5,0))+COUNTIFS(猫统计!AB:AB,">="&EOMONTH(A5,-1)+1,猫统计!AB:AB,"<="&EOMONTH(A5,0))+COUNTIFS(猫统计!AH:AH,">="&EOMONTH(A5,-1)+1,猫统计!AH:AH,"<="&EOMONTH(A5,0))+COUNTIFS(猫统计!AN:AN,">="&EOMONTH(A5,-1)+1,猫统计!AN:AN,"<="&EOMONTH(A5,0))+COUNTIFS(猫统计!AT:AT,">="&EOMONTH(A5,-1)+1,猫统计!AT:AT,"<="&EOMONTH(A5,0))+COUNTIFS(猫统计!AZ:AZ,">="&EOMONTH(A5,-1)+1,猫统计!AZ:AZ,"<="&EOMONTH(A5,0))+COUNTIFS(猫统计!BF:BF,">="&EOMONTH(A5,-1)+1,猫统计!BF:BF,"<="&EOMONTH(A5,0))+COUNTIFS(猫统计!BL:BL,">="&EOMONTH(A5,-1)+1,猫统计!BL:BL,"<="&EOMONTH(A5,0)) -> 3 | C5: =D5+E5 -> 13 | D5: =SUMIFS(猫统计!L:L,猫统计!J:J,">="&EOMONTH(A5,-1)+1,猫统计!J:J,"<="&EOMONTH(A5,0))+SUMIFS(猫统计!R:R,猫统计!P:P,">="&EOMONTH(A5,-1)+1,猫统计!P:P,"<="&EOMONTH(A5,0))+SUMIFS(猫统计!X:X,猫统计!V:V,">="&EOMONTH(A5,-1)+1,猫统计!V:V,"<="&EOMONTH(A5,0))+SUMIFS(猫统计!AD:AD,猫统计!AB:AB,">="&EOMONTH(A5,-1)+1,猫统计!AB:AB,"<="&EOMONTH(A5,0))+SUMIFS(猫统计!AJ:AJ,猫统计!AH:AH,">="&EOMONTH(A5,-1)+1,猫统计!AH:AH,"<="&EOMONTH(A5,0))+SUMIFS(猫统计!AP:AP,猫统计!AN:AN,">="&EOMONTH(A5,-1)+1,猫统计!AN:AN,"<="&EOMONTH(A5,0))+SUMIFS(猫统计!AV:AV,猫统计!AT:AT,">="&EOMONTH(A5,-1)+1,猫统计!AT:AT,"<="&EOMONTH(A5,0))+SUMIFS(猫统计!BB:BB,猫统计!AZ:AZ,">="&EOMONTH(A5,-1)+1,猫统计!AZ:AZ,"<="&EOMONTH(A5,0))+SUMIFS(猫统计!BH:BH,猫统计!BF:BF,">="&EOMONTH(A5,-1)+1,猫统计!BF:BF,"<="&EOMONTH(A5,0))+SUMIFS(猫统计!BN:BN,猫统计!BL:BL,">="&EOMONTH(A5,-1)+1,猫统计!BL:BL,"<="&EOMONTH(A5,0)) -> 6 | E5: =SUMIFS(猫统计!M:M,猫统计!J:J,">="&EOMONTH(A5,-1)+1,猫统计!J:J,"<="&EOMONTH(A5,0))+SUMIFS(猫统计!S:S,猫统计!P:P,">="&EOMONTH(A5,-1)+1,猫统计!P:P,"<="&EOMONTH(A5,0))+SUMIFS(猫统计!Y:Y,猫统计!V:V,">="&EOMONTH(A5,-1)+1,猫统计!V:V,"<="&EOMONTH(A5,0))+SUMIFS(猫统计!AE:AE,猫统计!AB:AB,">="&EOMONTH(A5,-1)+1,猫统计!AB:AB,"<="&EOMONTH(A5,0))+SUMIFS(猫统计!AK:AK,猫统计!AH:AH,">="&EOMONTH(A5,-1)+1,猫统计!AH:AH,"<="&EOMONTH(A5,0))+SUMIFS(猫统计!AQ:AQ,猫统计!AN:AN,">="&EOMONTH(A5,-1)+1,猫统计!AN:AN,"<="&EOMONTH(A5,0))+SUMIFS(猫统计!AW:AW,猫统计!AT:AT,">="&EOMONTH(A5,-1)+1,猫统计!AT:AT,"<="&EOMONTH(A5,0))+SUMIFS(猫统计!BC:BC,猫统计!AZ:AZ,">="&EOMONTH(A5,-1)+1,猫统计!AZ:AZ,"<="&EOMONTH(A5,0))+SUMIFS(猫统计!BI:BI,猫统计!BF:BF,">="&EOMONTH(A5,-1)+1,猫统计!BF:BF,"<="&EOMONTH(A5,0))+SUMIFS(猫统计!BO:BO,猫统计!BL:BL,">="&EOMONTH(A5,-1)+1,猫统计!BL:BL,"<="&EOMONTH(A5,0)) -> 7
A6: 44136 | B6: =COUNTIFS(猫统计!J:J,">="&EOMONTH(A6,-1)+1,猫统计!J:J,"<="&EOMONTH(A6,0))+COUNTIFS(猫统计!P:P,">="&EOMONTH(A6,-1)+1,猫统计!P:P,"<="&EOMONTH(A6,0))+COUNTIFS(猫统计!V:V,">="&EOMONTH(A6,-1)+1,猫统计!V:V,"<="&EOMONTH(A6,0))+COUNTIFS(猫统计!AB:AB,">="&EOMONTH(A6,-1)+1,猫统计!AB:AB,"<="&EOMONTH(A6,0))+COUNTIFS(猫统计!AH:AH,">="&EOMONTH(A6,-1)+1,猫统计!AH:AH,"<="&EOMONTH(A6,0))+COUNTIFS(猫统计!AN:AN,">="&EOMONTH(A6,-1)+1,猫统计!AN:AN,"<="&EOMONTH(A6,0))+COUNTIFS(猫统计!AT:AT,">="&EOMONTH(A6,-1)+1,猫统计!AT:AT,"<="&EOMONTH(A6,0))+COUNTIFS(猫统计!AZ:AZ,">="&EOMONTH(A6,-1)+1,猫统计!AZ:AZ,"<="&EOMONTH(A6,0))+COUNTIFS(猫统计!BF:BF,">="&EOMONTH(A6,-1)+1,猫统计!BF:BF,"<="&EOMONTH(A6,0))+COUNTIFS(猫统计!BL:BL,">="&EOMONTH(A6,-1)+1,猫统计!BL:BL,"<="&EOMONTH(A6,0)) -> 0 | C6: =D6+E6 -> 0 | D6: =SUMIFS(猫统计!L:L,猫统计!J:J,">="&EOMONTH(A6,-1)+1,猫统计!J:J,"<="&EOMONTH(A6,0))+SUMIFS(猫统计!R:R,猫统计!P:P,">="&EOMONTH(A6,-1)+1,猫统计!P:P,"<="&EOMONTH(A6,0))+SUMIFS(猫统计!X:X,猫统计!V:V,">="&EOMONTH(A6,-1)+1,猫统计!V:V,"<="&EOMONTH(A6,0))+SUMIFS(猫统计!AD:AD,猫统计!AB:AB,">="&EOMONTH(A6,-1)+1,猫统计!AB:AB,"<="&EOMONTH(A6,0))+SUMIFS(猫统计!AJ:AJ,猫统计!AH:AH,">="&EOMONTH(A6,-1)+1,猫统计!AH:AH,"<="&EOMONTH(A6,0))+SUMIFS(猫统计!AP:AP,猫统计!AN:AN,">="&EOMONTH(A6,-1)+1,猫统计!AN:AN,"<="&EOMONTH(A6,0))+SUMIFS(猫统计!AV:AV,猫统计!AT:AT,">="&EOMONTH(A6,-1)+1,猫统计!AT:AT,"<="&EOMONTH(A6,0))+SUMIFS(猫统计!BB:BB,猫统计!AZ:AZ,">="&EOMONTH(A6,-1)+1,猫统计!AZ:AZ,"<="&EOMONTH(A6,0))+SUMIFS(猫统计!BH:BH,猫统计!BF:BF,">="&EOMONTH(A6,-1)+1,猫统计!BF:BF,"<="&EOMONTH(A6,0))+SUMIFS(猫统计!BN:BN,猫统计!BL:BL,">="&EOMONTH(A6,-1)+1,猫统计!BL:BL,"<="&EOMONTH(A6,0)) -> 0 | E6: =SUMIFS(猫统计!M:M,猫统计!J:J,">="&EOMONTH(A6,-1)+1,猫统计!J:J,"<="&EOMONTH(A6,0))+SUMIFS(猫统计!S:S,猫统计!P:P,">="&EOMONTH(A6,-1)+1,猫统计!P:P,"<="&EOMONTH(A6,0))+SUMIFS(猫统计!Y:Y,猫统计!V:V,">="&EOMONTH(A6,-1)+1,猫统计!V:V,"<="&EOMONTH(A6,0))+SUMIFS(猫统计!AE:AE,猫统计!AB:AB,">="&EOMONTH(A6,-1)+1,猫统计!AB:AB,"<="&EOMONTH(A6,0))+SUMIFS(猫统计!AK:AK,猫统计!AH:AH,">="&EOMONTH(A6,-1)+1,猫统计!AH:AH,"<="&EOMONTH(A6,0))+SUMIFS(猫统计!AQ:AQ,猫统计!AN:AN,">="&EOMONTH(A6,-1)+1,猫统计!AN:AN,"<="&EOMONTH(A6,0))+SUMIFS(猫统计!AW:AW,猫统计!AT:AT,">="&EOMONTH(A6,-1)+1,猫统计!AT:AT,"<="&EOMONTH(A6,0))+SUMIFS(猫统计!BC:BC,猫统计!AZ:AZ,">="&EOMONTH(A6,-1)+1,猫统计!AZ:AZ,"<="&EOMONTH(A6,0))+SUMIFS(猫统计!BI:BI,猫统计!BF:BF,">="&EOMONTH(A6,-1)+1,猫统计!BF:BF,"<="&EOMONTH(A6,0))+SUMIFS(猫统计!BO:BO,猫统计!BL:BL,">="&EOMONTH(A6,-1)+1,猫统计!BL:BL,"<="&EOMONTH(A6,0)) -> 0
A7: 44166 | B7: =COUNTIFS(猫统计!J:J,">="&EOMONTH(A7,-1)+1,猫统计!J:J,"<="&EOMONTH(A7,0))+COUNTIFS(猫统计!P:P,">="&EOMONTH(A7,-1)+1,猫统计!P:P,"<="&EOMONTH(A7,0))+COUNTIFS(猫统计!V:V,">="&EOMONTH(A7,-1)+1,猫统计!V:V,"<="&EOMONTH(A7,0))+COUNTIFS(猫统计!AB:AB,">="&EOMONTH(A7,-1)+1,猫统计!AB:AB,"<="&EOMONTH(A7,0))+COUNTIFS(猫统计!AH:AH,">="&EOMONTH(A7,-1)+1,猫统计!AH:AH,"<="&EOMONTH(A7,0))+COUNTIFS(猫统计!AN:AN,">="&EOMONTH(A7,-1)+1,猫统计!AN:AN,"<="&EOMONTH(A7,0))+COUNTIFS(猫统计!AT:AT,">="&EOMONTH(A7,-1)+1,猫统计!AT:AT,"<="&EOMONTH(A7,0))+COUNTIFS(猫统计!AZ:AZ,">="&EOMONTH(A7,-1)+1,猫统计!AZ:AZ,"<="&EOMONTH(A7,0))+COUNTIFS(猫统计!BF:BF,">="&EOMONTH(A7,-1)+1,猫统计!BF:BF,"<="&EOMONTH(A7,0))+COUNTIFS(猫统计!BL:BL,">="&EOMONTH(A7,-1)+1,猫统计!BL:BL,"<="&EOMONTH(A7,0)) -> 0 | C7: =D7+E7 -> 0 | D7: =SUMIFS(猫统计!L:L,猫统计!J:J,">="&EOMONTH(A7,-1)+1,猫统计!J:J,"<="&EOMONTH(A7,0))+SUMIFS(猫统计!R:R,猫统计!P:P,">="&EOMONTH(A7,-1)+1,猫统计!P:P,"<="&EOMONTH(A7,0))+SUMIFS(猫统计!X:X,猫统计!V:V,">="&EOMONTH(A7,-1)+1,猫统计!V:V,"<="&EOMONTH(A7,0))+SUMIFS(猫统计!AD:AD,猫统计!AB:AB,">="&EOMONTH(A7,-1)+1,猫统计!AB:AB,"<="&EOMONTH(A7,0))+SUMIFS(猫统计!AJ:AJ,猫统计!AH:AH,">="&EOMONTH(A7,-1)+1,猫统计!AH:AH,"<="&EOMONTH(A7,0))+SUMIFS(猫统计!AP:AP,猫统计!AN:AN,">="&EOMONTH(A7,-1)+1,猫统计!AN:AN,"<="&EOMONTH(A7,0))+SUMIFS(猫统计!AV:AV,猫统计!AT:AT,">="&EOMONTH(A7,-1)+1,猫统计!AT:AT,"<="&EOMONTH(A7,0))+SUMIFS(猫统计!BB:BB,猫统计!AZ:AZ,">="&EOMONTH(A7,-1)+1,猫统计!AZ:AZ,"<="&EOMONTH(A7,0))+SUMIFS(猫统计!BH:BH,猫统计!BF:BF,">="&EOMONTH(A7,-1)+1,猫统计!BF:BF,"<="&EOMONTH(A7,0))+SUMIFS(猫统计!BN:BN,猫统计!BL:BL,">="&EOMONTH(A7,-1)+1,猫统计!BL:BL,"<="&EOMONTH(A7,0)) -> 0 | E7: =SUMIFS(猫统计!M:M,猫统计!J:J,">="&EOMONTH(A7,-1)+1,猫统计!J:J,"<="&EOMONTH(A7,0))+SUMIFS(猫统计!S:S,猫统计!P:P,">="&EOMONTH(A7,-1)+1,猫统计!P:P,"<="&EOMONTH(A7,0))+SUMIFS(猫统计!Y:Y,猫统计!V:V,">="&EOMONTH(A7,-1)+1,猫统计!V:V,"<="&EOMONTH(A7,0))+SUMIFS(猫统计!AE:AE,猫统计!AB:AB,">="&EOMONTH(A7,-1)+1,猫统计!AB:AB,"<="&EOMONTH(A7,0))+SUMIFS(猫统计!AK:AK,猫统计!AH:AH,">="&EOMONTH(A7,-1)+1,猫统计!AH:AH,"<="&EOMONTH(A7,0))+SUMIFS(猫统计!AQ:AQ,猫统计!AN:AN,">="&EOMONTH(A7,-1)+1,猫统计!AN:AN,"<="&EOMONTH(A7,0))+SUMIFS(猫统计!AW:AW,猫统计!AT:AT,">="&EOMONTH(A7,-1)+1,猫统计!AT:AT,"<="&EOMONTH(A7,0))+SUMIFS(猫统计!BC:BC,猫统计!AZ:AZ,">="&EOMONTH(A7,-1)+1,猫统计!AZ:AZ,"<="&EOMONTH(A7,0))+SUMIFS(猫统计!BI:BI,猫统计!BF:BF,">="&EOMONTH(A7,-1)+1,猫统计!BF:BF,"<="&EOMONTH(A7,0))+SUMIFS(猫统计!BO:BO,猫统计!BL:BL,">="&EOMONTH(A7,-1)+1,猫统计!BL:BL,"<="&EOMONTH(A7,0)) -> 0 | F7: =(E5+E6+E7)/(C5+C6+C7) -> 0.53846154 | G7: =(E5+E6+E7)/(B5+B6+B7) -> 2.3333333
A8: 44197 | B8: =COUNTIFS(猫统计!J:J,">="&EOMONTH(A8,-1)+1,猫统计!J:J,"<="&EOMONTH(A8,0))+COUNTIFS(猫统计!P:P,">="&EOMONTH(A8,-1)+1,猫统计!P:P,"<="&EOMONTH(A8,0))+COUNTIFS(猫统计!V:V,">="&EOMONTH(A8,-1)+1,猫统计!V:V,"<="&EOMONTH(A8,0))+COUNTIFS(猫统计!AB:AB,">="&EOMONTH(A8,-1)+1,猫统计!AB:AB,"<="&EOMONTH(A8,0))+COUNTIFS(猫统计!AH:AH,">="&EOMONTH(A8,-1)+1,猫统计!AH:AH,"<="&EOMONTH(A8,0))+COUNTIFS(猫统计!AN:AN,">="&EOMONTH(A8,-1)+1,猫统计!AN:AN,"<="&EOMONTH(A8,0))+COUNTIFS(猫统计!AT:AT,">="&EOMONTH(A8,-1)+1,猫统计!AT:AT,"<="&EOMONTH(A8,0))+COUNTIFS(猫统计!AZ:AZ,">="&EOMONTH(A8,-1)+1,猫统计!AZ:AZ,"<="&EOMONTH(A8,0))+COUNTIFS(猫统计!BF:BF,">="&EOMONTH(A8,-1)+1,猫统计!BF:BF,"<="&EOMONTH(A8,0))+COUNTIFS(猫统计!BL:BL,">="&EOMONTH(A8,-1)+1,猫统计!BL:BL,"<="&EOMONTH(A8,0)) -> 3 | C8: =D8+E8 -> 11 | D8: =SUMIFS(猫统计!L:L,猫统计!J:J,">="&EOMONTH(A8,-1)+1,猫统计!J:J,"<="&EOMONTH(A8,0))+SUMIFS(猫统计!R:R,猫统计!P:P,">="&EOMONTH(A8,-1)+1,猫统计!P:P,"<="&EOMONTH(A8,0))+SUMIFS(猫统计!X:X,猫统计!V:V,">="&EOMONTH(A8,-1)+1,猫统计!V:V,"<="&EOMONTH(A8,0))+SUMIFS(猫统计!AD:AD,猫统计!AB:AB,">="&EOMONTH(A8,-1)+1,猫统计!AB:AB,"<="&EOMONTH(A8,0))+SUMIFS(猫统计!AJ:AJ,猫统计!AH:AH,">="&EOMONTH(A8,-1)+1,猫统计!AH:AH,"<="&EOMONTH(A8,0))+SUMIFS(猫统计!AP:AP,猫统计!AN:AN,">="&EOMONTH(A8,-1)+1,猫统计!AN:AN,"<="&EOMONTH(A8,0))+SUMIFS(猫统计!AV:AV,猫统计!AT:AT,">="&EOMONTH(A8,-1)+1,猫统计!AT:AT,"<="&EOMONTH(A8,0))+SUMIFS(猫统计!BB:BB,猫统计!AZ:AZ,">="&EOMONTH(A8,-1)+1,猫统计!AZ:AZ,"<="&EOMONTH(A8,0))+SUMIFS(猫统计!BH:BH,猫统计!BF:BF,">="&EOMONTH(A8,-1)+1,猫统计!BF:BF,"<="&EOMONTH(A8,0))+SUMIFS(猫统计!BN:BN,猫统计!BL:BL,">="&EOMONTH(A8,-1)+1,猫统计!BL:BL,"<="&EOMONTH(A8,0)) -> 2 | E8: =SUMIFS(猫统计!M:M,猫统计!J:J,">="&EOMONTH(A8,-1)+1,猫统计!J:J,"<="&EOMONTH(A8,0))+SUMIFS(猫统计!S:S,猫统计!P:P,">="&EOMONTH(A8,-1)+1,猫统计!P:P,"<="&EOMONTH(A8,0))+SUMIFS(猫统计!Y:Y,猫统计!V:V,">="&EOMONTH(A8,-1)+1,猫统计!V:V,"<="&EOMONTH(A8,0))+SUMIFS(猫统计!AE:AE,猫统计!AB:AB,">="&EOMONTH(A8,-1)+1,猫统计!AB:AB,"<="&EOMONTH(A8,0))+SUMIFS(猫统计!AK:AK,猫统计!AH:AH,">="&EOMONTH(A8,-1)+1,猫统计!AH:AH,"<="&EOMONTH(A8,0))+SUMIFS(猫统计!AQ:AQ,猫统计!AN:AN,">="&EOMONTH(A8,-1)+1,猫统计!AN:AN,"<="&EOMONTH(A8,0))+SUMIFS(猫统计!AW:AW,猫统计!AT:AT,">="&EOMONTH(A8,-1)+1,猫统计!AT:AT,"<="&EOMONTH(A8,0))+SUMIFS(猫统计!BC:BC,猫统计!AZ:AZ,">="&EOMONTH(A8,-1)+1,猫统计!AZ:AZ,"<="&EOMONTH(A8,0))+SUMIFS(猫统计!BI:BI,猫统计!BF:BF,">="&EOMONTH(A8,-1)+1,猫统计!BF:BF,"<="&EOMONTH(A8,0))+SUMIFS(猫统计!BO:BO,猫统计!BL:BL,">="&EOMONTH(A8,-1)+1,猫统计!BL:BL,"<="&EOMONTH(A8,0)) -> 9
A9: 44228 | B9: =COUNTIFS(猫统计!J:J,">="&EOMONTH(A9,-1)+1,猫统计!J:J,"<="&EOMONTH(A9,0))+COUNTIFS(猫统计!P:P,">="&EOMONTH(A9,-1)+1,猫统计!P:P,"<="&EOMONTH(A9,0))+COUNTIFS(猫统计!V:V,">="&EOMONTH(A9,-1)+1,猫统计!V:V,"<="&EOMONTH(A9,0))+COUNTIFS(猫统计!AB:AB,">="&EOMONTH(A9,-1)+1,猫统计!AB:AB,"<="&EOMONTH(A9,0))+COUNTIFS(猫统计!AH:AH,">="&EOMONTH(A9,-1)+1,猫统计!AH:AH,"<="&EOMONTH(A9,0))+COUNTIFS(猫统计!AN:AN,">="&EOMONTH(A9,-1)+1,猫统计!AN:AN,"<="&EOMONTH(A9,0))+COUNTIFS(猫统计!AT:AT,">="&EOMONTH(A9,-1)+1,猫统计!AT:AT,"<="&EOMONTH(A9,0))+COUNTIFS(猫统计!AZ:AZ,">="&EOMONTH(A9,-1)+1,猫统计!AZ:AZ,"<="&EOMONTH(A9,0))+COUNTIFS(猫统计!BF:BF,">="&EOMONTH(A9,-1)+1,猫统计!BF:BF,"<="&EOMONTH(A9,0))+COUNTIFS(猫统计!BL:BL,">="&EOMONTH(A9,-1)+1,猫统计!BL:BL,"<="&EOMONTH(A9,0)) -> 2 | C9: =D9+E9 -> 7 | D9: =SUMIFS(猫统计!L:L,猫统计!J:J,">="&EOMONTH(A9,-1)+1,猫统计!J:J,"<="&EOMONTH(A9,0))+SUMIFS(猫统计!R:R,猫统计!P:P,">="&EOMONTH(A9,-1)+1,猫统计!P:P,"<="&EOMONTH(A9,0))+SUMIFS(猫统计!X:X,猫统计!V:V,">="&EOMONTH(A9,-1)+1,猫统计!V:V,"<="&EOMONTH(A9,0))+SUMIFS(猫统计!AD:AD,猫统计!AB:AB,">="&EOMONTH(A9,-1)+1,猫统计!AB:AB,"<="&EOMONTH(A9,0))+SUMIFS(猫统计!AJ:AJ,猫统计!AH:AH,">="&EOMONTH(A9,-1)+1,猫统计!AH:AH,"<="&EOMONTH(A9,0))+SUMIFS(猫统计!AP:AP,猫统计!AN:AN,">="&EOMONTH(A9,-1)+1,猫统计!AN:AN,"<="&EOMONTH(A9,0))+SUMIFS(猫统计!AV:AV,猫统计!AT:AT,">="&EOMONTH(A9,-1)+1,猫统计!AT:AT,"<="&EOMONTH(A9,0))+SUMIFS(猫统计!BB:BB,猫统计!AZ:AZ,">="&EOMONTH(A9,-1)+1,猫统计!AZ:AZ,"<="&EOMONTH(A9,0))+SUMIFS(猫统计!BH:BH,猫统计!BF:BF,">="&EOMONTH(A9,-1)+1,猫统计!BF:BF,"<="&EOMONTH(A9,0))+SUMIFS(猫统计!BN:BN,猫统计!BL:BL,">="&EOMONTH(A9,-1)+1,猫统计!BL:BL,"<="&EOMONTH(A9,0)) -> 0 | E9: =SUMIFS(猫统计!M:M,猫统计!J:J,">="&EOMONTH(A9,-1)+1,猫统计!J:J,"<="&EOMONTH(A9,0))+SUMIFS(猫统计!S:S,猫统计!P:P,">="&EOMONTH(A9,-1)+1,猫统计!P:P,"<="&EOMONTH(A9,0))+SUMIFS(猫统计!Y:Y,猫统计!V:V,">="&EOMONTH(A9,-1)+1,猫统计!V:V,"<="&EOMONTH(A9,0))+SUMIFS(猫统计!AE:AE,猫统计!AB:AB,">="&EOMONTH(A9,-1)+1,猫统计!AB:AB,"<="&EOMONTH(A9,0))+SUMIFS(猫统计!AK:AK,猫统计!AH:AH,">="&EOMONTH(A9,-1)+1,猫统计!AH:AH,"<="&EOMONTH(A9,0))+SUMIFS(猫统计!AQ:AQ,猫统计!AN:AN,">="&EOMONTH(A9,-1)+1,猫统计!AN:AN,"<="&EOMONTH(A9,0))+SUMIFS(猫统计!AW:AW,猫统计!AT:AT,">="&EOMONTH(A9,-1)+1,猫统计!AT:AT,"<="&EOMONTH(A9,0))+SUMIFS(猫统计!BC:BC,猫统计!AZ:AZ,">="&EOMONTH(A9,-1)+1,猫统计!AZ:AZ,"<="&EOMONTH(A9,0))+SUMIFS(猫统计!BI:BI,猫统计!BF:BF,">="&EOMONTH(A9,-1)+1,猫统计!BF:BF,"<="&EOMONTH(A9,0))+SUMIFS(猫统计!BO:BO,猫统计!BL:BL,">="&EOMONTH(A9,-1)+1,猫统计!BL:BL,"<="&EOMONTH(A9,0)) -> 7
A10: 44256 | B10: =COUNTIFS(猫统计!J:J,">="&EOMONTH(A10,-1)+1,猫统计!J:J,"<="&EOMONTH(A10,0))+COUNTIFS(猫统计!P:P,">="&EOMONTH(A10,-1)+1,猫统计!P:P,"<="&EOMONTH(A10,0))+COUNTIFS(猫统计!V:V,">="&EOMONTH(A10,-1)+1,猫统计!V:V,"<="&EOMONTH(A10,0))+COUNTIFS(猫统计!AB:AB,">="&EOMONTH(A10,-1)+1,猫统计!AB:AB,"<="&EOMONTH(A10,0))+COUNTIFS(猫统计!AH:AH,">="&EOMONTH(A10,-1)+1,猫统计!AH:AH,"<="&EOMONTH(A10,0))+COUNTIFS(猫统计!AN:AN,">="&EOMONTH(A10,-1)+1,猫统计!AN:AN,"<="&EOMONTH(A10,0))+COUNTIFS(猫统计!AT:AT,">="&EOMONTH(A10,-1)+1,猫统计!AT:AT,"<="&EOMONTH(A10,0))+COUNTIFS(猫统计!AZ:AZ,">="&EOMONTH(A10,-1)+1,猫统计!AZ:AZ,"<="&EOMONTH(A10,0))+COUNTIFS(猫统计!BF:BF,">="&EOMONTH(A10,-1)+1,猫统计!BF:BF,"<="&EOMONTH(A10,0))+COUNTIFS(猫统计!BL:BL,">="&EOMONTH(A10,-1)+1,猫统计!BL:BL,"<="&EOMONTH(A10,0)) -> 8 | C10: =D10+E10 -> 33 | D10: =SUMIFS(猫统计!L:L,猫统计!J:J,">="&EOMONTH(A10,-1)+1,猫统计!J:J,"<="&EOMONTH(A10,0))+SUMIFS(猫统计!R:R,猫统计!P:P,">="&EOMONTH(A10,-1)+1,猫统计!P:P,"<="&EOMONTH(A10,0))+SUMIFS(猫统计!X:X,猫统计!V:V,">="&EOMONTH(A10,-1)+1,猫统计!V:V,"<="&EOMONTH(A10,0))+SUMIFS(猫统计!AD:AD,猫统计!AB:AB,">="&EOMONTH(A10,-1)+1,猫统计!AB:AB,"<="&EOMONTH(A10,0))+SUMIFS(猫统计!AJ:AJ,猫统计!AH:AH,">="&EOMONTH(A10,-1)+1,猫统计!AH:AH,"<="&EOMONTH(A10,0))+SUMIFS(猫统计!AP:AP,猫统计!AN:AN,">="&EOMONTH(A10,-1)+1,猫统计!AN:AN,"<="&EOMONTH(A10,0))+SUMIFS(猫统计!AV:AV,猫统计!AT:AT,">="&EOMONTH(A10,-1)+1,猫统计!AT:AT,"<="&EOMONTH(A10,0))+SUMIFS(猫统计!BB:BB,猫统计!AZ:AZ,">="&EOMONTH(A10,-1)+1,猫统计!AZ:AZ,"<="&EOMONTH(A10,0))+SUMIFS(猫统计!BH:BH,猫统计!BF:BF,">="&EOMONTH(A10,-1)+1,猫统计!BF:BF,"<="&EOMONTH(A10,0))+SUMIFS(猫统计!BN:BN,猫统计!BL:BL,">="&EOMONTH(A10,-1)+1,猫统计!BL:BL,"<="&EOMONTH(A10,0)) -> 9 | E10: =SUMIFS(猫统计!M:M,猫统计!J:J,">="&EOMONTH(A10,-1)+1,猫统计!J:J,"<="&EOMONTH(A10,0))+SUMIFS(猫统计!S:S,猫统计!P:P,">="&EOMONTH(A10,-1)+1,猫统计!P:P,"<="&EOMONTH(A10,0))+SUMIFS(猫统计!Y:Y,猫统计!V:V,">="&EOMONTH(A10,-1)+1,猫统计!V:V,"<="&EOMONTH(A10,0))+SUMIFS(猫统计!AE:AE,猫统计!AB:AB,">="&EOMONTH(A10,-1)+1,猫统计!AB:AB,"<="&EOMONTH(A10,0))+SUMIFS(猫统计!AK:AK,猫统计!AH:AH,">="&EOMONTH(A10,-1)+1,猫统计!AH:AH,"<="&EOMONTH(A10,0))+SUMIFS(猫统计!AQ:AQ,猫统计!AN:AN,">="&EOMONTH(A10,-1)+1,猫统计!AN:AN,"<="&EOMONTH(A10,0))+SUMIFS(猫统计!AW:AW,猫统计!AT:AT,">="&EOMONTH(A10,-1)+1,猫统计!AT:AT,"<="&EOMONTH(A10,0))+SUMIFS(猫统计!BC:BC,猫统计!AZ:AZ,">="&EOMONTH(A10,-1)+1,猫统计!AZ:AZ,"<="&EOMONTH(A10,0))+SUMIFS(猫统计!BI:BI,猫统计!BF:BF,">="&EOMONTH(A10,-1)+1,猫统计!BF:BF,"<="&EOMONTH(A10,0))+SUMIFS(猫统计!BO:BO,猫统计!BL:BL,">="&EOMONTH(A10,-1)+1,猫统计!BL:BL,"<="&EOMONTH(A10,0)) -> 24 | F10: =(E8+E9+E10)/(C8+C9+C10) -> 0.78431373 | G10: =(E8+E9+E10)/(B8+B9+B10) -> 3.0769231
A11: 44287 | B11: =COUNTIFS(猫统计!J:J,">="&EOMONTH(A11,-1)+1,猫统计!J:J,"<="&EOMONTH(A11,0))+COUNTIFS(猫统计!P:P,">="&EOMONTH(A11,-1)+1,猫统计!P:P,"<="&EOMONTH(A11,0))+COUNTIFS(猫统计!V:V,">="&EOMONTH(A11,-1)+1,猫统计!V:V,"<="&EOMONTH(A11,0))+COUNTIFS(猫统计!AB:AB,">="&EOMONTH(A11,-1)+1,猫统计!AB:AB,"<="&EOMONTH(A11,0))+COUNTIFS(猫统计!AH:AH,">="&EOMONTH(A11,-1)+1,猫统计!AH:AH,"<="&EOMONTH(A11,0))+COUNTIFS(猫统计!AN:AN,">="&EOMONTH(A11,-1)+1,猫统计!AN:AN,"<="&EOMONTH(A11,0))+COUNTIFS(猫统计!AT:AT,">="&EOMONTH(A11,-1)+1,猫统计!AT:AT,"<="&EOMONTH(A11,0))+COUNTIFS(猫统计!AZ:AZ,">="&EOMONTH(A11,-1)+1,猫统计!AZ:AZ,"<="&EOMONTH(A11,0))+COUNTIFS(猫统计!BF:BF,">="&EOMONTH(A11,-1)+1,猫统计!BF:BF,"<="&EOMONTH(A11,0))+COUNTIFS(猫统计!BL:BL,">="&EOMONTH(A11,-1)+1,猫统计!BL:BL,"<="&EOMONTH(A11,0)) -> 4 | C11: =D11+E11 -> 21 | D11: =SUMIFS(猫统计!L:L,猫统计!J:J,">="&EOMONTH(A11,-1)+1,猫统计!J:J,"<="&EOMONTH(A11,0))+SUMIFS(猫统计!R:R,猫统计!P:P,">="&EOMONTH(A11,-1)+1,猫统计!P:P,"<="&EOMONTH(A11,0))+SUMIFS(猫统计!X:X,猫统计!V:V,">="&EOMONTH(A11,-1)+1,猫统计!V:V,"<="&EOMONTH(A11,0))+SUMIFS(猫统计!AD:AD,猫统计!AB:AB,">="&EOMONTH(A11,-1)+1,猫统计!AB:AB,"<="&EOMONTH(A11,0))+SUMIFS(猫统计!AJ:AJ,猫统计!AH:AH,">="&EOMONTH(A11,-1)+1,猫统计!AH:AH,"<="&EOMONTH(A11,0))+SUMIFS(猫统计!AP:AP,猫统计!AN:AN,">="&EOMONTH(A11,-1)+1,猫统计!AN:AN,"<="&EOMONTH(A11,0))+SUMIFS(猫统计!AV:AV,猫统计!AT:AT,">="&EOMONTH(A11,-1)+1,猫统计!AT:AT,"<="&EOMONTH(A11,0))+SUMIFS(猫统计!BB:BB,猫统计!AZ:AZ,">="&EOMONTH(A11,-1)+1,猫统计!AZ:AZ,"<="&EOMONTH(A11,0))+SUMIFS(猫统计!BH:BH,猫统计!BF:BF,">="&EOMONTH(A11,-1)+1,猫统计!BF:BF,"<="&EOMONTH(A11,0))+SUMIFS(猫统计!BN:BN,猫统计!BL:BL,">="&EOMONTH(A11,-1)+1,猫统计!BL:BL,"<="&EOMONTH(A11,0)) -> 5 | E11: =SUMIFS(猫统计!M:M,猫统计!J:J,">="&EOMONTH(A11,-1)+1,猫统计!J:J,"<="&EOMONTH(A11,0))+SUMIFS(猫统计!S:S,猫统计!P:P,">="&EOMONTH(A11,-1)+1,猫统计!P:P,"<="&EOMONTH(A11,0))+SUMIFS(猫统计!Y:Y,猫统计!V:V,">="&EOMONTH(A11,-1)+1,猫统计!V:V,"<="&EOMONTH(A11,0))+SUMIFS(猫统计!AE:AE,猫统计!AB:AB,">="&EOMONTH(A11,-1)+1,猫统计!AB:AB,"<="&EOMONTH(A11,0))+SUMIFS(猫统计!AK:AK,猫统计!AH:AH,">="&EOMONTH(A11,-1)+1,猫统计!AH:AH,"<="&EOMONTH(A11,0))+SUMIFS(猫统计!AQ:AQ,猫统计!AN:AN,">="&EOMONTH(A11,-1)+1,猫统计!AN:AN,"<="&EOMONTH(A11,0))+SUMIFS(猫统计!AW:AW,猫统计!AT:AT,">="&EOMONTH(A11,-1)+1,猫统计!AT:AT,"<="&EOMONTH(A11,0))+SUMIFS(猫统计!BC:BC,猫统计!AZ:AZ,">="&EOMONTH(A11,-1)+1,猫统计!AZ:AZ,"<="&EOMONTH(A11,0))+SUMIFS(猫统计!BI:BI,猫统计!BF:BF,">="&EOMONTH(A11,-1)+1,猫统计!BF:BF,"<="&EOMONTH(A11,0))+SUMIFS(猫统计!BO:BO,猫统计!BL:BL,">="&EOMONTH(A11,-1)+1,猫统计!BL:BL,"<="&EOMONTH(A11,0)) -> 16
A12: 44317 | B12: =COUNTIFS(猫统计!J:J,">="&EOMONTH(A12,-1)+1,猫统计!J:J,"<="&EOMONTH(A12,0))+COUNTIFS(猫统计!P:P,">="&EOMONTH(A12,-1)+1,猫统计!P:P,"<="&EOMONTH(A12,0))+COUNTIFS(猫统计!V:V,">="&EOMONTH(A12,-1)+1,猫统计!V:V,"<="&EOMONTH(A12,0))+COUNTIFS(猫统计!AB:AB,">="&EOMONTH(A12,-1)+1,猫统计!AB:AB,"<="&EOMONTH(A12,0))+COUNTIFS(猫统计!AH:AH,">="&EOMONTH(A12,-1)+1,猫统计!AH:AH,"<="&EOMONTH(A12,0))+COUNTIFS(猫统计!AN:AN,">="&EOMONTH(A12,-1)+1,猫统计!AN:AN,"<="&EOMONTH(A12,0))+COUNTIFS(猫统计!AT:AT,">="&EOMONTH(A12,-1)+1,猫统计!AT:AT,"<="&EOMONTH(A12,0))+COUNTIFS(猫统计!AZ:AZ,">="&EOMONTH(A12,-1)+1,猫统计!AZ:AZ,"<="&EOMONTH(A12,0))+COUNTIFS(猫统计!BF:BF,">="&EOMONTH(A12,-1)+1,猫统计!BF:BF,"<="&EOMONTH(A12,0))+COUNTIFS(猫统计!BL:BL,">="&EOMONTH(A12,-1)+1,猫统计!BL:BL,"<="&EOMONTH(A12,0)) -> 3 | C12: =D12+E12 -> 9 | D12: =SUMIFS(猫统计!L:L,猫统计!J:J,">="&EOMONTH(A12,-1)+1,猫统计!J:J,"<="&EOMONTH(A12,0))+SUMIFS(猫统计!R:R,猫统计!P:P,">="&EOMONTH(A12,-1)+1,猫统计!P:P,"<="&EOMONTH(A12,0))+SUMIFS(猫统计!X:X,猫统计!V:V,">="&EOMONTH(A12,-1)+1,猫统计!V:V,"<="&EOMONTH(A12,0))+SUMIFS(猫统计!AD:AD,猫统计!AB:AB,">="&EOMONTH(A12,-1)+1,猫统计!AB:AB,"<="&EOMONTH(A12,0))+SUMIFS(猫统计!AJ:AJ,猫统计!AH:AH,">="&EOMONTH(A12,-1)+1,猫统计!AH:AH,"<="&EOMONTH(A12,0))+SUMIFS(猫统计!AP:AP,猫统计!AN:AN,">="&EOMONTH(A12,-1)+1,猫统计!AN:AN,"<="&EOMONTH(A12,0))+SUMIFS(猫统计!AV:AV,猫统计!AT:AT,">="&EOMONTH(A12,-1)+1,猫统计!AT:AT,"<="&EOMONTH(A12,0))+SUMIFS(猫统计!BB:BB,猫统计!AZ:AZ,">="&EOMONTH(A12,-1)+1,猫统计!AZ:AZ,"<="&EOMONTH(A12,0))+SUMIFS(猫统计!BH:BH,猫统计!BF:BF,">="&EOMONTH(A12,-1)+1,猫统计!BF:BF,"<="&EOMONTH(A12,0))+SUMIFS(猫统计!BN:BN,猫统计!BL:BL,">="&EOMONTH(A12,-1)+1,猫统计!BL:BL,"<="&EOMONTH(A12,0)) -> 4 | E12: =SUMIFS(猫统计!M:M,猫统计!J:J,">="&EOMONTH(A12,-1)+1,猫统计!J:J,"<="&EOMONTH(A12,0))+SUMIFS(猫统计!S:S,猫统计!P:P,">="&EOMONTH(A12,-1)+1,猫统计!P:P,"<="&EOMONTH(A12,0))+SUMIFS(猫统计!Y:Y,猫统计!V:V,">="&EOMONTH(A12,-1)+1,猫统计!V:V,"<="&EOMONTH(A12,0))+SUMIFS(猫统计!AE:AE,猫统计!AB:AB,">="&EOMONTH(A12,-1)+1,猫统计!AB:AB,"<="&EOMONTH(A12,0))+SUMIFS(猫统计!AK:AK,猫统计!AH:AH,">="&EOMONTH(A12,-1)+1,猫统计!AH:AH,"<="&EOMONTH(A12,0))+SUMIFS(猫统计!AQ:AQ,猫统计!AN:AN,">="&EOMONTH(A12,-1)+1,猫统计!AN:AN,"<="&EOMONTH(A12,0))+SUMIFS(猫统计!AW:AW,猫统计!AT:AT,">="&EOMONTH(A12,-1)+1,猫统计!AT:AT,"<="&EOMONTH(A12,0))+SUMIFS(猫统计!BC:BC,猫统计!AZ:AZ,">="&EOMONTH(A12,-1)+1,猫统计!AZ:AZ,"<="&EOMONTH(A12,0))+SUMIFS(猫统计!BI:BI,猫统计!BF:BF,">="&EOMONTH(A12,-1)+1,猫统计!BF:BF,"<="&EOMONTH(A12,0))+SUMIFS(猫统计!BO:BO,猫统计!BL:BL,">="&EOMONTH(A12,-1)+1,猫统计!BL:BL,"<="&EOMONTH(A12,0)) -> 5
A13: 44348 | B13: =COUNTIFS(猫统计!J:J,">="&EOMONTH(A13,-1)+1,猫统计!J:J,"<="&EOMONTH(A13,0))+COUNTIFS(猫统计!P:P,">="&EOMONTH(A13,-1)+1,猫统计!P:P,"<="&EOMONTH(A13,0))+COUNTIFS(猫统计!V:V,">="&EOMONTH(A13,-1)+1,猫统计!V:V,"<="&EOMONTH(A13,0))+COUNTIFS(猫统计!AB:AB,">="&EOMONTH(A13,-1)+1,猫统计!AB:AB,"<="&EOMONTH(A13,0))+COUNTIFS(猫统计!AH:AH,">="&EOMONTH(A13,-1)+1,猫统计!AH:AH,"<="&EOMONTH(A13,0))+COUNTIFS(猫统计!AN:AN,">="&EOMONTH(A13,-1)+1,猫统计!AN:AN,"<="&EOMONTH(A13,0))+COUNTIFS(猫统计!AT:AT,">="&EOMONTH(A13,-1)+1,猫统计!AT:AT,"<="&EOMONTH(A13,0))+COUNTIFS(猫统计!AZ:AZ,">="&EOMONTH(A13,-1)+1,猫统计!AZ:AZ,"<="&EOMONTH(A13,0))+COUNTIFS(猫统计!BF:BF,">="&EOMONTH(A13,-1)+1,猫统计!BF:BF,"<="&EOMONTH(A13,0))+COUNTIFS(猫统计!BL:BL,">="&EOMONTH(A13,-1)+1,猫统计!BL:BL,"<="&EOMONTH(A13,0)) -> 0 | C13: =D13+E13 -> 0 | D13: =SUMIFS(猫统计!L:L,猫统计!J:J,">="&EOMONTH(A13,-1)+1,猫统计!J:J,"<="&EOMONTH(A13,0))+SUMIFS(猫统计!R:R,猫统计!P:P,">="&EOMONTH(A13,-1)+1,猫统计!P:P,"<="&EOMONTH(A13,0))+SUMIFS(猫统计!X:X,猫统计!V:V,">="&EOMONTH(A13,-1)+1,猫统计!V:V,"<="&EOMONTH(A13,0))+SUMIFS(猫统计!AD:AD,猫统计!AB:AB,">="&EOMONTH(A13,-1)+1,猫统计!AB:AB,"<="&EOMONTH(A13,0))+SUMIFS(猫统计!AJ:AJ,猫统计!AH:AH,">="&EOMONTH(A13,-1)+1,猫统计!AH:AH,"<="&EOMONTH(A13,0))+SUMIFS(猫统计!AP:AP,猫统计!AN:AN,">="&EOMONTH(A13,-1)+1,猫统计!AN:AN,"<="&EOMONTH(A13,0))+SUMIFS(猫统计!AV:AV,猫统计!AT:AT,">="&EOMONTH(A13,-1)+1,猫统计!AT:AT,"<="&EOMONTH(A13,0))+SUMIFS(猫统计!BB:BB,猫统计!AZ:AZ,">="&EOMONTH(A13,-1)+1,猫统计!AZ:AZ,"<="&EOMONTH(A13,0))+SUMIFS(猫统计!BH:BH,猫统计!BF:BF,">="&EOMONTH(A13,-1)+1,猫统计!BF:BF,"<="&EOMONTH(A13,0))+SUMIFS(猫统计!BN:BN,猫统计!BL:BL,">="&EOMONTH(A13,-1)+1,猫统计!BL:BL,"<="&EOMONTH(A13,0)) -> 0 | E13: =SUMIFS(猫统计!M:M,猫统计!J:J,">="&EOMONTH(A13,-1)+1,猫统计!J:J,"<="&EOMONTH(A13,0))+SUMIFS(猫统计!S:S,猫统计!P:P,">="&EOMONTH(A13,-1)+1,猫统计!P:P,"<="&EOMONTH(A13,0))+SUMIFS(猫统计!Y:Y,猫统计!V:V,">="&EOMONTH(A13,-1)+1,猫统计!V:V,"<="&EOMONTH(A13,0))+SUMIFS(猫统计!AE:AE,猫统计!AB:AB,">="&EOMONTH(A13,-1)+1,猫统计!AB:AB,"<="&EOMONTH(A13,0))+SUMIFS(猫统计!AK:AK,猫统计!AH:AH,">="&EOMONTH(A13,-1)+1,猫统计!AH:AH,"<="&EOMONTH(A13,0))+SUMIFS(猫统计!AQ:AQ,猫统计!AN:AN,">="&EOMONTH(A13,-1)+1,猫统计!AN:AN,"<="&EOMONTH(A13,0))+SUMIFS(猫统计!AW:AW,猫统计!AT:AT,">="&EOMONTH(A13,-1)+1,猫统计!AT:AT,"<="&EOMONTH(A13,0))+SUMIFS(猫统计!BC:BC,猫统计!AZ:AZ,">="&EOMONTH(A13,-1)+1,猫统计!AZ:AZ,"<="&EOMONTH(A13,0))+SUMIFS(猫统计!BI:BI,猫统计!BF:BF,">="&EOMONTH(A13,-1)+1,猫统计!BF:BF,"<="&EOMONTH(A13,0))+SUMIFS(猫统计!BO:BO,猫统计!BL:BL,">="&EOMONTH(A13,-1)+1,猫统计!BL:BL,"<="&EOMONTH(A13,0)) -> 0 | F13: =(E11+E12+E13)/(C11+C12+C13) -> 0.7 | G13: =(E11+E12+E13)/(B11+B12+B13) -> 3
A14: 44378 | B14: =COUNTIFS(猫统计!J:J,">="&EOMONTH(A14,-1)+1,猫统计!J:J,"<="&EOMONTH(A14,0))+COUNTIFS(猫统计!P:P,">="&EOMONTH(A14,-1)+1,猫统计!P:P,"<="&EOMONTH(A14,0))+COUNTIFS(猫统计!V:V,">="&EOMONTH(A14,-1)+1,猫统计!V:V,"<="&EOMONTH(A14,0))+COUNTIFS(猫统计!AB:AB,">="&EOMONTH(A14,-1)+1,猫统计!AB:AB,"<="&EOMONTH(A14,0))+COUNTIFS(猫统计!AH:AH,">="&EOMONTH(A14,-1)+1,猫统计!AH:AH,"<="&EOMONTH(A14,0))+COUNTIFS(猫统计!AN:AN,">="&EOMONTH(A14,-1)+1,猫统计!AN:AN,"<="&EOMONTH(A14,0))+COUNTIFS(猫统计!AT:AT,">="&EOMONTH(A14,-1)+1,猫统计!AT:AT,"<="&EOMONTH(A14,0))+COUNTIFS(猫统计!AZ:AZ,">="&EOMONTH(A14,-1)+1,猫统计!AZ:AZ,"<="&EOMONTH(A14,0))+COUNTIFS(猫统计!BF:BF,">="&EOMONTH(A14,-1)+1,猫统计!BF:BF,"<="&EOMONTH(A14,0))+COUNTIFS(猫统计!BL:BL,">="&EOMONTH(A14,-1)+1,猫统计!BL:BL,"<="&EOMONTH(A14,0)) -> 6 | C14: =D14+E14 -> 26 | D14: =SUMIFS(猫统计!L:L,猫统计!J:J,">="&EOMONTH(A14,-1)+1,猫统计!J:J,"<="&EOMONTH(A14,0))+SUMIFS(猫统计!R:R,猫统计!P:P,">="&EOMONTH(A14,-1)+1,猫统计!P:P,"<="&EOMONTH(A14,0))+SUMIFS(猫统计!X:X,猫统计!V:V,">="&EOMONTH(A14,-1)+1,猫统计!V:V,"<="&EOMONTH(A14,0))+SUMIFS(猫统计!AD:AD,猫统计!AB:AB,">="&EOMONTH(A14,-1)+1,猫统计!AB:AB,"<="&EOMONTH(A14,0))+SUMIFS(猫统计!AJ:AJ,猫统计!AH:AH,">="&EOMONTH(A14,-1)+1,猫统计!AH:AH,"<="&EOMONTH(A14,0))+SUMIFS(猫统计!AP:AP,猫统计!AN:AN,">="&EOMONTH(A14,-1)+1,猫统计!AN:AN,"<="&EOMONTH(A14,0))+SUMIFS(猫统计!AV:AV,猫统计!AT:AT,">="&EOMONTH(A14,-1)+1,猫统计!AT:AT,"<="&EOMONTH(A14,0))+SUMIFS(猫统计!BB:BB,猫统计!AZ:AZ,">="&EOMONTH(A14,-1)+1,猫统计!AZ:AZ,"<="&EOMONTH(A14,0))+SUMIFS(猫统计!BH:BH,猫统计!BF:BF,">="&EOMONTH(A14,-1)+1,猫统计!BF:BF,"<="&EOMONTH(A14,0))+SUMIFS(猫统计!BN:BN,猫统计!BL:BL,">="&EOMONTH(A14,-1)+1,猫统计!BL:BL,"<="&EOMONTH(A14,0)) -> 6 | E14: =SUMIFS(猫统计!M:M,猫统计!J:J,">="&EOMONTH(A14,-1)+1,猫统计!J:J,"<="&EOMONTH(A14,0))+SUMIFS(猫统计!S:S,猫统计!P:P,">="&EOMONTH(A14,-1)+1,猫统计!P:P,"<="&EOMONTH(A14,0))+SUMIFS(猫统计!Y:Y,猫统计!V:V,">="&EOMONTH(A14,-1)+1,猫统计!V:V,"<="&EOMONTH(A14,0))+SUMIFS(猫统计!AE:AE,猫统计!AB:AB,">="&EOMONTH(A14,-1)+1,猫统计!AB:AB,"<="&EOMONTH(A14,0))+SUMIFS(猫统计!AK:AK,猫统计!AH:AH,">="&EOMONTH(A14,-1)+1,猫统计!AH:AH,"<="&EOMONTH(A14,0))+SUMIFS(猫统计!AQ:AQ,猫统计!AN:AN,">="&EOMONTH(A14,-1)+1,猫统计!AN:AN,"<="&EOMONTH(A14,0))+SUMIFS(猫统计!AW:AW,猫统计!AT:AT,">="&EOMONTH(A14,-1)+1,猫统计!AT:AT,"<="&EOMONTH(A14,0))+SUMIFS(猫统计!BC:BC,猫统计!AZ:AZ,">="&EOMONTH(A14,-1)+1,猫统计!AZ:AZ,"<="&EOMONTH(A14,0))+SUMIFS(猫统计!BI:BI,猫统计!BF:BF,">="&EOMONTH(A14,-1)+1,猫统计!BF:BF,"<="&EOMONTH(A14,0))+SUMIFS(猫统计!BO:BO,猫统计!BL:BL,">="&EOMONTH(A14,-1)+1,猫统计!BL:BL,"<="&EOMONTH(A14,0)) -> 20
A15: 44409 | B15: =COUNTIFS(猫统计!J:J,">="&EOMONTH(A15,-1)+1,猫统计!J:J,"<="&EOMONTH(A15,0))+COUNTIFS(猫统计!P:P,">="&EOMONTH(A15,-1)+1,猫统计!P:P,"<="&EOMONTH(A15,0))+COUNTIFS(猫统计!V:V,">="&EOMONTH(A15,-1)+1,猫统计!V:V,"<="&EOMONTH(A15,0))+COUNTIFS(猫统计!AB:AB,">="&EOMONTH(A15,-1)+1,猫统计!AB:AB,"<="&EOMONTH(A15,0))+COUNTIFS(猫统计!AH:AH,">="&EOMONTH(A15,-1)+1,猫统计!AH:AH,"<="&EOMONTH(A15,0))+COUNTIFS(猫统计!AN:AN,">="&EOMONTH(A15,-1)+1,猫统计!AN:AN,"<="&EOMONTH(A15,0))+COUNTIFS(猫统计!AT:AT,">="&EOMONTH(A15,-1)+1,猫统计!AT:AT,"<="&EOMONTH(A15,0))+COUNTIFS(猫统计!AZ:AZ,">="&EOMONTH(A15,-1)+1,猫统计!AZ:AZ,"<="&EOMONTH(A15,0))+COUNTIFS(猫统计!BF:BF,">="&EOMONTH(A15,-1)+1,猫统计!BF:BF,"<="&EOMONTH(A15,0))+COUNTIFS(猫统计!BL:BL,">="&EOMONTH(A15,-1)+1,猫统计!BL:BL,"<="&EOMONTH(A15,0)) -> 3 | C15: =D15+E15 -> 15 | D15: =SUMIFS(猫统计!L:L,猫统计!J:J,">="&EOMONTH(A15,-1)+1,猫统计!J:J,"<="&EOMONTH(A15,0))+SUMIFS(猫统计!R:R,猫统计!P:P,">="&EOMONTH(A15,-1)+1,猫统计!P:P,"<="&EOMONTH(A15,0))+SUMIFS(猫统计!X:X,猫统计!V:V,">="&EOMONTH(A15,-1)+1,猫统计!V:V,"<="&EOMONTH(A15,0))+SUMIFS(猫统计!AD:AD,猫统计!AB:AB,">="&EOMONTH(A15,-1)+1,猫统计!AB:AB,"<="&EOMONTH(A15,0))+SUMIFS(猫统计!AJ:AJ,猫统计!AH:AH,">="&EOMONTH(A15,-1)+1,猫统计!AH:AH,"<="&EOMONTH(A15,0))+SUMIFS(猫统计!AP:AP,猫统计!AN:AN,">="&EOMONTH(A15,-1)+1,猫统计!AN:AN,"<="&EOMONTH(A15,0))+SUMIFS(猫统计!AV:AV,猫统计!AT:AT,">="&EOMONTH(A15,-1)+1,猫统计!AT:AT,"<="&EOMONTH(A15,0))+SUMIFS(猫统计!BB:BB,猫统计!AZ:AZ,">="&EOMONTH(A15,-1)+1,猫统计!AZ:AZ,"<="&EOMONTH(A15,0))+SUMIFS(猫统计!BH:BH,猫统计!BF:BF,">="&EOMONTH(A15,-1)+1,猫统计!BF:BF,"<="&EOMONTH(A15,0))+SUMIFS(猫统计!BN:BN,猫统计!BL:BL,">="&EOMONTH(A15,-1)+1,猫统计!BL:BL,"<="&EOMONTH(A15,0)) -> 0 | E15: =SUMIFS(猫统计!M:M,猫统计!J:J,">="&EOMONTH(A15,-1)+1,猫统计!J:J,"<="&EOMONTH(A15,0))+SUMIFS(猫统计!S:S,猫统计!P:P,">="&EOMONTH(A15,-1)+1,猫统计!P:P,"<="&EOMONTH(A15,0))+SUMIFS(猫统计!Y:Y,猫统计!V:V,">="&EOMONTH(A15,-1)+1,猫统计!V:V,"<="&EOMONTH(A15,0))+SUMIFS(猫统计!AE:AE,猫统计!AB:AB,">="&EOMONTH(A15,-1)+1,猫统计!AB:AB,"<="&EOMONTH(A15,0))+SUMIFS(猫统计!AK:AK,猫统计!AH:AH,">="&EOMONTH(A15,-1)+1,猫统计!AH:AH,"<="&EOMONTH(A15,0))+SUMIFS(猫统计!AQ:AQ,猫统计!AN:AN,">="&EOMONTH(A15,-1)+1,猫统计!AN:AN,"<="&EOMONTH(A15,0))+SUMIFS(猫统计!AW:AW,猫统计!AT:AT,">="&EOMONTH(A15,-1)+1,猫统计!AT:AT,"<="&EOMONTH(A15,0))+SUMIFS(猫统计!BC:BC,猫统计!AZ:AZ,">="&EOMONTH(A15,-1)+1,猫统计!AZ:AZ,"<="&EOMONTH(A15,0))+SUMIFS(猫统计!BI:BI,猫统计!BF:BF,">="&EOMONTH(A15,-1)+1,猫统计!BF:BF,"<="&EOMONTH(A15,0))+SUMIFS(猫统计!BO:BO,猫统计!BL:BL,">="&EOMONTH(A15,-1)+1,猫统计!BL:BL,"<="&EOMONTH(A15,0)) -> 15
A16: 44440 | B16: =COUNTIFS(猫统计!J:J,">="&EOMONTH(A16,-1)+1,猫统计!J:J,"<="&EOMONTH(A16,0))+COUNTIFS(猫统计!P:P,">="&EOMONTH(A16,-1)+1,猫统计!P:P,"<="&EOMONTH(A16,0))+COUNTIFS(猫统计!V:V,">="&EOMONTH(A16,-1)+1,猫统计!V:V,"<="&EOMONTH(A16,0))+COUNTIFS(猫统计!AB:AB,">="&EOMONTH(A16,-1)+1,猫统计!AB:AB,"<="&EOMONTH(A16,0))+COUNTIFS(猫统计!AH:AH,">="&EOMONTH(A16,-1)+1,猫统计!AH:AH,"<="&EOMONTH(A16,0))+COUNTIFS(猫统计!AN:AN,">="&EOMONTH(A16,-1)+1,猫统计!AN:AN,"<="&EOMONTH(A16,0))+COUNTIFS(猫统计!AT:AT,">="&EOMONTH(A16,-1)+1,猫统计!AT:AT,"<="&EOMONTH(A16,0))+COUNTIFS(猫统计!AZ:AZ,">="&EOMONTH(A16,-1)+1,猫统计!AZ:AZ,"<="&EOMONTH(A16,0))+COUNTIFS(猫统计!BF:BF,">="&EOMONTH(A16,-1)+1,猫统计!BF:BF,"<="&EOMONTH(A16,0))+COUNTIFS(猫统计!BL:BL,">="&EOMONTH(A16,-1)+1,猫统计!BL:BL,"<="&EOMONTH(A16,0)) -> 5 | C16: =D16+E16 -> 20 | D16: =SUMIFS(猫统计!L:L,猫统计!J:J,">="&EOMONTH(A16,-1)+1,猫统计!J:J,"<="&EOMONTH(A16,0))+SUMIFS(猫统计!R:R,猫统计!P:P,">="&EOMONTH(A16,-1)+1,猫统计!P:P,"<="&EOMONTH(A16,0))+SUMIFS(猫统计!X:X,猫统计!V:V,">="&EOMONTH(A16,-1)+1,猫统计!V:V,"<="&EOMONTH(A16,0))+SUMIFS(猫统计!AD:AD,猫统计!AB:AB,">="&EOMONTH(A16,-1)+1,猫统计!AB:AB,"<="&EOMONTH(A16,0))+SUMIFS(猫统计!AJ:AJ,猫统计!AH:AH,">="&EOMONTH(A16,-1)+1,猫统计!AH:AH,"<="&EOMONTH(A16,0))+SUMIFS(猫统计!AP:AP,猫统计!AN:AN,">="&EOMONTH(A16,-1)+1,猫统计!AN:AN,"<="&EOMONTH(A16,0))+SUMIFS(猫统计!AV:AV,猫统计!AT:AT,">="&EOMONTH(A16,-1)+1,猫统计!AT:AT,"<="&EOMONTH(A16,0))+SUMIFS(猫统计!BB:BB,猫统计!AZ:AZ,">="&EOMONTH(A16,-1)+1,猫统计!AZ:AZ,"<="&EOMONTH(A16,0))+SUMIFS(猫统计!BH:BH,猫统计!BF:BF,">="&EOMONTH(A16,-1)+1,猫统计!BF:BF,"<="&EOMONTH(A16,0))+SUMIFS(猫统计!BN:BN,猫统计!BL:BL,">="&EOMONTH(A16,-1)+1,猫统计!BL:BL,"<="&EOMONTH(A16,0)) -> 4 | E16: =SUMIFS(猫统计!M:M,猫统计!J:J,">="&EOMONTH(A16,-1)+1,猫统计!J:J,"<="&EOMONTH(A16,0))+SUMIFS(猫统计!S:S,猫统计!P:P,">="&EOMONTH(A16,-1)+1,猫统计!P:P,"<="&EOMONTH(A16,0))+SUMIFS(猫统计!Y:Y,猫统计!V:V,">="&EOMONTH(A16,-1)+1,猫统计!V:V,"<="&EOMONTH(A16,0))+SUMIFS(猫统计!AE:AE,猫统计!AB:AB,">="&EOMONTH(A16,-1)+1,猫统计!AB:AB,"<="&EOMONTH(A16,0))+SUMIFS(猫统计!AK:AK,猫统计!AH:AH,">="&EOMONTH(A16,-1)+1,猫统计!AH:AH,"<="&EOMONTH(A16,0))+SUMIFS(猫统计!AQ:AQ,猫统计!AN:AN,">="&EOMONTH(A16,-1)+1,猫统计!AN:AN,"<="&EOMONTH(A16,0))+SUMIFS(猫统计!AW:AW,猫统计!AT:AT,">="&EOMONTH(A16,-1)+1,猫统计!AT:AT,"<="&EOMONTH(A16,0))+SUMIFS(猫统计!BC:BC,猫统计!AZ:AZ,">="&EOMONTH(A16,-1)+1,猫统计!AZ:AZ,"<="&EOMONTH(A16,0))+SUMIFS(猫统计!BI:BI,猫统计!BF:BF,">="&EOMONTH(A16,-1)+1,猫统计!BF:BF,"<="&EOMONTH(A16,0))+SUMIFS(猫统计!BO:BO,猫统计!BL:BL,">="&EOMONTH(A16,-1)+1,猫统计!BL:BL,"<="&EOMONTH(A16,0)) -> 16 | F16: =(E14+E15+E16)/(C14+C15+C16) -> 0.83606557 | G16: =(E14+E15+E16)/(B14+B15+B16) -> 3.6428571
A17: 44470 | B17: =COUNTIFS(猫统计!J:J,">="&EOMONTH(A17,-1)+1,猫统计!J:J,"<="&EOMONTH(A17,0))+COUNTIFS(猫统计!P:P,">="&EOMONTH(A17,-1)+1,猫统计!P:P,"<="&EOMONTH(A17,0))+COUNTIFS(猫统计!V:V,">="&EOMONTH(A17,-1)+1,猫统计!V:V,"<="&EOMONTH(A17,0))+COUNTIFS(猫统计!AB:AB,">="&EOMONTH(A17,-1)+1,猫统计!AB:AB,"<="&EOMONTH(A17,0))+COUNTIFS(猫统计!AH:AH,">="&EOMONTH(A17,-1)+1,猫统计!AH:AH,"<="&EOMONTH(A17,0))+COUNTIFS(猫统计!AN:AN,">="&EOMONTH(A17,-1)+1,猫统计!AN:AN,"<="&EOMONTH(A17,0))+COUNTIFS(猫统计!AT:AT,">="&EOMONTH(A17,-1)+1,猫统计!AT:AT,"<="&EOMONTH(A17,0))+COUNTIFS(猫统计!AZ:AZ,">="&EOMONTH(A17,-1)+1,猫统计!AZ:AZ,"<="&EOMONTH(A17,0))+COUNTIFS(猫统计!BF:BF,">="&EOMONTH(A17,-1)+1,猫统计!BF:BF,"<="&EOMONTH(A17,0))+COUNTIFS(猫统计!BL:BL,">="&EOMONTH(A17,-1)+1,猫统计!BL:BL,"<="&EOMONTH(A17,0)) -> 3 | C17: =D17+E17 -> 17 | D17: =SUMIFS(猫统计!L:L,猫统计!J:J,">="&EOMONTH(A17,-1)+1,猫统计!J:J,"<="&EOMONTH(A17,0))+SUMIFS(猫统计!R:R,猫统计!P:P,">="&EOMONTH(A17,-1)+1,猫统计!P:P,"<="&EOMONTH(A17,0))+SUMIFS(猫统计!X:X,猫统计!V:V,">="&EOMONTH(A17,-1)+1,猫统计!V:V,"<="&EOMONTH(A17,0))+SUMIFS(猫统计!AD:AD,猫统计!AB:AB,">="&EOMONTH(A17,-1)+1,猫统计!AB:AB,"<="&EOMONTH(A17,0))+SUMIFS(猫统计!AJ:AJ,猫统计!AH:AH,">="&EOMONTH(A17,-1)+1,猫统计!AH:AH,"<="&EOMONTH(A17,0))+SUMIFS(猫统计!AP:AP,猫统计!AN:AN,">="&EOMONTH(A17,-1)+1,猫统计!AN:AN,"<="&EOMONTH(A17,0))+SUMIFS(猫统计!AV:AV,猫统计!AT:AT,">="&EOMONTH(A17,-1)+1,猫统计!AT:AT,"<="&EOMONTH(A17,0))+SUMIFS(猫统计!BB:BB,猫统计!AZ:AZ,">="&EOMONTH(A17,-1)+1,猫统计!AZ:AZ,"<="&EOMONTH(A17,0))+SUMIFS(猫统计!BH:BH,猫统计!BF:BF,">="&EOMONTH(A17,-1)+1,猫统计!BF:BF,"<="&EOMONTH(A17,0))+SUMIFS(猫统计!BN:BN,猫统计!BL:BL,">="&EOMONTH(A17,-1)+1,猫统计!BL:BL,"<="&EOMONTH(A17,0)) -> 4 | E17: =SUMIFS(猫统计!M:M,猫统计!J:J,">="&EOMONTH(A17,-1)+1,猫统计!J:J,"<="&EOMONTH(A17,0))+SUMIFS(猫统计!S:S,猫统计!P:P,">="&EOMONTH(A17,-1)+1,猫统计!P:P,"<="&EOMONTH(A17,0))+SUMIFS(猫统计!Y:Y,猫统计!V:V,">="&EOMONTH(A17,-1)+1,猫统计!V:V,"<="&EOMONTH(A17,0))+SUMIFS(猫统计!AE:AE,猫统计!AB:AB,">="&EOMONTH(A17,-1)+1,猫统计!AB:AB,"<="&EOMONTH(A17,0))+SUMIFS(猫统计!AK:AK,猫统计!AH:AH,">="&EOMONTH(A17,-1)+1,猫统计!AH:AH,"<="&EOMONTH(A17,0))+SUMIFS(猫统计!AQ:AQ,猫统计!AN:AN,">="&EOMONTH(A17,-1)+1,猫统计!AN:AN,"<="&EOMONTH(A17,0))+SUMIFS(猫统计!AW:AW,猫统计!AT:AT,">="&EOMONTH(A17,-1)+1,猫统计!AT:AT,"<="&EOMONTH(A17,0))+SUMIFS(猫统计!BC:BC,猫统计!AZ:AZ,">="&EOMONTH(A17,-1)+1,猫统计!AZ:AZ,"<="&EOMONTH(A17,0))+SUMIFS(猫统计!BI:BI,猫统计!BF:BF,">="&EOMONTH(A17,-1)+1,猫统计!BF:BF,"<="&EOMONTH(A17,0))+SUMIFS(猫统计!BO:BO,猫统计!BL:BL,">="&EOMONTH(A17,-1)+1,猫统计!BL:BL,"<="&EOMONTH(A17,0)) -> 13
A18: 44501 | B18: =COUNTIFS(猫统计!J:J,">="&EOMONTH(A18,-1)+1,猫统计!J:J,"<="&EOMONTH(A18,0))+COUNTIFS(猫统计!P:P,">="&EOMONTH(A18,-1)+1,猫统计!P:P,"<="&EOMONTH(A18,0))+COUNTIFS(猫统计!V:V,">="&EOMONTH(A18,-1)+1,猫统计!V:V,"<="&EOMONTH(A18,0))+COUNTIFS(猫统计!AB:AB,">="&EOMONTH(A18,-1)+1,猫统计!AB:AB,"<="&EOMONTH(A18,0))+COUNTIFS(猫统计!AH:AH,">="&EOMONTH(A18,-1)+1,猫统计!AH:AH,"<="&EOMONTH(A18,0))+COUNTIFS(猫统计!AN:AN,">="&EOMONTH(A18,-1)+1,猫统计!AN:AN,"<="&EOMONTH(A18,0))+COUNTIFS(猫统计!AT:AT,">="&EOMONTH(A18,-1)+1,猫统计!AT:AT,"<="&EOMONTH(A18,0))+COUNTIFS(猫统计!AZ:AZ,">="&EOMONTH(A18,-1)+1,猫统计!AZ:AZ,"<="&EOMONTH(A18,0))+COUNTIFS(猫统计!BF:BF,">="&EOMONTH(A18,-1)+1,猫统计!BF:BF,"<="&EOMONTH(A18,0))+COUNTIFS(猫统计!BL:BL,">="&EOMONTH(A18,-1)+1,猫统计!BL:BL,"<="&EOMONTH(A18,0)) -> 1 | C18: =D18+E18 -> 3 | D18: =SUMIFS(猫统计!L:L,猫统计!J:J,">="&EOMONTH(A18,-1)+1,猫统计!J:J,"<="&EOMONTH(A18,0))+SUMIFS(猫统计!R:R,猫统计!P:P,">="&EOMONTH(A18,-1)+1,猫统计!P:P,"<="&EOMONTH(A18,0))+SUMIFS(猫统计!X:X,猫统计!V:V,">="&EOMONTH(A18,-1)+1,猫统计!V:V,"<="&EOMONTH(A18,0))+SUMIFS(猫统计!AD:AD,猫统计!AB:AB,">="&EOMONTH(A18,-1)+1,猫统计!AB:AB,"<="&EOMONTH(A18,0))+SUMIFS(猫统计!AJ:AJ,猫统计!AH:AH,">="&EOMONTH(A18,-1)+1,猫统计!AH:AH,"<="&EOMONTH(A18,0))+SUMIFS(猫统计!AP:AP,猫统计!AN:AN,">="&EOMONTH(A18,-1)+1,猫统计!AN:AN,"<="&EOMONTH(A18,0))+SUMIFS(猫统计!AV:AV,猫统计!AT:AT,">="&EOMONTH(A18,-1)+1,猫统计!AT:AT,"<="&EOMONTH(A18,0))+SUMIFS(猫统计!BB:BB,猫统计!AZ:AZ,">="&EOMONTH(A18,-1)+1,猫统计!AZ:AZ,"<="&EOMONTH(A18,0))+SUMIFS(猫统计!BH:BH,猫统计!BF:BF,">="&EOMONTH(A18,-1)+1,猫统计!BF:BF,"<="&EOMONTH(A18,0))+SUMIFS(猫统计!BN:BN,猫统计!BL:BL,">="&EOMONTH(A18,-1)+1,猫统计!BL:BL,"<="&EOMONTH(A18,0)) -> 0 | E18: =SUMIFS(猫统计!M:M,猫统计!J:J,">="&EOMONTH(A18,-1)+1,猫统计!J:J,"<="&EOMONTH(A18,0))+SUMIFS(猫统计!S:S,猫统计!P:P,">="&EOMONTH(A18,-1)+1,猫统计!P:P,"<="&EOMONTH(A18,0))+SUMIFS(猫统计!Y:Y,猫统计!V:V,">="&EOMONTH(A18,-1)+1,猫统计!V:V,"<="&EOMONTH(A18,0))+SUMIFS(猫统计!AE:AE,猫统计!AB:AB,">="&EOMONTH(A18,-1)+1,猫统计!AB:AB,"<="&EOMONTH(A18,0))+SUMIFS(猫统计!AK:AK,猫统计!AH:AH,">="&EOMONTH(A18,-1)+1,猫统计!AH:AH,"<="&EOMONTH(A18,0))+SUMIFS(猫统计!AQ:AQ,猫统计!AN:AN,">="&EOMONTH(A18,-1)+1,猫统计!AN:AN,"<="&EOMONTH(A18,0))+SUMIFS(猫统计!AW:AW,猫统计!AT:AT,">="&EOMONTH(A18,-1)+1,猫统计!AT:AT,"<="&EOMONTH(A18,0))+SUMIFS(猫统计!BC:BC,猫统计!AZ:AZ,">="&EOMONTH(A18,-1)+1,猫统计!AZ:AZ,"<="&EOMONTH(A18,0))+SUMIFS(猫统计!BI:BI,猫统计!BF:BF,">="&EOMONTH(A18,-1)+1,猫统计!BF:BF,"<="&EOMONTH(A18,0))+SUMIFS(猫统计!BO:BO,猫统计!BL:BL,">="&EOMONTH(A18,-1)+1,猫统计!BL:BL,"<="&EOMONTH(A18,0)) -> 3
A19: 44531 | B19: =COUNTIFS(猫统计!J:J,">="&EOMONTH(A19,-1)+1,猫统计!J:J,"<="&EOMONTH(A19,0))+COUNTIFS(猫统计!P:P,">="&EOMONTH(A19,-1)+1,猫统计!P:P,"<="&EOMONTH(A19,0))+COUNTIFS(猫统计!V:V,">="&EOMONTH(A19,-1)+1,猫统计!V:V,"<="&EOMONTH(A19,0))+COUNTIFS(猫统计!AB:AB,">="&EOMONTH(A19,-1)+1,猫统计!AB:AB,"<="&EOMONTH(A19,0))+COUNTIFS(猫统计!AH:AH,">="&EOMONTH(A19,-1)+1,猫统计!AH:AH,"<="&EOMONTH(A19,0))+COUNTIFS(猫统计!AN:AN,">="&EOMONTH(A19,-1)+1,猫统计!AN:AN,"<="&EOMONTH(A19,0))+COUNTIFS(猫统计!AT:AT,">="&EOMONTH(A19,-1)+1,猫统计!AT:AT,"<="&EOMONTH(A19,0))+COUNTIFS(猫统计!AZ:AZ,">="&EOMONTH(A19,-1)+1,猫统计!AZ:AZ,"<="&EOMONTH(A19,0))+COUNTIFS(猫统计!BF:BF,">="&EOMONTH(A19,-1)+1,猫统计!BF:BF,"<="&EOMONTH(A19,0))+COUNTIFS(猫统计!BL:BL,">="&EOMONTH(A19,-1)+1,猫统计!BL:BL,"<="&EOMONTH(A19,0)) -> 1 | C19: =D19+E19 -> 5 | D19: =SUMIFS(猫统计!L:L,猫统计!J:J,">="&EOMONTH(A19,-1)+1,猫统计!J:J,"<="&EOMONTH(A19,0))+SUMIFS(猫统计!R:R,猫统计!P:P,">="&EOMONTH(A19,-1)+1,猫统计!P:P,"<="&EOMONTH(A19,0))+SUMIFS(猫统计!X:X,猫统计!V:V,">="&EOMONTH(A19,-1)+1,猫统计!V:V,"<="&EOMONTH(A19,0))+SUMIFS(猫统计!AD:AD,猫统计!AB:AB,">="&EOMONTH(A19,-1)+1,猫统计!AB:AB,"<="&EOMONTH(A19,0))+SUMIFS(猫统计!AJ:AJ,猫统计!AH:AH,">="&EOMONTH(A19,-1)+1,猫统计!AH:AH,"<="&EOMONTH(A19,0))+SUMIFS(猫统计!AP:AP,猫统计!AN:AN,">="&EOMONTH(A19,-1)+1,猫统计!AN:AN,"<="&EOMONTH(A19,0))+SUMIFS(猫统计!AV:AV,猫统计!AT:AT,">="&EOMONTH(A19,-1)+1,猫统计!AT:AT,"<="&EOMONTH(A19,0))+SUMIFS(猫统计!BB:BB,猫统计!AZ:AZ,">="&EOMONTH(A19,-1)+1,猫统计!AZ:AZ,"<="&EOMONTH(A19,0))+SUMIFS(猫统计!BH:BH,猫统计!BF:BF,">="&EOMONTH(A19,-1)+1,猫统计!BF:BF,"<="&EOMONTH(A19,0))+SUMIFS(猫统计!BN:BN,猫统计!BL:BL,">="&EOMONTH(A19,-1)+1,猫统计!BL:BL,"<="&EOMONTH(A19,0)) -> 0 | E19: =SUMIFS(猫统计!M:M,猫统计!J:J,">="&EOMONTH(A19,-1)+1,猫统计!J:J,"<="&EOMONTH(A19,0))+SUMIFS(猫统计!S:S,猫统计!P:P,">="&EOMONTH(A19,-1)+1,猫统计!P:P,"<="&EOMONTH(A19,0))+SUMIFS(猫统计!Y:Y,猫统计!V:V,">="&EOMONTH(A19,-1)+1,猫统计!V:V,"<="&EOMONTH(A19,0))+SUMIFS(猫统计!AE:AE,猫统计!AB:AB,">="&EOMONTH(A19,-1)+1,猫统计!AB:AB,"<="&EOMONTH(A19,0))+SUMIFS(猫统计!AK:AK,猫统计!AH:AH,">="&EOMONTH(A19,-1)+1,猫统计!AH:AH,"<="&EOMONTH(A19,0))+SUMIFS(猫统计!AQ:AQ,猫统计!AN:AN,">="&EOMONTH(A19,-1)+1,猫统计!AN:AN,"<="&EOMONTH(A19,0))+SUMIFS(猫统计!AW:AW,猫统计!AT:AT,">="&EOMONTH(A19,-1)+1,猫统计!AT:AT,"<="&EOMONTH(A19,0))+SUMIFS(猫统计!BC:BC,猫统计!AZ:AZ,">="&EOMONTH(A19,-1)+1,猫统计!AZ:AZ,"<="&EOMONTH(A19,0))+SUMIFS(猫统计!BI:BI,猫统计!BF:BF,">="&EOMONTH(A19,-1)+1,猫统计!BF:BF,"<="&EOMONTH(A19,0))+SUMIFS(猫统计!BO:BO,猫统计!BL:BL,">="&EOMONTH(A19,-1)+1,猫统计!BL:BL,"<="&EOMONTH(A19,0)) -> 5 | F19: =(E17+E18+E19)/(C17+C18+C19) -> 0.84 | G19: =(E17+E18+E19)/(B17+B18+B19) -> 4.2
A20: 44562 | B20: =COUNTIFS(猫统计!J:J,">="&EOMONTH(A20,-1)+1,猫统计!J:J,"<="&EOMONTH(A20,0))+COUNTIFS(猫统计!P:P,">="&EOMONTH(A20,-1)+1,猫统计!P:P,"<="&EOMONTH(A20,0))+COUNTIFS(猫统计!V:V,">="&EOMONTH(A20,-1)+1,猫统计!V:V,"<="&EOMONTH(A20,0))+COUNTIFS(猫统计!AB:AB,">="&EOMONTH(A20,-1)+1,猫统计!AB:AB,"<="&EOMONTH(A20,0))+COUNTIFS(猫统计!AH:AH,">="&EOMONTH(A20,-1)+1,猫统计!AH:AH,"<="&EOMONTH(A20,0))+COUNTIFS(猫统计!AN:AN,">="&EOMONTH(A20,-1)+1,猫统计!AN:AN,"<="&EOMONTH(A20,0))+COUNTIFS(猫统计!AT:AT,">="&EOMONTH(A20,-1)+1,猫统计!AT:AT,"<="&EOMONTH(A20,0))+COUNTIFS(猫统计!AZ:AZ,">="&EOMONTH(A20,-1)+1,猫统计!AZ:AZ,"<="&EOMONTH(A20,0))+COUNTIFS(猫统计!BF:BF,">="&EOMONTH(A20,-1)+1,猫统计!BF:BF,"<="&EOMONTH(A20,0))+COUNTIFS(猫统计!BL:BL,">="&EOMONTH(A20,-1)+1,猫统计!BL:BL,"<="&EOMONTH(A20,0)) -> 2 | C20: =D20+E20 -> 10 | D20: =SUMIFS(猫统计!L:L,猫统计!J:J,">="&EOMONTH(A20,-1)+1,猫统计!J:J,"<="&EOMONTH(A20,0))+SUMIFS(猫统计!R:R,猫统计!P:P,">="&EOMONTH(A20,-1)+1,猫统计!P:P,"<="&EOMONTH(A20,0))+SUMIFS(猫统计!X:X,猫统计!V:V,">="&EOMONTH(A20,-1)+1,猫统计!V:V,"<="&EOMONTH(A20,0))+SUMIFS(猫统计!AD:AD,猫统计!AB:AB,">="&EOMONTH(A20,-1)+1,猫统计!AB:AB,"<="&EOMONTH(A20,0))+SUMIFS(猫统计!AJ:AJ,猫统计!AH:AH,">="&EOMONTH(A20,-1)+1,猫统计!AH:AH,"<="&EOMONTH(A20,0))+SUMIFS(猫统计!AP:AP,猫统计!AN:AN,">="&EOMONTH(A20,-1)+1,猫统计!AN:AN,"<="&EOMONTH(A20,0))+SUMIFS(猫统计!AV:AV,猫统计!AT:AT,">="&EOMONTH(A20,-1)+1,猫统计!AT:AT,"<="&EOMONTH(A20,0))+SUMIFS(猫统计!BB:BB,猫统计!AZ:AZ,">="&EOMONTH(A20,-1)+1,猫统计!AZ:AZ,"<="&EOMONTH(A20,0))+SUMIFS(猫统计!BH:BH,猫统计!BF:BF,">="&EOMONTH(A20,-1)+1,猫统计!BF:BF,"<="&EOMONTH(A20,0))+SUMIFS(猫统计!BN:BN,猫统计!BL:BL,">="&EOMONTH(A20,-1)+1,猫统计!BL:BL,"<="&EOMONTH(A20,0)) -> 4 | E20: =SUMIFS(猫统计!M:M,猫统计!J:J,">="&EOMONTH(A20,-1)+1,猫统计!J:J,"<="&EOMONTH(A20,0))+SUMIFS(猫统计!S:S,猫统计!P:P,">="&EOMONTH(A20,-1)+1,猫统计!P:P,"<="&EOMONTH(A20,0))+SUMIFS(猫统计!Y:Y,猫统计!V:V,">="&EOMONTH(A20,-1)+1,猫统计!V:V,"<="&EOMONTH(A20,0))+SUMIFS(猫统计!AE:AE,猫统计!AB:AB,">="&EOMONTH(A20,-1)+1,猫统计!AB:AB,"<="&EOMONTH(A20,0))+SUMIFS(猫统计!AK:AK,猫统计!AH:AH,">="&EOMONTH(A20,-1)+1,猫统计!AH:AH,"<="&EOMONTH(A20,0))+SUMIFS(猫统计!AQ:AQ,猫统计!AN:AN,">="&EOMONTH(A20,-1)+1,猫统计!AN:AN,"<="&EOMONTH(A20,0))+SUMIFS(猫统计!AW:AW,猫统计!AT:AT,">="&EOMONTH(A20,-1)+1,猫统计!AT:AT,"<="&EOMONTH(A20,0))+SUMIFS(猫统计!BC:BC,猫统计!AZ:AZ,">="&EOMONTH(A20,-1)+1,猫统计!AZ:AZ,"<="&EOMONTH(A20,0))+SUMIFS(猫统计!BI:BI,猫统计!BF:BF,">="&EOMONTH(A20,-1)+1,猫统计!BF:BF,"<="&EOMONTH(A20,0))+SUMIFS(猫统计!BO:BO,猫统计!BL:BL,">="&EOMONTH(A20,-1)+1,猫统计!BL:BL,"<="&EOMONTH(A20,0)) -> 6
A21: 44593 | B21: =COUNTIFS(猫统计!J:J,">="&EOMONTH(A21,-1)+1,猫统计!J:J,"<="&EOMONTH(A21,0))+COUNTIFS(猫统计!P:P,">="&EOMONTH(A21,-1)+1,猫统计!P:P,"<="&EOMONTH(A21,0))+COUNTIFS(猫统计!V:V,">="&EOMONTH(A21,-1)+1,猫统计!V:V,"<="&EOMONTH(A21,0))+COUNTIFS(猫统计!AB:AB,">="&EOMONTH(A21,-1)+1,猫统计!AB:AB,"<="&EOMONTH(A21,0))+COUNTIFS(猫统计!AH:AH,">="&EOMONTH(A21,-1)+1,猫统计!AH:AH,"<="&EOMONTH(A21,0))+COUNTIFS(猫统计!AN:AN,">="&EOMONTH(A21,-1)+1,猫统计!AN:AN,"<="&EOMONTH(A21,0))+COUNTIFS(猫统计!AT:AT,">="&EOMONTH(A21,-1)+1,猫统计!AT:AT,"<="&EOMONTH(A21,0))+COUNTIFS(猫统计!AZ:AZ,">="&EOMONTH(A21,-1)+1,猫统计!AZ:AZ,"<="&EOMONTH(A21,0))+COUNTIFS(猫统计!BF:BF,">="&EOMONTH(A21,-1)+1,猫统计!BF:BF,"<="&EOMONTH(A21,0))+COUNTIFS(猫统计!BL:BL,">="&EOMONTH(A21,-1)+1,猫统计!BL:BL,"<="&EOMONTH(A21,0)) -> 1 | C21: =D21+E21 -> 4 | D21: =SUMIFS(猫统计!L:L,猫统计!J:J,">="&EOMONTH(A21,-1)+1,猫统计!J:J,"<="&EOMONTH(A21,0))+SUMIFS(猫统计!R:R,猫统计!P:P,">="&EOMONTH(A21,-1)+1,猫统计!P:P,"<="&EOMONTH(A21,0))+SUMIFS(猫统计!X:X,猫统计!V:V,">="&EOMONTH(A21,-1)+1,猫统计!V:V,"<="&EOMONTH(A21,0))+SUMIFS(猫统计!AD:AD,猫统计!AB:AB,">="&EOMONTH(A21,-1)+1,猫统计!AB:AB,"<="&EOMONTH(A21,0))+SUMIFS(猫统计!AJ:AJ,猫统计!AH:AH,">="&EOMONTH(A21,-1)+1,猫统计!AH:AH,"<="&EOMONTH(A21,0))+SUMIFS(猫统计!AP:AP,猫统计!AN:AN,">="&EOMONTH(A21,-1)+1,猫统计!AN:AN,"<="&EOMONTH(A21,0))+SUMIFS(猫统计!AV:AV,猫统计!AT:AT,">="&EOMONTH(A21,-1)+1,猫统计!AT:AT,"<="&EOMONTH(A21,0))+SUMIFS(猫统计!BB:BB,猫统计!AZ:AZ,">="&EOMONTH(A21,-1)+1,猫统计!AZ:AZ,"<="&EOMONTH(A21,0))+SUMIFS(猫统计!BH:BH,猫统计!BF:BF,">="&EOMONTH(A21,-1)+1,猫统计!BF:BF,"<="&EOMONTH(A21,0))+SUMIFS(猫统计!BN:BN,猫统计!BL:BL,">="&EOMONTH(A21,-1)+1,猫统计!BL:BL,"<="&EOMONTH(A21,0)) -> 0 | E21: =SUMIFS(猫统计!M:M,猫统计!J:J,">="&EOMONTH(A21,-1)+1,猫统计!J:J,"<="&EOMONTH(A21,0))+SUMIFS(猫统计!S:S,猫统计!P:P,">="&EOMONTH(A21,-1)+1,猫统计!P:P,"<="&EOMONTH(A21,0))+SUMIFS(猫统计!Y:Y,猫统计!V:V,">="&EOMONTH(A21,-1)+1,猫统计!V:V,"<="&EOMONTH(A21,0))+SUMIFS(猫统计!AE:AE,猫统计!AB:AB,">="&EOMONTH(A21,-1)+1,猫统计!AB:AB,"<="&EOMONTH(A21,0))+SUMIFS(猫统计!AK:AK,猫统计!AH:AH,">="&EOMONTH(A21,-1)+1,猫统计!AH:AH,"<="&EOMONTH(A21,0))+SUMIFS(猫统计!AQ:AQ,猫统计!AN:AN,">="&EOMONTH(A21,-1)+1,猫统计!AN:AN,"<="&EOMONTH(A21,0))+SUMIFS(猫统计!AW:AW,猫统计!AT:AT,">="&EOMONTH(A21,-1)+1,猫统计!AT:AT,"<="&EOMONTH(A21,0))+SUMIFS(猫统计!BC:BC,猫统计!AZ:AZ,">="&EOMONTH(A21,-1)+1,猫统计!AZ:AZ,"<="&EOMONTH(A21,0))+SUMIFS(猫统计!BI:BI,猫统计!BF:BF,">="&EOMONTH(A21,-1)+1,猫统计!BF:BF,"<="&EOMONTH(A21,0))+SUMIFS(猫统计!BO:BO,猫统计!BL:BL,">="&EOMONTH(A21,-1)+1,猫统计!BL:BL,"<="&EOMONTH(A21,0)) -> 4
A22: 44621 | B22: =COUNTIFS(猫统计!J:J,">="&EOMONTH(A22,-1)+1,猫统计!J:J,"<="&EOMONTH(A22,0))+COUNTIFS(猫统计!P:P,">="&EOMONTH(A22,-1)+1,猫统计!P:P,"<="&EOMONTH(A22,0))+COUNTIFS(猫统计!V:V,">="&EOMONTH(A22,-1)+1,猫统计!V:V,"<="&EOMONTH(A22,0))+COUNTIFS(猫统计!AB:AB,">="&EOMONTH(A22,-1)+1,猫统计!AB:AB,"<="&EOMONTH(A22,0))+COUNTIFS(猫统计!AH:AH,">="&EOMONTH(A22,-1)+1,猫统计!AH:AH,"<="&EOMONTH(A22,0))+COUNTIFS(猫统计!AN:AN,">="&EOMONTH(A22,-1)+1,猫统计!AN:AN,"<="&EOMONTH(A22,0))+COUNTIFS(猫统计!AT:AT,">="&EOMONTH(A22,-1)+1,猫统计!AT:AT,"<="&EOMONTH(A22,0))+COUNTIFS(猫统计!AZ:AZ,">="&EOMONTH(A22,-1)+1,猫统计!AZ:AZ,"<="&EOMONTH(A22,0))+COUNTIFS(猫统计!BF:BF,">="&EOMONTH(A22,-1)+1,猫统计!BF:BF,"<="&EOMONTH(A22,0))+COUNTIFS(猫统计!BL:BL,">="&EOMONTH(A22,-1)+1,猫统计!BL:BL,"<="&EOMONTH(A22,0)) -> 2 | C22: =D22+E22 -> 11 | D22: =SUMIFS(猫统计!L:L,猫统计!J:J,">="&EOMONTH(A22,-1)+1,猫统计!J:J,"<="&EOMONTH(A22,0))+SUMIFS(猫统计!R:R,猫统计!P:P,">="&EOMONTH(A22,-1)+1,猫统计!P:P,"<="&EOMONTH(A22,0))+SUMIFS(猫统计!X:X,猫统计!V:V,">="&EOMONTH(A22,-1)+1,猫统计!V:V,"<="&EOMONTH(A22,0))+SUMIFS(猫统计!AD:AD,猫统计!AB:AB,">="&EOMONTH(A22,-1)+1,猫统计!AB:AB,"<="&EOMONTH(A22,0))+SUMIFS(猫统计!AJ:AJ,猫统计!AH:AH,">="&EOMONTH(A22,-1)+1,猫统计!AH:AH,"<="&EOMONTH(A22,0))+SUMIFS(猫统计!AP:AP,猫统计!AN:AN,">="&EOMONTH(A22,-1)+1,猫统计!AN:AN,"<="&EOMONTH(A22,0))+SUMIFS(猫统计!AV:AV,猫统计!AT:AT,">="&EOMONTH(A22,-1)+1,猫统计!AT:AT,"<="&EOMONTH(A22,0))+SUMIFS(猫统计!BB:BB,猫统计!AZ:AZ,">="&EOMONTH(A22,-1)+1,猫统计!AZ:AZ,"<="&EOMONTH(A22,0))+SUMIFS(猫统计!BH:BH,猫统计!BF:BF,">="&EOMONTH(A22,-1)+1,猫统计!BF:BF,"<="&EOMONTH(A22,0))+SUMIFS(猫统计!BN:BN,猫统计!BL:BL,">="&EOMONTH(A22,-1)+1,猫统计!BL:BL,"<="&EOMONTH(A22,0)) -> 1 | E22: =SUMIFS(猫统计!M:M,猫统计!J:J,">="&EOMONTH(A22,-1)+1,猫统计!J:J,"<="&EOMONTH(A22,0))+SUMIFS(猫统计!S:S,猫统计!P:P,">="&EOMONTH(A22,-1)+1,猫统计!P:P,"<="&EOMONTH(A22,0))+SUMIFS(猫统计!Y:Y,猫统计!V:V,">="&EOMONTH(A22,-1)+1,猫统计!V:V,"<="&EOMONTH(A22,0))+SUMIFS(猫统计!AE:AE,猫统计!AB:AB,">="&EOMONTH(A22,-1)+1,猫统计!AB:AB,"<="&EOMONTH(A22,0))+SUMIFS(猫统计!AK:AK,猫统计!AH:AH,">="&EOMONTH(A22,-1)+1,猫统计!AH:AH,"<="&EOMONTH(A22,0))+SUMIFS(猫统计!AQ:AQ,猫统计!AN:AN,">="&EOMONTH(A22,-1)+1,猫统计!AN:AN,"<="&EOMONTH(A22,0))+SUMIFS(猫统计!AW:AW,猫统计!AT:AT,">="&EOMONTH(A22,-1)+1,猫统计!AT:AT,"<="&EOMONTH(A22,0))+SUMIFS(猫统计!BC:BC,猫统计!AZ:AZ,">="&EOMONTH(A22,-1)+1,猫统计!AZ:AZ,"<="&EOMONTH(A22,0))+SUMIFS(猫统计!BI:BI,猫统计!BF:BF,">="&EOMONTH(A22,-1)+1,猫统计!BF:BF,"<="&EOMONTH(A22,0))+SUMIFS(猫统计!BO:BO,猫统计!BL:BL,">="&EOMONTH(A22,-1)+1,猫统计!BL:BL,"<="&EOMONTH(A22,0)) -> 10 | F22: =(E20+E21+E22)/(C20+C21+C22) -> 0.8 | G22: =(E20+E21+E22)/(B20+B21+B22) -> 4
A23: 44652 | B23: =COUNTIFS(猫统计!J:J,">="&EOMONTH(A23,-1)+1,猫统计!J:J,"<="&EOMONTH(A23,0))+COUNTIFS(猫统计!P:P,">="&EOMONTH(A23,-1)+1,猫统计!P:P,"<="&EOMONTH(A23,0))+COUNTIFS(猫统计!V:V,">="&EOMONTH(A23,-1)+1,猫统计!V:V,"<="&EOMONTH(A23,0))+COUNTIFS(猫统计!AB:AB,">="&EOMONTH(A23,-1)+1,猫统计!AB:AB,"<="&EOMONTH(A23,0))+COUNTIFS(猫统计!AH:AH,">="&EOMONTH(A23,-1)+1,猫统计!AH:AH,"<="&EOMONTH(A23,0))+COUNTIFS(猫统计!AN:AN,">="&EOMONTH(A23,-1)+1,猫统计!AN:AN,"<="&EOMONTH(A23,0))+COUNTIFS(猫统计!AT:AT,">="&EOMONTH(A23,-1)+1,猫统计!AT:AT,"<="&EOMONTH(A23,0))+COUNTIFS(猫统计!AZ:AZ,">="&EOMONTH(A23,-1)+1,猫统计!AZ:AZ,"<="&EOMONTH(A23,0))+COUNTIFS(猫统计!BF:BF,">="&EOMONTH(A23,-1)+1,猫统计!BF:BF,"<="&EOMONTH(A23,0))+COUNTIFS(猫统计!BL:BL,">="&EOMONTH(A23,-1)+1,猫统计!BL:BL,"<="&EOMONTH(A23,0)) -> 5 | C23: =D23+E23 -> 19 | D23: =SUMIFS(猫统计!L:L,猫统计!J:J,">="&EOMONTH(A23,-1)+1,猫统计!J:J,"<="&EOMONTH(A23,0))+SUMIFS(猫统计!R:R,猫统计!P:P,">="&EOMONTH(A23,-1)+1,猫统计!P:P,"<="&EOMONTH(A23,0))+SUMIFS(猫统计!X:X,猫统计!V:V,">="&EOMONTH(A23,-1)+1,猫统计!V:V,"<="&EOMONTH(A23,0))+SUMIFS(猫统计!AD:AD,猫统计!AB:AB,">="&EOMONTH(A23,-1)+1,猫统计!AB:AB,"<="&EOMONTH(A23,0))+SUMIFS(猫统计!AJ:AJ,猫统计!AH:AH,">="&EOMONTH(A23,-1)+1,猫统计!AH:AH,"<="&EOMONTH(A23,0))+SUMIFS(猫统计!AP:AP,猫统计!AN:AN,">="&EOMONTH(A23,-1)+1,猫统计!AN:AN,"<="&EOMONTH(A23,0))+SUMIFS(猫统计!AV:AV,猫统计!AT:AT,">="&EOMONTH(A23,-1)+1,猫统计!AT:AT,"<="&EOMONTH(A23,0))+SUMIFS(猫统计!BB:BB,猫统计!AZ:AZ,">="&EOMONTH(A23,-1)+1,猫统计!AZ:AZ,"<="&EOMONTH(A23,0))+SUMIFS(猫统计!BH:BH,猫统计!BF:BF,">="&EOMONTH(A23,-1)+1,猫统计!BF:BF,"<="&EOMONTH(A23,0))+SUMIFS(猫统计!BN:BN,猫统计!BL:BL,">="&EOMONTH(A23,-1)+1,猫统计!BL:BL,"<="&EOMONTH(A23,0)) -> 10 | E23: =SUMIFS(猫统计!M:M,猫统计!J:J,">="&EOMONTH(A23,-1)+1,猫统计!J:J,"<="&EOMONTH(A23,0))+SUMIFS(猫统计!S:S,猫统计!P:P,">="&EOMONTH(A23,-1)+1,猫统计!P:P,"<="&EOMONTH(A23,0))+SUMIFS(猫统计!Y:Y,猫统计!V:V,">="&EOMONTH(A23,-1)+1,猫统计!V:V,"<="&EOMONTH(A23,0))+SUMIFS(猫统计!AE:AE,猫统计!AB:AB,">="&EOMONTH(A23,-1)+1,猫统计!AB:AB,"<="&EOMONTH(A23,0))+SUMIFS(猫统计!AK:AK,猫统计!AH:AH,">="&EOMONTH(A23,-1)+1,猫统计!AH:AH,"<="&EOMONTH(A23,0))+SUMIFS(猫统计!AQ:AQ,猫统计!AN:AN,">="&EOMONTH(A23,-1)+1,猫统计!AN:AN,"<="&EOMONTH(A23,0))+SUMIFS(猫统计!AW:AW,猫统计!AT:AT,">="&EOMONTH(A23,-1)+1,猫统计!AT:AT,"<="&EOMONTH(A23,0))+SUMIFS(猫统计!BC:BC,猫统计!AZ:AZ,">="&EOMONTH(A23,-1)+1,猫统计!AZ:AZ,"<="&EOMONTH(A23,0))+SUMIFS(猫统计!BI:BI,猫统计!BF:BF,">="&EOMONTH(A23,-1)+1,猫统计!BF:BF,"<="&EOMONTH(A23,0))+SUMIFS(猫统计!BO:BO,猫统计!BL:BL,">="&EOMONTH(A23,-1)+1,猫统计!BL:BL,"<="&EOMONTH(A23,0)) -> 9
A24: 44682 | B24: =COUNTIFS(猫统计!J:J,">="&EOMONTH(A24,-1)+1,猫统计!J:J,"<="&EOMONTH(A24,0))+COUNTIFS(猫统计!P:P,">="&EOMONTH(A24,-1)+1,猫统计!P:P,"<="&EOMONTH(A24,0))+COUNTIFS(猫统计!V:V,">="&EOMONTH(A24,-1)+1,猫统计!V:V,"<="&EOMONTH(A24,0))+COUNTIFS(猫统计!AB:AB,">="&EOMONTH(A24,-1)+1,猫统计!AB:AB,"<="&EOMONTH(A24,0))+COUNTIFS(猫统计!AH:AH,">="&EOMONTH(A24,-1)+1,猫统计!AH:AH,"<="&EOMONTH(A24,0))+COUNTIFS(猫统计!AN:AN,">="&EOMONTH(A24,-1)+1,猫统计!AN:AN,"<="&EOMONTH(A24,0))+COUNTIFS(猫统计!AT:AT,">="&EOMONTH(A24,-1)+1,猫统计!AT:AT,"<="&EOMONTH(A24,0))+COUNTIFS(猫统计!AZ:AZ,">="&EOMONTH(A24,-1)+1,猫统计!AZ:AZ,"<="&EOMONTH(A24,0))+COUNTIFS(猫统计!BF:BF,">="&EOMONTH(A24,-1)+1,猫统计!BF:BF,"<="&EOMONTH(A24,0))+COUNTIFS(猫统计!BL:BL,">="&EOMONTH(A24,-1)+1,猫统计!BL:BL,"<="&EOMONTH(A24,0)) -> 2 | C24: =D24+E24 -> 10 | D24: =SUMIFS(猫统计!L:L,猫统计!J:J,">="&EOMONTH(A24,-1)+1,猫统计!J:J,"<="&EOMONTH(A24,0))+SUMIFS(猫统计!R:R,猫统计!P:P,">="&EOMONTH(A24,-1)+1,猫统计!P:P,"<="&EOMONTH(A24,0))+SUMIFS(猫统计!X:X,猫统计!V:V,">="&EOMONTH(A24,-1)+1,猫统计!V:V,"<="&EOMONTH(A24,0))+SUMIFS(猫统计!AD:AD,猫统计!AB:AB,">="&EOMONTH(A24,-1)+1,猫统计!AB:AB,"<="&EOMONTH(A24,0))+SUMIFS(猫统计!AJ:AJ,猫统计!AH:AH,">="&EOMONTH(A24,-1)+1,猫统计!AH:AH,"<="&EOMONTH(A24,0))+SUMIFS(猫统计!AP:AP,猫统计!AN:AN,">="&EOMONTH(A24,-1)+1,猫统计!AN:AN,"<="&EOMONTH(A24,0))+SUMIFS(猫统计!AV:AV,猫统计!AT:AT,">="&EOMONTH(A24,-1)+1,猫统计!AT:AT,"<="&EOMONTH(A24,0))+SUMIFS(猫统计!BB:BB,猫统计!AZ:AZ,">="&EOMONTH(A24,-1)+1,猫统计!AZ:AZ,"<="&EOMONTH(A24,0))+SUMIFS(猫统计!BH:BH,猫统计!BF:BF,">="&EOMONTH(A24,-1)+1,猫统计!BF:BF,"<="&EOMONTH(A24,0))+SUMIFS(猫统计!BN:BN,猫统计!BL:BL,">="&EOMONTH(A24,-1)+1,猫统计!BL:BL,"<="&EOMONTH(A24,0)) -> 1 | E24: =SUMIFS(猫统计!M:M,猫统计!J:J,">="&EOMONTH(A24,-1)+1,猫统计!J:J,"<="&EOMONTH(A24,0))+SUMIFS(猫统计!S:S,猫统计!P:P,">="&EOMONTH(A24,-1)+1,猫统计!P:P,"<="&EOMONTH(A24,0))+SUMIFS(猫统计!Y:Y,猫统计!V:V,">="&EOMONTH(A24,-1)+1,猫统计!V:V,"<="&EOMONTH(A24,0))+SUMIFS(猫统计!AE:AE,猫统计!AB:AB,">="&EOMONTH(A24,-1)+1,猫统计!AB:AB,"<="&EOMONTH(A24,0))+SUMIFS(猫统计!AK:AK,猫统计!AH:AH,">="&EOMONTH(A24,-1)+1,猫统计!AH:AH,"<="&EOMONTH(A24,0))+SUMIFS(猫统计!AQ:AQ,猫统计!AN:AN,">="&EOMONTH(A24,-1)+1,猫统计!AN:AN,"<="&EOMONTH(A24,0))+SUMIFS(猫统计!AW:AW,猫统计!AT:AT,">="&EOMONTH(A24,-1)+1,猫统计!AT:AT,"<="&EOMONTH(A24,0))+SUMIFS(猫统计!BC:BC,猫统计!AZ:AZ,">="&EOMONTH(A24,-1)+1,猫统计!AZ:AZ,"<="&EOMONTH(A24,0))+SUMIFS(猫统计!BI:BI,猫统计!BF:BF,">="&EOMONTH(A24,-1)+1,猫统计!BF:BF,"<="&EOMONTH(A24,0))+SUMIFS(猫统计!BO:BO,猫统计!BL:BL,">="&EOMONTH(A24,-1)+1,猫统计!BL:BL,"<="&EOMONTH(A24,0)) -> 9
A25: 44713 | B25: =COUNTIFS(猫统计!J:J,">="&EOMONTH(A25,-1)+1,猫统计!J:J,"<="&EOMONTH(A25,0))+COUNTIFS(猫统计!P:P,">="&EOMONTH(A25,-1)+1,猫统计!P:P,"<="&EOMONTH(A25,0))+COUNTIFS(猫统计!V:V,">="&EOMONTH(A25,-1)+1,猫统计!V:V,"<="&EOMONTH(A25,0))+COUNTIFS(猫统计!AB:AB,">="&EOMONTH(A25,-1)+1,猫统计!AB:AB,"<="&EOMONTH(A25,0))+COUNTIFS(猫统计!AH:AH,">="&EOMONTH(A25,-1)+1,猫统计!AH:AH,"<="&EOMONTH(A25,0))+COUNTIFS(猫统计!AN:AN,">="&EOMONTH(A25,-1)+1,猫统计!AN:AN,"<="&EOMONTH(A25,0))+COUNTIFS(猫统计!AT:AT,">="&EOMONTH(A25,-1)+1,猫统计!AT:AT,"<="&EOMONTH(A25,0))+COUNTIFS(猫统计!AZ:AZ,">="&EOMONTH(A25,-1)+1,猫统计!AZ:AZ,"<="&EOMONTH(A25,0))+COUNTIFS(猫统计!BF:BF,">="&EOMONTH(A25,-1)+1,猫统计!BF:BF,"<="&EOMONTH(A25,0))+COUNTIFS(猫统计!BL:BL,">="&EOMONTH(A25,-1)+1,猫统计!BL:BL,"<="&EOMONTH(A25,0)) -> 5 | C25: =D25+E25 -> 26 | D25: =SUMIFS(猫统计!L:L,猫统计!J:J,">="&EOMONTH(A25,-1)+1,猫统计!J:J,"<="&EOMONTH(A25,0))+SUMIFS(猫统计!R:R,猫统计!P:P,">="&EOMONTH(A25,-1)+1,猫统计!P:P,"<="&EOMONTH(A25,0))+SUMIFS(猫统计!X:X,猫统计!V:V,">="&EOMONTH(A25,-1)+1,猫统计!V:V,"<="&EOMONTH(A25,0))+SUMIFS(猫统计!AD:AD,猫统计!AB:AB,">="&EOMONTH(A25,-1)+1,猫统计!AB:AB,"<="&EOMONTH(A25,0))+SUMIFS(猫统计!AJ:AJ,猫统计!AH:AH,">="&EOMONTH(A25,-1)+1,猫统计!AH:AH,"<="&EOMONTH(A25,0))+SUMIFS(猫统计!AP:AP,猫统计!AN:AN,">="&EOMONTH(A25,-1)+1,猫统计!AN:AN,"<="&EOMONTH(A25,0))+SUMIFS(猫统计!AV:AV,猫统计!AT:AT,">="&EOMONTH(A25,-1)+1,猫统计!AT:AT,"<="&EOMONTH(A25,0))+SUMIFS(猫统计!BB:BB,猫统计!AZ:AZ,">="&EOMONTH(A25,-1)+1,猫统计!AZ:AZ,"<="&EOMONTH(A25,0))+SUMIFS(猫统计!BH:BH,猫统计!BF:BF,">="&EOMONTH(A25,-1)+1,猫统计!BF:BF,"<="&EOMONTH(A25,0))+SUMIFS(猫统计!BN:BN,猫统计!BL:BL,">="&EOMONTH(A25,-1)+1,猫统计!BL:BL,"<="&EOMONTH(A25,0)) -> 10 | E25: =SUMIFS(猫统计!M:M,猫统计!J:J,">="&EOMONTH(A25,-1)+1,猫统计!J:J,"<="&EOMONTH(A25,0))+SUMIFS(猫统计!S:S,猫统计!P:P,">="&EOMONTH(A25,-1)+1,猫统计!P:P,"<="&EOMONTH(A25,0))+SUMIFS(猫统计!Y:Y,猫统计!V:V,">="&EOMONTH(A25,-1)+1,猫统计!V:V,"<="&EOMONTH(A25,0))+SUMIFS(猫统计!AE:AE,猫统计!AB:AB,">="&EOMONTH(A25,-1)+1,猫统计!AB:AB,"<="&EOMONTH(A25,0))+SUMIFS(猫统计!AK:AK,猫统计!AH:AH,">="&EOMONTH(A25,-1)+1,猫统计!AH:AH,"<="&EOMONTH(A25,0))+SUMIFS(猫统计!AQ:AQ,猫统计!AN:AN,">="&EOMONTH(A25,-1)+1,猫统计!AN:AN,"<="&EOMONTH(A25,0))+SUMIFS(猫统计!AW:AW,猫统计!AT:AT,">="&EOMONTH(A25,-1)+1,猫统计!AT:AT,"<="&EOMONTH(A25,0))+SUMIFS(猫统计!BC:BC,猫统计!AZ:AZ,">="&EOMONTH(A25,-1)+1,猫统计!AZ:AZ,"<="&EOMONTH(A25,0))+SUMIFS(猫统计!BI:BI,猫统计!BF:BF,">="&EOMONTH(A25,-1)+1,猫统计!BF:BF,"<="&EOMONTH(A25,0))+SUMIFS(猫统计!BO:BO,猫统计!BL:BL,">="&EOMONTH(A25,-1)+1,猫统计!BL:BL,"<="&EOMONTH(A25,0)) -> 16 | F25: =(E23+E24+E25)/(C23+C24+C25) -> 0.61818182 | G25: =(E23+E24+E25)/(B23+B24+B25) -> 2.8333333
A26: 44743 | B26: =COUNTIFS(猫统计!J:J,">="&EOMONTH(A26,-1)+1,猫统计!J:J,"<="&EOMONTH(A26,0))+COUNTIFS(猫统计!P:P,">="&EOMONTH(A26,-1)+1,猫统计!P:P,"<="&EOMONTH(A26,0))+COUNTIFS(猫统计!V:V,">="&EOMONTH(A26,-1)+1,猫统计!V:V,"<="&EOMONTH(A26,0))+COUNTIFS(猫统计!AB:AB,">="&EOMONTH(A26,-1)+1,猫统计!AB:AB,"<="&EOMONTH(A26,0))+COUNTIFS(猫统计!AH:AH,">="&EOMONTH(A26,-1)+1,猫统计!AH:AH,"<="&EOMONTH(A26,0))+COUNTIFS(猫统计!AN:AN,">="&EOMONTH(A26,-1)+1,猫统计!AN:AN,"<="&EOMONTH(A26,0))+COUNTIFS(猫统计!AT:AT,">="&EOMONTH(A26,-1)+1,猫统计!AT:AT,"<="&EOMONTH(A26,0))+COUNTIFS(猫统计!AZ:AZ,">="&EOMONTH(A26,-1)+1,猫统计!AZ:AZ,"<="&EOMONTH(A26,0))+COUNTIFS(猫统计!BF:BF,">="&EOMONTH(A26,-1)+1,猫统计!BF:BF,"<="&EOMONTH(A26,0))+COUNTIFS(猫统计!BL:BL,">="&EOMONTH(A26,-1)+1,猫统计!BL:BL,"<="&EOMONTH(A26,0)) -> 5 | C26: =D26+E26 -> 22 | D26: =SUMIFS(猫统计!L:L,猫统计!J:J,">="&EOMONTH(A26,-1)+1,猫统计!J:J,"<="&EOMONTH(A26,0))+SUMIFS(猫统计!R:R,猫统计!P:P,">="&EOMONTH(A26,-1)+1,猫统计!P:P,"<="&EOMONTH(A26,0))+SUMIFS(猫统计!X:X,猫统计!V:V,">="&EOMONTH(A26,-1)+1,猫统计!V:V,"<="&EOMONTH(A26,0))+SUMIFS(猫统计!AD:AD,猫统计!AB:AB,">="&EOMONTH(A26,-1)+1,猫统计!AB:AB,"<="&EOMONTH(A26,0))+SUMIFS(猫统计!AJ:AJ,猫统计!AH:AH,">="&EOMONTH(A26,-1)+1,猫统计!AH:AH,"<="&EOMONTH(A26,0))+SUMIFS(猫统计!AP:AP,猫统计!AN:AN,">="&EOMONTH(A26,-1)+1,猫统计!AN:AN,"<="&EOMONTH(A26,0))+SUMIFS(猫统计!AV:AV,猫统计!AT:AT,">="&EOMONTH(A26,-1)+1,猫统计!AT:AT,"<="&EOMONTH(A26,0))+SUMIFS(猫统计!BB:BB,猫统计!AZ:AZ,">="&EOMONTH(A26,-1)+1,猫统计!AZ:AZ,"<="&EOMONTH(A26,0))+SUMIFS(猫统计!BH:BH,猫统计!BF:BF,">="&EOMONTH(A26,-1)+1,猫统计!BF:BF,"<="&EOMONTH(A26,0))+SUMIFS(猫统计!BN:BN,猫统计!BL:BL,">="&EOMONTH(A26,-1)+1,猫统计!BL:BL,"<="&EOMONTH(A26,0)) -> 11 | E26: =SUMIFS(猫统计!M:M,猫统计!J:J,">="&EOMONTH(A26,-1)+1,猫统计!J:J,"<="&EOMONTH(A26,0))+SUMIFS(猫统计!S:S,猫统计!P:P,">="&EOMONTH(A26,-1)+1,猫统计!P:P,"<="&EOMONTH(A26,0))+SUMIFS(猫统计!Y:Y,猫统计!V:V,">="&EOMONTH(A26,-1)+1,猫统计!V:V,"<="&EOMONTH(A26,0))+SUMIFS(猫统计!AE:AE,猫统计!AB:AB,">="&EOMONTH(A26,-1)+1,猫统计!AB:AB,"<="&EOMONTH(A26,0))+SUMIFS(猫统计!AK:AK,猫统计!AH:AH,">="&EOMONTH(A26,-1)+1,猫统计!AH:AH,"<="&EOMONTH(A26,0))+SUMIFS(猫统计!AQ:AQ,猫统计!AN:AN,">="&EOMONTH(A26,-1)+1,猫统计!AN:AN,"<="&EOMONTH(A26,0))+SUMIFS(猫统计!AW:AW,猫统计!AT:AT,">="&EOMONTH(A26,-1)+1,猫统计!AT:AT,"<="&EOMONTH(A26,0))+SUMIFS(猫统计!BC:BC,猫统计!AZ:AZ,">="&EOMONTH(A26,-1)+1,猫统计!AZ:AZ,"<="&EOMONTH(A26,0))+SUMIFS(猫统计!BI:BI,猫统计!BF:BF,">="&EOMONTH(A26,-1)+1,猫统计!BF:BF,"<="&EOMONTH(A26,0))+SUMIFS(猫统计!BO:BO,猫统计!BL:BL,">="&EOMONTH(A26,-1)+1,猫统计!BL:BL,"<="&EOMONTH(A26,0)) -> 11
A27: 44774 | B27: =COUNTIFS(猫统计!J:J,">="&EOMONTH(A27,-1)+1,猫统计!J:J,"<="&EOMONTH(A27,0))+COUNTIFS(猫统计!P:P,">="&EOMONTH(A27,-1)+1,猫统计!P:P,"<="&EOMONTH(A27,0))+COUNTIFS(猫统计!V:V,">="&EOMONTH(A27,-1)+1,猫统计!V:V,"<="&EOMONTH(A27,0))+COUNTIFS(猫统计!AB:AB,">="&EOMONTH(A27,-1)+1,猫统计!AB:AB,"<="&EOMONTH(A27,0))+COUNTIFS(猫统计!AH:AH,">="&EOMONTH(A27,-1)+1,猫统计!AH:AH,"<="&EOMONTH(A27,0))+COUNTIFS(猫统计!AN:AN,">="&EOMONTH(A27,-1)+1,猫统计!AN:AN,"<="&EOMONTH(A27,0))+COUNTIFS(猫统计!AT:AT,">="&EOMONTH(A27,-1)+1,猫统计!AT:AT,"<="&EOMONTH(A27,0))+COUNTIFS(猫统计!AZ:AZ,">="&EOMONTH(A27,-1)+1,猫统计!AZ:AZ,"<="&EOMONTH(A27,0))+COUNTIFS(猫统计!BF:BF,">="&EOMONTH(A27,-1)+1,猫统计!BF:BF,"<="&EOMONTH(A27,0))+COUNTIFS(猫统计!BL:BL,">="&EOMONTH(A27,-1)+1,猫统计!BL:BL,"<="&EOMONTH(A27,0)) -> 2 | C27: =D27+E27 -> 9 | D27: =SUMIFS(猫统计!L:L,猫统计!J:J,">="&EOMONTH(A27,-1)+1,猫统计!J:J,"<="&EOMONTH(A27,0))+SUMIFS(猫统计!R:R,猫统计!P:P,">="&EOMONTH(A27,-1)+1,猫统计!P:P,"<="&EOMONTH(A27,0))+SUMIFS(猫统计!X:X,猫统计!V:V,">="&EOMONTH(A27,-1)+1,猫统计!V:V,"<="&EOMONTH(A27,0))+SUMIFS(猫统计!AD:AD,猫统计!AB:AB,">="&EOMONTH(A27,-1)+1,猫统计!AB:AB,"<="&EOMONTH(A27,0))+SUMIFS(猫统计!AJ:AJ,猫统计!AH:AH,">="&EOMONTH(A27,-1)+1,猫统计!AH:AH,"<="&EOMONTH(A27,0))+SUMIFS(猫统计!AP:AP,猫统计!AN:AN,">="&EOMONTH(A27,-1)+1,猫统计!AN:AN,"<="&EOMONTH(A27,0))+SUMIFS(猫统计!AV:AV,猫统计!AT:AT,">="&EOMONTH(A27,-1)+1,猫统计!AT:AT,"<="&EOMONTH(A27,0))+SUMIFS(猫统计!BB:BB,猫统计!AZ:AZ,">="&EOMONTH(A27,-1)+1,猫统计!AZ:AZ,"<="&EOMONTH(A27,0))+SUMIFS(猫统计!BH:BH,猫统计!BF:BF,">="&EOMONTH(A27,-1)+1,猫统计!BF:BF,"<="&EOMONTH(A27,0))+SUMIFS(猫统计!BN:BN,猫统计!BL:BL,">="&EOMONTH(A27,-1)+1,猫统计!BL:BL,"<="&EOMONTH(A27,0)) -> 1 | E27: =SUMIFS(猫统计!M:M,猫统计!J:J,">="&EOMONTH(A27,-1)+1,猫统计!J:J,"<="&EOMONTH(A27,0))+SUMIFS(猫统计!S:S,猫统计!P:P,">="&EOMONTH(A27,-1)+1,猫统计!P:P,"<="&EOMONTH(A27,0))+SUMIFS(猫统计!Y:Y,猫统计!V:V,">="&EOMONTH(A27,-1)+1,猫统计!V:V,"<="&EOMONTH(A27,0))+SUMIFS(猫统计!AE:AE,猫统计!AB:AB,">="&EOMONTH(A27,-1)+1,猫统计!AB:AB,"<="&EOMONTH(A27,0))+SUMIFS(猫统计!AK:AK,猫统计!AH:AH,">="&EOMONTH(A27,-1)+1,猫统计!AH:AH,"<="&EOMONTH(A27,0))+SUMIFS(猫统计!AQ:AQ,猫统计!AN:AN,">="&EOMONTH(A27,-1)+1,猫统计!AN:AN,"<="&EOMONTH(A27,0))+SUMIFS(猫统计!AW:AW,猫统计!AT:AT,">="&EOMONTH(A27,-1)+1,猫统计!AT:AT,"<="&EOMONTH(A27,0))+SUMIFS(猫统计!BC:BC,猫统计!AZ:AZ,">="&EOMONTH(A27,-1)+1,猫统计!AZ:AZ,"<="&EOMONTH(A27,0))+SUMIFS(猫统计!BI:BI,猫统计!BF:BF,">="&EOMONTH(A27,-1)+1,猫统计!BF:BF,"<="&EOMONTH(A27,0))+SUMIFS(猫统计!BO:BO,猫统计!BL:BL,">="&EOMONTH(A27,-1)+1,猫统计!BL:BL,"<="&EOMONTH(A27,0)) -> 8
A28: 44805 | B28: =COUNTIFS(猫统计!J:J,">="&EOMONTH(A28,-1)+1,猫统计!J:J,"<="&EOMONTH(A28,0))+COUNTIFS(猫统计!P:P,">="&EOMONTH(A28,-1)+1,猫统计!P:P,"<="&EOMONTH(A28,0))+COUNTIFS(猫统计!V:V,">="&EOMONTH(A28,-1)+1,猫统计!V:V,"<="&EOMONTH(A28,0))+COUNTIFS(猫统计!AB:AB,">="&EOMONTH(A28,-1)+1,猫统计!AB:AB,"<="&EOMONTH(A28,0))+COUNTIFS(猫统计!AH:AH,">="&EOMONTH(A28,-1)+1,猫统计!AH:AH,"<="&EOMONTH(A28,0))+COUNTIFS(猫统计!AN:AN,">="&EOMONTH(A28,-1)+1,猫统计!AN:AN,"<="&EOMONTH(A28,0))+COUNTIFS(猫统计!AT:AT,">="&EOMONTH(A28,-1)+1,猫统计!AT:AT,"<="&EOMONTH(A28,0))+COUNTIFS(猫统计!AZ:AZ,">="&EOMONTH(A28,-1)+1,猫统计!AZ:AZ,"<="&EOMONTH(A28,0))+COUNTIFS(猫统计!BF:BF,">="&EOMONTH(A28,-1)+1,猫统计!BF:BF,"<="&EOMONTH(A28,0))+COUNTIFS(猫统计!BL:BL,">="&EOMONTH(A28,-1)+1,猫统计!BL:BL,"<="&EOMONTH(A28,0)) -> 2 | C28: =D28+E28 -> 9 | D28: =SUMIFS(猫统计!L:L,猫统计!J:J,">="&EOMONTH(A28,-1)+1,猫统计!J:J,"<="&EOMONTH(A28,0))+SUMIFS(猫统计!R:R,猫统计!P:P,">="&EOMONTH(A28,-1)+1,猫统计!P:P,"<="&EOMONTH(A28,0))+SUMIFS(猫统计!X:X,猫统计!V:V,">="&EOMONTH(A28,-1)+1,猫统计!V:V,"<="&EOMONTH(A28,0))+SUMIFS(猫统计!AD:AD,猫统计!AB:AB,">="&EOMONTH(A28,-1)+1,猫统计!AB:AB,"<="&EOMONTH(A28,0))+SUMIFS(猫统计!AJ:AJ,猫统计!AH:AH,">="&EOMONTH(A28,-1)+1,猫统计!AH:AH,"<="&EOMONTH(A28,0))+SUMIFS(猫统计!AP:AP,猫统计!AN:AN,">="&EOMONTH(A28,-1)+1,猫统计!AN:AN,"<="&EOMONTH(A28,0))+SUMIFS(猫统计!AV:AV,猫统计!AT:AT,">="&EOMONTH(A28,-1)+1,猫统计!AT:AT,"<="&EOMONTH(A28,0))+SUMIFS(猫统计!BB:BB,猫统计!AZ:AZ,">="&EOMONTH(A28,-1)+1,猫统计!AZ:AZ,"<="&EOMONTH(A28,0))+SUMIFS(猫统计!BH:BH,猫统计!BF:BF,">="&EOMONTH(A28,-1)+1,猫统计!BF:BF,"<="&EOMONTH(A28,0))+SUMIFS(猫统计!BN:BN,猫统计!BL:BL,">="&EOMONTH(A28,-1)+1,猫统计!BL:BL,"<="&EOMONTH(A28,0)) -> 0 | E28: =SUMIFS(猫统计!M:M,猫统计!J:J,">="&EOMONTH(A28,-1)+1,猫统计!J:J,"<="&EOMONTH(A28,0))+SUMIFS(猫统计!S:S,猫统计!P:P,">="&EOMONTH(A28,-1)+1,猫统计!P:P,"<="&EOMONTH(A28,0))+SUMIFS(猫统计!Y:Y,猫统计!V:V,">="&EOMONTH(A28,-1)+1,猫统计!V:V,"<="&EOMONTH(A28,0))+SUMIFS(猫统计!AE:AE,猫统计!AB:AB,">="&EOMONTH(A28,-1)+1,猫统计!AB:AB,"<="&EOMONTH(A28,0))+SUMIFS(猫统计!AK:AK,猫统计!AH:AH,">="&EOMONTH(A28,-1)+1,猫统计!AH:AH,"<="&EOMONTH(A28,0))+SUMIFS(猫统计!AQ:AQ,猫统计!AN:AN,">="&EOMONTH(A28,-1)+1,猫统计!AN:AN,"<="&EOMONTH(A28,0))+SUMIFS(猫统计!AW:AW,猫统计!AT:AT,">="&EOMONTH(A28,-1)+1,猫统计!AT:AT,"<="&EOMONTH(A28,0))+SUMIFS(猫统计!BC:BC,猫统计!AZ:AZ,">="&EOMONTH(A28,-1)+1,猫统计!AZ:AZ,"<="&EOMONTH(A28,0))+SUMIFS(猫统计!BI:BI,猫统计!BF:BF,">="&EOMONTH(A28,-1)+1,猫统计!BF:BF,"<="&EOMONTH(A28,0))+SUMIFS(猫统计!BO:BO,猫统计!BL:BL,">="&EOMONTH(A28,-1)+1,猫统计!BL:BL,"<="&EOMONTH(A28,0)) -> 9 | F28: =(E26+E27+E28)/(C26+C27+C28) -> 0.7 | G28: =(E26+E27+E28)/(B26+B27+B28) -> 3.1111111
A29: 44835 | B29: =COUNTIFS(猫统计!J:J,">="&EOMONTH(A29,-1)+1,猫统计!J:J,"<="&EOMONTH(A29,0))+COUNTIFS(猫统计!P:P,">="&EOMONTH(A29,-1)+1,猫统计!P:P,"<="&EOMONTH(A29,0))+COUNTIFS(猫统计!V:V,">="&EOMONTH(A29,-1)+1,猫统计!V:V,"<="&EOMONTH(A29,0))+COUNTIFS(猫统计!AB:AB,">="&EOMONTH(A29,-1)+1,猫统计!AB:AB,"<="&EOMONTH(A29,0))+COUNTIFS(猫统计!AH:AH,">="&EOMONTH(A29,-1)+1,猫统计!AH:AH,"<="&EOMONTH(A29,0))+COUNTIFS(猫统计!AN:AN,">="&EOMONTH(A29,-1)+1,猫统计!AN:AN,"<="&EOMONTH(A29,0))+COUNTIFS(猫统计!AT:AT,">="&EOMONTH(A29,-1)+1,猫统计!AT:AT,"<="&EOMONTH(A29,0))+COUNTIFS(猫统计!AZ:AZ,">="&EOMONTH(A29,-1)+1,猫统计!AZ:AZ,"<="&EOMONTH(A29,0))+COUNTIFS(猫统计!BF:BF,">="&EOMONTH(A29,-1)+1,猫统计!BF:BF,"<="&EOMONTH(A29,0))+COUNTIFS(猫统计!BL:BL,">="&EOMONTH(A29,-1)+1,猫统计!BL:BL,"<="&EOMONTH(A29,0)) -> 0 | C29: =D29+E29 -> 0 | D29: =SUMIFS(猫统计!L:L,猫统计!J:J,">="&EOMONTH(A29,-1)+1,猫统计!J:J,"<="&EOMONTH(A29,0))+SUMIFS(猫统计!R:R,猫统计!P:P,">="&EOMONTH(A29,-1)+1,猫统计!P:P,"<="&EOMONTH(A29,0))+SUMIFS(猫统计!X:X,猫统计!V:V,">="&EOMONTH(A29,-1)+1,猫统计!V:V,"<="&EOMONTH(A29,0))+SUMIFS(猫统计!AD:AD,猫统计!AB:AB,">="&EOMONTH(A29,-1)+1,猫统计!AB:AB,"<="&EOMONTH(A29,0))+SUMIFS(猫统计!AJ:AJ,猫统计!AH:AH,">="&EOMONTH(A29,-1)+1,猫统计!AH:AH,"<="&EOMONTH(A29,0))+SUMIFS(猫统计!AP:AP,猫统计!AN:AN,">="&EOMONTH(A29,-1)+1,猫统计!AN:AN,"<="&EOMONTH(A29,0))+SUMIFS(猫统计!AV:AV,猫统计!AT:AT,">="&EOMONTH(A29,-1)+1,猫统计!AT:AT,"<="&EOMONTH(A29,0))+SUMIFS(猫统计!BB:BB,猫统计!AZ:AZ,">="&EOMONTH(A29,-1)+1,猫统计!AZ:AZ,"<="&EOMONTH(A29,0))+SUMIFS(猫统计!BH:BH,猫统计!BF:BF,">="&EOMONTH(A29,-1)+1,猫统计!BF:BF,"<="&EOMONTH(A29,0))+SUMIFS(猫统计!BN:BN,猫统计!BL:BL,">="&EOMONTH(A29,-1)+1,猫统计!BL:BL,"<="&EOMONTH(A29,0)) -> 0 | E29: =SUMIFS(猫统计!M:M,猫统计!J:J,">="&EOMONTH(A29,-1)+1,猫统计!J:J,"<="&EOMONTH(A29,0))+SUMIFS(猫统计!S:S,猫统计!P:P,">="&EOMONTH(A29,-1)+1,猫统计!P:P,"<="&EOMONTH(A29,0))+SUMIFS(猫统计!Y:Y,猫统计!V:V,">="&EOMONTH(A29,-1)+1,猫统计!V:V,"<="&EOMONTH(A29,0))+SUMIFS(猫统计!AE:AE,猫统计!AB:AB,">="&EOMONTH(A29,-1)+1,猫统计!AB:AB,"<="&EOMONTH(A29,0))+SUMIFS(猫统计!AK:AK,猫统计!AH:AH,">="&EOMONTH(A29,-1)+1,猫统计!AH:AH,"<="&EOMONTH(A29,0))+SUMIFS(猫统计!AQ:AQ,猫统计!AN:AN,">="&EOMONTH(A29,-1)+1,猫统计!AN:AN,"<="&EOMONTH(A29,0))+SUMIFS(猫统计!AW:AW,猫统计!AT:AT,">="&EOMONTH(A29,-1)+1,猫统计!AT:AT,"<="&EOMONTH(A29,0))+SUMIFS(猫统计!BC:BC,猫统计!AZ:AZ,">="&EOMONTH(A29,-1)+1,猫统计!AZ:AZ,"<="&EOMONTH(A29,0))+SUMIFS(猫统计!BI:BI,猫统计!BF:BF,">="&EOMONTH(A29,-1)+1,猫统计!BF:BF,"<="&EOMONTH(A29,0))+SUMIFS(猫统计!BO:BO,猫统计!BL:BL,">="&EOMONTH(A29,-1)+1,猫统计!BL:BL,"<="&EOMONTH(A29,0)) -> 0
A30: 44866 | B30: =COUNTIFS(猫统计!J:J,">="&EOMONTH(A30,-1)+1,猫统计!J:J,"<="&EOMONTH(A30,0))+COUNTIFS(猫统计!P:P,">="&EOMONTH(A30,-1)+1,猫统计!P:P,"<="&EOMONTH(A30,0))+COUNTIFS(猫统计!V:V,">="&EOMONTH(A30,-1)+1,猫统计!V:V,"<="&EOMONTH(A30,0))+COUNTIFS(猫统计!AB:AB,">="&EOMONTH(A30,-1)+1,猫统计!AB:AB,"<="&EOMONTH(A30,0))+COUNTIFS(猫统计!AH:AH,">="&EOMONTH(A30,-1)+1,猫统计!AH:AH,"<="&EOMONTH(A30,0))+COUNTIFS(猫统计!AN:AN,">="&EOMONTH(A30,-1)+1,猫统计!AN:AN,"<="&EOMONTH(A30,0))+COUNTIFS(猫统计!AT:AT,">="&EOMONTH(A30,-1)+1,猫统计!AT:AT,"<="&EOMONTH(A30,0))+COUNTIFS(猫统计!AZ:AZ,">="&EOMONTH(A30,-1)+1,猫统计!AZ:AZ,"<="&EOMONTH(A30,0))+COUNTIFS(猫统计!BF:BF,">="&EOMONTH(A30,-1)+1,猫统计!BF:BF,"<="&EOMONTH(A30,0))+COUNTIFS(猫统计!BL:BL,">="&EOMONTH(A30,-1)+1,猫统计!BL:BL,"<="&EOMONTH(A30,0)) -> 0 | C30: =D30+E30 -> 0 | D30: =SUMIFS(猫统计!L:L,猫统计!J:J,">="&EOMONTH(A30,-1)+1,猫统计!J:J,"<="&EOMONTH(A30,0))+SUMIFS(猫统计!R:R,猫统计!P:P,">="&EOMONTH(A30,-1)+1,猫统计!P:P,"<="&EOMONTH(A30,0))+SUMIFS(猫统计!X:X,猫统计!V:V,">="&EOMONTH(A30,-1)+1,猫统计!V:V,"<="&EOMONTH(A30,0))+SUMIFS(猫统计!AD:AD,猫统计!AB:AB,">="&EOMONTH(A30,-1)+1,猫统计!AB:AB,"<="&EOMONTH(A30,0))+SUMIFS(猫统计!AJ:AJ,猫统计!AH:AH,">="&EOMONTH(A30,-1)+1,猫统计!AH:AH,"<="&EOMONTH(A30,0))+SUMIFS(猫统计!AP:AP,猫统计!AN:AN,">="&EOMONTH(A30,-1)+1,猫统计!AN:AN,"<="&EOMONTH(A30,0))+SUMIFS(猫统计!AV:AV,猫统计!AT:AT,">="&EOMONTH(A30,-1)+1,猫统计!AT:AT,"<="&EOMONTH(A30,0))+SUMIFS(猫统计!BB:BB,猫统计!AZ:AZ,">="&EOMONTH(A30,-1)+1,猫统计!AZ:AZ,"<="&EOMONTH(A30,0))+SUMIFS(猫统计!BH:BH,猫统计!BF:BF,">="&EOMONTH(A30,-1)+1,猫统计!BF:BF,"<="&EOMONTH(A30,0))+SUMIFS(猫统计!BN:BN,猫统计!BL:BL,">="&EOMONTH(A30,-1)+1,猫统计!BL:BL,"<="&EOMONTH(A30,0)) -> 0 | E30: =SUMIFS(猫统计!M:M,猫统计!J:J,">="&EOMONTH(A30,-1)+1,猫统计!J:J,"<="&EOMONTH(A30,0))+SUMIFS(猫统计!S:S,猫统计!P:P,">="&EOMONTH(A30,-1)+1,猫统计!P:P,"<="&EOMONTH(A30,0))+SUMIFS(猫统计!Y:Y,猫统计!V:V,">="&EOMONTH(A30,-1)+1,猫统计!V:V,"<="&EOMONTH(A30,0))+SUMIFS(猫统计!AE:AE,猫统计!AB:AB,">="&EOMONTH(A30,-1)+1,猫统计!AB:AB,"<="&EOMONTH(A30,0))+SUMIFS(猫统计!AK:AK,猫统计!AH:AH,">="&EOMONTH(A30,-1)+1,猫统计!AH:AH,"<="&EOMONTH(A30,0))+SUMIFS(猫统计!AQ:AQ,猫统计!AN:AN,">="&EOMONTH(A30,-1)+1,猫统计!AN:AN,"<="&EOMONTH(A30,0))+SUMIFS(猫统计!AW:AW,猫统计!AT:AT,">="&EOMONTH(A30,-1)+1,猫统计!AT:AT,"<="&EOMONTH(A30,0))+SUMIFS(猫统计!BC:BC,猫统计!AZ:AZ,">="&EOMONTH(A30,-1)+1,猫统计!AZ:AZ,"<="&EOMONTH(A30,0))+SUMIFS(猫统计!BI:BI,猫统计!BF:BF,">="&EOMONTH(A30,-1)+1,猫统计!BF:BF,"<="&EOMONTH(A30,0))+SUMIFS(猫统计!BO:BO,猫统计!BL:BL,">="&EOMONTH(A30,-1)+1,猫统计!BL:BL,"<="&EOMONTH(A30,0)) -> 0
A31: 44896 | B31: =COUNTIFS(猫统计!J:J,">="&EOMONTH(A31,-1)+1,猫统计!J:J,"<="&EOMONTH(A31,0))+COUNTIFS(猫统计!P:P,">="&EOMONTH(A31,-1)+1,猫统计!P:P,"<="&EOMONTH(A31,0))+COUNTIFS(猫统计!V:V,">="&EOMONTH(A31,-1)+1,猫统计!V:V,"<="&EOMONTH(A31,0))+COUNTIFS(猫统计!AB:AB,">="&EOMONTH(A31,-1)+1,猫统计!AB:AB,"<="&EOMONTH(A31,0))+COUNTIFS(猫统计!AH:AH,">="&EOMONTH(A31,-1)+1,猫统计!AH:AH,"<="&EOMONTH(A31,0))+COUNTIFS(猫统计!AN:AN,">="&EOMONTH(A31,-1)+1,猫统计!AN:AN,"<="&EOMONTH(A31,0))+COUNTIFS(猫统计!AT:AT,">="&EOMONTH(A31,-1)+1,猫统计!AT:AT,"<="&EOMONTH(A31,0))+COUNTIFS(猫统计!AZ:AZ,">="&EOMONTH(A31,-1)+1,猫统计!AZ:AZ,"<="&EOMONTH(A31,0))+COUNTIFS(猫统计!BF:BF,">="&EOMONTH(A31,-1)+1,猫统计!BF:BF,"<="&EOMONTH(A31,0))+COUNTIFS(猫统计!BL:BL,">="&EOMONTH(A31,-1)+1,猫统计!BL:BL,"<="&EOMONTH(A31,0)) -> 1 | C31: =D31+E31 -> 3 | D31: =SUMIFS(猫统计!L:L,猫统计!J:J,">="&EOMONTH(A31,-1)+1,猫统计!J:J,"<="&EOMONTH(A31,0))+SUMIFS(猫统计!R:R,猫统计!P:P,">="&EOMONTH(A31,-1)+1,猫统计!P:P,"<="&EOMONTH(A31,0))+SUMIFS(猫统计!X:X,猫统计!V:V,">="&EOMONTH(A31,-1)+1,猫统计!V:V,"<="&EOMONTH(A31,0))+SUMIFS(猫统计!AD:AD,猫统计!AB:AB,">="&EOMONTH(A31,-1)+1,猫统计!AB:AB,"<="&EOMONTH(A31,0))+SUMIFS(猫统计!AJ:AJ,猫统计!AH:AH,">="&EOMONTH(A31,-1)+1,猫统计!AH:AH,"<="&EOMONTH(A31,0))+SUMIFS(猫统计!AP:AP,猫统计!AN:AN,">="&EOMONTH(A31,-1)+1,猫统计!AN:AN,"<="&EOMONTH(A31,0))+SUMIFS(猫统计!AV:AV,猫统计!AT:AT,">="&EOMONTH(A31,-1)+1,猫统计!AT:AT,"<="&EOMONTH(A31,0))+SUMIFS(猫统计!BB:BB,猫统计!AZ:AZ,">="&EOMONTH(A31,-1)+1,猫统计!AZ:AZ,"<="&EOMONTH(A31,0))+SUMIFS(猫统计!BH:BH,猫统计!BF:BF,">="&EOMONTH(A31,-1)+1,猫统计!BF:BF,"<="&EOMONTH(A31,0))+SUMIFS(猫统计!BN:BN,猫统计!BL:BL,">="&EOMONTH(A31,-1)+1,猫统计!BL:BL,"<="&EOMONTH(A31,0)) -> 0 | E31: =SUMIFS(猫统计!M:M,猫统计!J:J,">="&EOMONTH(A31,-1)+1,猫统计!J:J,"<="&EOMONTH(A31,0))+SUMIFS(猫统计!S:S,猫统计!P:P,">="&EOMONTH(A31,-1)+1,猫统计!P:P,"<="&EOMONTH(A31,0))+SUMIFS(猫统计!Y:Y,猫统计!V:V,">="&EOMONTH(A31,-1)+1,猫统计!V:V,"<="&EOMONTH(A31,0))+SUMIFS(猫统计!AE:AE,猫统计!AB:AB,">="&EOMONTH(A31,-1)+1,猫统计!AB:AB,"<="&EOMONTH(A31,0))+SUMIFS(猫统计!AK:AK,猫统计!AH:AH,">="&EOMONTH(A31,-1)+1,猫统计!AH:AH,"<="&EOMONTH(A31,0))+SUMIFS(猫统计!AQ:AQ,猫统计!AN:AN,">="&EOMONTH(A31,-1)+1,猫统计!AN:AN,"<="&EOMONTH(A31,0))+SUMIFS(猫统计!AW:AW,猫统计!AT:AT,">="&EOMONTH(A31,-1)+1,猫统计!AT:AT,"<="&EOMONTH(A31,0))+SUMIFS(猫统计!BC:BC,猫统计!AZ:AZ,">="&EOMONTH(A31,-1)+1,猫统计!AZ:AZ,"<="&EOMONTH(A31,0))+SUMIFS(猫统计!BI:BI,猫统计!BF:BF,">="&EOMONTH(A31,-1)+1,猫统计!BF:BF,"<="&EOMONTH(A31,0))+SUMIFS(猫统计!BO:BO,猫统计!BL:BL,">="&EOMONTH(A31,-1)+1,猫统计!BL:BL,"<="&EOMONTH(A31,0)) -> 3 | F31: =(E29+E30+E31)/(C29+C30+C31) -> 1 | G31: =(E29+E30+E31)/(B29+B30+B31) -> 3
A32: 44927 | B32: =COUNTIFS(猫统计!J:J,">="&EOMONTH(A32,-1)+1,猫统计!J:J,"<="&EOMONTH(A32,0))+COUNTIFS(猫统计!P:P,">="&EOMONTH(A32,-1)+1,猫统计!P:P,"<="&EOMONTH(A32,0))+COUNTIFS(猫统计!V:V,">="&EOMONTH(A32,-1)+1,猫统计!V:V,"<="&EOMONTH(A32,0))+COUNTIFS(猫统计!AB:AB,">="&EOMONTH(A32,-1)+1,猫统计!AB:AB,"<="&EOMONTH(A32,0))+COUNTIFS(猫统计!AH:AH,">="&EOMONTH(A32,-1)+1,猫统计!AH:AH,"<="&EOMONTH(A32,0))+COUNTIFS(猫统计!AN:AN,">="&EOMONTH(A32,-1)+1,猫统计!AN:AN,"<="&EOMONTH(A32,0))+COUNTIFS(猫统计!AT:AT,">="&EOMONTH(A32,-1)+1,猫统计!AT:AT,"<="&EOMONTH(A32,0))+COUNTIFS(猫统计!AZ:AZ,">="&EOMONTH(A32,-1)+1,猫统计!AZ:AZ,"<="&EOMONTH(A32,0))+COUNTIFS(猫统计!BF:BF,">="&EOMONTH(A32,-1)+1,猫统计!BF:BF,"<="&EOMONTH(A32,0))+COUNTIFS(猫统计!BL:BL,">="&EOMONTH(A32,-1)+1,猫统计!BL:BL,"<="&EOMONTH(A32,0)) -> 2 | C32: =D32+E32 -> 7 | D32: =SUMIFS(猫统计!L:L,猫统计!J:J,">="&EOMONTH(A32,-1)+1,猫统计!J:J,"<="&EOMONTH(A32,0))+SUMIFS(猫统计!R:R,猫统计!P:P,">="&EOMONTH(A32,-1)+1,猫统计!P:P,"<="&EOMONTH(A32,0))+SUMIFS(猫统计!X:X,猫统计!V:V,">="&EOMONTH(A32,-1)+1,猫统计!V:V,"<="&EOMONTH(A32,0))+SUMIFS(猫统计!AD:AD,猫统计!AB:AB,">="&EOMONTH(A32,-1)+1,猫统计!AB:AB,"<="&EOMONTH(A32,0))+SUMIFS(猫统计!AJ:AJ,猫统计!AH:AH,">="&EOMONTH(A32,-1)+1,猫统计!AH:AH,"<="&EOMONTH(A32,0))+SUMIFS(猫统计!AP:AP,猫统计!AN:AN,">="&EOMONTH(A32,-1)+1,猫统计!AN:AN,"<="&EOMONTH(A32,0))+SUMIFS(猫统计!AV:AV,猫统计!AT:AT,">="&EOMONTH(A32,-1)+1,猫统计!AT:AT,"<="&EOMONTH(A32,0))+SUMIFS(猫统计!BB:BB,猫统计!AZ:AZ,">="&EOMONTH(A32,-1)+1,猫统计!AZ:AZ,"<="&EOMONTH(A32,0))+SUMIFS(猫统计!BH:BH,猫统计!BF:BF,">="&EOMONTH(A32,-1)+1,猫统计!BF:BF,"<="&EOMONTH(A32,0))+SUMIFS(猫统计!BN:BN,猫统计!BL:BL,">="&EOMONTH(A32,-1)+1,猫统计!BL:BL,"<="&EOMONTH(A32,0)) -> 0 | E32: =SUMIFS(猫统计!M:M,猫统计!J:J,">="&EOMONTH(A32,-1)+1,猫统计!J:J,"<="&EOMONTH(A32,0))+SUMIFS(猫统计!S:S,猫统计!P:P,">="&EOMONTH(A32,-1)+1,猫统计!P:P,"<="&EOMONTH(A32,0))+SUMIFS(猫统计!Y:Y,猫统计!V:V,">="&EOMONTH(A32,-1)+1,猫统计!V:V,"<="&EOMONTH(A32,0))+SUMIFS(猫统计!AE:AE,猫统计!AB:AB,">="&EOMONTH(A32,-1)+1,猫统计!AB:AB,"<="&EOMONTH(A32,0))+SUMIFS(猫统计!AK:AK,猫统计!AH:AH,">="&EOMONTH(A32,-1)+1,猫统计!AH:AH,"<="&EOMONTH(A32,0))+SUMIFS(猫统计!AQ:AQ,猫统计!AN:AN,">="&EOMONTH(A32,-1)+1,猫统计!AN:AN,"<="&EOMONTH(A32,0))+SUMIFS(猫统计!AW:AW,猫统计!AT:AT,">="&EOMONTH(A32,-1)+1,猫统计!AT:AT,"<="&EOMONTH(A32,0))+SUMIFS(猫统计!BC:BC,猫统计!AZ:AZ,">="&EOMONTH(A32,-1)+1,猫统计!AZ:AZ,"<="&EOMONTH(A32,0))+SUMIFS(猫统计!BI:BI,猫统计!BF:BF,">="&EOMONTH(A32,-1)+1,猫统计!BF:BF,"<="&EOMONTH(A32,0))+SUMIFS(猫统计!BO:BO,猫统计!BL:BL,">="&EOMONTH(A32,-1)+1,猫统计!BL:BL,"<="&EOMONTH(A32,0)) -> 7
A33: 44958 | B33: =COUNTIFS(猫统计!J:J,">="&EOMONTH(A33,-1)+1,猫统计!J:J,"<="&EOMONTH(A33,0))+COUNTIFS(猫统计!P:P,">="&EOMONTH(A33,-1)+1,猫统计!P:P,"<="&EOMONTH(A33,0))+COUNTIFS(猫统计!V:V,">="&EOMONTH(A33,-1)+1,猫统计!V:V,"<="&EOMONTH(A33,0))+COUNTIFS(猫统计!AB:AB,">="&EOMONTH(A33,-1)+1,猫统计!AB:AB,"<="&EOMONTH(A33,0))+COUNTIFS(猫统计!AH:AH,">="&EOMONTH(A33,-1)+1,猫统计!AH:AH,"<="&EOMONTH(A33,0))+COUNTIFS(猫统计!AN:AN,">="&EOMONTH(A33,-1)+1,猫统计!AN:AN,"<="&EOMONTH(A33,0))+COUNTIFS(猫统计!AT:AT,">="&EOMONTH(A33,-1)+1,猫统计!AT:AT,"<="&EOMONTH(A33,0))+COUNTIFS(猫统计!AZ:AZ,">="&EOMONTH(A33,-1)+1,猫统计!AZ:AZ,"<="&EOMONTH(A33,0))+COUNTIFS(猫统计!BF:BF,">="&EOMONTH(A33,-1)+1,猫统计!BF:BF,"<="&EOMONTH(A33,0))+COUNTIFS(猫统计!BL:BL,">="&EOMONTH(A33,-1)+1,猫统计!BL:BL,"<="&EOMONTH(A33,0)) -> 3 | C33: =D33+E33 -> 10 | D33: =SUMIFS(猫统计!L:L,猫统计!J:J,">="&EOMONTH(A33,-1)+1,猫统计!J:J,"<="&EOMONTH(A33,0))+SUMIFS(猫统计!R:R,猫统计!P:P,">="&EOMONTH(A33,-1)+1,猫统计!P:P,"<="&EOMONTH(A33,0))+SUMIFS(猫统计!X:X,猫统计!V:V,">="&EOMONTH(A33,-1)+1,猫统计!V:V,"<="&EOMONTH(A33,0))+SUMIFS(猫统计!AD:AD,猫统计!AB:AB,">="&EOMONTH(A33,-1)+1,猫统计!AB:AB,"<="&EOMONTH(A33,0))+SUMIFS(猫统计!AJ:AJ,猫统计!AH:AH,">="&EOMONTH(A33,-1)+1,猫统计!AH:AH,"<="&EOMONTH(A33,0))+SUMIFS(猫统计!AP:AP,猫统计!AN:AN,">="&EOMONTH(A33,-1)+1,猫统计!AN:AN,"<="&EOMONTH(A33,0))+SUMIFS(猫统计!AV:AV,猫统计!AT:AT,">="&EOMONTH(A33,-1)+1,猫统计!AT:AT,"<="&EOMONTH(A33,0))+SUMIFS(猫统计!BB:BB,猫统计!AZ:AZ,">="&EOMONTH(A33,-1)+1,猫统计!AZ:AZ,"<="&EOMONTH(A33,0))+SUMIFS(猫统计!BH:BH,猫统计!BF:BF,">="&EOMONTH(A33,-1)+1,猫统计!BF:BF,"<="&EOMONTH(A33,0))+SUMIFS(猫统计!BN:BN,猫统计!BL:BL,">="&EOMONTH(A33,-1)+1,猫统计!BL:BL,"<="&EOMONTH(A33,0)) -> 5 | E33: =SUMIFS(猫统计!M:M,猫统计!J:J,">="&EOMONTH(A33,-1)+1,猫统计!J:J,"<="&EOMONTH(A33,0))+SUMIFS(猫统计!S:S,猫统计!P:P,">="&EOMONTH(A33,-1)+1,猫统计!P:P,"<="&EOMONTH(A33,0))+SUMIFS(猫统计!Y:Y,猫统计!V:V,">="&EOMONTH(A33,-1)+1,猫统计!V:V,"<="&EOMONTH(A33,0))+SUMIFS(猫统计!AE:AE,猫统计!AB:AB,">="&EOMONTH(A33,-1)+1,猫统计!AB:AB,"<="&EOMONTH(A33,0))+SUMIFS(猫统计!AK:AK,猫统计!AH:AH,">="&EOMONTH(A33,-1)+1,猫统计!AH:AH,"<="&EOMONTH(A33,0))+SUMIFS(猫统计!AQ:AQ,猫统计!AN:AN,">="&EOMONTH(A33,-1)+1,猫统计!AN:AN,"<="&EOMONTH(A33,0))+SUMIFS(猫统计!AW:AW,猫统计!AT:AT,">="&EOMONTH(A33,-1)+1,猫统计!AT:AT,"<="&EOMONTH(A33,0))+SUMIFS(猫统计!BC:BC,猫统计!AZ:AZ,">="&EOMONTH(A33,-1)+1,猫统计!AZ:AZ,"<="&EOMONTH(A33,0))+SUMIFS(猫统计!BI:BI,猫统计!BF:BF,">="&EOMONTH(A33,-1)+1,猫统计!BF:BF,"<="&EOMONTH(A33,0))+SUMIFS(猫统计!BO:BO,猫统计!BL:BL,">="&EOMONTH(A33,-1)+1,猫统计!BL:BL,"<="&EOMONTH(A33,0)) -> 5
A34: 44986 | B34: =COUNTIFS(猫统计!J:J,">="&EOMONTH(A34,-1)+1,猫统计!J:J,"<="&EOMONTH(A34,0))+COUNTIFS(猫统计!P:P,">="&EOMONTH(A34,-1)+1,猫统计!P:P,"<="&EOMONTH(A34,0))+COUNTIFS(猫统计!V:V,">="&EOMONTH(A34,-1)+1,猫统计!V:V,"<="&EOMONTH(A34,0))+COUNTIFS(猫统计!AB:AB,">="&EOMONTH(A34,-1)+1,猫统计!AB:AB,"<="&EOMONTH(A34,0))+COUNTIFS(猫统计!AH:AH,">="&EOMONTH(A34,-1)+1,猫统计!AH:AH,"<="&EOMONTH(A34,0))+COUNTIFS(猫统计!AN:AN,">="&EOMONTH(A34,-1)+1,猫统计!AN:AN,"<="&EOMONTH(A34,0))+COUNTIFS(猫统计!AT:AT,">="&EOMONTH(A34,-1)+1,猫统计!AT:AT,"<="&EOMONTH(A34,0))+COUNTIFS(猫统计!AZ:AZ,">="&EOMONTH(A34,-1)+1,猫统计!AZ:AZ,"<="&EOMONTH(A34,0))+COUNTIFS(猫统计!BF:BF,">="&EOMONTH(A34,-1)+1,猫统计!BF:BF,"<="&EOMONTH(A34,0))+COUNTIFS(猫统计!BL:BL,">="&EOMONTH(A34,-1)+1,猫统计!BL:BL,"<="&EOMONTH(A34,0)) -> 5 | C34: =D34+E34 -> 20 | D34: =SUMIFS(猫统计!L:L,猫统计!J:J,">="&EOMONTH(A34,-1)+1,猫统计!J:J,"<="&EOMONTH(A34,0))+SUMIFS(猫统计!R:R,猫统计!P:P,">="&EOMONTH(A34,-1)+1,猫统计!P:P,"<="&EOMONTH(A34,0))+SUMIFS(猫统计!X:X,猫统计!V:V,">="&EOMONTH(A34,-1)+1,猫统计!V:V,"<="&EOMONTH(A34,0))+SUMIFS(猫统计!AD:AD,猫统计!AB:AB,">="&EOMONTH(A34,-1)+1,猫统计!AB:AB,"<="&EOMONTH(A34,0))+SUMIFS(猫统计!AJ:AJ,猫统计!AH:AH,">="&EOMONTH(A34,-1)+1,猫统计!AH:AH,"<="&EOMONTH(A34,0))+SUMIFS(猫统计!AP:AP,猫统计!AN:AN,">="&EOMONTH(A34,-1)+1,猫统计!AN:AN,"<="&EOMONTH(A34,0))+SUMIFS(猫统计!AV:AV,猫统计!AT:AT,">="&EOMONTH(A34,-1)+1,猫统计!AT:AT,"<="&EOMONTH(A34,0))+SUMIFS(猫统计!BB:BB,猫统计!AZ:AZ,">="&EOMONTH(A34,-1)+1,猫统计!AZ:AZ,"<="&EOMONTH(A34,0))+SUMIFS(猫统计!BH:BH,猫统计!BF:BF,">="&EOMONTH(A34,-1)+1,猫统计!BF:BF,"<="&EOMONTH(A34,0))+SUMIFS(猫统计!BN:BN,猫统计!BL:BL,">="&EOMONTH(A34,-1)+1,猫统计!BL:BL,"<="&EOMONTH(A34,0)) -> 3 | E34: =SUMIFS(猫统计!M:M,猫统计!J:J,">="&EOMONTH(A34,-1)+1,猫统计!J:J,"<="&EOMONTH(A34,0))+SUMIFS(猫统计!S:S,猫统计!P:P,">="&EOMONTH(A34,-1)+1,猫统计!P:P,"<="&EOMONTH(A34,0))+SUMIFS(猫统计!Y:Y,猫统计!V:V,">="&EOMONTH(A34,-1)+1,猫统计!V:V,"<="&EOMONTH(A34,0))+SUMIFS(猫统计!AE:AE,猫统计!AB:AB,">="&EOMONTH(A34,-1)+1,猫统计!AB:AB,"<="&EOMONTH(A34,0))+SUMIFS(猫统计!AK:AK,猫统计!AH:AH,">="&EOMONTH(A34,-1)+1,猫统计!AH:AH,"<="&EOMONTH(A34,0))+SUMIFS(猫统计!AQ:AQ,猫统计!AN:AN,">="&EOMONTH(A34,-1)+1,猫统计!AN:AN,"<="&EOMONTH(A34,0))+SUMIFS(猫统计!AW:AW,猫统计!AT:AT,">="&EOMONTH(A34,-1)+1,猫统计!AT:AT,"<="&EOMONTH(A34,0))+SUMIFS(猫统计!BC:BC,猫统计!AZ:AZ,">="&EOMONTH(A34,-1)+1,猫统计!AZ:AZ,"<="&EOMONTH(A34,0))+SUMIFS(猫统计!BI:BI,猫统计!BF:BF,">="&EOMONTH(A34,-1)+1,猫统计!BF:BF,"<="&EOMONTH(A34,0))+SUMIFS(猫统计!BO:BO,猫统计!BL:BL,">="&EOMONTH(A34,-1)+1,猫统计!BL:BL,"<="&EOMONTH(A34,0)) -> 17 | F34: =(E32+E33+E34)/(C32+C33+C34) -> 0.78378378 | G34: =(E32+E33+E34)/(B32+B33+B34) -> 2.9
A35: 45017 | B35: =COUNTIFS(猫统计!J:J,">="&EOMONTH(A35,-1)+1,猫统计!J:J,"<="&EOMONTH(A35,0))+COUNTIFS(猫统计!P:P,">="&EOMONTH(A35,-1)+1,猫统计!P:P,"<="&EOMONTH(A35,0))+COUNTIFS(猫统计!V:V,">="&EOMONTH(A35,-1)+1,猫统计!V:V,"<="&EOMONTH(A35,0))+COUNTIFS(猫统计!AB:AB,">="&EOMONTH(A35,-1)+1,猫统计!AB:AB,"<="&EOMONTH(A35,0))+COUNTIFS(猫统计!AH:AH,">="&EOMONTH(A35,-1)+1,猫统计!AH:AH,"<="&EOMONTH(A35,0))+COUNTIFS(猫统计!AN:AN,">="&EOMONTH(A35,-1)+1,猫统计!AN:AN,"<="&EOMONTH(A35,0))+COUNTIFS(猫统计!AT:AT,">="&EOMONTH(A35,-1)+1,猫统计!AT:AT,"<="&EOMONTH(A35,0))+COUNTIFS(猫统计!AZ:AZ,">="&EOMONTH(A35,-1)+1,猫统计!AZ:AZ,"<="&EOMONTH(A35,0))+COUNTIFS(猫统计!BF:BF,">="&EOMONTH(A35,-1)+1,猫统计!BF:BF,"<="&EOMONTH(A35,0))+COUNTIFS(猫统计!BL:BL,">="&EOMONTH(A35,-1)+1,猫统计!BL:BL,"<="&EOMONTH(A35,0)) -> 3 | C35: =D35+E35 -> 12 | D35: =SUMIFS(猫统计!L:L,猫统计!J:J,">="&EOMONTH(A35,-1)+1,猫统计!J:J,"<="&EOMONTH(A35,0))+SUMIFS(猫统计!R:R,猫统计!P:P,">="&EOMONTH(A35,-1)+1,猫统计!P:P,"<="&EOMONTH(A35,0))+SUMIFS(猫统计!X:X,猫统计!V:V,">="&EOMONTH(A35,-1)+1,猫统计!V:V,"<="&EOMONTH(A35,0))+SUMIFS(猫统计!AD:AD,猫统计!AB:AB,">="&EOMONTH(A35,-1)+1,猫统计!AB:AB,"<="&EOMONTH(A35,0))+SUMIFS(猫统计!AJ:AJ,猫统计!AH:AH,">="&EOMONTH(A35,-1)+1,猫统计!AH:AH,"<="&EOMONTH(A35,0))+SUMIFS(猫统计!AP:AP,猫统计!AN:AN,">="&EOMONTH(A35,-1)+1,猫统计!AN:AN,"<="&EOMONTH(A35,0))+SUMIFS(猫统计!AV:AV,猫统计!AT:AT,">="&EOMONTH(A35,-1)+1,猫统计!AT:AT,"<="&EOMONTH(A35,0))+SUMIFS(猫统计!BB:BB,猫统计!AZ:AZ,">="&EOMONTH(A35,-1)+1,猫统计!AZ:AZ,"<="&EOMONTH(A35,0))+SUMIFS(猫统计!BH:BH,猫统计!BF:BF,">="&EOMONTH(A35,-1)+1,猫统计!BF:BF,"<="&EOMONTH(A35,0))+SUMIFS(猫统计!BN:BN,猫统计!BL:BL,">="&EOMONTH(A35,-1)+1,猫统计!BL:BL,"<="&EOMONTH(A35,0)) -> 0 | E35: =SUMIFS(猫统计!M:M,猫统计!J:J,">="&EOMONTH(A35,-1)+1,猫统计!J:J,"<="&EOMONTH(A35,0))+SUMIFS(猫统计!S:S,猫统计!P:P,">="&EOMONTH(A35,-1)+1,猫统计!P:P,"<="&EOMONTH(A35,0))+SUMIFS(猫统计!Y:Y,猫统计!V:V,">="&EOMONTH(A35,-1)+1,猫统计!V:V,"<="&EOMONTH(A35,0))+SUMIFS(猫统计!AE:AE,猫统计!AB:AB,">="&EOMONTH(A35,-1)+1,猫统计!AB:AB,"<="&EOMONTH(A35,0))+SUMIFS(猫统计!AK:AK,猫统计!AH:AH,">="&EOMONTH(A35,-1)+1,猫统计!AH:AH,"<="&EOMONTH(A35,0))+SUMIFS(猫统计!AQ:AQ,猫统计!AN:AN,">="&EOMONTH(A35,-1)+1,猫统计!AN:AN,"<="&EOMONTH(A35,0))+SUMIFS(猫统计!AW:AW,猫统计!AT:AT,">="&EOMONTH(A35,-1)+1,猫统计!AT:AT,"<="&EOMONTH(A35,0))+SUMIFS(猫统计!BC:BC,猫统计!AZ:AZ,">="&EOMONTH(A35,-1)+1,猫统计!AZ:AZ,"<="&EOMONTH(A35,0))+SUMIFS(猫统计!BI:BI,猫统计!BF:BF,">="&EOMONTH(A35,-1)+1,猫统计!BF:BF,"<="&EOMONTH(A35,0))+SUMIFS(猫统计!BO:BO,猫统计!BL:BL,">="&EOMONTH(A35,-1)+1,猫统计!BL:BL,"<="&EOMONTH(A35,0)) -> 12
A36: 45047 | B36: =COUNTIFS(猫统计!J:J,">="&EOMONTH(A36,-1)+1,猫统计!J:J,"<="&EOMONTH(A36,0))+COUNTIFS(猫统计!P:P,">="&EOMONTH(A36,-1)+1,猫统计!P:P,"<="&EOMONTH(A36,0))+COUNTIFS(猫统计!V:V,">="&EOMONTH(A36,-1)+1,猫统计!V:V,"<="&EOMONTH(A36,0))+COUNTIFS(猫统计!AB:AB,">="&EOMONTH(A36,-1)+1,猫统计!AB:AB,"<="&EOMONTH(A36,0))+COUNTIFS(猫统计!AH:AH,">="&EOMONTH(A36,-1)+1,猫统计!AH:AH,"<="&EOMONTH(A36,0))+COUNTIFS(猫统计!AN:AN,">="&EOMONTH(A36,-1)+1,猫统计!AN:AN,"<="&EOMONTH(A36,0))+COUNTIFS(猫统计!AT:AT,">="&EOMONTH(A36,-1)+1,猫统计!AT:AT,"<="&EOMONTH(A36,0))+COUNTIFS(猫统计!AZ:AZ,">="&EOMONTH(A36,-1)+1,猫统计!AZ:AZ,"<="&EOMONTH(A36,0))+COUNTIFS(猫统计!BF:BF,">="&EOMONTH(A36,-1)+1,猫统计!BF:BF,"<="&EOMONTH(A36,0))+COUNTIFS(猫统计!BL:BL,">="&EOMONTH(A36,-1)+1,猫统计!BL:BL,"<="&EOMONTH(A36,0)) -> 3 | C36: =D36+E36 -> 15 | D36: =SUMIFS(猫统计!L:L,猫统计!J:J,">="&EOMONTH(A36,-1)+1,猫统计!J:J,"<="&EOMONTH(A36,0))+SUMIFS(猫统计!R:R,猫统计!P:P,">="&EOMONTH(A36,-1)+1,猫统计!P:P,"<="&EOMONTH(A36,0))+SUMIFS(猫统计!X:X,猫统计!V:V,">="&EOMONTH(A36,-1)+1,猫统计!V:V,"<="&EOMONTH(A36,0))+SUMIFS(猫统计!AD:AD,猫统计!AB:AB,">="&EOMONTH(A36,-1)+1,猫统计!AB:AB,"<="&EOMONTH(A36,0))+SUMIFS(猫统计!AJ:AJ,猫统计!AH:AH,">="&EOMONTH(A36,-1)+1,猫统计!AH:AH,"<="&EOMONTH(A36,0))+SUMIFS(猫统计!AP:AP,猫统计!AN:AN,">="&EOMONTH(A36,-1)+1,猫统计!AN:AN,"<="&EOMONTH(A36,0))+SUMIFS(猫统计!AV:AV,猫统计!AT:AT,">="&EOMONTH(A36,-1)+1,猫统计!AT:AT,"<="&EOMONTH(A36,0))+SUMIFS(猫统计!BB:BB,猫统计!AZ:AZ,">="&EOMONTH(A36,-1)+1,猫统计!AZ:AZ,"<="&EOMONTH(A36,0))+SUMIFS(猫统计!BH:BH,猫统计!BF:BF,">="&EOMONTH(A36,-1)+1,猫统计!BF:BF,"<="&EOMONTH(A36,0))+SUMIFS(猫统计!BN:BN,猫统计!BL:BL,">="&EOMONTH(A36,-1)+1,猫统计!BL:BL,"<="&EOMONTH(A36,0)) -> 8 | E36: =SUMIFS(猫统计!M:M,猫统计!J:J,">="&EOMONTH(A36,-1)+1,猫统计!J:J,"<="&EOMONTH(A36,0))+SUMIFS(猫统计!S:S,猫统计!P:P,">="&EOMONTH(A36,-1)+1,猫统计!P:P,"<="&EOMONTH(A36,0))+SUMIFS(猫统计!Y:Y,猫统计!V:V,">="&EOMONTH(A36,-1)+1,猫统计!V:V,"<="&EOMONTH(A36,0))+SUMIFS(猫统计!AE:AE,猫统计!AB:AB,">="&EOMONTH(A36,-1)+1,猫统计!AB:AB,"<="&EOMONTH(A36,0))+SUMIFS(猫统计!AK:AK,猫统计!AH:AH,">="&EOMONTH(A36,-1)+1,猫统计!AH:AH,"<="&EOMONTH(A36,0))+SUMIFS(猫统计!AQ:AQ,猫统计!AN:AN,">="&EOMONTH(A36,-1)+1,猫统计!AN:AN,"<="&EOMONTH(A36,0))+SUMIFS(猫统计!AW:AW,猫统计!AT:AT,">="&EOMONTH(A36,-1)+1,猫统计!AT:AT,"<="&EOMONTH(A36,0))+SUMIFS(猫统计!BC:BC,猫统计!AZ:AZ,">="&EOMONTH(A36,-1)+1,猫统计!AZ:AZ,"<="&EOMONTH(A36,0))+SUMIFS(猫统计!BI:BI,猫统计!BF:BF,">="&EOMONTH(A36,-1)+1,猫统计!BF:BF,"<="&EOMONTH(A36,0))+SUMIFS(猫统计!BO:BO,猫统计!BL:BL,">="&EOMONTH(A36,-1)+1,猫统计!BL:BL,"<="&EOMONTH(A36,0)) -> 7
A37: 45078 | B37: =COUNTIFS(猫统计!J:J,">="&EOMONTH(A37,-1)+1,猫统计!J:J,"<="&EOMONTH(A37,0))+COUNTIFS(猫统计!P:P,">="&EOMONTH(A37,-1)+1,猫统计!P:P,"<="&EOMONTH(A37,0))+COUNTIFS(猫统计!V:V,">="&EOMONTH(A37,-1)+1,猫统计!V:V,"<="&EOMONTH(A37,0))+COUNTIFS(猫统计!AB:AB,">="&EOMONTH(A37,-1)+1,猫统计!AB:AB,"<="&EOMONTH(A37,0))+COUNTIFS(猫统计!AH:AH,">="&EOMONTH(A37,-1)+1,猫统计!AH:AH,"<="&EOMONTH(A37,0))+COUNTIFS(猫统计!AN:AN,">="&EOMONTH(A37,-1)+1,猫统计!AN:AN,"<="&EOMONTH(A37,0))+COUNTIFS(猫统计!AT:AT,">="&EOMONTH(A37,-1)+1,猫统计!AT:AT,"<="&EOMONTH(A37,0))+COUNTIFS(猫统计!AZ:AZ,">="&EOMONTH(A37,-1)+1,猫统计!AZ:AZ,"<="&EOMONTH(A37,0))+COUNTIFS(猫统计!BF:BF,">="&EOMONTH(A37,-1)+1,猫统计!BF:BF,"<="&EOMONTH(A37,0))+COUNTIFS(猫统计!BL:BL,">="&EOMONTH(A37,-1)+1,猫统计!BL:BL,"<="&EOMONTH(A37,0)) -> 1 | C37: =D37+E37 -> 7 | D37: =SUMIFS(猫统计!L:L,猫统计!J:J,">="&EOMONTH(A37,-1)+1,猫统计!J:J,"<="&EOMONTH(A37,0))+SUMIFS(猫统计!R:R,猫统计!P:P,">="&EOMONTH(A37,-1)+1,猫统计!P:P,"<="&EOMONTH(A37,0))+SUMIFS(猫统计!X:X,猫统计!V:V,">="&EOMONTH(A37,-1)+1,猫统计!V:V,"<="&EOMONTH(A37,0))+SUMIFS(猫统计!AD:AD,猫统计!AB:AB,">="&EOMONTH(A37,-1)+1,猫统计!AB:AB,"<="&EOMONTH(A37,0))+SUMIFS(猫统计!AJ:AJ,猫统计!AH:AH,">="&EOMONTH(A37,-1)+1,猫统计!AH:AH,"<="&EOMONTH(A37,0))+SUMIFS(猫统计!AP:AP,猫统计!AN:AN,">="&EOMONTH(A37,-1)+1,猫统计!AN:AN,"<="&EOMONTH(A37,0))+SUMIFS(猫统计!AV:AV,猫统计!AT:AT,">="&EOMONTH(A37,-1)+1,猫统计!AT:AT,"<="&EOMONTH(A37,0))+SUMIFS(猫统计!BB:BB,猫统计!AZ:AZ,">="&EOMONTH(A37,-1)+1,猫统计!AZ:AZ,"<="&EOMONTH(A37,0))+SUMIFS(猫统计!BH:BH,猫统计!BF:BF,">="&EOMONTH(A37,-1)+1,猫统计!BF:BF,"<="&EOMONTH(A37,0))+SUMIFS(猫统计!BN:BN,猫统计!BL:BL,">="&EOMONTH(A37,-1)+1,猫统计!BL:BL,"<="&EOMONTH(A37,0)) -> 3 | E37: =SUMIFS(猫统计!M:M,猫统计!J:J,">="&EOMONTH(A37,-1)+1,猫统计!J:J,"<="&EOMONTH(A37,0))+SUMIFS(猫统计!S:S,猫统计!P:P,">="&EOMONTH(A37,-1)+1,猫统计!P:P,"<="&EOMONTH(A37,0))+SUMIFS(猫统计!Y:Y,猫统计!V:V,">="&EOMONTH(A37,-1)+1,猫统计!V:V,"<="&EOMONTH(A37,0))+SUMIFS(猫统计!AE:AE,猫统计!AB:AB,">="&EOMONTH(A37,-1)+1,猫统计!AB:AB,"<="&EOMONTH(A37,0))+SUMIFS(猫统计!AK:AK,猫统计!AH:AH,">="&EOMONTH(A37,-1)+1,猫统计!AH:AH,"<="&EOMONTH(A37,0))+SUMIFS(猫统计!AQ:AQ,猫统计!AN:AN,">="&EOMONTH(A37,-1)+1,猫统计!AN:AN,"<="&EOMONTH(A37,0))+SUMIFS(猫统计!AW:AW,猫统计!AT:AT,">="&EOMONTH(A37,-1)+1,猫统计!AT:AT,"<="&EOMONTH(A37,0))+SUMIFS(猫统计!BC:BC,猫统计!AZ:AZ,">="&EOMONTH(A37,-1)+1,猫统计!AZ:AZ,"<="&EOMONTH(A37,0))+SUMIFS(猫统计!BI:BI,猫统计!BF:BF,">="&EOMONTH(A37,-1)+1,猫统计!BF:BF,"<="&EOMONTH(A37,0))+SUMIFS(猫统计!BO:BO,猫统计!BL:BL,">="&EOMONTH(A37,-1)+1,猫统计!BL:BL,"<="&EOMONTH(A37,0)) -> 4 | F37: =(E35+E36+E37)/(C35+C36+C37) -> 0.67647059 | G37: =(E35+E36+E37)/(B35+B36+B37) -> 3.2857143
A38: 45108 | B38: =COUNTIFS(猫统计!J:J,">="&EOMONTH(A38,-1)+1,猫统计!J:J,"<="&EOMONTH(A38,0))+COUNTIFS(猫统计!P:P,">="&EOMONTH(A38,-1)+1,猫统计!P:P,"<="&EOMONTH(A38,0))+COUNTIFS(猫统计!V:V,">="&EOMONTH(A38,-1)+1,猫统计!V:V,"<="&EOMONTH(A38,0))+COUNTIFS(猫统计!AB:AB,">="&EOMONTH(A38,-1)+1,猫统计!AB:AB,"<="&EOMONTH(A38,0))+COUNTIFS(猫统计!AH:AH,">="&EOMONTH(A38,-1)+1,猫统计!AH:AH,"<="&EOMONTH(A38,0))+COUNTIFS(猫统计!AN:AN,">="&EOMONTH(A38,-1)+1,猫统计!AN:AN,"<="&EOMONTH(A38,0))+COUNTIFS(猫统计!AT:AT,">="&EOMONTH(A38,-1)+1,猫统计!AT:AT,"<="&EOMONTH(A38,0))+COUNTIFS(猫统计!AZ:AZ,">="&EOMONTH(A38,-1)+1,猫统计!AZ:AZ,"<="&EOMONTH(A38,0))+COUNTIFS(猫统计!BF:BF,">="&EOMONTH(A38,-1)+1,猫统计!BF:BF,"<="&EOMONTH(A38,0))+COUNTIFS(猫统计!BL:BL,">="&EOMONTH(A38,-1)+1,猫统计!BL:BL,"<="&EOMONTH(A38,0)) -> 1 | C38: =D38+E38 -> 6 | D38: =SUMIFS(猫统计!L:L,猫统计!J:J,">="&EOMONTH(A38,-1)+1,猫统计!J:J,"<="&EOMONTH(A38,0))+SUMIFS(猫统计!R:R,猫统计!P:P,">="&EOMONTH(A38,-1)+1,猫统计!P:P,"<="&EOMONTH(A38,0))+SUMIFS(猫统计!X:X,猫统计!V:V,">="&EOMONTH(A38,-1)+1,猫统计!V:V,"<="&EOMONTH(A38,0))+SUMIFS(猫统计!AD:AD,猫统计!AB:AB,">="&EOMONTH(A38,-1)+1,猫统计!AB:AB,"<="&EOMONTH(A38,0))+SUMIFS(猫统计!AJ:AJ,猫统计!AH:AH,">="&EOMONTH(A38,-1)+1,猫统计!AH:AH,"<="&EOMONTH(A38,0))+SUMIFS(猫统计!AP:AP,猫统计!AN:AN,">="&EOMONTH(A38,-1)+1,猫统计!AN:AN,"<="&EOMONTH(A38,0))+SUMIFS(猫统计!AV:AV,猫统计!AT:AT,">="&EOMONTH(A38,-1)+1,猫统计!AT:AT,"<="&EOMONTH(A38,0))+SUMIFS(猫统计!BB:BB,猫统计!AZ:AZ,">="&EOMONTH(A38,-1)+1,猫统计!AZ:AZ,"<="&EOMONTH(A38,0))+SUMIFS(猫统计!BH:BH,猫统计!BF:BF,">="&EOMONTH(A38,-1)+1,猫统计!BF:BF,"<="&EOMONTH(A38,0))+SUMIFS(猫统计!BN:BN,猫统计!BL:BL,">="&EOMONTH(A38,-1)+1,猫统计!BL:BL,"<="&EOMONTH(A38,0)) -> 0 | E38: =SUMIFS(猫统计!M:M,猫统计!J:J,">="&EOMONTH(A38,-1)+1,猫统计!J:J,"<="&EOMONTH(A38,0))+SUMIFS(猫统计!S:S,猫统计!P:P,">="&EOMONTH(A38,-1)+1,猫统计!P:P,"<="&EOMONTH(A38,0))+SUMIFS(猫统计!Y:Y,猫统计!V:V,">="&EOMONTH(A38,-1)+1,猫统计!V:V,"<="&EOMONTH(A38,0))+SUMIFS(猫统计!AE:AE,猫统计!AB:AB,">="&EOMONTH(A38,-1)+1,猫统计!AB:AB,"<="&EOMONTH(A38,0))+SUMIFS(猫统计!AK:AK,猫统计!AH:AH,">="&EOMONTH(A38,-1)+1,猫统计!AH:AH,"<="&EOMONTH(A38,0))+SUMIFS(猫统计!AQ:AQ,猫统计!AN:AN,">="&EOMONTH(A38,-1)+1,猫统计!AN:AN,"<="&EOMONTH(A38,0))+SUMIFS(猫统计!AW:AW,猫统计!AT:AT,">="&EOMONTH(A38,-1)+1,猫统计!AT:AT,"<="&EOMONTH(A38,0))+SUMIFS(猫统计!BC:BC,猫统计!AZ:AZ,">="&EOMONTH(A38,-1)+1,猫统计!AZ:AZ,"<="&EOMONTH(A38,0))+SUMIFS(猫统计!BI:BI,猫统计!BF:BF,">="&EOMONTH(A38,-1)+1,猫统计!BF:BF,"<="&EOMONTH(A38,0))+SUMIFS(猫统计!BO:BO,猫统计!BL:BL,">="&EOMONTH(A38,-1)+1,猫统计!BL:BL,"<="&EOMONTH(A38,0)) -> 6
A39: 45139 | B39: =COUNTIFS(猫统计!J:J,">="&EOMONTH(A39,-1)+1,猫统计!J:J,"<="&EOMONTH(A39,0))+COUNTIFS(猫统计!P:P,">="&EOMONTH(A39,-1)+1,猫统计!P:P,"<="&EOMONTH(A39,0))+COUNTIFS(猫统计!V:V,">="&EOMONTH(A39,-1)+1,猫统计!V:V,"<="&EOMONTH(A39,0))+COUNTIFS(猫统计!AB:AB,">="&EOMONTH(A39,-1)+1,猫统计!AB:AB,"<="&EOMONTH(A39,0))+COUNTIFS(猫统计!AH:AH,">="&EOMONTH(A39,-1)+1,猫统计!AH:AH,"<="&EOMONTH(A39,0))+COUNTIFS(猫统计!AN:AN,">="&EOMONTH(A39,-1)+1,猫统计!AN:AN,"<="&EOMONTH(A39,0))+COUNTIFS(猫统计!AT:AT,">="&EOMONTH(A39,-1)+1,猫统计!AT:AT,"<="&EOMONTH(A39,0))+COUNTIFS(猫统计!AZ:AZ,">="&EOMONTH(A39,-1)+1,猫统计!AZ:AZ,"<="&EOMONTH(A39,0))+COUNTIFS(猫统计!BF:BF,">="&EOMONTH(A39,-1)+1,猫统计!BF:BF,"<="&EOMONTH(A39,0))+COUNTIFS(猫统计!BL:BL,">="&EOMONTH(A39,-1)+1,猫统计!BL:BL,"<="&EOMONTH(A39,0)) -> 2 | C39: =D39+E39 -> 10 | D39: =SUMIFS(猫统计!L:L,猫统计!J:J,">="&EOMONTH(A39,-1)+1,猫统计!J:J,"<="&EOMONTH(A39,0))+SUMIFS(猫统计!R:R,猫统计!P:P,">="&EOMONTH(A39,-1)+1,猫统计!P:P,"<="&EOMONTH(A39,0))+SUMIFS(猫统计!X:X,猫统计!V:V,">="&EOMONTH(A39,-1)+1,猫统计!V:V,"<="&EOMONTH(A39,0))+SUMIFS(猫统计!AD:AD,猫统计!AB:AB,">="&EOMONTH(A39,-1)+1,猫统计!AB:AB,"<="&EOMONTH(A39,0))+SUMIFS(猫统计!AJ:AJ,猫统计!AH:AH,">="&EOMONTH(A39,-1)+1,猫统计!AH:AH,"<="&EOMONTH(A39,0))+SUMIFS(猫统计!AP:AP,猫统计!AN:AN,">="&EOMONTH(A39,-1)+1,猫统计!AN:AN,"<="&EOMONTH(A39,0))+SUMIFS(猫统计!AV:AV,猫统计!AT:AT,">="&EOMONTH(A39,-1)+1,猫统计!AT:AT,"<="&EOMONTH(A39,0))+SUMIFS(猫统计!BB:BB,猫统计!AZ:AZ,">="&EOMONTH(A39,-1)+1,猫统计!AZ:AZ,"<="&EOMONTH(A39,0))+SUMIFS(猫统计!BH:BH,猫统计!BF:BF,">="&EOMONTH(A39,-1)+1,猫统计!BF:BF,"<="&EOMONTH(A39,0))+SUMIFS(猫统计!BN:BN,猫统计!BL:BL,">="&EOMONTH(A39,-1)+1,猫统计!BL:BL,"<="&EOMONTH(A39,0)) -> 0 | E39: =SUMIFS(猫统计!M:M,猫统计!J:J,">="&EOMONTH(A39,-1)+1,猫统计!J:J,"<="&EOMONTH(A39,0))+SUMIFS(猫统计!S:S,猫统计!P:P,">="&EOMONTH(A39,-1)+1,猫统计!P:P,"<="&EOMONTH(A39,0))+SUMIFS(猫统计!Y:Y,猫统计!V:V,">="&EOMONTH(A39,-1)+1,猫统计!V:V,"<="&EOMONTH(A39,0))+SUMIFS(猫统计!AE:AE,猫统计!AB:AB,">="&EOMONTH(A39,-1)+1,猫统计!AB:AB,"<="&EOMONTH(A39,0))+SUMIFS(猫统计!AK:AK,猫统计!AH:AH,">="&EOMONTH(A39,-1)+1,猫统计!AH:AH,"<="&EOMONTH(A39,0))+SUMIFS(猫统计!AQ:AQ,猫统计!AN:AN,">="&EOMONTH(A39,-1)+1,猫统计!AN:AN,"<="&EOMONTH(A39,0))+SUMIFS(猫统计!AW:AW,猫统计!AT:AT,">="&EOMONTH(A39,-1)+1,猫统计!AT:AT,"<="&EOMONTH(A39,0))+SUMIFS(猫统计!BC:BC,猫统计!AZ:AZ,">="&EOMONTH(A39,-1)+1,猫统计!AZ:AZ,"<="&EOMONTH(A39,0))+SUMIFS(猫统计!BI:BI,猫统计!BF:BF,">="&EOMONTH(A39,-1)+1,猫统计!BF:BF,"<="&EOMONTH(A39,0))+SUMIFS(猫统计!BO:BO,猫统计!BL:BL,">="&EOMONTH(A39,-1)+1,猫统计!BL:BL,"<="&EOMONTH(A39,0)) -> 10
A40: 45170 | B40: =COUNTIFS(猫统计!J:J,">="&EOMONTH(A40,-1)+1,猫统计!J:J,"<="&EOMONTH(A40,0))+COUNTIFS(猫统计!P:P,">="&EOMONTH(A40,-1)+1,猫统计!P:P,"<="&EOMONTH(A40,0))+COUNTIFS(猫统计!V:V,">="&EOMONTH(A40,-1)+1,猫统计!V:V,"<="&EOMONTH(A40,0))+COUNTIFS(猫统计!AB:AB,">="&EOMONTH(A40,-1)+1,猫统计!AB:AB,"<="&EOMONTH(A40,0))+COUNTIFS(猫统计!AH:AH,">="&EOMONTH(A40,-1)+1,猫统计!AH:AH,"<="&EOMONTH(A40,0))+COUNTIFS(猫统计!AN:AN,">="&EOMONTH(A40,-1)+1,猫统计!AN:AN,"<="&EOMONTH(A40,0))+COUNTIFS(猫统计!AT:AT,">="&EOMONTH(A40,-1)+1,猫统计!AT:AT,"<="&EOMONTH(A40,0))+COUNTIFS(猫统计!AZ:AZ,">="&EOMONTH(A40,-1)+1,猫统计!AZ:AZ,"<="&EOMONTH(A40,0))+COUNTIFS(猫统计!BF:BF,">="&EOMONTH(A40,-1)+1,猫统计!BF:BF,"<="&EOMONTH(A40,0))+COUNTIFS(猫统计!BL:BL,">="&EOMONTH(A40,-1)+1,猫统计!BL:BL,"<="&EOMONTH(A40,0)) -> 3 | C40: =D40+E40 -> 8 | D40: =SUMIFS(猫统计!L:L,猫统计!J:J,">="&EOMONTH(A40,-1)+1,猫统计!J:J,"<="&EOMONTH(A40,0))+SUMIFS(猫统计!R:R,猫统计!P:P,">="&EOMONTH(A40,-1)+1,猫统计!P:P,"<="&EOMONTH(A40,0))+SUMIFS(猫统计!X:X,猫统计!V:V,">="&EOMONTH(A40,-1)+1,猫统计!V:V,"<="&EOMONTH(A40,0))+SUMIFS(猫统计!AD:AD,猫统计!AB:AB,">="&EOMONTH(A40,-1)+1,猫统计!AB:AB,"<="&EOMONTH(A40,0))+SUMIFS(猫统计!AJ:AJ,猫统计!AH:AH,">="&EOMONTH(A40,-1)+1,猫统计!AH:AH,"<="&EOMONTH(A40,0))+SUMIFS(猫统计!AP:AP,猫统计!AN:AN,">="&EOMONTH(A40,-1)+1,猫统计!AN:AN,"<="&EOMONTH(A40,0))+SUMIFS(猫统计!AV:AV,猫统计!AT:AT,">="&EOMONTH(A40,-1)+1,猫统计!AT:AT,"<="&EOMONTH(A40,0))+SUMIFS(猫统计!BB:BB,猫统计!AZ:AZ,">="&EOMONTH(A40,-1)+1,猫统计!AZ:AZ,"<="&EOMONTH(A40,0))+SUMIFS(猫统计!BH:BH,猫统计!BF:BF,">="&EOMONTH(A40,-1)+1,猫统计!BF:BF,"<="&EOMONTH(A40,0))+SUMIFS(猫统计!BN:BN,猫统计!BL:BL,">="&EOMONTH(A40,-1)+1,猫统计!BL:BL,"<="&EOMONTH(A40,0)) -> 3 | E40: =SUMIFS(猫统计!M:M,猫统计!J:J,">="&EOMONTH(A40,-1)+1,猫统计!J:J,"<="&EOMONTH(A40,0))+SUMIFS(猫统计!S:S,猫统计!P:P,">="&EOMONTH(A40,-1)+1,猫统计!P:P,"<="&EOMONTH(A40,0))+SUMIFS(猫统计!Y:Y,猫统计!V:V,">="&EOMONTH(A40,-1)+1,猫统计!V:V,"<="&EOMONTH(A40,0))+SUMIFS(猫统计!AE:AE,猫统计!AB:AB,">="&EOMONTH(A40,-1)+1,猫统计!AB:AB,"<="&EOMONTH(A40,0))+SUMIFS(猫统计!AK:AK,猫统计!AH:AH,">="&EOMONTH(A40,-1)+1,猫统计!AH:AH,"<="&EOMONTH(A40,0))+SUMIFS(猫统计!AQ:AQ,猫统计!AN:AN,">="&EOMONTH(A40,-1)+1,猫统计!AN:AN,"<="&EOMONTH(A40,0))+SUMIFS(猫统计!AW:AW,猫统计!AT:AT,">="&EOMONTH(A40,-1)+1,猫统计!AT:AT,"<="&EOMONTH(A40,0))+SUMIFS(猫统计!BC:BC,猫统计!AZ:AZ,">="&EOMONTH(A40,-1)+1,猫统计!AZ:AZ,"<="&EOMONTH(A40,0))+SUMIFS(猫统计!BI:BI,猫统计!BF:BF,">="&EOMONTH(A40,-1)+1,猫统计!BF:BF,"<="&EOMONTH(A40,0))+SUMIFS(猫统计!BO:BO,猫统计!BL:BL,">="&EOMONTH(A40,-1)+1,猫统计!BL:BL,"<="&EOMONTH(A40,0)) -> 5 | F40: =(E38+E39+E40)/(C38+C39+C40) -> 0.875 | G40: =(E38+E39+E40)/(B38+B39+B40) -> 3.5
A41: 45200 | B41: =COUNTIFS(猫统计!J:J,">="&EOMONTH(A41,-1)+1,猫统计!J:J,"<="&EOMONTH(A41,0))+COUNTIFS(猫统计!P:P,">="&EOMONTH(A41,-1)+1,猫统计!P:P,"<="&EOMONTH(A41,0))+COUNTIFS(猫统计!V:V,">="&EOMONTH(A41,-1)+1,猫统计!V:V,"<="&EOMONTH(A41,0))+COUNTIFS(猫统计!AB:AB,">="&EOMONTH(A41,-1)+1,猫统计!AB:AB,"<="&EOMONTH(A41,0))+COUNTIFS(猫统计!AH:AH,">="&EOMONTH(A41,-1)+1,猫统计!AH:AH,"<="&EOMONTH(A41,0))+COUNTIFS(猫统计!AN:AN,">="&EOMONTH(A41,-1)+1,猫统计!AN:AN,"<="&EOMONTH(A41,0))+COUNTIFS(猫统计!AT:AT,">="&EOMONTH(A41,-1)+1,猫统计!AT:AT,"<="&EOMONTH(A41,0))+COUNTIFS(猫统计!AZ:AZ,">="&EOMONTH(A41,-1)+1,猫统计!AZ:AZ,"<="&EOMONTH(A41,0))+COUNTIFS(猫统计!BF:BF,">="&EOMONTH(A41,-1)+1,猫统计!BF:BF,"<="&EOMONTH(A41,0))+COUNTIFS(猫统计!BL:BL,">="&EOMONTH(A41,-1)+1,猫统计!BL:BL,"<="&EOMONTH(A41,0)) -> 0 | C41: =D41+E41 -> 0 | D41: =SUMIFS(猫统计!L:L,猫统计!J:J,">="&EOMONTH(A41,-1)+1,猫统计!J:J,"<="&EOMONTH(A41,0))+SUMIFS(猫统计!R:R,猫统计!P:P,">="&EOMONTH(A41,-1)+1,猫统计!P:P,"<="&EOMONTH(A41,0))+SUMIFS(猫统计!X:X,猫统计!V:V,">="&EOMONTH(A41,-1)+1,猫统计!V:V,"<="&EOMONTH(A41,0))+SUMIFS(猫统计!AD:AD,猫统计!AB:AB,">="&EOMONTH(A41,-1)+1,猫统计!AB:AB,"<="&EOMONTH(A41,0))+SUMIFS(猫统计!AJ:AJ,猫统计!AH:AH,">="&EOMONTH(A41,-1)+1,猫统计!AH:AH,"<="&EOMONTH(A41,0))+SUMIFS(猫统计!AP:AP,猫统计!AN:AN,">="&EOMONTH(A41,-1)+1,猫统计!AN:AN,"<="&EOMONTH(A41,0))+SUMIFS(猫统计!AV:AV,猫统计!AT:AT,">="&EOMONTH(A41,-1)+1,猫统计!AT:AT,"<="&EOMONTH(A41,0))+SUMIFS(猫统计!BB:BB,猫统计!AZ:AZ,">="&EOMONTH(A41,-1)+1,猫统计!AZ:AZ,"<="&EOMONTH(A41,0))+SUMIFS(猫统计!BH:BH,猫统计!BF:BF,">="&EOMONTH(A41,-1)+1,猫统计!BF:BF,"<="&EOMONTH(A41,0))+SUMIFS(猫统计!BN:BN,猫统计!BL:BL,">="&EOMONTH(A41,-1)+1,猫统计!BL:BL,"<="&EOMONTH(A41,0)) -> 0 | E41: =SUMIFS(猫统计!M:M,猫统计!J:J,">="&EOMONTH(A41,-1)+1,猫统计!J:J,"<="&EOMONTH(A41,0))+SUMIFS(猫统计!S:S,猫统计!P:P,">="&EOMONTH(A41,-1)+1,猫统计!P:P,"<="&EOMONTH(A41,0))+SUMIFS(猫统计!Y:Y,猫统计!V:V,">="&EOMONTH(A41,-1)+1,猫统计!V:V,"<="&EOMONTH(A41,0))+SUMIFS(猫统计!AE:AE,猫统计!AB:AB,">="&EOMONTH(A41,-1)+1,猫统计!AB:AB,"<="&EOMONTH(A41,0))+SUMIFS(猫统计!AK:AK,猫统计!AH:AH,">="&EOMONTH(A41,-1)+1,猫统计!AH:AH,"<="&EOMONTH(A41,0))+SUMIFS(猫统计!AQ:AQ,猫统计!AN:AN,">="&EOMONTH(A41,-1)+1,猫统计!AN:AN,"<="&EOMONTH(A41,0))+SUMIFS(猫统计!AW:AW,猫统计!AT:AT,">="&EOMONTH(A41,-1)+1,猫统计!AT:AT,"<="&EOMONTH(A41,0))+SUMIFS(猫统计!BC:BC,猫统计!AZ:AZ,">="&EOMONTH(A41,-1)+1,猫统计!AZ:AZ,"<="&EOMONTH(A41,0))+SUMIFS(猫统计!BI:BI,猫统计!BF:BF,">="&EOMONTH(A41,-1)+1,猫统计!BF:BF,"<="&EOMONTH(A41,0))+SUMIFS(猫统计!BO:BO,猫统计!BL:BL,">="&EOMONTH(A41,-1)+1,猫统计!BL:BL,"<="&EOMONTH(A41,0)) -> 0
A42: 45231 | B42: =COUNTIFS(猫统计!J:J,">="&EOMONTH(A42,-1)+1,猫统计!J:J,"<="&EOMONTH(A42,0))+COUNTIFS(猫统计!P:P,">="&EOMONTH(A42,-1)+1,猫统计!P:P,"<="&EOMONTH(A42,0))+COUNTIFS(猫统计!V:V,">="&EOMONTH(A42,-1)+1,猫统计!V:V,"<="&EOMONTH(A42,0))+COUNTIFS(猫统计!AB:AB,">="&EOMONTH(A42,-1)+1,猫统计!AB:AB,"<="&EOMONTH(A42,0))+COUNTIFS(猫统计!AH:AH,">="&EOMONTH(A42,-1)+1,猫统计!AH:AH,"<="&EOMONTH(A42,0))+COUNTIFS(猫统计!AN:AN,">="&EOMONTH(A42,-1)+1,猫统计!AN:AN,"<="&EOMONTH(A42,0))+COUNTIFS(猫统计!AT:AT,">="&EOMONTH(A42,-1)+1,猫统计!AT:AT,"<="&EOMONTH(A42,0))+COUNTIFS(猫统计!AZ:AZ,">="&EOMONTH(A42,-1)+1,猫统计!AZ:AZ,"<="&EOMONTH(A42,0))+COUNTIFS(猫统计!BF:BF,">="&EOMONTH(A42,-1)+1,猫统计!BF:BF,"<="&EOMONTH(A42,0))+COUNTIFS(猫统计!BL:BL,">="&EOMONTH(A42,-1)+1,猫统计!BL:BL,"<="&EOMONTH(A42,0)) -> 2 | C42: =D42+E42 -> 8 | D42: =SUMIFS(猫统计!L:L,猫统计!J:J,">="&EOMONTH(A42,-1)+1,猫统计!J:J,"<="&EOMONTH(A42,0))+SUMIFS(猫统计!R:R,猫统计!P:P,">="&EOMONTH(A42,-1)+1,猫统计!P:P,"<="&EOMONTH(A42,0))+SUMIFS(猫统计!X:X,猫统计!V:V,">="&EOMONTH(A42,-1)+1,猫统计!V:V,"<="&EOMONTH(A42,0))+SUMIFS(猫统计!AD:AD,猫统计!AB:AB,">="&EOMONTH(A42,-1)+1,猫统计!AB:AB,"<="&EOMONTH(A42,0))+SUMIFS(猫统计!AJ:AJ,猫统计!AH:AH,">="&EOMONTH(A42,-1)+1,猫统计!AH:AH,"<="&EOMONTH(A42,0))+SUMIFS(猫统计!AP:AP,猫统计!AN:AN,">="&EOMONTH(A42,-1)+1,猫统计!AN:AN,"<="&EOMONTH(A42,0))+SUMIFS(猫统计!AV:AV,猫统计!AT:AT,">="&EOMONTH(A42,-1)+1,猫统计!AT:AT,"<="&EOMONTH(A42,0))+SUMIFS(猫统计!BB:BB,猫统计!AZ:AZ,">="&EOMONTH(A42,-1)+1,猫统计!AZ:AZ,"<="&EOMONTH(A42,0))+SUMIFS(猫统计!BH:BH,猫统计!BF:BF,">="&EOMONTH(A42,-1)+1,猫统计!BF:BF,"<="&EOMONTH(A42,0))+SUMIFS(猫统计!BN:BN,猫统计!BL:BL,">="&EOMONTH(A42,-1)+1,猫统计!BL:BL,"<="&EOMONTH(A42,0)) -> 0 | E42: =SUMIFS(猫统计!M:M,猫统计!J:J,">="&EOMONTH(A42,-1)+1,猫统计!J:J,"<="&EOMONTH(A42,0))+SUMIFS(猫统计!S:S,猫统计!P:P,">="&EOMONTH(A42,-1)+1,猫统计!P:P,"<="&EOMONTH(A42,0))+SUMIFS(猫统计!Y:Y,猫统计!V:V,">="&EOMONTH(A42,-1)+1,猫统计!V:V,"<="&EOMONTH(A42,0))+SUMIFS(猫统计!AE:AE,猫统计!AB:AB,">="&EOMONTH(A42,-1)+1,猫统计!AB:AB,"<="&EOMONTH(A42,0))+SUMIFS(猫统计!AK:AK,猫统计!AH:AH,">="&EOMONTH(A42,-1)+1,猫统计!AH:AH,"<="&EOMONTH(A42,0))+SUMIFS(猫统计!AQ:AQ,猫统计!AN:AN,">="&EOMONTH(A42,-1)+1,猫统计!AN:AN,"<="&EOMONTH(A42,0))+SUMIFS(猫统计!AW:AW,猫统计!AT:AT,">="&EOMONTH(A42,-1)+1,猫统计!AT:AT,"<="&EOMONTH(A42,0))+SUMIFS(猫统计!BC:BC,猫统计!AZ:AZ,">="&EOMONTH(A42,-1)+1,猫统计!AZ:AZ,"<="&EOMONTH(A42,0))+SUMIFS(猫统计!BI:BI,猫统计!BF:BF,">="&EOMONTH(A42,-1)+1,猫统计!BF:BF,"<="&EOMONTH(A42,0))+SUMIFS(猫统计!BO:BO,猫统计!BL:BL,">="&EOMONTH(A42,-1)+1,猫统计!BL:BL,"<="&EOMONTH(A42,0)) -> 8
A43: 45261 | B43: =COUNTIFS(猫统计!J:J,">="&EOMONTH(A43,-1)+1,猫统计!J:J,"<="&EOMONTH(A43,0))+COUNTIFS(猫统计!P:P,">="&EOMONTH(A43,-1)+1,猫统计!P:P,"<="&EOMONTH(A43,0))+COUNTIFS(猫统计!V:V,">="&EOMONTH(A43,-1)+1,猫统计!V:V,"<="&EOMONTH(A43,0))+COUNTIFS(猫统计!AB:AB,">="&EOMONTH(A43,-1)+1,猫统计!AB:AB,"<="&EOMONTH(A43,0))+COUNTIFS(猫统计!AH:AH,">="&EOMONTH(A43,-1)+1,猫统计!AH:AH,"<="&EOMONTH(A43,0))+COUNTIFS(猫统计!AN:AN,">="&EOMONTH(A43,-1)+1,猫统计!AN:AN,"<="&EOMONTH(A43,0))+COUNTIFS(猫统计!AT:AT,">="&EOMONTH(A43,-1)+1,猫统计!AT:AT,"<="&EOMONTH(A43,0))+COUNTIFS(猫统计!AZ:AZ,">="&EOMONTH(A43,-1)+1,猫统计!AZ:AZ,"<="&EOMONTH(A43,0))+COUNTIFS(猫统计!BF:BF,">="&EOMONTH(A43,-1)+1,猫统计!BF:BF,"<="&EOMONTH(A43,0))+COUNTIFS(猫统计!BL:BL,">="&EOMONTH(A43,-1)+1,猫统计!BL:BL,"<="&EOMONTH(A43,0)) -> 1 | C43: =D43+E43 -> 2 | D43: =SUMIFS(猫统计!L:L,猫统计!J:J,">="&EOMONTH(A43,-1)+1,猫统计!J:J,"<="&EOMONTH(A43,0))+SUMIFS(猫统计!R:R,猫统计!P:P,">="&EOMONTH(A43,-1)+1,猫统计!P:P,"<="&EOMONTH(A43,0))+SUMIFS(猫统计!X:X,猫统计!V:V,">="&EOMONTH(A43,-1)+1,猫统计!V:V,"<="&EOMONTH(A43,0))+SUMIFS(猫统计!AD:AD,猫统计!AB:AB,">="&EOMONTH(A43,-1)+1,猫统计!AB:AB,"<="&EOMONTH(A43,0))+SUMIFS(猫统计!AJ:AJ,猫统计!AH:AH,">="&EOMONTH(A43,-1)+1,猫统计!AH:AH,"<="&EOMONTH(A43,0))+SUMIFS(猫统计!AP:AP,猫统计!AN:AN,">="&EOMONTH(A43,-1)+1,猫统计!AN:AN,"<="&EOMONTH(A43,0))+SUMIFS(猫统计!AV:AV,猫统计!AT:AT,">="&EOMONTH(A43,-1)+1,猫统计!AT:AT,"<="&EOMONTH(A43,0))+SUMIFS(猫统计!BB:BB,猫统计!AZ:AZ,">="&EOMONTH(A43,-1)+1,猫统计!AZ:AZ,"<="&EOMONTH(A43,0))+SUMIFS(猫统计!BH:BH,猫统计!BF:BF,">="&EOMONTH(A43,-1)+1,猫统计!BF:BF,"<="&EOMONTH(A43,0))+SUMIFS(猫统计!BN:BN,猫统计!BL:BL,">="&EOMONTH(A43,-1)+1,猫统计!BL:BL,"<="&EOMONTH(A43,0)) -> 2 | E43: =SUMIFS(猫统计!M:M,猫统计!J:J,">="&EOMONTH(A43,-1)+1,猫统计!J:J,"<="&EOMONTH(A43,0))+SUMIFS(猫统计!S:S,猫统计!P:P,">="&EOMONTH(A43,-1)+1,猫统计!P:P,"<="&EOMONTH(A43,0))+SUMIFS(猫统计!Y:Y,猫统计!V:V,">="&EOMONTH(A43,-1)+1,猫统计!V:V,"<="&EOMONTH(A43,0))+SUMIFS(猫统计!AE:AE,猫统计!AB:AB,">="&EOMONTH(A43,-1)+1,猫统计!AB:AB,"<="&EOMONTH(A43,0))+SUMIFS(猫统计!AK:AK,猫统计!AH:AH,">="&EOMONTH(A43,-1)+1,猫统计!AH:AH,"<="&EOMONTH(A43,0))+SUMIFS(猫统计!AQ:AQ,猫统计!AN:AN,">="&EOMONTH(A43,-1)+1,猫统计!AN:AN,"<="&EOMONTH(A43,0))+SUMIFS(猫统计!AW:AW,猫统计!AT:AT,">="&EOMONTH(A43,-1)+1,猫统计!AT:AT,"<="&EOMONTH(A43,0))+SUMIFS(猫统计!BC:BC,猫统计!AZ:AZ,">="&EOMONTH(A43,-1)+1,猫统计!AZ:AZ,"<="&EOMONTH(A43,0))+SUMIFS(猫统计!BI:BI,猫统计!BF:BF,">="&EOMONTH(A43,-1)+1,猫统计!BF:BF,"<="&EOMONTH(A43,0))+SUMIFS(猫统计!BO:BO,猫统计!BL:BL,">="&EOMONTH(A43,-1)+1,猫统计!BL:BL,"<="&EOMONTH(A43,0)) -> 0 | F43: =(E41+E42+E43)/(C41+C42+C43) -> 0.8 | G43: =(E41+E42+E43)/(B41+B42+B43) -> 2.6666667
A44: 45292 | B44: =COUNTIFS(猫统计!J:J,">="&EOMONTH(A44,-1)+1,猫统计!J:J,"<="&EOMONTH(A44,0))+COUNTIFS(猫统计!P:P,">="&EOMONTH(A44,-1)+1,猫统计!P:P,"<="&EOMONTH(A44,0))+COUNTIFS(猫统计!V:V,">="&EOMONTH(A44,-1)+1,猫统计!V:V,"<="&EOMONTH(A44,0))+COUNTIFS(猫统计!AB:AB,">="&EOMONTH(A44,-1)+1,猫统计!AB:AB,"<="&EOMONTH(A44,0))+COUNTIFS(猫统计!AH:AH,">="&EOMONTH(A44,-1)+1,猫统计!AH:AH,"<="&EOMONTH(A44,0))+COUNTIFS(猫统计!AN:AN,">="&EOMONTH(A44,-1)+1,猫统计!AN:AN,"<="&EOMONTH(A44,0))+COUNTIFS(猫统计!AT:AT,">="&EOMONTH(A44,-1)+1,猫统计!AT:AT,"<="&EOMONTH(A44,0))+COUNTIFS(猫统计!AZ:AZ,">="&EOMONTH(A44,-1)+1,猫统计!AZ:AZ,"<="&EOMONTH(A44,0))+COUNTIFS(猫统计!BF:BF,">="&EOMONTH(A44,-1)+1,猫统计!BF:BF,"<="&EOMONTH(A44,0))+COUNTIFS(猫统计!BL:BL,">="&EOMONTH(A44,-1)+1,猫统计!BL:BL,"<="&EOMONTH(A44,0)) -> 3 | C44: =D44+E44 -> 13 | D44: =SUMIFS(猫统计!L:L,猫统计!J:J,">="&EOMONTH(A44,-1)+1,猫统计!J:J,"<="&EOMONTH(A44,0))+SUMIFS(猫统计!R:R,猫统计!P:P,">="&EOMONTH(A44,-1)+1,猫统计!P:P,"<="&EOMONTH(A44,0))+SUMIFS(猫统计!X:X,猫统计!V:V,">="&EOMONTH(A44,-1)+1,猫统计!V:V,"<="&EOMONTH(A44,0))+SUMIFS(猫统计!AD:AD,猫统计!AB:AB,">="&EOMONTH(A44,-1)+1,猫统计!AB:AB,"<="&EOMONTH(A44,0))+SUMIFS(猫统计!AJ:AJ,猫统计!AH:AH,">="&EOMONTH(A44,-1)+1,猫统计!AH:AH,"<="&EOMONTH(A44,0))+SUMIFS(猫统计!AP:AP,猫统计!AN:AN,">="&EOMONTH(A44,-1)+1,猫统计!AN:AN,"<="&EOMONTH(A44,0))+SUMIFS(猫统计!AV:AV,猫统计!AT:AT,">="&EOMONTH(A44,-1)+1,猫统计!AT:AT,"<="&EOMONTH(A44,0))+SUMIFS(猫统计!BB:BB,猫统计!AZ:AZ,">="&EOMONTH(A44,-1)+1,猫统计!AZ:AZ,"<="&EOMONTH(A44,0))+SUMIFS(猫统计!BH:BH,猫统计!BF:BF,">="&EOMONTH(A44,-1)+1,猫统计!BF:BF,"<="&EOMONTH(A44,0))+SUMIFS(猫统计!BN:BN,猫统计!BL:BL,">="&EOMONTH(A44,-1)+1,猫统计!BL:BL,"<="&EOMONTH(A44,0)) -> 1 | E44: =SUMIFS(猫统计!M:M,猫统计!J:J,">="&EOMONTH(A44,-1)+1,猫统计!J:J,"<="&EOMONTH(A44,0))+SUMIFS(猫统计!S:S,猫统计!P:P,">="&EOMONTH(A44,-1)+1,猫统计!P:P,"<="&EOMONTH(A44,0))+SUMIFS(猫统计!Y:Y,猫统计!V:V,">="&EOMONTH(A44,-1)+1,猫统计!V:V,"<="&EOMONTH(A44,0))+SUMIFS(猫统计!AE:AE,猫统计!AB:AB,">="&EOMONTH(A44,-1)+1,猫统计!AB:AB,"<="&EOMONTH(A44,0))+SUMIFS(猫统计!AK:AK,猫统计!AH:AH,">="&EOMONTH(A44,-1)+1,猫统计!AH:AH,"<="&EOMONTH(A44,0))+SUMIFS(猫统计!AQ:AQ,猫统计!AN:AN,">="&EOMONTH(A44,-1)+1,猫统计!AN:AN,"<="&EOMONTH(A44,0))+SUMIFS(猫统计!AW:AW,猫统计!AT:AT,">="&EOMONTH(A44,-1)+1,猫统计!AT:AT,"<="&EOMONTH(A44,0))+SUMIFS(猫统计!BC:BC,猫统计!AZ:AZ,">="&EOMONTH(A44,-1)+1,猫统计!AZ:AZ,"<="&EOMONTH(A44,0))+SUMIFS(猫统计!BI:BI,猫统计!BF:BF,">="&EOMONTH(A44,-1)+1,猫统计!BF:BF,"<="&EOMONTH(A44,0))+SUMIFS(猫统计!BO:BO,猫统计!BL:BL,">="&EOMONTH(A44,-1)+1,猫统计!BL:BL,"<="&EOMONTH(A44,0)) -> 12
A45: 45323 | B45: =COUNTIFS(猫统计!J:J,">="&EOMONTH(A45,-1)+1,猫统计!J:J,"<="&EOMONTH(A45,0))+COUNTIFS(猫统计!P:P,">="&EOMONTH(A45,-1)+1,猫统计!P:P,"<="&EOMONTH(A45,0))+COUNTIFS(猫统计!V:V,">="&EOMONTH(A45,-1)+1,猫统计!V:V,"<="&EOMONTH(A45,0))+COUNTIFS(猫统计!AB:AB,">="&EOMONTH(A45,-1)+1,猫统计!AB:AB,"<="&EOMONTH(A45,0))+COUNTIFS(猫统计!AH:AH,">="&EOMONTH(A45,-1)+1,猫统计!AH:AH,"<="&EOMONTH(A45,0))+COUNTIFS(猫统计!AN:AN,">="&EOMONTH(A45,-1)+1,猫统计!AN:AN,"<="&EOMONTH(A45,0))+COUNTIFS(猫统计!AT:AT,">="&EOMONTH(A45,-1)+1,猫统计!AT:AT,"<="&EOMONTH(A45,0))+COUNTIFS(猫统计!AZ:AZ,">="&EOMONTH(A45,-1)+1,猫统计!AZ:AZ,"<="&EOMONTH(A45,0))+COUNTIFS(猫统计!BF:BF,">="&EOMONTH(A45,-1)+1,猫统计!BF:BF,"<="&EOMONTH(A45,0))+COUNTIFS(猫统计!BL:BL,">="&EOMONTH(A45,-1)+1,猫统计!BL:BL,"<="&EOMONTH(A45,0)) -> 1 | C45: =D45+E45 -> 3 | D45: =SUMIFS(猫统计!L:L,猫统计!J:J,">="&EOMONTH(A45,-1)+1,猫统计!J:J,"<="&EOMONTH(A45,0))+SUMIFS(猫统计!R:R,猫统计!P:P,">="&EOMONTH(A45,-1)+1,猫统计!P:P,"<="&EOMONTH(A45,0))+SUMIFS(猫统计!X:X,猫统计!V:V,">="&EOMONTH(A45,-1)+1,猫统计!V:V,"<="&EOMONTH(A45,0))+SUMIFS(猫统计!AD:AD,猫统计!AB:AB,">="&EOMONTH(A45,-1)+1,猫统计!AB:AB,"<="&EOMONTH(A45,0))+SUMIFS(猫统计!AJ:AJ,猫统计!AH:AH,">="&EOMONTH(A45,-1)+1,猫统计!AH:AH,"<="&EOMONTH(A45,0))+SUMIFS(猫统计!AP:AP,猫统计!AN:AN,">="&EOMONTH(A45,-1)+1,猫统计!AN:AN,"<="&EOMONTH(A45,0))+SUMIFS(猫统计!AV:AV,猫统计!AT:AT,">="&EOMONTH(A45,-1)+1,猫统计!AT:AT,"<="&EOMONTH(A45,0))+SUMIFS(猫统计!BB:BB,猫统计!AZ:AZ,">="&EOMONTH(A45,-1)+1,猫统计!AZ:AZ,"<="&EOMONTH(A45,0))+SUMIFS(猫统计!BH:BH,猫统计!BF:BF,">="&EOMONTH(A45,-1)+1,猫统计!BF:BF,"<="&EOMONTH(A45,0))+SUMIFS(猫统计!BN:BN,猫统计!BL:BL,">="&EOMONTH(A45,-1)+1,猫统计!BL:BL,"<="&EOMONTH(A45,0)) -> 1 | E45: =SUMIFS(猫统计!M:M,猫统计!J:J,">="&EOMONTH(A45,-1)+1,猫统计!J:J,"<="&EOMONTH(A45,0))+SUMIFS(猫统计!S:S,猫统计!P:P,">="&EOMONTH(A45,-1)+1,猫统计!P:P,"<="&EOMONTH(A45,0))+SUMIFS(猫统计!Y:Y,猫统计!V:V,">="&EOMONTH(A45,-1)+1,猫统计!V:V,"<="&EOMONTH(A45,0))+SUMIFS(猫统计!AE:AE,猫统计!AB:AB,">="&EOMONTH(A45,-1)+1,猫统计!AB:AB,"<="&EOMONTH(A45,0))+SUMIFS(猫统计!AK:AK,猫统计!AH:AH,">="&EOMONTH(A45,-1)+1,猫统计!AH:AH,"<="&EOMONTH(A45,0))+SUMIFS(猫统计!AQ:AQ,猫统计!AN:AN,">="&EOMONTH(A45,-1)+1,猫统计!AN:AN,"<="&EOMONTH(A45,0))+SUMIFS(猫统计!AW:AW,猫统计!AT:AT,">="&EOMONTH(A45,-1)+1,猫统计!AT:AT,"<="&EOMONTH(A45,0))+SUMIFS(猫统计!BC:BC,猫统计!AZ:AZ,">="&EOMONTH(A45,-1)+1,猫统计!AZ:AZ,"<="&EOMONTH(A45,0))+SUMIFS(猫统计!BI:BI,猫统计!BF:BF,">="&EOMONTH(A45,-1)+1,猫统计!BF:BF,"<="&EOMONTH(A45,0))+SUMIFS(猫统计!BO:BO,猫统计!BL:BL,">="&EOMONTH(A45,-1)+1,猫统计!BL:BL,"<="&EOMONTH(A45,0)) -> 2
A46: 45352 | B46: =COUNTIFS(猫统计!J:J,">="&EOMONTH(A46,-1)+1,猫统计!J:J,"<="&EOMONTH(A46,0))+COUNTIFS(猫统计!P:P,">="&EOMONTH(A46,-1)+1,猫统计!P:P,"<="&EOMONTH(A46,0))+COUNTIFS(猫统计!V:V,">="&EOMONTH(A46,-1)+1,猫统计!V:V,"<="&EOMONTH(A46,0))+COUNTIFS(猫统计!AB:AB,">="&EOMONTH(A46,-1)+1,猫统计!AB:AB,"<="&EOMONTH(A46,0))+COUNTIFS(猫统计!AH:AH,">="&EOMONTH(A46,-1)+1,猫统计!AH:AH,"<="&EOMONTH(A46,0))+COUNTIFS(猫统计!AN:AN,">="&EOMONTH(A46,-1)+1,猫统计!AN:AN,"<="&EOMONTH(A46,0))+COUNTIFS(猫统计!AT:AT,">="&EOMONTH(A46,-1)+1,猫统计!AT:AT,"<="&EOMONTH(A46,0))+COUNTIFS(猫统计!AZ:AZ,">="&EOMONTH(A46,-1)+1,猫统计!AZ:AZ,"<="&EOMONTH(A46,0))+COUNTIFS(猫统计!BF:BF,">="&EOMONTH(A46,-1)+1,猫统计!BF:BF,"<="&EOMONTH(A46,0))+COUNTIFS(猫统计!BL:BL,">="&EOMONTH(A46,-1)+1,猫统计!BL:BL,"<="&EOMONTH(A46,0)) -> 0 | C46: =D46+E46 -> 0 | D46: =SUMIFS(猫统计!L:L,猫统计!J:J,">="&EOMONTH(A46,-1)+1,猫统计!J:J,"<="&EOMONTH(A46,0))+SUMIFS(猫统计!R:R,猫统计!P:P,">="&EOMONTH(A46,-1)+1,猫统计!P:P,"<="&EOMONTH(A46,0))+SUMIFS(猫统计!X:X,猫统计!V:V,">="&EOMONTH(A46,-1)+1,猫统计!V:V,"<="&EOMONTH(A46,0))+SUMIFS(猫统计!AD:AD,猫统计!AB:AB,">="&EOMONTH(A46,-1)+1,猫统计!AB:AB,"<="&EOMONTH(A46,0))+SUMIFS(猫统计!AJ:AJ,猫统计!AH:AH,">="&EOMONTH(A46,-1)+1,猫统计!AH:AH,"<="&EOMONTH(A46,0))+SUMIFS(猫统计!AP:AP,猫统计!AN:AN,">="&EOMONTH(A46,-1)+1,猫统计!AN:AN,"<="&EOMONTH(A46,0))+SUMIFS(猫统计!AV:AV,猫统计!AT:AT,">="&EOMONTH(A46,-1)+1,猫统计!AT:AT,"<="&EOMONTH(A46,0))+SUMIFS(猫统计!BB:BB,猫统计!AZ:AZ,">="&EOMONTH(A46,-1)+1,猫统计!AZ:AZ,"<="&EOMONTH(A46,0))+SUMIFS(猫统计!BH:BH,猫统计!BF:BF,">="&EOMONTH(A46,-1)+1,猫统计!BF:BF,"<="&EOMONTH(A46,0))+SUMIFS(猫统计!BN:BN,猫统计!BL:BL,">="&EOMONTH(A46,-1)+1,猫统计!BL:BL,"<="&EOMONTH(A46,0)) -> 0 | E46: =SUMIFS(猫统计!M:M,猫统计!J:J,">="&EOMONTH(A46,-1)+1,猫统计!J:J,"<="&EOMONTH(A46,0))+SUMIFS(猫统计!S:S,猫统计!P:P,">="&EOMONTH(A46,-1)+1,猫统计!P:P,"<="&EOMONTH(A46,0))+SUMIFS(猫统计!Y:Y,猫统计!V:V,">="&EOMONTH(A46,-1)+1,猫统计!V:V,"<="&EOMONTH(A46,0))+SUMIFS(猫统计!AE:AE,猫统计!AB:AB,">="&EOMONTH(A46,-1)+1,猫统计!AB:AB,"<="&EOMONTH(A46,0))+SUMIFS(猫统计!AK:AK,猫统计!AH:AH,">="&EOMONTH(A46,-1)+1,猫统计!AH:AH,"<="&EOMONTH(A46,0))+SUMIFS(猫统计!AQ:AQ,猫统计!AN:AN,">="&EOMONTH(A46,-1)+1,猫统计!AN:AN,"<="&EOMONTH(A46,0))+SUMIFS(猫统计!AW:AW,猫统计!AT:AT,">="&EOMONTH(A46,-1)+1,猫统计!AT:AT,"<="&EOMONTH(A46,0))+SUMIFS(猫统计!BC:BC,猫统计!AZ:AZ,">="&EOMONTH(A46,-1)+1,猫统计!AZ:AZ,"<="&EOMONTH(A46,0))+SUMIFS(猫统计!BI:BI,猫统计!BF:BF,">="&EOMONTH(A46,-1)+1,猫统计!BF:BF,"<="&EOMONTH(A46,0))+SUMIFS(猫统计!BO:BO,猫统计!BL:BL,">="&EOMONTH(A46,-1)+1,猫统计!BL:BL,"<="&EOMONTH(A46,0)) -> 0 | F46: =(E44+E45+E46)/(C44+C45+C46) -> 0.875 | G46: =(E44+E45+E46)/(B44+B45+B46) -> 3.5
A47: 45383 | B47: =COUNTIFS(猫统计!J:J,">="&EOMONTH(A47,-1)+1,猫统计!J:J,"<="&EOMONTH(A47,0))+COUNTIFS(猫统计!P:P,">="&EOMONTH(A47,-1)+1,猫统计!P:P,"<="&EOMONTH(A47,0))+COUNTIFS(猫统计!V:V,">="&EOMONTH(A47,-1)+1,猫统计!V:V,"<="&EOMONTH(A47,0))+COUNTIFS(猫统计!AB:AB,">="&EOMONTH(A47,-1)+1,猫统计!AB:AB,"<="&EOMONTH(A47,0))+COUNTIFS(猫统计!AH:AH,">="&EOMONTH(A47,-1)+1,猫统计!AH:AH,"<="&EOMONTH(A47,0))+COUNTIFS(猫统计!AN:AN,">="&EOMONTH(A47,-1)+1,猫统计!AN:AN,"<="&EOMONTH(A47,0))+COUNTIFS(猫统计!AT:AT,">="&EOMONTH(A47,-1)+1,猫统计!AT:AT,"<="&EOMONTH(A47,0))+COUNTIFS(猫统计!AZ:AZ,">="&EOMONTH(A47,-1)+1,猫统计!AZ:AZ,"<="&EOMONTH(A47,0))+COUNTIFS(猫统计!BF:BF,">="&EOMONTH(A47,-1)+1,猫统计!BF:BF,"<="&EOMONTH(A47,0))+COUNTIFS(猫统计!BL:BL,">="&EOMONTH(A47,-1)+1,猫统计!BL:BL,"<="&EOMONTH(A47,0)) -> 1 | C47: =D47+E47 -> 1 | D47: =SUMIFS(猫统计!L:L,猫统计!J:J,">="&EOMONTH(A47,-1)+1,猫统计!J:J,"<="&EOMONTH(A47,0))+SUMIFS(猫统计!R:R,猫统计!P:P,">="&EOMONTH(A47,-1)+1,猫统计!P:P,"<="&EOMONTH(A47,0))+SUMIFS(猫统计!X:X,猫统计!V:V,">="&EOMONTH(A47,-1)+1,猫统计!V:V,"<="&EOMONTH(A47,0))+SUMIFS(猫统计!AD:AD,猫统计!AB:AB,">="&EOMONTH(A47,-1)+1,猫统计!AB:AB,"<="&EOMONTH(A47,0))+SUMIFS(猫统计!AJ:AJ,猫统计!AH:AH,">="&EOMONTH(A47,-1)+1,猫统计!AH:AH,"<="&EOMONTH(A47,0))+SUMIFS(猫统计!AP:AP,猫统计!AN:AN,">="&EOMONTH(A47,-1)+1,猫统计!AN:AN,"<="&EOMONTH(A47,0))+SUMIFS(猫统计!AV:AV,猫统计!AT:AT,">="&EOMONTH(A47,-1)+1,猫统计!AT:AT,"<="&EOMONTH(A47,0))+SUMIFS(猫统计!BB:BB,猫统计!AZ:AZ,">="&EOMONTH(A47,-1)+1,猫统计!AZ:AZ,"<="&EOMONTH(A47,0))+SUMIFS(猫统计!BH:BH,猫统计!BF:BF,">="&EOMONTH(A47,-1)+1,猫统计!BF:BF,"<="&EOMONTH(A47,0))+SUMIFS(猫统计!BN:BN,猫统计!BL:BL,">="&EOMONTH(A47,-1)+1,猫统计!BL:BL,"<="&EOMONTH(A47,0)) -> 0 | E47: =SUMIFS(猫统计!M:M,猫统计!J:J,">="&EOMONTH(A47,-1)+1,猫统计!J:J,"<="&EOMONTH(A47,0))+SUMIFS(猫统计!S:S,猫统计!P:P,">="&EOMONTH(A47,-1)+1,猫统计!P:P,"<="&EOMONTH(A47,0))+SUMIFS(猫统计!Y:Y,猫统计!V:V,">="&EOMONTH(A47,-1)+1,猫统计!V:V,"<="&EOMONTH(A47,0))+SUMIFS(猫统计!AE:AE,猫统计!AB:AB,">="&EOMONTH(A47,-1)+1,猫统计!AB:AB,"<="&EOMONTH(A47,0))+SUMIFS(猫统计!AK:AK,猫统计!AH:AH,">="&EOMONTH(A47,-1)+1,猫统计!AH:AH,"<="&EOMONTH(A47,0))+SUMIFS(猫统计!AQ:AQ,猫统计!AN:AN,">="&EOMONTH(A47,-1)+1,猫统计!AN:AN,"<="&EOMONTH(A47,0))+SUMIFS(猫统计!AW:AW,猫统计!AT:AT,">="&EOMONTH(A47,-1)+1,猫统计!AT:AT,"<="&EOMONTH(A47,0))+SUMIFS(猫统计!BC:BC,猫统计!AZ:AZ,">="&EOMONTH(A47,-1)+1,猫统计!AZ:AZ,"<="&EOMONTH(A47,0))+SUMIFS(猫统计!BI:BI,猫统计!BF:BF,">="&EOMONTH(A47,-1)+1,猫统计!BF:BF,"<="&EOMONTH(A47,0))+SUMIFS(猫统计!BO:BO,猫统计!BL:BL,">="&EOMONTH(A47,-1)+1,猫统计!BL:BL,"<="&EOMONTH(A47,0)) -> 1
A48: 45413 | B48: =COUNTIFS(猫统计!J:J,">="&EOMONTH(A48,-1)+1,猫统计!J:J,"<="&EOMONTH(A48,0))+COUNTIFS(猫统计!P:P,">="&EOMONTH(A48,-1)+1,猫统计!P:P,"<="&EOMONTH(A48,0))+COUNTIFS(猫统计!V:V,">="&EOMONTH(A48,-1)+1,猫统计!V:V,"<="&EOMONTH(A48,0))+COUNTIFS(猫统计!AB:AB,">="&EOMONTH(A48,-1)+1,猫统计!AB:AB,"<="&EOMONTH(A48,0))+COUNTIFS(猫统计!AH:AH,">="&EOMONTH(A48,-1)+1,猫统计!AH:AH,"<="&EOMONTH(A48,0))+COUNTIFS(猫统计!AN:AN,">="&EOMONTH(A48,-1)+1,猫统计!AN:AN,"<="&EOMONTH(A48,0))+COUNTIFS(猫统计!AT:AT,">="&EOMONTH(A48,-1)+1,猫统计!AT:AT,"<="&EOMONTH(A48,0))+COUNTIFS(猫统计!AZ:AZ,">="&EOMONTH(A48,-1)+1,猫统计!AZ:AZ,"<="&EOMONTH(A48,0))+COUNTIFS(猫统计!BF:BF,">="&EOMONTH(A48,-1)+1,猫统计!BF:BF,"<="&EOMONTH(A48,0))+COUNTIFS(猫统计!BL:BL,">="&EOMONTH(A48,-1)+1,猫统计!BL:BL,"<="&EOMONTH(A48,0)) -> 6 | C48: =D48+E48 -> 17 | D48: =SUMIFS(猫统计!L:L,猫统计!J:J,">="&EOMONTH(A48,-1)+1,猫统计!J:J,"<="&EOMONTH(A48,0))+SUMIFS(猫统计!R:R,猫统计!P:P,">="&EOMONTH(A48,-1)+1,猫统计!P:P,"<="&EOMONTH(A48,0))+SUMIFS(猫统计!X:X,猫统计!V:V,">="&EOMONTH(A48,-1)+1,猫统计!V:V,"<="&EOMONTH(A48,0))+SUMIFS(猫统计!AD:AD,猫统计!AB:AB,">="&EOMONTH(A48,-1)+1,猫统计!AB:AB,"<="&EOMONTH(A48,0))+SUMIFS(猫统计!AJ:AJ,猫统计!AH:AH,">="&EOMONTH(A48,-1)+1,猫统计!AH:AH,"<="&EOMONTH(A48,0))+SUMIFS(猫统计!AP:AP,猫统计!AN:AN,">="&EOMONTH(A48,-1)+1,猫统计!AN:AN,"<="&EOMONTH(A48,0))+SUMIFS(猫统计!AV:AV,猫统计!AT:AT,">="&EOMONTH(A48,-1)+1,猫统计!AT:AT,"<="&EOMONTH(A48,0))+SUMIFS(猫统计!BB:BB,猫统计!AZ:AZ,">="&EOMONTH(A48,-1)+1,猫统计!AZ:AZ,"<="&EOMONTH(A48,0))+SUMIFS(猫统计!BH:BH,猫统计!BF:BF,">="&EOMONTH(A48,-1)+1,猫统计!BF:BF,"<="&EOMONTH(A48,0))+SUMIFS(猫统计!BN:BN,猫统计!BL:BL,">="&EOMONTH(A48,-1)+1,猫统计!BL:BL,"<="&EOMONTH(A48,0)) -> 9 | E48: =SUMIFS(猫统计!M:M,猫统计!J:J,">="&EOMONTH(A48,-1)+1,猫统计!J:J,"<="&EOMONTH(A48,0))+SUMIFS(猫统计!S:S,猫统计!P:P,">="&EOMONTH(A48,-1)+1,猫统计!P:P,"<="&EOMONTH(A48,0))+SUMIFS(猫统计!Y:Y,猫统计!V:V,">="&EOMONTH(A48,-1)+1,猫统计!V:V,"<="&EOMONTH(A48,0))+SUMIFS(猫统计!AE:AE,猫统计!AB:AB,">="&EOMONTH(A48,-1)+1,猫统计!AB:AB,"<="&EOMONTH(A48,0))+SUMIFS(猫统计!AK:AK,猫统计!AH:AH,">="&EOMONTH(A48,-1)+1,猫统计!AH:AH,"<="&EOMONTH(A48,0))+SUMIFS(猫统计!AQ:AQ,猫统计!AN:AN,">="&EOMONTH(A48,-1)+1,猫统计!AN:AN,"<="&EOMONTH(A48,0))+SUMIFS(猫统计!AW:AW,猫统计!AT:AT,">="&EOMONTH(A48,-1)+1,猫统计!AT:AT,"<="&EOMONTH(A48,0))+SUMIFS(猫统计!BC:BC,猫统计!AZ:AZ,">="&EOMONTH(A48,-1)+1,猫统计!AZ:AZ,"<="&EOMONTH(A48,0))+SUMIFS(猫统计!BI:BI,猫统计!BF:BF,">="&EOMONTH(A48,-1)+1,猫统计!BF:BF,"<="&EOMONTH(A48,0))+SUMIFS(猫统计!BO:BO,猫统计!BL:BL,">="&EOMONTH(A48,-1)+1,猫统计!BL:BL,"<="&EOMONTH(A48,0)) -> 8
A49: 45444 | B49: =COUNTIFS(猫统计!J:J,">="&EOMONTH(A49,-1)+1,猫统计!J:J,"<="&EOMONTH(A49,0))+COUNTIFS(猫统计!P:P,">="&EOMONTH(A49,-1)+1,猫统计!P:P,"<="&EOMONTH(A49,0))+COUNTIFS(猫统计!V:V,">="&EOMONTH(A49,-1)+1,猫统计!V:V,"<="&EOMONTH(A49,0))+COUNTIFS(猫统计!AB:AB,">="&EOMONTH(A49,-1)+1,猫统计!AB:AB,"<="&EOMONTH(A49,0))+COUNTIFS(猫统计!AH:AH,">="&EOMONTH(A49,-1)+1,猫统计!AH:AH,"<="&EOMONTH(A49,0))+COUNTIFS(猫统计!AN:AN,">="&EOMONTH(A49,-1)+1,猫统计!AN:AN,"<="&EOMONTH(A49,0))+COUNTIFS(猫统计!AT:AT,">="&EOMONTH(A49,-1)+1,猫统计!AT:AT,"<="&EOMONTH(A49,0))+COUNTIFS(猫统计!AZ:AZ,">="&EOMONTH(A49,-1)+1,猫统计!AZ:AZ,"<="&EOMONTH(A49,0))+COUNTIFS(猫统计!BF:BF,">="&EOMONTH(A49,-1)+1,猫统计!BF:BF,"<="&EOMONTH(A49,0))+COUNTIFS(猫统计!BL:BL,">="&EOMONTH(A49,-1)+1,猫统计!BL:BL,"<="&EOMONTH(A49,0)) -> 2 | C49: =D49+E49 -> 7 | D49: =SUMIFS(猫统计!L:L,猫统计!J:J,">="&EOMONTH(A49,-1)+1,猫统计!J:J,"<="&EOMONTH(A49,0))+SUMIFS(猫统计!R:R,猫统计!P:P,">="&EOMONTH(A49,-1)+1,猫统计!P:P,"<="&EOMONTH(A49,0))+SUMIFS(猫统计!X:X,猫统计!V:V,">="&EOMONTH(A49,-1)+1,猫统计!V:V,"<="&EOMONTH(A49,0))+SUMIFS(猫统计!AD:AD,猫统计!AB:AB,">="&EOMONTH(A49,-1)+1,猫统计!AB:AB,"<="&EOMONTH(A49,0))+SUMIFS(猫统计!AJ:AJ,猫统计!AH:AH,">="&EOMONTH(A49,-1)+1,猫统计!AH:AH,"<="&EOMONTH(A49,0))+SUMIFS(猫统计!AP:AP,猫统计!AN:AN,">="&EOMONTH(A49,-1)+1,猫统计!AN:AN,"<="&EOMONTH(A49,0))+SUMIFS(猫统计!AV:AV,猫统计!AT:AT,">="&EOMONTH(A49,-1)+1,猫统计!AT:AT,"<="&EOMONTH(A49,0))+SUMIFS(猫统计!BB:BB,猫统计!AZ:AZ,">="&EOMONTH(A49,-1)+1,猫统计!AZ:AZ,"<="&EOMONTH(A49,0))+SUMIFS(猫统计!BH:BH,猫统计!BF:BF,">="&EOMONTH(A49,-1)+1,猫统计!BF:BF,"<="&EOMONTH(A49,0))+SUMIFS(猫统计!BN:BN,猫统计!BL:BL,">="&EOMONTH(A49,-1)+1,猫统计!BL:BL,"<="&EOMONTH(A49,0)) -> 0 | E49: =SUMIFS(猫统计!M:M,猫统计!J:J,">="&EOMONTH(A49,-1)+1,猫统计!J:J,"<="&EOMONTH(A49,0))+SUMIFS(猫统计!S:S,猫统计!P:P,">="&EOMONTH(A49,-1)+1,猫统计!P:P,"<="&EOMONTH(A49,0))+SUMIFS(猫统计!Y:Y,猫统计!V:V,">="&EOMONTH(A49,-1)+1,猫统计!V:V,"<="&EOMONTH(A49,0))+SUMIFS(猫统计!AE:AE,猫统计!AB:AB,">="&EOMONTH(A49,-1)+1,猫统计!AB:AB,"<="&EOMONTH(A49,0))+SUMIFS(猫统计!AK:AK,猫统计!AH:AH,">="&EOMONTH(A49,-1)+1,猫统计!AH:AH,"<="&EOMONTH(A49,0))+SUMIFS(猫统计!AQ:AQ,猫统计!AN:AN,">="&EOMONTH(A49,-1)+1,猫统计!AN:AN,"<="&EOMONTH(A49,0))+SUMIFS(猫统计!AW:AW,猫统计!AT:AT,">="&EOMONTH(A49,-1)+1,猫统计!AT:AT,"<="&EOMONTH(A49,0))+SUMIFS(猫统计!BC:BC,猫统计!AZ:AZ,">="&EOMONTH(A49,-1)+1,猫统计!AZ:AZ,"<="&EOMONTH(A49,0))+SUMIFS(猫统计!BI:BI,猫统计!BF:BF,">="&EOMONTH(A49,-1)+1,猫统计!BF:BF,"<="&EOMONTH(A49,0))+SUMIFS(猫统计!BO:BO,猫统计!BL:BL,">="&EOMONTH(A49,-1)+1,猫统计!BL:BL,"<="&EOMONTH(A49,0)) -> 7 | F49: =(E47+E48+E49)/(C47+C48+C49) -> 0.64 | G49: =(E47+E48+E49)/(B47+B48+B49) -> 1.7777778
A50: 45474 | B50: =COUNTIFS(猫统计!J:J,">="&EOMONTH(A50,-1)+1,猫统计!J:J,"<="&EOMONTH(A50,0))+COUNTIFS(猫统计!P:P,">="&EOMONTH(A50,-1)+1,猫统计!P:P,"<="&EOMONTH(A50,0))+COUNTIFS(猫统计!V:V,">="&EOMONTH(A50,-1)+1,猫统计!V:V,"<="&EOMONTH(A50,0))+COUNTIFS(猫统计!AB:AB,">="&EOMONTH(A50,-1)+1,猫统计!AB:AB,"<="&EOMONTH(A50,0))+COUNTIFS(猫统计!AH:AH,">="&EOMONTH(A50,-1)+1,猫统计!AH:AH,"<="&EOMONTH(A50,0))+COUNTIFS(猫统计!AN:AN,">="&EOMONTH(A50,-1)+1,猫统计!AN:AN,"<="&EOMONTH(A50,0))+COUNTIFS(猫统计!AT:AT,">="&EOMONTH(A50,-1)+1,猫统计!AT:AT,"<="&EOMONTH(A50,0))+COUNTIFS(猫统计!AZ:AZ,">="&EOMONTH(A50,-1)+1,猫统计!AZ:AZ,"<="&EOMONTH(A50,0))+COUNTIFS(猫统计!BF:BF,">="&EOMONTH(A50,-1)+1,猫统计!BF:BF,"<="&EOMONTH(A50,0))+COUNTIFS(猫统计!BL:BL,">="&EOMONTH(A50,-1)+1,猫统计!BL:BL,"<="&EOMONTH(A50,0)) -> 0 | C50: =D50+E50 -> 0 | D50: =SUMIFS(猫统计!L:L,猫统计!J:J,">="&EOMONTH(A50,-1)+1,猫统计!J:J,"<="&EOMONTH(A50,0))+SUMIFS(猫统计!R:R,猫统计!P:P,">="&EOMONTH(A50,-1)+1,猫统计!P:P,"<="&EOMONTH(A50,0))+SUMIFS(猫统计!X:X,猫统计!V:V,">="&EOMONTH(A50,-1)+1,猫统计!V:V,"<="&EOMONTH(A50,0))+SUMIFS(猫统计!AD:AD,猫统计!AB:AB,">="&EOMONTH(A50,-1)+1,猫统计!AB:AB,"<="&EOMONTH(A50,0))+SUMIFS(猫统计!AJ:AJ,猫统计!AH:AH,">="&EOMONTH(A50,-1)+1,猫统计!AH:AH,"<="&EOMONTH(A50,0))+SUMIFS(猫统计!AP:AP,猫统计!AN:AN,">="&EOMONTH(A50,-1)+1,猫统计!AN:AN,"<="&EOMONTH(A50,0))+SUMIFS(猫统计!AV:AV,猫统计!AT:AT,">="&EOMONTH(A50,-1)+1,猫统计!AT:AT,"<="&EOMONTH(A50,0))+SUMIFS(猫统计!BB:BB,猫统计!AZ:AZ,">="&EOMONTH(A50,-1)+1,猫统计!AZ:AZ,"<="&EOMONTH(A50,0))+SUMIFS(猫统计!BH:BH,猫统计!BF:BF,">="&EOMONTH(A50,-1)+1,猫统计!BF:BF,"<="&EOMONTH(A50,0))+SUMIFS(猫统计!BN:BN,猫统计!BL:BL,">="&EOMONTH(A50,-1)+1,猫统计!BL:BL,"<="&EOMONTH(A50,0)) -> 0 | E50: =SUMIFS(猫统计!M:M,猫统计!J:J,">="&EOMONTH(A50,-1)+1,猫统计!J:J,"<="&EOMONTH(A50,0))+SUMIFS(猫统计!S:S,猫统计!P:P,">="&EOMONTH(A50,-1)+1,猫统计!P:P,"<="&EOMONTH(A50,0))+SUMIFS(猫统计!Y:Y,猫统计!V:V,">="&EOMONTH(A50,-1)+1,猫统计!V:V,"<="&EOMONTH(A50,0))+SUMIFS(猫统计!AE:AE,猫统计!AB:AB,">="&EOMONTH(A50,-1)+1,猫统计!AB:AB,"<="&EOMONTH(A50,0))+SUMIFS(猫统计!AK:AK,猫统计!AH:AH,">="&EOMONTH(A50,-1)+1,猫统计!AH:AH,"<="&EOMONTH(A50,0))+SUMIFS(猫统计!AQ:AQ,猫统计!AN:AN,">="&EOMONTH(A50,-1)+1,猫统计!AN:AN,"<="&EOMONTH(A50,0))+SUMIFS(猫统计!AW:AW,猫统计!AT:AT,">="&EOMONTH(A50,-1)+1,猫统计!AT:AT,"<="&EOMONTH(A50,0))+SUMIFS(猫统计!BC:BC,猫统计!AZ:AZ,">="&EOMONTH(A50,-1)+1,猫统计!AZ:AZ,"<="&EOMONTH(A50,0))+SUMIFS(猫统计!BI:BI,猫统计!BF:BF,">="&EOMONTH(A50,-1)+1,猫统计!BF:BF,"<="&EOMONTH(A50,0))+SUMIFS(猫统计!BO:BO,猫统计!BL:BL,">="&EOMONTH(A50,-1)+1,猫统计!BL:BL,"<="&EOMONTH(A50,0)) -> 0
A51: 45505 | B51: =COUNTIFS(猫统计!J:J,">="&EOMONTH(A51,-1)+1,猫统计!J:J,"<="&EOMONTH(A51,0))+COUNTIFS(猫统计!P:P,">="&EOMONTH(A51,-1)+1,猫统计!P:P,"<="&EOMONTH(A51,0))+COUNTIFS(猫统计!V:V,">="&EOMONTH(A51,-1)+1,猫统计!V:V,"<="&EOMONTH(A51,0))+COUNTIFS(猫统计!AB:AB,">="&EOMONTH(A51,-1)+1,猫统计!AB:AB,"<="&EOMONTH(A51,0))+COUNTIFS(猫统计!AH:AH,">="&EOMONTH(A51,-1)+1,猫统计!AH:AH,"<="&EOMONTH(A51,0))+COUNTIFS(猫统计!AN:AN,">="&EOMONTH(A51,-1)+1,猫统计!AN:AN,"<="&EOMONTH(A51,0))+COUNTIFS(猫统计!AT:AT,">="&EOMONTH(A51,-1)+1,猫统计!AT:AT,"<="&EOMONTH(A51,0))+COUNTIFS(猫统计!AZ:AZ,">="&EOMONTH(A51,-1)+1,猫统计!AZ:AZ,"<="&EOMONTH(A51,0))+COUNTIFS(猫统计!BF:BF,">="&EOMONTH(A51,-1)+1,猫统计!BF:BF,"<="&EOMONTH(A51,0))+COUNTIFS(猫统计!BL:BL,">="&EOMONTH(A51,-1)+1,猫统计!BL:BL,"<="&EOMONTH(A51,0)) -> 2 | C51: =D51+E51 -> 7 | D51: =SUMIFS(猫统计!L:L,猫统计!J:J,">="&EOMONTH(A51,-1)+1,猫统计!J:J,"<="&EOMONTH(A51,0))+SUMIFS(猫统计!R:R,猫统计!P:P,">="&EOMONTH(A51,-1)+1,猫统计!P:P,"<="&EOMONTH(A51,0))+SUMIFS(猫统计!X:X,猫统计!V:V,">="&EOMONTH(A51,-1)+1,猫统计!V:V,"<="&EOMONTH(A51,0))+SUMIFS(猫统计!AD:AD,猫统计!AB:AB,">="&EOMONTH(A51,-1)+1,猫统计!AB:AB,"<="&EOMONTH(A51,0))+SUMIFS(猫统计!AJ:AJ,猫统计!AH:AH,">="&EOMONTH(A51,-1)+1,猫统计!AH:AH,"<="&EOMONTH(A51,0))+SUMIFS(猫统计!AP:AP,猫统计!AN:AN,">="&EOMONTH(A51,-1)+1,猫统计!AN:AN,"<="&EOMONTH(A51,0))+SUMIFS(猫统计!AV:AV,猫统计!AT:AT,">="&EOMONTH(A51,-1)+1,猫统计!AT:AT,"<="&EOMONTH(A51,0))+SUMIFS(猫统计!BB:BB,猫统计!AZ:AZ,">="&EOMONTH(A51,-1)+1,猫统计!AZ:AZ,"<="&EOMONTH(A51,0))+SUMIFS(猫统计!BH:BH,猫统计!BF:BF,">="&EOMONTH(A51,-1)+1,猫统计!BF:BF,"<="&EOMONTH(A51,0))+SUMIFS(猫统计!BN:BN,猫统计!BL:BL,">="&EOMONTH(A51,-1)+1,猫统计!BL:BL,"<="&EOMONTH(A51,0)) -> 3 | E51: =SUMIFS(猫统计!M:M,猫统计!J:J,">="&EOMONTH(A51,-1)+1,猫统计!J:J,"<="&EOMONTH(A51,0))+SUMIFS(猫统计!S:S,猫统计!P:P,">="&EOMONTH(A51,-1)+1,猫统计!P:P,"<="&EOMONTH(A51,0))+SUMIFS(猫统计!Y:Y,猫统计!V:V,">="&EOMONTH(A51,-1)+1,猫统计!V:V,"<="&EOMONTH(A51,0))+SUMIFS(猫统计!AE:AE,猫统计!AB:AB,">="&EOMONTH(A51,-1)+1,猫统计!AB:AB,"<="&EOMONTH(A51,0))+SUMIFS(猫统计!AK:AK,猫统计!AH:AH,">="&EOMONTH(A51,-1)+1,猫统计!AH:AH,"<="&EOMONTH(A51,0))+SUMIFS(猫统计!AQ:AQ,猫统计!AN:AN,">="&EOMONTH(A51,-1)+1,猫统计!AN:AN,"<="&EOMONTH(A51,0))+SUMIFS(猫统计!AW:AW,猫统计!AT:AT,">="&EOMONTH(A51,-1)+1,猫统计!AT:AT,"<="&EOMONTH(A51,0))+SUMIFS(猫统计!BC:BC,猫统计!AZ:AZ,">="&EOMONTH(A51,-1)+1,猫统计!AZ:AZ,"<="&EOMONTH(A51,0))+SUMIFS(猫统计!BI:BI,猫统计!BF:BF,">="&EOMONTH(A51,-1)+1,猫统计!BF:BF,"<="&EOMONTH(A51,0))+SUMIFS(猫统计!BO:BO,猫统计!BL:BL,">="&EOMONTH(A51,-1)+1,猫统计!BL:BL,"<="&EOMONTH(A51,0)) -> 4
A52: 45536 | B52: =COUNTIFS(猫统计!J:J,">="&EOMONTH(A52,-1)+1,猫统计!J:J,"<="&EOMONTH(A52,0))+COUNTIFS(猫统计!P:P,">="&EOMONTH(A52,-1)+1,猫统计!P:P,"<="&EOMONTH(A52,0))+COUNTIFS(猫统计!V:V,">="&EOMONTH(A52,-1)+1,猫统计!V:V,"<="&EOMONTH(A52,0))+COUNTIFS(猫统计!AB:AB,">="&EOMONTH(A52,-1)+1,猫统计!AB:AB,"<="&EOMONTH(A52,0))+COUNTIFS(猫统计!AH:AH,">="&EOMONTH(A52,-1)+1,猫统计!AH:AH,"<="&EOMONTH(A52,0))+COUNTIFS(猫统计!AN:AN,">="&EOMONTH(A52,-1)+1,猫统计!AN:AN,"<="&EOMONTH(A52,0))+COUNTIFS(猫统计!AT:AT,">="&EOMONTH(A52,-1)+1,猫统计!AT:AT,"<="&EOMONTH(A52,0))+COUNTIFS(猫统计!AZ:AZ,">="&EOMONTH(A52,-1)+1,猫统计!AZ:AZ,"<="&EOMONTH(A52,0))+COUNTIFS(猫统计!BF:BF,">="&EOMONTH(A52,-1)+1,猫统计!BF:BF,"<="&EOMONTH(A52,0))+COUNTIFS(猫统计!BL:BL,">="&EOMONTH(A52,-1)+1,猫统计!BL:BL,"<="&EOMONTH(A52,0)) -> 2 | C52: =D52+E52 -> 6 | D52: =SUMIFS(猫统计!L:L,猫统计!J:J,">="&EOMONTH(A52,-1)+1,猫统计!J:J,"<="&EOMONTH(A52,0))+SUMIFS(猫统计!R:R,猫统计!P:P,">="&EOMONTH(A52,-1)+1,猫统计!P:P,"<="&EOMONTH(A52,0))+SUMIFS(猫统计!X:X,猫统计!V:V,">="&EOMONTH(A52,-1)+1,猫统计!V:V,"<="&EOMONTH(A52,0))+SUMIFS(猫统计!AD:AD,猫统计!AB:AB,">="&EOMONTH(A52,-1)+1,猫统计!AB:AB,"<="&EOMONTH(A52,0))+SUMIFS(猫统计!AJ:AJ,猫统计!AH:AH,">="&EOMONTH(A52,-1)+1,猫统计!AH:AH,"<="&EOMONTH(A52,0))+SUMIFS(猫统计!AP:AP,猫统计!AN:AN,">="&EOMONTH(A52,-1)+1,猫统计!AN:AN,"<="&EOMONTH(A52,0))+SUMIFS(猫统计!AV:AV,猫统计!AT:AT,">="&EOMONTH(A52,-1)+1,猫统计!AT:AT,"<="&EOMONTH(A52,0))+SUMIFS(猫统计!BB:BB,猫统计!AZ:AZ,">="&EOMONTH(A52,-1)+1,猫统计!AZ:AZ,"<="&EOMONTH(A52,0))+SUMIFS(猫统计!BH:BH,猫统计!BF:BF,">="&EOMONTH(A52,-1)+1,猫统计!BF:BF,"<="&EOMONTH(A52,0))+SUMIFS(猫统计!BN:BN,猫统计!BL:BL,">="&EOMONTH(A52,-1)+1,猫统计!BL:BL,"<="&EOMONTH(A52,0)) -> 2 | E52: =SUMIFS(猫统计!M:M,猫统计!J:J,">="&EOMONTH(A52,-1)+1,猫统计!J:J,"<="&EOMONTH(A52,0))+SUMIFS(猫统计!S:S,猫统计!P:P,">="&EOMONTH(A52,-1)+1,猫统计!P:P,"<="&EOMONTH(A52,0))+SUMIFS(猫统计!Y:Y,猫统计!V:V,">="&EOMONTH(A52,-1)+1,猫统计!V:V,"<="&EOMONTH(A52,0))+SUMIFS(猫统计!AE:AE,猫统计!AB:AB,">="&EOMONTH(A52,-1)+1,猫统计!AB:AB,"<="&EOMONTH(A52,0))+SUMIFS(猫统计!AK:AK,猫统计!AH:AH,">="&EOMONTH(A52,-1)+1,猫统计!AH:AH,"<="&EOMONTH(A52,0))+SUMIFS(猫统计!AQ:AQ,猫统计!AN:AN,">="&EOMONTH(A52,-1)+1,猫统计!AN:AN,"<="&EOMONTH(A52,0))+SUMIFS(猫统计!AW:AW,猫统计!AT:AT,">="&EOMONTH(A52,-1)+1,猫统计!AT:AT,"<="&EOMONTH(A52,0))+SUMIFS(猫统计!BC:BC,猫统计!AZ:AZ,">="&EOMONTH(A52,-1)+1,猫统计!AZ:AZ,"<="&EOMONTH(A52,0))+SUMIFS(猫统计!BI:BI,猫统计!BF:BF,">="&EOMONTH(A52,-1)+1,猫统计!BF:BF,"<="&EOMONTH(A52,0))+SUMIFS(猫统计!BO:BO,猫统计!BL:BL,">="&EOMONTH(A52,-1)+1,猫统计!BL:BL,"<="&EOMONTH(A52,0)) -> 4 | F52: =(E50+E51+E52)/(C50+C51+C52) -> 0.61538462 | G52: =(E50+E51+E52)/(B50+B51+B52) -> 2
A53: 45566 | B53: =COUNTIFS(猫统计!J:J,">="&EOMONTH(A53,-1)+1,猫统计!J:J,"<="&EOMONTH(A53,0))+COUNTIFS(猫统计!P:P,">="&EOMONTH(A53,-1)+1,猫统计!P:P,"<="&EOMONTH(A53,0))+COUNTIFS(猫统计!V:V,">="&EOMONTH(A53,-1)+1,猫统计!V:V,"<="&EOMONTH(A53,0))+COUNTIFS(猫统计!AB:AB,">="&EOMONTH(A53,-1)+1,猫统计!AB:AB,"<="&EOMONTH(A53,0))+COUNTIFS(猫统计!AH:AH,">="&EOMONTH(A53,-1)+1,猫统计!AH:AH,"<="&EOMONTH(A53,0))+COUNTIFS(猫统计!AN:AN,">="&EOMONTH(A53,-1)+1,猫统计!AN:AN,"<="&EOMONTH(A53,0))+COUNTIFS(猫统计!AT:AT,">="&EOMONTH(A53,-1)+1,猫统计!AT:AT,"<="&EOMONTH(A53,0))+COUNTIFS(猫统计!AZ:AZ,">="&EOMONTH(A53,-1)+1,猫统计!AZ:AZ,"<="&EOMONTH(A53,0))+COUNTIFS(猫统计!BF:BF,">="&EOMONTH(A53,-1)+1,猫统计!BF:BF,"<="&EOMONTH(A53,0))+COUNTIFS(猫统计!BL:BL,">="&EOMONTH(A53,-1)+1,猫统计!BL:BL,"<="&EOMONTH(A53,0)) -> 1 | C53: =D53+E53 -> 4 | D53: =SUMIFS(猫统计!L:L,猫统计!J:J,">="&EOMONTH(A53,-1)+1,猫统计!J:J,"<="&EOMONTH(A53,0))+SUMIFS(猫统计!R:R,猫统计!P:P,">="&EOMONTH(A53,-1)+1,猫统计!P:P,"<="&EOMONTH(A53,0))+SUMIFS(猫统计!X:X,猫统计!V:V,">="&EOMONTH(A53,-1)+1,猫统计!V:V,"<="&EOMONTH(A53,0))+SUMIFS(猫统计!AD:AD,猫统计!AB:AB,">="&EOMONTH(A53,-1)+1,猫统计!AB:AB,"<="&EOMONTH(A53,0))+SUMIFS(猫统计!AJ:AJ,猫统计!AH:AH,">="&EOMONTH(A53,-1)+1,猫统计!AH:AH,"<="&EOMONTH(A53,0))+SUMIFS(猫统计!AP:AP,猫统计!AN:AN,">="&EOMONTH(A53,-1)+1,猫统计!AN:AN,"<="&EOMONTH(A53,0))+SUMIFS(猫统计!AV:AV,猫统计!AT:AT,">="&EOMONTH(A53,-1)+1,猫统计!AT:AT,"<="&EOMONTH(A53,0))+SUMIFS(猫统计!BB:BB,猫统计!AZ:AZ,">="&EOMONTH(A53,-1)+1,猫统计!AZ:AZ,"<="&EOMONTH(A53,0))+SUMIFS(猫统计!BH:BH,猫统计!BF:BF,">="&EOMONTH(A53,-1)+1,猫统计!BF:BF,"<="&EOMONTH(A53,0))+SUMIFS(猫统计!BN:BN,猫统计!BL:BL,">="&EOMONTH(A53,-1)+1,猫统计!BL:BL,"<="&EOMONTH(A53,0)) -> 1 | E53: =SUMIFS(猫统计!M:M,猫统计!J:J,">="&EOMONTH(A53,-1)+1,猫统计!J:J,"<="&EOMONTH(A53,0))+SUMIFS(猫统计!S:S,猫统计!P:P,">="&EOMONTH(A53,-1)+1,猫统计!P:P,"<="&EOMONTH(A53,0))+SUMIFS(猫统计!Y:Y,猫统计!V:V,">="&EOMONTH(A53,-1)+1,猫统计!V:V,"<="&EOMONTH(A53,0))+SUMIFS(猫统计!AE:AE,猫统计!AB:AB,">="&EOMONTH(A53,-1)+1,猫统计!AB:AB,"<="&EOMONTH(A53,0))+SUMIFS(猫统计!AK:AK,猫统计!AH:AH,">="&EOMONTH(A53,-1)+1,猫统计!AH:AH,"<="&EOMONTH(A53,0))+SUMIFS(猫统计!AQ:AQ,猫统计!AN:AN,">="&EOMONTH(A53,-1)+1,猫统计!AN:AN,"<="&EOMONTH(A53,0))+SUMIFS(猫统计!AW:AW,猫统计!AT:AT,">="&EOMONTH(A53,-1)+1,猫统计!AT:AT,"<="&EOMONTH(A53,0))+SUMIFS(猫统计!BC:BC,猫统计!AZ:AZ,">="&EOMONTH(A53,-1)+1,猫统计!AZ:AZ,"<="&EOMONTH(A53,0))+SUMIFS(猫统计!BI:BI,猫统计!BF:BF,">="&EOMONTH(A53,-1)+1,猫统计!BF:BF,"<="&EOMONTH(A53,0))+SUMIFS(猫统计!BO:BO,猫统计!BL:BL,">="&EOMONTH(A53,-1)+1,猫统计!BL:BL,"<="&EOMONTH(A53,0)) -> 3
A54: 45597 | B54: =COUNTIFS(猫统计!J:J,">="&EOMONTH(A54,-1)+1,猫统计!J:J,"<="&EOMONTH(A54,0))+COUNTIFS(猫统计!P:P,">="&EOMONTH(A54,-1)+1,猫统计!P:P,"<="&EOMONTH(A54,0))+COUNTIFS(猫统计!V:V,">="&EOMONTH(A54,-1)+1,猫统计!V:V,"<="&EOMONTH(A54,0))+COUNTIFS(猫统计!AB:AB,">="&EOMONTH(A54,-1)+1,猫统计!AB:AB,"<="&EOMONTH(A54,0))+COUNTIFS(猫统计!AH:AH,">="&EOMONTH(A54,-1)+1,猫统计!AH:AH,"<="&EOMONTH(A54,0))+COUNTIFS(猫统计!AN:AN,">="&EOMONTH(A54,-1)+1,猫统计!AN:AN,"<="&EOMONTH(A54,0))+COUNTIFS(猫统计!AT:AT,">="&EOMONTH(A54,-1)+1,猫统计!AT:AT,"<="&EOMONTH(A54,0))+COUNTIFS(猫统计!AZ:AZ,">="&EOMONTH(A54,-1)+1,猫统计!AZ:AZ,"<="&EOMONTH(A54,0))+COUNTIFS(猫统计!BF:BF,">="&EOMONTH(A54,-1)+1,猫统计!BF:BF,"<="&EOMONTH(A54,0))+COUNTIFS(猫统计!BL:BL,">="&EOMONTH(A54,-1)+1,猫统计!BL:BL,"<="&EOMONTH(A54,0)) -> 0 | C54: =D54+E54 -> 0 | D54: =SUMIFS(猫统计!L:L,猫统计!J:J,">="&EOMONTH(A54,-1)+1,猫统计!J:J,"<="&EOMONTH(A54,0))+SUMIFS(猫统计!R:R,猫统计!P:P,">="&EOMONTH(A54,-1)+1,猫统计!P:P,"<="&EOMONTH(A54,0))+SUMIFS(猫统计!X:X,猫统计!V:V,">="&EOMONTH(A54,-1)+1,猫统计!V:V,"<="&EOMONTH(A54,0))+SUMIFS(猫统计!AD:AD,猫统计!AB:AB,">="&EOMONTH(A54,-1)+1,猫统计!AB:AB,"<="&EOMONTH(A54,0))+SUMIFS(猫统计!AJ:AJ,猫统计!AH:AH,">="&EOMONTH(A54,-1)+1,猫统计!AH:AH,"<="&EOMONTH(A54,0))+SUMIFS(猫统计!AP:AP,猫统计!AN:AN,">="&EOMONTH(A54,-1)+1,猫统计!AN:AN,"<="&EOMONTH(A54,0))+SUMIFS(猫统计!AV:AV,猫统计!AT:AT,">="&EOMONTH(A54,-1)+1,猫统计!AT:AT,"<="&EOMONTH(A54,0))+SUMIFS(猫统计!BB:BB,猫统计!AZ:AZ,">="&EOMONTH(A54,-1)+1,猫统计!AZ:AZ,"<="&EOMONTH(A54,0))+SUMIFS(猫统计!BH:BH,猫统计!BF:BF,">="&EOMONTH(A54,-1)+1,猫统计!BF:BF,"<="&EOMONTH(A54,0))+SUMIFS(猫统计!BN:BN,猫统计!BL:BL,">="&EOMONTH(A54,-1)+1,猫统计!BL:BL,"<="&EOMONTH(A54,0)) -> 0 | E54: =SUMIFS(猫统计!M:M,猫统计!J:J,">="&EOMONTH(A54,-1)+1,猫统计!J:J,"<="&EOMONTH(A54,0))+SUMIFS(猫统计!S:S,猫统计!P:P,">="&EOMONTH(A54,-1)+1,猫统计!P:P,"<="&EOMONTH(A54,0))+SUMIFS(猫统计!Y:Y,猫统计!V:V,">="&EOMONTH(A54,-1)+1,猫统计!V:V,"<="&EOMONTH(A54,0))+SUMIFS(猫统计!AE:AE,猫统计!AB:AB,">="&EOMONTH(A54,-1)+1,猫统计!AB:AB,"<="&EOMONTH(A54,0))+SUMIFS(猫统计!AK:AK,猫统计!AH:AH,">="&EOMONTH(A54,-1)+1,猫统计!AH:AH,"<="&EOMONTH(A54,0))+SUMIFS(猫统计!AQ:AQ,猫统计!AN:AN,">="&EOMONTH(A54,-1)+1,猫统计!AN:AN,"<="&EOMONTH(A54,0))+SUMIFS(猫统计!AW:AW,猫统计!AT:AT,">="&EOMONTH(A54,-1)+1,猫统计!AT:AT,"<="&EOMONTH(A54,0))+SUMIFS(猫统计!BC:BC,猫统计!AZ:AZ,">="&EOMONTH(A54,-1)+1,猫统计!AZ:AZ,"<="&EOMONTH(A54,0))+SUMIFS(猫统计!BI:BI,猫统计!BF:BF,">="&EOMONTH(A54,-1)+1,猫统计!BF:BF,"<="&EOMONTH(A54,0))+SUMIFS(猫统计!BO:BO,猫统计!BL:BL,">="&EOMONTH(A54,-1)+1,猫统计!BL:BL,"<="&EOMONTH(A54,0)) -> 0
A55: 45627 | B55: =COUNTIFS(猫统计!J:J,">="&EOMONTH(A55,-1)+1,猫统计!J:J,"<="&EOMONTH(A55,0))+COUNTIFS(猫统计!P:P,">="&EOMONTH(A55,-1)+1,猫统计!P:P,"<="&EOMONTH(A55,0))+COUNTIFS(猫统计!V:V,">="&EOMONTH(A55,-1)+1,猫统计!V:V,"<="&EOMONTH(A55,0))+COUNTIFS(猫统计!AB:AB,">="&EOMONTH(A55,-1)+1,猫统计!AB:AB,"<="&EOMONTH(A55,0))+COUNTIFS(猫统计!AH:AH,">="&EOMONTH(A55,-1)+1,猫统计!AH:AH,"<="&EOMONTH(A55,0))+COUNTIFS(猫统计!AN:AN,">="&EOMONTH(A55,-1)+1,猫统计!AN:AN,"<="&EOMONTH(A55,0))+COUNTIFS(猫统计!AT:AT,">="&EOMONTH(A55,-1)+1,猫统计!AT:AT,"<="&EOMONTH(A55,0))+COUNTIFS(猫统计!AZ:AZ,">="&EOMONTH(A55,-1)+1,猫统计!AZ:AZ,"<="&EOMONTH(A55,0))+COUNTIFS(猫统计!BF:BF,">="&EOMONTH(A55,-1)+1,猫统计!BF:BF,"<="&EOMONTH(A55,0))+COUNTIFS(猫统计!BL:BL,">="&EOMONTH(A55,-1)+1,猫统计!BL:BL,"<="&EOMONTH(A55,0)) -> 0 | C55: =D55+E55 -> 0 | D55: =SUMIFS(猫统计!L:L,猫统计!J:J,">="&EOMONTH(A55,-1)+1,猫统计!J:J,"<="&EOMONTH(A55,0))+SUMIFS(猫统计!R:R,猫统计!P:P,">="&EOMONTH(A55,-1)+1,猫统计!P:P,"<="&EOMONTH(A55,0))+SUMIFS(猫统计!X:X,猫统计!V:V,">="&EOMONTH(A55,-1)+1,猫统计!V:V,"<="&EOMONTH(A55,0))+SUMIFS(猫统计!AD:AD,猫统计!AB:AB,">="&EOMONTH(A55,-1)+1,猫统计!AB:AB,"<="&EOMONTH(A55,0))+SUMIFS(猫统计!AJ:AJ,猫统计!AH:AH,">="&EOMONTH(A55,-1)+1,猫统计!AH:AH,"<="&EOMONTH(A55,0))+SUMIFS(猫统计!AP:AP,猫统计!AN:AN,">="&EOMONTH(A55,-1)+1,猫统计!AN:AN,"<="&EOMONTH(A55,0))+SUMIFS(猫统计!AV:AV,猫统计!AT:AT,">="&EOMONTH(A55,-1)+1,猫统计!AT:AT,"<="&EOMONTH(A55,0))+SUMIFS(猫统计!BB:BB,猫统计!AZ:AZ,">="&EOMONTH(A55,-1)+1,猫统计!AZ:AZ,"<="&EOMONTH(A55,0))+SUMIFS(猫统计!BH:BH,猫统计!BF:BF,">="&EOMONTH(A55,-1)+1,猫统计!BF:BF,"<="&EOMONTH(A55,0))+SUMIFS(猫统计!BN:BN,猫统计!BL:BL,">="&EOMONTH(A55,-1)+1,猫统计!BL:BL,"<="&EOMONTH(A55,0)) -> 0 | E55: =SUMIFS(猫统计!M:M,猫统计!J:J,">="&EOMONTH(A55,-1)+1,猫统计!J:J,"<="&EOMONTH(A55,0))+SUMIFS(猫统计!S:S,猫统计!P:P,">="&EOMONTH(A55,-1)+1,猫统计!P:P,"<="&EOMONTH(A55,0))+SUMIFS(猫统计!Y:Y,猫统计!V:V,">="&EOMONTH(A55,-1)+1,猫统计!V:V,"<="&EOMONTH(A55,0))+SUMIFS(猫统计!AE:AE,猫统计!AB:AB,">="&EOMONTH(A55,-1)+1,猫统计!AB:AB,"<="&EOMONTH(A55,0))+SUMIFS(猫统计!AK:AK,猫统计!AH:AH,">="&EOMONTH(A55,-1)+1,猫统计!AH:AH,"<="&EOMONTH(A55,0))+SUMIFS(猫统计!AQ:AQ,猫统计!AN:AN,">="&EOMONTH(A55,-1)+1,猫统计!AN:AN,"<="&EOMONTH(A55,0))+SUMIFS(猫统计!AW:AW,猫统计!AT:AT,">="&EOMONTH(A55,-1)+1,猫统计!AT:AT,"<="&EOMONTH(A55,0))+SUMIFS(猫统计!BC:BC,猫统计!AZ:AZ,">="&EOMONTH(A55,-1)+1,猫统计!AZ:AZ,"<="&EOMONTH(A55,0))+SUMIFS(猫统计!BI:BI,猫统计!BF:BF,">="&EOMONTH(A55,-1)+1,猫统计!BF:BF,"<="&EOMONTH(A55,0))+SUMIFS(猫统计!BO:BO,猫统计!BL:BL,">="&EOMONTH(A55,-1)+1,猫统计!BL:BL,"<="&EOMONTH(A55,0)) -> 0 | F55: =(E53+E54+E55)/(C53+C54+C55) -> 0.75 | G55: =(E53+E54+E55)/(B53+B54+B55) -> 3

Sheet 账单
A1: 日期 | B1: 猫粮 | C1: 猫砂 | D1: 零食 | E1: 消耗品 | F1: 疫苗 | G1: 常用药 | H1: 治疗费 | I1: 不常用药 | J1: 运费 | K1: 买猫 | L1: 其它 | M1: 每月总计 | N1: 卖猫 | O1: 每月盈亏 | P1: 总盈亏 | S1: 猫粮 | T1: 猫砂 | U1: 零食 | V1: 消耗品 | W1: 疫苗 | X1: 常用药 | Y1: 治疗费 | Z1: 不常用药 | AA1: 运费 | AB1: 买猫 | AC1: 其它 | AD1: 总计 | AE1: 卖猫 | AF1: 利润 | AG1: 猫数量 | AH1: 单位猫成本
A2: 43556 | B2: 366 | C2: 226 | D2: 171 | E2: 0 | F2: 0 | G2: 525 | H2: 0 | I2: 0 | J2: 0 | K2: 0 | L2: 3094 | M2: =SUM(B2:L2)*-1 -> -4382 | N2: 0 | O2: =(N2+M2) -> -4382 | P2: -4382 | R2: 2019第1季度 | S2: 0 | T2: 0 | U2: 0 | V2: 0 | W2: 0 | X2: 0 | Y2: 0 | Z2: 0 | AA2: 0 | AB2: 0 | AC2: 0 | AD2: 0 | AE2: 0 | AF2: =AE2+AD2 -> 0 | BJ2: .
A3: 43586 | B3: 57 | C3: 0 | D3: 262 | E3: 0 | F3: 0 | G3: 264 | H3: 0 | I3: 0 | J3: 0 | K3: 0 | L3: 2306 | M3: =SUM(B3:L3)*-1 -> -2889 | N3: 0 | O3: =(N3+M3) -> -2889 | P3: =P2+O3 -> -7271 | R3: 2019第2季度 | S3: =SUM(B2:B4) -> 423 | T3: =SUM(C2:C4) -> 226 | U3: =SUM(D2:D4) -> 648 | V3: =SUM(E2:E4) -> 0 | W3: =SUM(F2:F4) -> 0 | X3: =SUM(G2:G4) -> 1014 | Y3: =SUM(H2:H4) -> 0 | Z3: =SUM(I2:I4) -> 0 | ... AE3: =SUM(N2:N4) -> 0 | AF3: =AE3+AD3 -> -17848
A4: 43617 | B4: 0 | C4: 0 | D4: 215 | E4: 0 | F4: 0 | G4: 225 | H4: 0 | I4: 0 | J4: 0 | K4: 0 | L4: 10137 | M4: =SUM(B4:L4)*-1 -> -10577 | N4: 0 | O4: =(N4+M4) -> -10577 | P4: =P3+O4 -> -17848 | R4: 2019第3季度 | S4: =SUM(B5:B7) -> 2172 | T4: =SUM(C5:C7) -> 710 | U4: =SUM(D5:D7) -> 285 | V4: =SUM(E5:E7) -> 0 | W4: =SUM(F5:F7) -> 0 | X4: =SUM(G5:G7) -> 4908 | Y4: =SUM(H5:H7) -> 0 | Z4: =SUM(I5:I7) -> 0 | ... AE4: =SUM(N5:N7) -> 6600 | AF4: =AE4+AD4 -> -24455
A5: 43647 | B5: 1323 | C5: 328 | D5: 137 | E5: 0 | F5: 0 | G5: 1177 | H5: 0 | I5: 0 | J5: 0 | K5: 0 | L5: 3302 | M5: =SUM(B5:L5)*-1 -> -6267 | N5: 0 | O5: =(N5+M5) -> -6267 | P5: =P4+O5 -> -24115 | R5: 2019第4季度 | S5: =SUM(B8:B10) -> 4971 | T5: =SUM(C8:C10) -> 708 | U5: =SUM(D8:D10) -> 295 | V5: =SUM(E8:E10) -> 0 | W5: =SUM(F8:F10) -> 0 | X5: =SUM(G8:G10) -> 6046 | Y5: =SUM(H8:H10) -> 0 | Z5: =SUM(I8:I10) -> 0 | ... AE5: =SUM(N8:N10) -> 9000 | AF5: =AE5+AD5 -> -33828
A6: 43678 | B6: 690 | C6: 332 | D6: 148 | E6: 0 | F6: 0 | G6: 892 | H6: 0 | I6: 0 | J6: 0 | K6: 0 | L6: 4016 | M6: =SUM(B6:L6)*-1 -> -6078 | N6: 0 | O6: =(N6+M6) -> -6078 | P6: =P5+O6 -> -30193 | R6: 2020第1季度 | S6: =SUM(B11:B13) -> 3325 | T6: =SUM(C11:C13) -> 894 | U6: =SUM(D11:D13) -> 2150 | V6: =SUM(E11:E13) -> 0 | W6: =SUM(F11:F13) -> 0 | X6: =SUM(G11:G13) -> 5082 | Y6: =SUM(H11:H13) -> 0 | Z6: =SUM(I11:I13) -> 0 | ... AE6: =SUM(N11:N13) -> 37400 | AF6: =AE6+AD6 -> -22788
A7: 43709 | B7: 159 | C7: 50 | D7: 0 | E7: 0 | F7: 0 | G7: 2839 | H7: 0 | I7: 0 | J7: 0 | K7: 0 | L7: 15662 | M7: =SUM(B7:L7)*-1 -> -18710 | N7: =卖猫!M2 -> 6600 | O7: =(N7+M7) -> -12110 | P7: =P6+O7 -> -42303 | R7: 2020第2季度 | S7: =SUM(B14:B16) -> 4287 | T7: =SUM(C14:C16) -> 2784 | U7: =SUM(D14:D16) -> 1788 | V7: =SUM(E14:E16) -> 514 | W7: =SUM(F14:F16) -> 0 | X7: =SUM(G14:G16) -> 8628 | Y7: =SUM(H14:H16) -> 0 | Z7: =SUM(I14:I16) -> 0 | ... AE7: =SUM(N14:N16) -> 46800 | AF7: =AE7+AD7 -> -23197
A8: 43739 | B8: 1496 | C8: 189 | D8: 0 | E8: 0 | F8: 0 | G8: 1303 | H8: 0 | I8: 0 | J8: 0 | K8: 0 | L8: 6783 | M8: =SUM(B8:L8)*-1 -> -9771 | N8: =卖猫!M3 -> 500 | O8: =(N8+M8) -> -9271 | P8: =P7+O8 -> -51574 | R8: 2020第3季度 | S8: =SUM(B17:B19) -> 1526 | T8: =SUM(C17:C19) -> 1352 | U8: =SUM(D17:D19) -> 1641 | V8: =SUM(E17:E19) -> 1252 | W8: =SUM(F17:F19) -> 100 | X8: =SUM(G17:G19) -> 712 | Y8: =SUM(H17:H19) -> 3500 | Z8: =SUM(I17:I19) -> 1697 | ... AE8: =SUM(N17:N19) -> 21000 | AF8: =AE8+AD8 -> -25332
A9: 43770 | B9: 802 | C9: 390 | D9: 28 | E9: 0 | F9: 0 | G9: 1018 | H9: 0 | I9: 0 | J9: 0 | K9: 0 | L9: 7686 | M9: =SUM(B9:L9)*-1 -> -9924 | N9: =卖猫!M4 -> 4900 | O9: =(N9+M9) -> -5024 | P9: =P8+O9 -> -56598 | R9: 2020第4季度 | S9: =SUM(B20:B22) -> 6107 | T9: =SUM(C20:C22) -> 2214 | U9: =SUM(D20:D22) -> 313 | V9: =SUM(E20:E22) -> 1517 | W9: =SUM(F20:F22) -> 3085 | X9: =SUM(G20:G22) -> 1854 | Y9: =SUM(H20:H22) -> 0 | Z9: =SUM(I20:I22) -> 591 | ... AE9: =SUM(N20:N22) -> 10500 | AF9: =AE9+AD9 -> -16436
A10: 43800 | B10: 2673 | C10: 129 | D10: 267 | E10: 0 | F10: 0 | G10: 3725 | H10: 0 | I10: 0 | J10: 0 | K10: 10400 | L10: 5939 | M10: =SUM(B10:L10)*-1 -> -23133 | N10: =卖猫!M5 -> 3600 | O10: =(N10+M10) -> -19533 | P10: =P9+O10 -> -76131 | R10: 2021第1季度 | S10: =SUM(B23:B25) -> 4546 | T10: =SUM(C23:C25) -> 1530 | U10: =SUM(D23:D25) -> 726 | V10: =SUM(E23:E25) -> 2001 | W10: =SUM(F23:F25) -> 2019 | X10: =SUM(G23:G25) -> 2655 | Y10: =SUM(H23:H25) -> 1400 | Z10: =SUM(I23:I25) -> 540 | ... AE10: =SUM(N23:N25) -> 24400 | AF10: =AE10+AD10 -> -100
A11: 43831 | B11: 1070 | C11: 32 | D11: 708 | E11: 0 | F11: 0 | G11: 2752 | H11: 0 | I11: 0 | J11: 0 | K11: 3900 | L11: 1319 | M11: =SUM(B11:L11)*-1 -> -9781 | N11: =卖猫!M6 -> 2500 | O11: =(N11+M11) -> -7281 | P11: =P10+O11 -> -83412 | R11: 2021第2季度 | S11: =SUM(B26:B28) -> 12003 | T11: =SUM(C26:C28) -> 2163 | U11: =SUM(D26:D28) -> 679 | V11: =SUM(E26:E28) -> 2306 | W11: =SUM(F26:F28) -> 2040 | X11: =SUM(G26:G28) -> 1759 | Y11: =SUM(H26:H28) -> 1110 | Z11: =SUM(I26:I28) -> 835 | ... AE11: =SUM(N26:N28) -> 41195 | AF11: =AE11+AD11 -> -23179
A12: 43862 | B12: 0 | C12: 693 | D12: 893 | E12: 0 | F12: 0 | G12: 1120 | H12: 0 | I12: 0 | J12: 0 | K12: 4000 | L12: 1985 | M12: =SUM(B12:L12)*-1 -> -8691 | N12: =卖猫!M7 -> 8800 | O12: =(N12+M12) -> 109 | P12: =P11+O12 -> -83303 | R12: 2021第3季度 | S12: =SUM(B29:B31) -> 6271 | T12: =SUM(C29:C31) -> 2901 | U12: =SUM(D29:D31) -> 804 | V12: =SUM(E29:E31) -> 1251 | W12: =SUM(F29:F31) -> 1163 | X12: =SUM(G29:G31) -> 2688 | Y12: =SUM(H29:H31) -> 490 | Z12: =SUM(I29:I31) -> 5535 | ... AE12: =SUM(N29:N31) -> 33845 | AF12: =AE12+AD12 -> 11495
A13: 43891 | B13: 2255 | C13: 169 | D13: 549 | E13: 0 | F13: 0 | G13: 1210 | H13: 0 | I13: 0 | J13: 0 | K13: 31000 | L13: 6533 | M13: =SUM(B13:L13)*-1 -> -41716 | N13: =卖猫!M8 -> 26100 | O13: =(N13+M13) -> -15616 | P13: =P12+O13 -> -98919 | R13: 2021第4季度 | S13: =SUM(B32:B34) -> 10268 | T13: =SUM(C32:C34) -> 4174 | U13: =SUM(D32:D34) -> 1536 | V13: =SUM(E32:E34) -> 1897 | W13: =SUM(F32:F34) -> 3781 | X13: =SUM(G32:G34) -> 1388 | Y13: =SUM(H32:H34) -> 1724 | Z13: =SUM(I32:I34) -> 2820 | ... AE13: =SUM(N32:N34) -> 45195 | AF13: =AE13+AD13 -> 12741 | AG13: =(数量统计!K2+数量统计!K3+数量统计!K4)/3 -> 100.33333 | AH13: =((AD13+AB13)/AG13*-1)/3 -> 105.16279
A14: 43922 | B14: 0 | C14: 536 | D14: 285 | E14: 0 | F14: 0 | G14: 6446 | H14: 0 | I14: 0 | J14: 0 | K14: 26932 | L14: 2028 | M14: =SUM(B14:L14)*-1 -> -36227 | N14: =卖猫!M9 -> 18800 | O14: =(N14+M14) -> -17427 | P14: =P13+O14 -> -116346 | R14: 2022第1季度 | S14: =SUM(B35:B37) -> 6551 | T14: =SUM(C35:C37) -> 1420 | U14: =SUM(D35:D37) -> 751 | V14: =SUM(E35:E37) -> 1605 | W14: =SUM(F35:F37) -> 4129 | X14: =SUM(G35:G37) -> 2088 | Y14: =SUM(H35:H37) -> 450 | Z14: =SUM(I35:I37) -> 1438 | ... AE14: =SUM(N35:N37) -> 21045 | AF14: =AE14+AD14 -> -6067 | AG14: =(数量统计!K5+数量统计!K6+数量统计!K7)/3 -> 72.666667 | AH14: =((AD14+AB14)/AG14*-1)/3 -> 124.36697
A15: 43952 | B15: 0 | C15: 898 | D15: 588 | E15: 403 | F15: 0 | G15: 931 | H15: 0 | I15: 0 | J15: 0 | K15: 7000 | L15: 1270 | M15: =SUM(B15:L15)*-1 -> -11090 | N15: =卖猫!M10 -> 9300 | O15: =(N15+M15) -> -1790 | P15: =P14+O15 -> -118136 | R15: 2022第2季度 | S15: =SUM(B38:B40) -> 4551 | T15: =SUM(C38:C40) -> 4267 | U15: =SUM(D38:D40) -> 1283 | V15: =SUM(E38:E40) -> 1390 | W15: =SUM(F38:F40) -> 1496 | X15: =SUM(G38:G40) -> 867 | Y15: =SUM(H38:H40) -> 416 | Z15: =SUM(I38:I40) -> 472 | ... AE15: =SUM(N38:N40) -> 32009 | AF15: =AE15+AD15 -> 13700 | AG15: =(数量统计!K8+数量统计!K9+数量统计!K10)/3 -> 68.666667 | AH15: =((AD15+AB15)/AG15*-1)/3 -> 76.742718
A16: 43983 | B16: 4287 | C16: 1350 | D16: 915 | E16: 111 | F16: 0 | G16: 1251 | H16: 0 | I16: 0 | J16: 0 | K16: 8980 | L16: 5786 | M16: =SUM(B16:L16)*-1 -> -22680 | N16: =卖猫!M11 -> 18700 | O16: =(N16+M16) -> -3980 | P16: =P15+O16 -> -122116 | R16: 2022第3季度 | S16: =SUM(B41:B43) -> 7201 | T16: =SUM(C41:C43) -> 3291 | U16: =SUM(D41:D43) -> 2193 | V16: =SUM(E41:E43) -> 669 | W16: =SUM(F41:F43) -> 2652 | X16: =SUM(G41:G43) -> 1474 | Y16: =SUM(H41:H43) -> 0 | Z16: =SUM(I41:I43) -> 2732 | ... AE16: =SUM(N41:N43) -> 17699 | AF16: =AE16+AD16 -> -9288 | AG16: =(数量统计!K11+数量统计!K12+数量统计!K13)/3 -> 66.666667 | AH16: =((AD16+AB16)/AG16*-1)/3 -> 134.935
A17: 44013 | B17: ='2020-07'!F2 -> 927 | C17: ='2020-07'!F3 -> 224 | D17: ='2020-07'!F4 -> 563 | E17: ='2020-07'!F5 -> 151 | F17: ='2020-07'!F6 -> 0 | G17: ='2020-07'!F7 -> 207 | H17: ='2020-07'!F8 -> 0 | I17: ='2020-07'!F9 -> 0 | J17: ='2020-07'!F10 -> 300 | K17: ='2020-07'!F11 -> 12600 | L17: ='2020-07'!F12 -> 2626 | M17: =SUM(B17:L17)*-1 -> -17598 | N17: =卖猫!M12 -> 5700 | O17: =(N17+M17) -> -11898 | P17: =P16+O17 -> -134014 | R17: 2022第4季度 | S17: =SUM(B44:B46) -> 4938 | T17: =SUM(C44:C46) -> 2139 | U17: =SUM(D44:D46) -> 512 | V17: =SUM(E44:E46) -> 1031 | W17: =SUM(F44:F46) -> 0 | X17: =SUM(G44:G46) -> 735 | Y17: =SUM(H44:H46) -> 0 | Z17: =SUM(I44:I46) -> 500 | ... AE17: =SUM(N44:N46) -> 17648 | AF17: =AE17+AD17 -> -5747 | AG17: =(数量统计!K14+数量统计!K15+数量统计!K16)/3 -> 41.333333 | AH17: =((AD17+AB17)/AG17*-1)/3 -> 144.98387
A18: 44044 | B18: ='2020-08'!F2 -> 461 | C18: ='2020-08'!F3 -> 18 | D18: ='2020-08'!F4 -> 0 | E18: ='2020-08'!F5 -> 849 | F18: ='2020-08'!F6 -> 0 | G18: ='2020-08'!F7 -> 260 | H18: ='2020-08'!F8 -> 3500 | I18: ='2020-08'!F9 -> 1697 | J18: ='2020-08'!F10 -> 0 | K18: ='2020-08'!F11 -> 3700 | L18: ='2020-08'!F12 -> 2787 | M18: =SUM(B18:L18)*-1 -> -13272 | N18: =卖猫!M13 -> 6100 | O18: =(N18+M18) -> -7172 | P18: =P17+O18 -> -141186 | R18: 2023第1季度 | S18: =SUM(B47:B49) -> 3332 | T18: =SUM(C47:C49) -> 1592 | U18: =SUM(D47:D49) -> 0 | V18: =SUM(E47:E49) -> 1539 | W18: =SUM(F47:F49) -> 501 | X18: =SUM(G47:G49) -> 1206 | Y18: =SUM(H47:H49) -> 2290 | Z18: =SUM(I47:I49) -> 1360 | ... AE18: =SUM(N47:N49) -> 19400 | AF18: =AE18+AD18 -> -560 | AG18: =(数量统计!K17+数量统计!K18+数量统计!K19)/3 -> 45.666667 | AH18: =((AD18+AB18)/AG18*-1)/3 -> 128.17518
A19: 44075 | B19: ='2020-09'!F2 -> 138 | C19: ='2020-09'!F3 -> 1110 | D19: ='2020-09'!F4 -> 1078 | E19: ='2020-09'!F5 -> 252 | F19: ='2020-09'!F6 -> 100 | G19: ='2020-09'!F7 -> 245 | H19: ='2020-09'!F8 -> 0 | I19: ='2020-09'!F9 -> 0 | J19: ='2020-09'!F10 -> 360 | K19: ='2020-09'!F11 -> 6800 | L19: ='2020-09'!F12 -> 5379 | M19: =SUM(B19:L19)*-1 -> -15462 | N19: =卖猫!M14 -> 9200 | O19: =(N19+M19) -> -6262 | P19: =P18+O19 -> -147448 | R19: 2023第2季度 | S19: =SUM(B50:B52) -> 3707 | T19: =SUM(C50:C52) -> 2610 | U19: =SUM(D50:D52) -> 1390 | V19: =SUM(E50:E52) -> 666 | W19: =SUM(F50:F52) -> 1022 | X19: =SUM(G50:G52) -> 2017 | Y19: =SUM(H50:H52) -> 230 | Z19: =SUM(I50:I52) -> 306 | ... AE19: =SUM(N50:N52) -> 23800 | AF19: =AE19+AD19 -> 5632.7 | AG19: =(数量统计!K20+数量统计!K21+数量统计!K22)/3 -> 60.666667 | AH19: =((AD19+AB19)/AG19*-1)/3 -> 86.084066
A20: 44105 | B20: ='2020-10'!F2 -> 1467 | C20: ='2020-10'!F3 -> 1280 | D20: ='2020-10'!F4 -> 75 | E20: ='2020-10'!F5 -> 285 | F20: ='2020-10'!F6 -> 0 | G20: ='2020-10'!F7 -> 532 | H20: ='2020-10'!F8 -> 0 | I20: ='2020-10'!F9 -> 0 | J20: ='2020-10'!F10 -> 300 | K20: ='2020-10'!F11 -> 3600 | L20: ='2020-10'!F12 -> 446 | M20: =SUM(B20:L20)*-1 -> -7985 | N20: =卖猫!M15 -> 3800 | O20: =(N20+M20) -> -4185 | P20: =P19+O20 -> -151633 | R20: 2023第3季度 | S20: =SUM(B53:B55) -> 2625 | T20: =SUM(C53:C55) -> 2835 | U20: =SUM(D53:D55) -> 1200 | V20: =SUM(E53:E55) -> 692 | W20: =SUM(F53:F55) -> 1056 | X20: =SUM(G53:G55) -> 732 | Y20: =SUM(H53:H55) -> 0 | Z20: =SUM(I53:I55) -> 0 | ... AE20: =SUM(N53:N55) -> 12000 | AF20: =AE20+AD20 -> -4055 | AG20: =(数量统计!K23+数量统计!K24+数量统计!K25)/3 -> 64.333333 | AH20: =((AD20+AB20)/AG20*-1)/3 -> 83.186528
A21: 44136 | B21: ='2020-11'!F2 -> 930 | C21: ='2020-11'!F3 -> 54 | D21: ='2020-11'!F4 -> 238 | E21: ='2020-11'!F5 -> 241 | F21: ='2020-11'!F6 -> 718 | G21: ='2020-11'!F7 -> 577 | H21: ='2020-11'!F8 -> 0 | I21: ='2020-11'!F9 -> 0 | J21: ='2020-11'!F10 -> 0 | K21: ='2020-11'!F11 -> 200 | L21: ='2020-11'!F12 -> 114 | M21: =SUM(B21:L21)*-1 -> -3072 | N21: =卖猫!M16 -> 0 | O21: =(N21+M21) -> -3072 | P21: =P20+O21 -> -154705 | R21: 2023第4季度 | S21: =SUM(B56:B58) -> 5332 | T21: =SUM(C56:C58) -> 1935 | U21: =SUM(D56:D58) -> 1183 | V21: =SUM(E56:E58) -> 1012 | W21: =SUM(F56:F58) -> 3500 | X21: =SUM(G56:G58) -> 537 | Y21: =SUM(H56:H58) -> 0 | Z21: =SUM(I56:I58) -> 360 | ... AE21: =SUM(N56:N58) -> 4500 | AF21: =AE21+AD21 -> -18899 | AG21: =(数量统计!K26+数量统计!K27+数量统计!K28)/3 -> 52.666667 | AH21: =((AD21+AB21)/AG21*-1)/3 -> 135.43671
A22: 44166 | B22: ='2020-12'!F2 -> 3710 | C22: ='2020-12'!F3 -> 880 | D22: ='2020-12'!F4 -> 0 | E22: ='2020-12'!F5 -> 991 | F22: ='2020-12'!F6 -> 2367 | G22: ='2020-12'!F7 -> 745 | H22: ='2020-12'!F8 -> 0 | I22: ='2020-12'!F9 -> 591 | J22: ='2020-12'!F10 -> 100 | K22: ='2020-12'!F11 -> 300 | L22: ='2020-12'!F12 -> 6195 | M22: =SUM(B22:L22)*-1 -> -15879 | N22: =卖猫!M17 -> 6700 | O22: =(N22+M22) -> -9179 | P22: =P21+O22 -> -163884 | R22: 2024第1季度 | S22: =SUM(B59:B61) -> 3426 | T22: =SUM(C59:C61) -> 2520 | U22: =SUM(D59:D61) -> 556 | V22: =SUM(E59:E61) -> 809 | W22: =SUM(F59:F61) -> 0 | X22: =SUM(G59:G61) -> 954 | Y22: =SUM(H59:H61) -> 900 | Z22: =SUM(I59:I61) -> 0 | ... AE22: =SUM(N59:N61) -> 14400 | AF22: =AE22+AD22 -> -1303 | AG22: =(数量统计!K29+数量统计!K30+数量统计!K31)/3 -> 48.666667 | AH22: =((AD22+AB22)/AG22*-1)/3 -> 107.55479
A23: 44197 | B23: ='2021-01'!F2 -> 2256 | C23: ='2021-01'!F3 -> 0 | D23: ='2021-01'!F4 -> 164 | E23: ='2021-01'!F5 -> 478 | F23: ='2021-01'!F6 -> 1243 | G23: ='2021-01'!F7 -> 1585 | H23: ='2021-01'!F8 -> 1400 | I23: ='2021-01'!F9 -> 10 | J23: ='2021-01'!F10 -> 0 | K23: ='2021-01'!F11 -> 0 | L23: ='2021-01'!F12 -> 1245 | M23: =SUM(B23:L23)*-1 -> -8381 | N23: =卖猫!M18 -> 16100 | O23: =(N23+M23) -> 7719 | P23: =P22+O23 -> -156165 | R23: 2024第2季度 | S23: =SUM(B62:B64) -> 82 | T23: =SUM(C62:C64) -> 1020 | U23: =SUM(D62:D64) -> 966 | V23: =SUM(E62:E64) -> 574 | W23: =SUM(F62:F64) -> 1458 | X23: =SUM(G62:G64) -> 752 | Y23: =SUM(H62:H64) -> 2960 | Z23: =SUM(I62:I64) -> 36 | ... AE23: =SUM(N62:N64) -> 19100 | AF23: =AE23+AD23 -> 10870 | AG23: =(数量统计!K32+数量统计!K33+数量统计!K34)/3 -> 40.333333 | AH23: =((AD23+AB23)/AG23*-1)/3 -> 68.016529
A24: 44228 | B24: ='2021-02'!F2 -> 180 | C24: ='2021-02'!F3 -> 880 | D24: ='2021-02'!F4 -> 180 | E24: ='2021-02'!F5 -> 639 | F24: ='2021-02'!F6 -> 0 | G24: ='2021-02'!F7 -> 865 | H24: ='2021-02'!F8 -> 0 | I24: ='2021-02'!F9 -> 298 | J24: ='2021-02'!F10 -> 93 | K24: ='2021-02'!F11 -> 1000 | L24: ='2021-02'!F12 -> 1768 | M24: =SUM(B24:L24)*-1 -> -5903 | N24: =卖猫!M19 -> 4800 | O24: =(N24+M24) -> -1103 | P24: =P23+O24 -> -157268 | R24: 2024第3季度 | S24: =SUM(B65:B67) -> 4544 | T24: =SUM(C65:C67) -> 1200 | U24: =SUM(D65:D67) -> 0 | V24: =SUM(E65:E67) -> 782 | W24: =SUM(F65:F67) -> 0 | X24: =SUM(G65:G67) -> 721 | Y24: =SUM(H65:H67) -> 0 | Z24: =SUM(I65:I67) -> 703 | ... AE24: =SUM(N65:N67) -> 10666 | AF24: =AE24+AD24 -> 2328.5 | AG24: =(数量统计!K35+数量统计!K36+数量统计!K37)/3 -> 33.333333 | AH24: =((AD24+AB24)/AG24*-1)/3 -> 83.375
A25: 44256 | B25: ='2021-03'!F2 -> 2110 | C25: ='2021-03'!F3 -> 650 | D25: ='2021-03'!F4 -> 382 | E25: ='2021-03'!F5 -> 884 | F25: ='2021-03'!F6 -> 776 | G25: ='2021-03'!F7 -> 205 | H25: ='2021-03'!F8 -> 0 | I25: ='2021-03'!F9 -> 232 | J25: ='2021-03'!F10 -> 1788 | K25: ='2021-03'!F11 -> 0 | L25: ='2021-03'!F12 -> 3189 | M25: =SUM(B25:L25)*-1 -> -10216 | N25: =卖猫!M20 -> 3500 | O25: =(N25+M25) -> -6716 | P25: =P24+O25 -> -163984 | R25: 2024第4季度 | S25: =SUM(B68:B70) -> 0 | T25: =SUM(C68:C70) -> 0 | U25: =SUM(D68:D70) -> 0 | V25: =SUM(E68:E70) -> 0 | W25: =SUM(F68:F70) -> 0 | X25: =SUM(G68:G70) -> 0 | Y25: =SUM(H68:H70) -> 0 | Z25: =SUM(I68:I70) -> 0 | ... AE25: =SUM(N68:N70) -> 0 | AF25: =AE25+AD25 -> 0 | AG25: =(数量统计!K38+数量统计!K39+数量统计!K40)/3 -> 10.333333 | AH25: =((AD25+AB25)/AG25*-1)/3 -> 0
A26: 44287 | B26: ='2021-04'!F2 -> 2075 | C26: ='2021-04'!F3 -> 0 | D26: ='2021-04'!F4 -> 155 | E26: ='2021-04'!F5 -> 225 | F26: ='2021-04'!F6 -> 0 | G26: ='2021-04'!F7 -> 928 | H26: ='2021-04'!F8 -> 0 | I26: ='2021-04'!F9 -> 0 | J26: ='2021-04'!F10 -> 274 | K26: ='2021-04'!F11 -> 2800 | L26: ='2021-04'!F12 -> 35217 | M26: =SUM(B26:L26)*-1 -> -41674 | N26: =卖猫!M21 -> 2900 | O26: =(N26+M26) -> -38774 | P26: =P25+O26 -> -202758
A27: 44317 | B27: ='2021-05'!F2 -> 8049 | C27: ='2021-05'!F3 -> 1395 | D27: ='2021-05'!F4 -> 414 | E27: ='2021-05'!F5 -> 1001 | F27: ='2021-05'!F6 -> 0 | G27: ='2021-05'!F7 -> 225 | H27: ='2021-05'!F8 -> 0 | I27: ='2021-05'!F9 -> 235 | J27: ='2021-05'!F10 -> 160 | K27: ='2021-05'!F11 -> 0 | L27: ='2021-05'!F12 -> 2142 | M27: =SUM(B27:L27)*-1 -> -13621 | N27: =卖猫!M22 -> 10550 | O27: =(N27+M27) -> -3071 | P27: =P26+O27 -> -205829
A28: 44348 | B28: ='2021-06'!F2 -> 1879 | C28: ='2021-06'!F3 -> 768 | D28: ='2021-06'!F4 -> 110 | E28: ='2021-06'!F5 -> 1080 | F28: ='2021-06'!F6 -> 2040 | G28: ='2021-06'!F7 -> 606 | H28: ='2021-06'!F8 -> 1110 | I28: ='2021-06'!F9 -> 600 | J28: ='2021-06'!F10 -> 453 | K28: ='2021-06'!F11 -> 0 | L28: ='2021-06'!F12 -> 433 | M28: =SUM(B28:L28)*-1 -> -9079 | N28: =卖猫!M23 -> 27745 | O28: =(N28+M28) -> 18666 | P28: =P27+O28 -> -187163
A29: 44378 | B29: ='2021-07'!F2 -> 680 | C29: ='2021-07'!F3 -> 0 | D29: ='2021-07'!F4 -> 380 | E29: ='2021-07'!F5 -> 856 | F29: ='2021-07'!F6 -> 80 | G29: ='2021-07'!F7 -> 1060 | H29: ='2021-07'!F8 -> 0 | I29: ='2021-07'!F9 -> 2720 | J29: ='2021-07'!F10 -> 0 | K29: ='2021-07'!F11 -> 0 | L29: ='2021-07'!F12 -> 209 | M29: =SUM(B29:L29)*-1 -> -5985 | N29: =卖猫!M24 -> 9110 | O29: =(N29+M29) -> 3125 | P29: =P28+O29 -> -184038
A30: 44409 | B30: ='2021-08'!F2 -> 4260 | C30: ='2021-08'!F3 -> 840 | D30: ='2021-08'!F4 -> 54 | E30: ='2021-08'!F5 -> 348 | F30: ='2021-08'!F6 -> 1083 | G30: ='2021-08'!F7 -> 372 | H30: ='2021-08'!F8 -> 490 | I30: ='2021-08'!F9 -> 2602 | J30: ='2021-08'!F10 -> 222 | K30: ='2021-08'!F11 -> 0 | L30: ='2021-08'!F12 -> 471 | M30: =SUM(B30:L30)*-1 -> -10742 | N30: =卖猫!M25 -> 9135 | O30: =(N30+M30) -> -1607 | P30: =P29+O30 -> -185645
A31: 44440 | B31: ='2021-09'!F2 -> 1331 | C31: ='2021-09'!F3 -> 2061 | D31: ='2021-09'!F4 -> 370 | E31: ='2021-09'!F5 -> 47 | F31: ='2021-09'!F6 -> 0 | G31: ='2021-09'!F7 -> 1256 | H31: ='2021-09'!F8 -> 0 | I31: ='2021-09'!F9 -> 213 | J31: ='2021-09'!F10 -> 230 | K31: ='2021-09'!F11 -> 0 | L31: ='2021-09'!F12 -> 115 | M31: =SUM(B31:L31)*-1 -> -5623 | N31: =卖猫!M26 -> 15600 | O31: =(N31+M31) -> 9977 | P31: =P30+O31 -> -175668
A32: 44470 | B32: ='2021-10'!F2 -> 4190 | C32: ='2021-10'!F3 -> 447 | D32: ='2021-10'!F4 -> 300 | E32: ='2021-10'!F5 -> 943 | F32: ='2021-10'!F6 -> 495 | G32: ='2021-10'!F7 -> 634 | H32: ='2021-10'!F8 -> 560 | I32: ='2021-10'!F9 -> 1247 | J32: ='2021-10'!F10 -> 169 | K32: ='2021-10'!F11 -> 800 | L32: ='2021-10'!F12 -> 1649 | M32: =SUM(B32:L32)*-1 -> -11434 | N32: =卖猫!M27 -> 7260 | O32: =(N32+M32) -> -4174 | P32: =P31+O32 -> -179842
A33: 44501 | B33: ='2021-11'!F2 -> 4538 | C33: ='2021-11'!F3 -> 2241 | D33: ='2021-11'!F4 -> 573 | E33: ='2021-11'!F5 -> 689 | F33: ='2021-11'!F6 -> 0 | G33: ='2021-11'!F7 -> 166 | H33: ='2021-11'!F8 -> 0 | I33: ='2021-11'!F9 -> 1199 | J33: ='2021-11'!F10 -> 160 | K33: ='2021-11'!F11 -> 0 | L33: ='2021-11'!F12 -> 1049 | M33: =SUM(B33:L33)*-1 -> -10615 | N33: =卖猫!M28 -> 19930 | O33: =(N33+M33) -> 9315 | P33: =P32+O33 -> -170527
A34: 44531 | B34: ='2021-12'!F2 -> 1540 | C34: ='2021-12'!F3 -> 1486 | D34: ='2021-12'!F4 -> 663 | E34: ='2021-12'!F5 -> 265 | F34: ='2021-12'!F6 -> 3286 | G34: ='2021-12'!F7 -> 588 | H34: ='2021-12'!F8 -> 1164 | I34: ='2021-12'!F9 -> 374 | J34: ='2021-12'!F10 -> 312 | K34: ='2021-12'!F11 -> 0 | L34: ='2021-12'!F12 -> 727 | M34: =SUM(B34:L34)*-1 -> -10405 | N34: =卖猫!M29 -> 18005 | O34: =(N34+M34) -> 7600 | P34: =P33+O34 -> -162927
A35: 44562 | B35: ='2022-01'!F2 -> 3272 | C35: ='2022-01'!F3 -> 240 | D35: ='2022-01'!F4 -> 251 | E35: ='2022-01'!F5 -> 476 | F35: ='2022-01'!F6 -> 346 | G35: ='2022-01'!F7 -> 1630 | H35: ='2022-01'!F8 -> 450 | I35: ='2022-01'!F9 -> 192 | J35: ='2022-01'!F10 -> 609 | K35: ='2022-01'!F11 -> 0 | L35: ='2022-01'!F12 -> 1390 | M35: =SUM(B35:L35)*-1 -> -8856 | N35: =卖猫!M30 -> 7100 | O35: =(N35+M35) -> -1756 | P35: =P34+O35 -> -164683
A36: 44593 | B36: ='2022-02'!F2 -> 1241 | C36: ='2022-02'!F3 -> 0 | D36: ='2022-02'!F4 -> 255 | E36: ='2022-02'!F5 -> 701 | F36: ='2022-02'!F6 -> 0 | G36: ='2022-02'!F7 -> 122 | H36: ='2022-02'!F8 -> 0 | I36: ='2022-02'!F9 -> 70 | J36: ='2022-02'!F10 -> 28 | K36: ='2022-02'!F11 -> 0 | L36: ='2022-02'!F12 -> 5188 | M36: =SUM(B36:L36)*-1 -> -7605 | N36: =卖猫!M31 -> 7825 | O36: =(N36+M36) -> 220 | P36: =P35+O36 -> -164463
A37: 44621 | B37: ='2022-03'!F2 -> 2038 | C37: ='2022-03'!F3 -> 1180 | D37: ='2022-03'!F4 -> 245 | E37: ='2022-03'!F5 -> 428 | F37: ='2022-03'!F6 -> 3783 | G37: ='2022-03'!F7 -> 336 | H37: ='2022-03'!F8 -> 0 | I37: ='2022-03'!F9 -> 1176 | J37: ='2022-03'!F10 -> 208 | K37: ='2022-03'!F11 -> 0 | L37: ='2022-03'!F12 -> 1257 | M37: =SUM(B37:L37)*-1 -> -10651 | N37: =卖猫!M32 -> 6120 | O37: =(N37+M37) -> -4531 | P37: =P36+O37 -> -168994
A38: 44652 | B38: ='2022-04'!F2 -> 2175 | C38: ='2022-04'!F3 -> 860 | D38: ='2022-04'!F4 -> 251 | E38: ='2022-04'!F5 -> 660 | F38: ='2022-04'!F6 -> 0 | G38: ='2022-04'!F7 -> 522 | H38: ='2022-04'!F8 -> 416 | I38: ='2022-04'!F9 -> 0 | J38: ='2022-04'!F10 -> 128 | K38: ='2022-04'!F11 -> 0 | L38: ='2022-04'!F12 -> 156 | M38: =SUM(B38:L38)*-1 -> -5168 | N38: =卖猫!M33 -> 14190 | O38: =(N38+M38) -> 9022 | P38: =P37+O38 -> -159972
A39: 44682 | B39: ='2022-05'!F2 -> 2326 | C39: ='2022-05'!F3 -> 0 | D39: ='2022-05'!F4 -> 316 | E39: ='2022-05'!F5 -> 30 | F39: ='2022-05'!F6 -> 1496 | G39: ='2022-05'!F7 -> 250 | H39: ='2022-05'!F8 -> 0 | I39: ='2022-05'!F9 -> 322 | J39: ='2022-05'!F10 -> 383 | K39: ='2022-05'!F11 -> 2500 | L39: ='2022-05'!F12 -> 68 | M39: =SUM(B39:L39)*-1 -> -7691 | N39: =卖猫!M34 -> 9492 | O39: =(N39+M39) -> 1801 | P39: =P38+O39 -> -158171
A40: 44713 | B40: ='2022-06'!F2 -> 50 | C40: ='2022-06'!F3 -> 3407 | D40: ='2022-06'!F4 -> 716 | E40: ='2022-06'!F5 -> 700 | F40: ='2022-06'!F6 -> 0 | G40: ='2022-06'!F7 -> 95 | H40: ='2022-06'!F8 -> 0 | I40: ='2022-06'!F9 -> 150 | J40: ='2022-06'!F10 -> 32 | K40: ='2022-06'!F11 -> 0 | L40: ='2022-06'!F12 -> 300 | M40: =SUM(B40:L40)*-1 -> -5450 | N40: =卖猫!M35 -> 8327 | O40: =(N40+M40) -> 2877 | P40: =P39+O40 -> -155294
A41: 44743 | B41: ='2022-07'!F2 -> 1910 | C41: ='2022-07'!F3 -> 272 | D41: ='2022-07'!F4 -> 260 | E41: ='2022-07'!F5 -> 225 | F41: ='2022-07'!F6 -> 2500 | G41: ='2022-07'!F7 -> 366 | H41: ='2022-07'!F8 -> 0 | I41: ='2022-07'!F9 -> 390 | J41: ='2022-07'!F10 -> 0 | K41: ='2022-07'!F11 -> 0 | L41: ='2022-07'!F12 -> 5138 | M41: =SUM(B41:L41)*-1 -> -11061 | N41: =卖猫!M36 -> 2960 | O41: =(N41+M41) -> -8101 | P41: =P40+O41 -> -163395
A42: 44774 | B42: ='2022-08'!F2 -> 2350 | C42: ='2022-08'!F3 -> 1083 | D42: ='2022-08'!F4 -> 1414 | E42: ='2022-08'!F5 -> 444 | F42: ='2022-08'!F6 -> 152 | G42: ='2022-08'!F7 -> 758 | H42: ='2022-08'!F8 -> 0 | I42: ='2022-08'!F9 -> 1790 | J42: ='2022-08'!F10 -> 184 | K42: ='2022-08'!F11 -> 0 | L42: ='2022-08'!F12 -> 1169 | M42: =SUM(B42:L42)*-1 -> -9344 | N42: =卖猫!M37 -> 14739 | O42: =(N42+M42) -> 5395 | P42: =P41+O42 -> -158000
A43: 44805 | B43: ='2022-09'!F2 -> 2941 | C43: ='2022-09'!F3 -> 1936 | D43: ='2022-09'!F4 -> 519 | E43: ='2022-09'!F5 -> 0 | F43: ='2022-09'!F6 -> 0 | G43: ='2022-09'!F7 -> 350 | H43: ='2022-09'!F8 -> 0 | I43: ='2022-09'!F9 -> 552 | J43: ='2022-09'!F10 -> 0 | K43: ='2022-09'!F11 -> 0 | L43: ='2022-09'!F12 -> 284 | M43: =SUM(B43:L43)*-1 -> -6582 | N43: =卖猫!M38 -> 0 | O43: =(N43+M43) -> -6582 | P43: =P42+O43 -> -164582
A44: 44835 | B44: ='2022-10'!F2 -> 3098 | C44: ='2022-10'!F3 -> 950 | D44: ='2022-10'!F4 -> 36 | E44: ='2022-10'!F5 -> 365 | F44: ='2022-10'!F6 -> 0 | G44: ='2022-10'!F7 -> 374 | H44: ='2022-10'!F8 -> 0 | I44: ='2022-10'!F9 -> 0 | J44: ='2022-10'!F10 -> 0 | K44: ='2022-10'!F11 -> 0 | L44: ='2022-10'!F12 -> 7276 | M44: =SUM(B44:L44)*-1 -> -12099 | N44: =卖猫!M39 -> 1363 | O44: =(N44+M44) -> -10736 | P44: =P43+O44 -> -175318
A45: 44866 | B45: ='2022-11'!F2 -> 1340 | C45: ='2022-11'!F3 -> 909 | D45: ='2022-11'!F4 -> 209 | E45: ='2022-11'!F5 -> 640 | F45: ='2022-11'!F6 -> 0 | G45: ='2022-11'!F7 -> 285 | H45: ='2022-11'!F8 -> 0 | I45: ='2022-11'!F9 -> 500 | J45: ='2022-11'!F10 -> 28 | K45: ='2022-11'!F11 -> 817 | L45: ='2022-11'!F12 -> 347 | M45: =SUM(B45:L45)*-1 -> -5075 | N45: =卖猫!M40 -> 13100 | O45: =(N45+M45) -> 8025 | P45: =P44+O45 -> -167293
A46: 44896 | B46: ='2022-12'!F2 -> 500 | C46: ='2022-12'!F3 -> 280 | D46: ='2022-12'!F4 -> 267 | E46: ='2022-12'!F5 -> 26 | F46: ='2022-12'!F6 -> 0 | G46: ='2022-12'!F7 -> 76 | H46: ='2022-12'!F8 -> 0 | I46: ='2022-12'!F9 -> 0 | J46: ='2022-12'!F10 -> 0 | K46: ='2022-12'!F11 -> 4600 | L46: ='2022-12'!F12 -> 472 | M46: =SUM(B46:L46)*-1 -> -6221 | N46: =卖猫!M41 -> 3185 | O46: =(N46+M46) -> -3036 | P46: =P45+O46 -> -170329
A47: 44927 | B47: ='2023-01'!F2 -> 1000 | C47: ='2023-01'!F3 -> 512 | D47: ='2023-01'!F4 -> 0 | E47: ='2023-01'!F5 -> 214 | F47: ='2023-01'!F6 -> 0 | G47: ='2023-01'!F7 -> 410 | H47: ='2023-01'!F8 -> 1550 | I47: ='2023-01'!F9 -> 500 | J47: ='2023-01'!F10 -> 0 | K47: ='2023-01'!F11 -> 0 | L47: ='2023-01'!F12 -> 339 | M47: =SUM(B47:L47)*-1 -> -4525 | N47: =卖猫!M42 -> 500 | O47: =(N47+M47) -> -4025 | P47: =P46+O47 -> -174354
A48: 44958 | B48: ='2023-02'!F2 -> 235 | C48: ='2023-02'!F3 -> 0 | D48: ='2023-02'!F4 -> 0 | E48: ='2023-02'!F5 -> 788 | F48: ='2023-02'!F6 -> 0 | G48: ='2023-02'!F7 -> 130 | H48: ='2023-02'!F8 -> 740 | I48: ='2023-02'!F9 -> 650 | J48: ='2023-02'!F10 -> 0 | K48: ='2023-02'!F11 -> 0 | L48: ='2023-02'!F12 -> 5176 | M48: =SUM(B48:L48)*-1 -> -7719 | N48: =卖猫!M43 -> 2500 | O48: =(N48+M48) -> -5219 | P48: =P47+O48 -> -179573
A49: 44986 | B49: ='2023-03'!F2 -> 2097 | C49: ='2023-03'!F3 -> 1080 | D49: ='2023-03'!F4 -> 0 | E49: ='2023-03'!F5 -> 537 | F49: ='2023-03'!F6 -> 501 | G49: ='2023-03'!F7 -> 666 | H49: ='2023-03'!F8 -> 0 | I49: ='2023-03'!F9 -> 210 | J49: ='2023-03'!F10 -> 125 | K49: ='2023-03'!F11 -> 2400 | L49: ='2023-03'!F12 -> 100 | M49: =SUM(B49:L49)*-1 -> -7716 | N49: =卖猫!M44 -> 16400 | O49: =(N49+M49) -> 8684 | P49: =P48+O49 -> -170889
A50: 45017 | B50: ='2023-04'!F2 -> 1350 | C50: ='2023-04'!F3 -> 110 | D50: ='2023-04'!F4 -> 337 | E50: ='2023-04'!F5 -> 372 | F50: ='2023-04'!F6 -> 0 | G50: ='2023-04'!F7 -> 525 | H50: ='2023-04'!F8 -> 0 | I50: ='2023-04'!F9 -> 34 | J50: ='2023-04'!F10 -> 0 | K50: ='2023-04'!F11 -> 0 | L50: ='2023-04'!F12 -> 0 | M50: =SUM(B50:L50)*-1 -> -2728 | N50: =卖猫!M45 -> 2500 | O50: =(N50+M50) -> -228 | P50: =P49+O50 -> -171117
A51: 45047 | B51: ='2023-05'!F2 -> 1163 | C51: ='2023-05'!F3 -> 2030 | D51: ='2023-05'!F4 -> 515 | E51: ='2023-05'!F5 -> 100 | F51: ='2023-05'!F6 -> 66 | G51: ='2023-05'!F7 -> 1092 | H51: ='2023-05'!F8 -> 230 | I51: ='2023-05'!F9 -> 272 | J51: ='2023-05'!F10 -> 257 | K51: ='2023-05'!F11 -> 2500 | L51: ='2023-05'!F12 -> 279 | M51: =SUM(B51:L51)*-1 -> -8504 | N51: =卖猫!M46 -> 12400 | O51: =(N51+M51) -> 3896 | P51: =P50+O51 -> -167221
A52: 45078 | B52: ='2023-06'!F2 -> 1194 | C52: ='2023-06'!F3 -> 470 | D52: ='2023-06'!F4 -> 538 | E52: ='2023-06'!F5 -> 194 | F52: ='2023-06'!F6 -> 956 | G52: ='2023-06'!F7 -> 400 | H52: ='2023-06'!F8 -> 0 | I52: ='2023-06'!F9 -> 0 | J52: ='2023-06'!F10 -> 56 | K52: ='2023-06'!F11 -> 0 | L52: ='2023-06'!F12 -> 3127.3 | M52: =SUM(B52:L52)*-1 -> -6935.3 | N52: =卖猫!M47 -> 8900 | O52: =(N52+M52) -> 1964.7 | P52: =P51+O52 -> -165256.3
A53: 45108 | B53: ='2023-07'!F2 -> 800 | C53: ='2023-07'!F3 -> 35 | D53: ='2023-07'!F4 -> 614 | E53: ='2023-07'!F5 -> 86 | F53: ='2023-07'!F6 -> 956 | G53: ='2023-07'!F7 -> 196 | H53: ='2023-07'!F8 -> 0 | I53: ='2023-07'!F9 -> 0 | J53: ='2023-07'!F10 -> 0 | K53: ='2023-07'!F11 -> 0 | L53: ='2023-07'!F12 -> 2589 | M53: =SUM(B53:L53)*-1 -> -5276 | N53: =卖猫!M48 -> 4000 | O53: =(N53+M53) -> -1276 | P53: =P52+O53 -> -166532.3
A54: 45139 | B54: ='2023-08'!F2 -> 1825 | C54: ='2023-08'!F3 -> 1050 | D54: ='2023-08'!F4 -> 324 | E54: ='2023-08'!F5 -> 491 | F54: ='2023-08'!F6 -> 100 | G54: ='2023-08'!F7 -> 146 | H54: ='2023-08'!F8 -> 0 | I54: ='2023-08'!F9 -> 0 | J54: ='2023-08'!F10 -> 0 | K54: ='2023-08'!F11 -> 0 | L54: ='2023-08'!F12 -> 1935 | M54: =SUM(B54:L54)*-1 -> -5871 | N54: =卖猫!M49 -> 6000 | O54: =(N54+M54) -> 129 | P54: =P53+O54 -> -166403.3
A55: 45170 | B55: ='2023-09'!F2 -> 0 | C55: ='2023-09'!F3 -> 1750 | D55: ='2023-09'!F4 -> 262 | E55: ='2023-09'!F5 -> 115 | F55: ='2023-09'!F6 -> 0 | G55: ='2023-09'!F7 -> 390 | H55: ='2023-09'!F8 -> 0 | I55: ='2023-09'!F9 -> 0 | J55: ='2023-09'!F10 -> 66 | K55: ='2023-09'!F11 -> 0 | L55: ='2023-09'!F12 -> 2325 | M55: =SUM(B55:L55)*-1 -> -4908 | N55: =卖猫!M50 -> 2000 | O55: =(N55+M55) -> -2908 | P55: =P54+O55 -> -169311.3
A56: 45200 | B56: ='2023-10'!F2 -> 5314 | C56: ='2023-10'!F3 -> 0 | D56: ='2023-10'!F4 -> 249 | E56: ='2023-10'!F5 -> 363 | F56: ='2023-10'!F6 -> 3500 | G56: ='2023-10'!F7 -> 180 | H56: ='2023-10'!F8 -> 0 | I56: ='2023-10'!F9 -> 360 | J56: ='2023-10'!F10 -> 0 | K56: ='2023-10'!F11 -> 0 | L56: ='2023-10'!F12 -> 4320 | M56: =SUM(B56:L56)*-1 -> -14286 | N56: =卖猫!M51 -> 4500 | O56: =(N56+M56) -> -9786 | P56: =P55+O56 -> -179097.3
A57: 45231 | B57: ='2023-11'!F2 -> 18 | C57: ='2023-11'!F3 -> 0 | D57: ='2023-11'!F4 -> 475 | E57: ='2023-11'!F5 -> 215 | F57: ='2023-11'!F6 -> 0 | G57: ='2023-11'!F7 -> 127 | H57: ='2023-11'!F8 -> 0 | I57: ='2023-11'!F9 -> 0 | J57: ='2023-11'!F10 -> 300 | K57: ='2023-11'!F11 -> 2000 | L57: ='2023-11'!F12 -> 2674 | M57: =SUM(B57:L57)*-1 -> -5809 | N57: =卖猫!M52 -> 0 | O57: =(N57+M57) -> -5809 | P57: =P56+O57 -> -184906.3
A58: 45261 | B58: ='2023-12'!F2 -> 0 | C58: ='2023-12'!F3 -> 1935 | D58: ='2023-12'!F4 -> 459 | E58: ='2023-12'!F5 -> 434 | F58: ='2023-12'!F6 -> 0 | G58: ='2023-12'!F7 -> 230 | H58: ='2023-12'!F8 -> 0 | I58: ='2023-12'!F9 -> 0 | J58: ='2023-12'!F10 -> 0 | K58: ='2023-12'!F11 -> 0 | L58: ='2023-12'!F12 -> 246 | M58: =SUM(B58:L58)*-1 -> -3304 | N58: =卖猫!M53 -> 0 | O58: =(N58+M58) -> -3304 | P58: =P57+O58 -> -188210.3
A59: 45292 | B59: ='2024-01'!F2 -> 0 | C59: ='2024-01'!F3 -> 0 | D59: ='2024-01'!F4 -> 0 | E59: ='2024-01'!F5 -> 129 | F59: ='2024-01'!F6 -> 0 | G59: ='2024-01'!F7 -> 43 | H59: ='2024-01'!F8 -> 0 | I59: ='2024-01'!F9 -> 0 | J59: ='2024-01'!F10 -> 0 | K59: ='2024-01'!F11 -> 0 | L59: ='2024-01'!F12 -> 2124 | M59: =SUM(B59:L59)*-1 -> -2296 | N59: =卖猫!M54 -> 2300 | O59: =(N59+M59) -> 4 | P59: =P58+O59 -> -188206.3
A60: 45323 | B60: ='2024-02'!F2 -> 1854 | C60: ='2024-02'!F3 -> 2520 | D60: ='2024-02'!F4 -> 340 | E60: ='2024-02'!F5 -> 78 | F60: ='2024-02'!F6 -> 0 | G60: ='2024-02'!F7 -> 250 | H60: ='2024-02'!F8 -> 400 | I60: ='2024-02'!F9 -> 0 | J60: ='2024-02'!F10 -> 0 | K60: ='2024-02'!F11 -> 0 | L60: ='2024-02'!F12 -> 2217 | M60: =SUM(B60:L60)*-1 -> -7659 | N60: =卖猫!M55 -> 4300 | O60: =(N60+M60) -> -3359 | P60: =P59+O60 -> -191565.3
A61: 45352 | B61: ='2024-03'!F2 -> 1572 | C61: ='2024-03'!F3 -> 0 | D61: ='2024-03'!F4 -> 216 | E61: ='2024-03'!F5 -> 602 | F61: ='2024-03'!F6 -> 0 | G61: ='2024-03'!F7 -> 661 | H61: ='2024-03'!F8 -> 500 | I61: ='2024-03'!F9 -> 0 | J61: ='2024-03'!F10 -> 129 | K61: ='2024-03'!F11 -> 0 | L61: ='2024-03'!F12 -> 2068 | M61: =SUM(B61:L61)*-1 -> -5748 | N61: =卖猫!M56 -> 7800 | O61: =(N61+M61) -> 2052 | P61: =P60+O61 -> -189513.3
A62: 45383 | B62: ='2024-04'!F2 -> 0 | C62: ='2024-04'!F3 -> 0 | D62: ='2024-04'!F4 -> 298 | E62: ='2024-04'!F5 -> 271 | F62: ='2024-04'!F6 -> 0 | G62: ='2024-04'!F7 -> 112 | H62: ='2024-04'!F8 -> 2360 | I62: ='2024-04'!F9 -> 0 | J62: ='2024-04'!F10 -> 114 | K62: ='2024-04'!F11 -> 0 | L62: ='2024-04'!F12 -> 92 | M62: =SUM(B62:L62)*-1 -> -3247 | N62: =卖猫!M57 -> 3700 | O62: =(N62+M62) -> 453 | P62: =P61+O62 -> -189060.3
A63: 45413 | B63: ='2024-05'!F2 -> 82 | C63: ='2024-05'!F3 -> 0 | D63: ='2024-05'!F4 -> 251 | E63: ='2024-05'!F5 -> 50 | F63: ='2024-05'!F6 -> 0 | G63: ='2024-05'!F7 -> 0 | H63: ='2024-05'!F8 -> 600 | I63: ='2024-05'!F9 -> 0 | J63: ='2024-05'!F10 -> 22 | K63: ='2024-05'!F11 -> 0 | L63: ='2024-05'!F12 -> 100 | M63: =SUM(B63:L63)*-1 -> -1105 | N63: =卖猫!M58 -> 13400 | O63: =(N63+M63) -> 12295 | P63: =P62+O63 -> -176765.3
A64: 45444 | B64: ='2024-06'!F2 -> 0 | C64: ='2024-06'!F3 -> 1020 | D64: ='2024-06'!F4 -> 417 | E64: ='2024-06'!F5 -> 253 | F64: ='2024-06'!F6 -> 1458 | G64: ='2024-06'!F7 -> 640 | H64: ='2024-06'!F8 -> 0 | I64: ='2024-06'!F9 -> 36 | J64: ='2024-06'!F10 -> 0 | K64: ='2024-06'!F11 -> 0 | L64: ='2024-06'!F12 -> 54 | M64: =SUM(B64:L64)*-1 -> -3878 | N64: =卖猫!M59 -> 2000 | O64: =(N64+M64) -> -1878 | P64: =P63+O64 -> -178643.3
A65: 45474 | B65: ='2024-07'!F2 -> 2324 | C65: ='2024-07'!F3 -> 0 | D65: ='2024-07'!F4 -> 0 | E65: ='2024-07'!F5 -> 24 | F65: ='2024-07'!F6 -> 0 | G65: ='2024-07'!F7 -> 96 | H65: ='2024-07'!F8 -> 0 | I65: ='2024-07'!F9 -> 0 | J65: ='2024-07'!F10 -> 0 | K65: ='2024-07'!F11 -> 0 | L65: ='2024-07'!F12 -> 82 | M65: =SUM(B65:L65)*-1 -> -2526 | N65: =卖猫!M60 -> 0 | O65: =(N65+M65) -> -2526 | P65: =P64+O65 -> -181169.3
A66: 45505 | B66: ='2024-08'!F2 -> 410 | C66: ='2024-08'!F3 -> 0 | D66: ='2024-08'!F4 -> 0 | E66: ='2024-08'!F5 -> 633 | F66: ='2024-08'!F6 -> 0 | G66: ='2024-08'!F7 -> 625 | H66: ='2024-08'!F8 -> 0 | I66: ='2024-08'!F9 -> 669 | J66: ='2024-08'!F10 -> 0 | K66: ='2024-08'!F11 -> 0 | L66: ='2024-08'!F12 -> 7.5 | M66: =SUM(B66:L66)*-1 -> -2344.5 | N66: =卖猫!M61 -> 700 | O66: =(N66+M66) -> -1644.5 | P66: =P65+O66 -> -182813.8
A67: 45536 | B67: ='2024-09'!F2 -> 1810 | C67: ='2024-09'!F3 -> 1200 | D67: ='2024-09'!F4 -> 0 | E67: ='2024-09'!F5 -> 125 | F67: ='2024-09'!F6 -> 0 | G67: ='2024-09'!F7 -> 0 | H67: ='2024-09'!F8 -> 0 | I67: ='2024-09'!F9 -> 34 | J67: ='2024-09'!F10 -> 284 | K67: ='2024-09'!F11 -> 0 | L67: ='2024-09'!F12 -> 14 | M67: =SUM(B67:L67)*-1 -> -3467 | N67: =卖猫!M62 -> 9966 | O67: =(N67+M67) -> 6499 | P67: =P66+O67 -> -176314.8
A68: 45566 | B68: ='2024-10'!F2 -> 0 | C68: ='2024-10'!F3 -> 0 | D68: ='2024-10'!F4 -> 0 | E68: ='2024-10'!F5 -> 0 | F68: ='2024-10'!F6 -> 0 | G68: ='2024-10'!F7 -> 0 | H68: ='2024-10'!F8 -> 0 | I68: ='2024-10'!F9 -> 0 | J68: ='2024-10'!F10 -> 0 | K68: ='2024-10'!F11 -> 0 | L68: ='2024-10'!F12 -> 0 | M68: =SUM(B68:L68)*-1 -> 0 | N68: =卖猫!M63 -> 0 | O68: =(N68+M68) -> 0 | P68: =P67+O68 -> -176314.8
A69: 45597
A70: 45627

Sheet 卖猫
A1: 猫名 | B1: 进价 | C1: 出售价 | D1: 数量 | E1: 品种 | F1: 出售渠道 | G1: 月份 | H1: 猫妈 | I1: 窝次 | J1: 累计 | L1: 月份 | M1: 成交总计 | N1: 成交数量 | O1: 个人 | P1: 代理 | Q1: 猫舍 | R1: 店铺 | S1: 咸鱼 | T1: 季度个人 | U1: 季度代理 | V1: 季度猫舍 | W1: 季度店铺 | X1: 季度咸鱼 | Y1: 季度均价
A2: 小红(尖尖儿子) | B2: 0 | C2: 1500 | D2: 1 | E2: 布偶 | F2: 咸鱼 | G2: 43709 | H2: 尖尖 | I2: 1 | J2: 1500 | L2: 43709 | M2: =SUMIF(G:G,L2,C:C) -> 6600 | N2: =SUMIF(G:G,L2,D:D) -> 2 | O2: =SUMIFS(C:C,F:F,"个人",G:G,L2) -> 5100 | P2: =SUMIFS(C:C,F:F,"代理",G:G,L2) -> 0 | Q2: =SUMIFS(C:C,F:F,"猫舍",G:G,L2) -> 0 | R2: =SUMIFS(C:C,F:F,"店铺",G:G,L2) -> 0 | S2: =SUMIFS(C:C,F:F,"咸鱼",G:G,L2) -> 1500 | T2: 5100 | U2: 0 | V2: 0 | W2: 0 | X2: 1500 | Y2: =M2/N2 -> 3300
A3: 土豆 | B3: 4700 | C3: 5100 | D3: 1 | E3: 布偶 | F3: 个人 | G3: 43709 | J3: =SUM(C3,J2) -> 6600 | L3: 43739 | M3: =SUMIF(G:G,L3,C:C) -> 500 | N3: =SUMIF(G:G,L3,D:D) -> 1 | O3: =SUMIFS(C:C,F:F,"个人",G:G,L3) -> 0 | P3: =SUMIFS(C:C,F:F,"代理",G:G,L3) -> 0 | Q3: =SUMIFS(C:C,F:F,"猫舍",G:G,L3) -> 0 | R3: =SUMIFS(C:C,F:F,"店铺",G:G,L3) -> 0 | S3: =SUMIFS(C:C,F:F,"咸鱼",G:G,L3) -> 500
A4: 蓝猫(腿腿女儿) | B4: 0 | C4: 500 | D4: 1 | E4: 英短 | F4: 咸鱼 | G4: 43739 | H4: 腿腿 | I4: 1 | J4: =SUM(C4,J3) -> 7100 | L4: 43770 | M4: =SUMIF(G:G,L4,C:C) -> 4900 | N4: =SUMIF(G:G,L4,D:D) -> 2 | O4: =SUMIFS(C:C,F:F,"个人",G:G,L4) -> 2900 | P4: =SUMIFS(C:C,F:F,"代理",G:G,L4) -> 0 | Q4: =SUMIFS(C:C,F:F,"猫舍",G:G,L4) -> 2000 | R4: =SUMIFS(C:C,F:F,"店铺",G:G,L4) -> 0 | S4: =SUMIFS(C:C,F:F,"咸鱼",G:G,L4) -> 0
A5: 布偶双色(机场家) | B5: 2000 | C5: 2900 | D5: 1 | E5: 布偶 | F5: 个人 | G5: 43770 | J5: =SUM(C5,J4) -> 10000 | L5: 43800 | M5: =SUMIF(G:G,L5,C:C) -> 3600 | N5: =SUMIF(G:G,L5,D:D) -> 2 | O5: =SUMIFS(C:C,F:F,"个人",G:G,L5) -> 0 | P5: =SUMIFS(C:C,F:F,"代理",G:G,L5) -> 0 | Q5: =SUMIFS(C:C,F:F,"猫舍",G:G,L5) -> 3600 | R5: =SUMIFS(C:C,F:F,"店铺",G:G,L5) -> 0 | S5: =SUMIFS(C:C,F:F,"咸鱼",G:G,L5) -> 0 | T5: =O3+O4+O5 -> 2900 | U5: =P3+P4+P5 -> 0 | V5: =Q3+Q4+Q5 -> 5600 | W5: =R3+R4+R5 -> 0 | X5: =S3+S4+S5 -> 500 | Y5: =(M3+M4+M5)/(N3+N4+N5) -> 1800
A6: 大白(小白家) | B6: 1500 | C6: 2000 | D6: 1 | E6: 金渐层 | F6: 猫舍 | G6: 43770 | J6: =SUM(C6,J5) -> 12000 | L6: 43831 | M6: =SUMIF(G:G,L6,C:C) -> 2500 | N6: =SUMIF(G:G,L6,D:D) -> 3 | O6: =SUMIFS(C:C,F:F,"个人",G:G,L6) -> 0 | P6: =SUMIFS(C:C,F:F,"代理",G:G,L6) -> 0 | Q6: =SUMIFS(C:C,F:F,"猫舍",G:G,L6) -> 2000 | R6: =SUMIFS(C:C,F:F,"店铺",G:G,L6) -> 0 | S6: =SUMIFS(C:C,F:F,"咸鱼",G:G,L6) -> 500
A7: 小粉(尖尖女儿) | B7: 0 | C7: 2000 | D7: 1 | E7: 布偶 | F7: 猫舍 | G7: 43800 | H7: 尖尖 | I7: 1 | J7: =SUM(C7,J6) -> 14000 | L7: 43862 | M7: =SUMIF(G:G,L7,C:C) -> 8800 | N7: =SUMIF(G:G,L7,D:D) -> 1 | O7: =SUMIFS(C:C,F:F,"个人",G:G,L7) -> 0 | P7: =SUMIFS(C:C,F:F,"代理",G:G,L7) -> 0 | Q7: =SUMIFS(C:C,F:F,"猫舍",G:G,L7) -> 8800 | R7: =SUMIFS(C:C,F:F,"店铺",G:G,L7) -> 0 | S7: =SUMIFS(C:C,F:F,"咸鱼",G:G,L7) -> 0
A8: 小墨(机场家) | B8: 700 | C8: 1600 | D8: 1 | E8: 布偶 | F8: 猫舍 | G8: 43800 | J8: =SUM(C8,J7) -> 15600 | L8: 43891 | M8: =SUMIF(G:G,L8,C:C) -> 26100 | N8: =SUMIF(G:G,L8,D:D) -> 11 | O8: =SUMIFS(C:C,F:F,"个人",G:G,L8) -> 7300 | P8: =SUMIFS(C:C,F:F,"代理",G:G,L8) -> 0 | Q8: =SUMIFS(C:C,F:F,"猫舍",G:G,L8) -> 18800 | R8: =SUMIFS(C:C,F:F,"店铺",G:G,L8) -> 0 | S8: =SUMIFS(C:C,F:F,"咸鱼",G:G,L8) -> 0 | T8: =O6+O7+O8 -> 7300 | U8: =P6+P7+P8 -> 0 | V8: =Q6+Q7+Q8 -> 29600 | W8: =R6+R7+R8 -> 0 | X8: =S6+S7+S8 -> 500 | Y8: =(M6+M7+M8)/(N6+N7+N8) -> 2493.3333
A9: 小紫(尖尖儿子) | B9: 0 | C9: 1200 | D9: 1 | E9: 布偶 | F9: 猫舍 | G9: 43831 | H9: 尖尖 | I9: 1 | J9: =SUM(C9,J8) -> 16800 | L9: 43922 | M9: =SUMIF(G:G,L9,C:C) -> 18800 | N9: =SUMIF(G:G,L9,D:D) -> 5 | O9: =SUMIFS(C:C,F:F,"个人",G:G,L9) -> 15000 | P9: =SUMIFS(C:C,F:F,"代理",G:G,L9) -> 0 | Q9: =SUMIFS(C:C,F:F,"猫舍",G:G,L9) -> 3800 | R9: =SUMIFS(C:C,F:F,"店铺",G:G,L9) -> 0 | S9: =SUMIFS(C:C,F:F,"咸鱼",G:G,L9) -> 0
A10: 小蓝(尖尖儿子) | B10: 0 | C10: 800 | D10: 1 | E10: 布偶 | F10: 猫舍 | G10: 43831 | H10: 尖尖 | I10: 1 | J10: =SUM(C10,J9) -> 17600 | L10: 43952 | M10: =SUMIF(G:G,L10,C:C) -> 9300 | N10: =SUMIF(G:G,L10,D:D) -> 5 | O10: =SUMIFS(C:C,F:F,"个人",G:G,L10) -> 0 | P10: =SUMIFS(C:C,F:F,"代理",G:G,L10) -> 1600 | Q10: =SUMIFS(C:C,F:F,"猫舍",G:G,L10) -> 5300 | R10: =SUMIFS(C:C,F:F,"店铺",G:G,L10) -> 0 | S10: =SUMIFS(C:C,F:F,"咸鱼",G:G,L10) -> 2400
A11: 小五 | B11: 0 | C11: 500 | D11: 1 | E11: 英短 | F11: 咸鱼 | G11: 43831 | J11: =SUM(C11,J10) -> 18100 | L11: 43983 | M11: =SUMIF(G:G,L11,C:C) -> 18700 | N11: =SUMIF(G:G,L11,D:D) -> 3 | O11: =SUMIFS(C:C,F:F,"个人",G:G,L11) -> 8000 | P11: =SUMIFS(C:C,F:F,"代理",G:G,L11) -> 0 | Q11: =SUMIFS(C:C,F:F,"猫舍",G:G,L11) -> 4000 | R11: =SUMIFS(C:C,F:F,"店铺",G:G,L11) -> 0 | S11: =SUMIFS(C:C,F:F,"咸鱼",G:G,L11) -> 6700 | T11: =O9+O10+O11 -> 23000 | U11: =P9+P10+P11 -> 1600 | V11: =Q9+Q10+Q11 -> 13100 | W11: =R9+R10+R11 -> 0 | X11: =S9+S10+S11 -> 9100 | Y11: =(M9+M10+M11)/(N9+N10+N11) -> 3600
A12: 金渐层长毛(长毛金渐层家) | B12: 5000 | C12: 8800 | D12: 1 | E12: 金渐层 | F12: 猫舍 | G12: 43862 | J12: =SUM(C12,J11) -> 26900 | L12: 44013 | M12: =SUMIF(G:G,L12,C:C) -> 5700 | N12: =SUMIF(G:G,L12,D:D) -> 2 | O12: =SUMIFS(C:C,F:F,"个人",G:G,L12) -> 1700 | P12: =SUMIFS(C:C,F:F,"代理",G:G,L12) -> 0 | Q12: =SUMIFS(C:C,F:F,"猫舍",G:G,L12) -> 4000 | R12: =SUMIFS(C:C,F:F,"店铺",G:G,L12) -> 0 | S12: =SUMIFS(C:C,F:F,"咸鱼",G:G,L12) -> 0
A13: 德文*3 | B13: 7700 | C13: 8800 | D13: 3 | E13: 德文 | F13: 猫舍 | G13: 43891 | J13: =SUM(C13,J12) -> 35700 | L13: 44044 | M13: =SUMIF(G:G,L13,C:C) -> 6100 | N13: =SUMIF(G:G,L13,D:D) -> 6 | O13: =SUMIFS(C:C,F:F,"个人",G:G,L13) -> 1900 | P13: =SUMIFS(C:C,F:F,"代理",G:G,L13) -> 3900 | Q13: =SUMIFS(C:C,F:F,"猫舍",G:G,L13) -> 300 | R13: =SUMIFS(C:C,F:F,"店铺",G:G,L13) -> 0 | S13: =SUMIFS(C:C,F:F,"咸鱼",G:G,L13) -> 0
A14: 乳白矮脚(金州家) | B14: 1700 | C14: 2200 | D14: 1 | E14: 英短 | F14: 猫舍 | G14: 43891 | J14: =SUM(C14,J13) -> 37900 | L14: 44075 | M14: =SUMIF(G:G,L14,C:C) -> 9200 | N14: =SUMIF(G:G,L14,D:D) -> 9 | O14: =SUMIFS(C:C,F:F,"个人",G:G,L14) -> 180 | P14: =SUMIFS(C:C,F:F,"代理",G:G,L14) -> 2000 | Q14: =SUMIFS(C:C,F:F,"猫舍",G:G,L14) -> 5520 | R14: =SUMIFS(C:C,F:F,"店铺",G:G,L14) -> 0 | S14: =SUMIFS(C:C,F:F,"咸鱼",G:G,L14) -> 1500 | T14: =O12+O13+O14 -> 3780 | U14: =P12+P13+P14 -> 5900 | V14: =Q12+Q13+Q14 -> 9820 | W14: =R12+R13+R14 -> 0 | X14: =S12+S13+S14 -> 1500 | Y14: =(M12+M13+M14)/(N12+N13+N14) -> 1235.2941
A15: 布偶母*2(金州家) | B15: 2800 | C15: 3800 | D15: 2 | E15: 布偶 | F15: 猫舍 | G15: 43891 | J15: =SUM(C15,J14) -> 41700 | L15: 44105 | M15: =SUMIF(G:G,L15,C:C) -> 3800 | N15: =SUMIF(G:G,L15,D:D) -> 10 | O15: =SUMIFS(C:C,F:F,"个人",G:G,L15) -> 200 | P15: =SUMIFS(C:C,F:F,"代理",G:G,L15) -> 0 | Q15: =SUMIFS(C:C,F:F,"猫舍",G:G,L15) -> 3600 | R15: =SUMIFS(C:C,F:F,"店铺",G:G,L15) -> 0 | S15: =SUMIFS(C:C,F:F,"咸鱼",G:G,L15) -> 0
A16: 柯尼斯 | B16: 1200 | C16: 1600 | D16: 1 | E16: 柯尼斯 | F16: 猫舍 | G16: 43891 | J16: =SUM(C16,J15) -> 43300 | L16: 44136 | M16: =SUMIF(G:G,L16,C:C) -> 0 | N16: =SUMIF(G:G,L16,D:D) -> 0 | O16: =SUMIFS(C:C,F:F,"个人",G:G,L16) -> 0 | P16: =SUMIFS(C:C,F:F,"代理",G:G,L16) -> 0 | Q16: =SUMIFS(C:C,F:F,"猫舍",G:G,L16) -> 0 | R16: =SUMIFS(C:C,F:F,"店铺",G:G,L16) -> 0 | S16: =SUMIFS(C:C,F:F,"咸鱼",G:G,L16) -> 0
A17: 蓝金长毛 | B17: 5500 | C17: 6000 | D17: 1 | E17: 金渐层 | F17: 个人 | G17: 43891 | J17: =SUM(C17,J16) -> 49300 | L17: 44166 | M17: =SUMIF(G:G,L17,C:C) -> 6700 | N17: =SUMIF(G:G,L17,D:D) -> 8 | O17: =SUMIFS(C:C,F:F,"个人",G:G,L17) -> 400 | P17: =SUMIFS(C:C,F:F,"代理",G:G,L17) -> 0 | Q17: =SUMIFS(C:C,F:F,"猫舍",G:G,L17) -> 3200 | R17: =SUMIFS(C:C,F:F,"店铺",G:G,L17) -> 0 | S17: =SUMIFS(C:C,F:F,"咸鱼",G:G,L17) -> 3100 | T17: =O15+O16+O17 -> 600 | U17: =P15+P16+P17 -> 0 | V17: =Q15+Q16+Q17 -> 6800 | W17: =R15+R16+R17 -> 0 | X17: =S15+S16+S17 -> 3100 | Y17: =(M15+M16+M17)/(N15+N16+N17) -> 583.33333
A18: 银渐层母 | B18: 1000 | C18: 1300 | D18: 1 | E18: 银渐层 | F18: 个人 | G18: 43891 | J18: =SUM(C18,J17) -> 50600 | L18: 44197 | M18: =SUMIF(G:G,L18,C:C) -> 16100 | N18: =SUMIF(G:G,L18,D:D) -> 7 | O18: =SUMIFS(C:C,F:F,"个人",G:G,L18) -> 0 | P18: =SUMIFS(C:C,F:F,"代理",G:G,L18) -> 6500 | Q18: =SUMIFS(C:C,F:F,"猫舍",G:G,L18) -> 5800 | R18: =SUMIFS(C:C,F:F,"店铺",G:G,L18) -> 0 | S18: =SUMIFS(C:C,F:F,"咸鱼",G:G,L18) -> 3800
A19: 银渐层公*2 | B19: 1800 | C19: 2400 | D19: 2 | E19: 银渐层 | F19: 猫舍 | G19: 43891 | J19: =SUM(C19,J18) -> 53000 | L19: 44228 | M19: =SUMIF(G:G,L19,C:C) -> 4800 | N19: =SUMIF(G:G,L19,D:D) -> 7 | O19: =SUMIFS(C:C,F:F,"个人",G:G,L19) -> 0 | P19: =SUMIFS(C:C,F:F,"代理",G:G,L19) -> 0 | Q19: =SUMIFS(C:C,F:F,"猫舍",G:G,L19) -> 4000 | R19: =SUMIFS(C:C,F:F,"店铺",G:G,L19) -> 0 | S19: =SUMIFS(C:C,F:F,"咸鱼",G:G,L19) -> 800
A20: 高峰银渐层 | B20: 900 | C20: 1500 | D20: 1 | E20: 银渐层 | F20: 个人 | G20: 43922 | J20: =SUM(C20,J19) -> 54500 | L20: 44256 | M20: =SUMIF(G:G,L20,C:C) -> 3500 | N20: =SUMIF(G:G,L20,D:D) -> 8 | O20: =SUMIFS(C:C,F:F,"个人",G:G,L20) -> 1400 | P20: =SUMIFS(C:C,F:F,"代理",G:G,L20) -> 1350 | Q20: =SUMIFS(C:C,F:F,"猫舍",G:G,L20) -> 750 | R20: =SUMIFS(C:C,F:F,"店铺",G:G,L20) -> 0 | S20: =SUMIFS(C:C,F:F,"咸鱼",G:G,L20) -> 0 | T20: =O18+O19+O20 -> 1400 | U20: =P18+P19+P20 -> 7850 | V20: =Q18+Q19+Q20 -> 10550 | W20: =R18+R19+R20 -> 0 | X20: =S18+S19+S20 -> 4600 | Y20: =(M18+M19+M20)/(N18+N19+N20) -> 1109.0909
